Workbook

Sheet CHINA
A1: 44284 | B1: CHINA
B2: ST ROSE | C2: Freight | D2: =1500000/D4 -> 50 | E2: usd/cbm | F2: Yangtze River ports
A3: 264.172 | B3: SANTOS | C3: Freight | D3: =(+'Freight matrix'!J24)*A4 -> 43.395 | E3: usd/cbm
A4: 0.789 | C4: Volume | D4: 30000 | E4: cbm
C6: Basis | D6: 0.1 | E6: cpg
B7: US | C7: APR | D7: MAY | E7: JUN | F7: JUL | G7: AUG | H7: SEP | I7: OCT | J7: NOV | K7: DEC | L7: JAN | M7: FEB | N7: MAR
B8: CHIP | C8: =+'settlement day'!F9 -> 0 | D8: =+'settlement day'!G9 -> 0 | E8: =+'settlement day'!H9 -> 0 | F8: =+'settlement day'!I9 -> 0 | G8: =+'settlement day'!J9 -> 0 | H8: =+'settlement day'!K9 -> 0 | I8: =+'settlement day'!L9 -> 0 | J8: =+'settlement day'!M9 -> 0 | K8: =+'settlement day'!N9 -> 0
B10: FOB IMTT | C10: =+(C8+$D$6)*$A$3 -> 26.4172 | D10: =+(D8+$D$6)*$A$3 -> 26.4172 | E10: =+(E8+$D$6)*$A$3 -> 26.4172 | F10: =+(F8+$D$6)*$A$3 -> 26.4172 | G10: =+(G8+$D$6)*$A$3 -> 26.4172 | H10: =+(H8+$D$6)*$A$3 -> 26.4172 | I10: =+(I8+$D$6)*$A$3 -> 26.4172 | J10: =+(J8+$D$6)*$A$3 -> 26.4172 | K10: =+(K8+$D$6)*$A$3 -> 26.4172
B11: CIF China usd/cbm | C11: =+C10+$D$2 -> 76.4172 | D11: =+D10+$D$2 -> 76.4172 | E11: =+E10+$D$2 -> 76.4172 | F11: =+F10+$D$2 -> 76.4172 | G11: =+G10+$D$2 -> 76.4172 | H11: =+H10+$D$2 -> 76.4172 | I11: =+I10+$D$2 -> 76.4172 | J11: =+J10+$D$2 -> 76.4172 | K11: =+K10+$D$2 -> 76.4172
A12: 1.45 | B12: Import duty | C12: =+C11*$A$12 -> 110.80494 | D12: =+D11*$A$12 -> 110.80494 | E12: =+E11*$A$12 -> 110.80494 | F12: =+F11*$A$12 -> 110.80494 | G12: =+G11*$A$12 -> 110.80494 | H12: =+H11*$A$12 -> 110.80494 | I12: =+I11*$A$12 -> 110.80494 | J12: =+J11*$A$12 -> 110.80494 | K12: =+K11*$A$12 -> 110.80494
B14: CIF usd/mt | C14: =+C12/$A$4 -> 140.43719 | D14: =+D12/$A$4 -> 140.43719 | E14: =+E12/$A$4 -> 140.43719 | F14: =+F12/$A$4 -> 140.43719 | G14: =+G12/$A$4 -> 140.43719 | H14: =+H12/$A$4 -> 140.43719 | I14: =+I12/$A$4 -> 140.43719 | J14: =+J12/$A$4 -> 140.43719 | K14: =+K12/$A$4 -> 140.43719
A17: inland | B17: BRAZIL | C17: APR | D17: MAY | E17: JUN | F17: JUL | G17: AUG | H17: SEP | I17: OCT | J17: NOV | K17: DEC | L17: JAN | M17: FEB | N17: MAR
A18: =+'mkt data'!G6+'mkt data'!G8 -> 90 | B18: B3 | C18: =+'settlement day'!F13 -> 0 | D18: =+'settlement day'!G13 -> 0 | E18: =+'settlement day'!H13 -> 0 | F18: =+'settlement day'!I13 -> 0 | G18: =+'settlement day'!J13 -> 0 | H18: =+'settlement day'!K13 -> 0 | I18: =+'settlement day'!L13 -> 0 | J18: =+'settlement day'!M13 -> 0 | K18: =+'settlement day'!N13 -> 0
A19: brl/cbm | B19: BRL/USD | C19: =+D19 -> 0 | D19: =+'settlement day'!G30 -> 0 | E19: =+'settlement day'!H30 -> 0 | F19: =+'settlement day'!I30 -> 0 | G19: =+'settlement day'!J30 -> 0 | H19: =+'settlement day'!K30 -> 0 | I19: =+'settlement day'!L30 -> 0 | J19: =+'settlement day'!M30 -> 0 | K19: =+'settlement day'!N30 -> 0
B20: hydrous FOB BRZ | C20: =+(C18+$A$18)/C19 -> #DIV/0! | D20: =+(D18+$A$18)/D19 -> #DIV/0! | E20: =+(E18+$A$18)/E19 -> #DIV/0! | F20: =+(F18+$A$18)/F19 -> #DIV/0! | G20: =+(G18+$A$18)/G19 -> #DIV/0! | H20: =+(H18+$A$18)/H19 -> #DIV/0! | I20: =+(I18+$A$18)/I19 -> #DIV/0! | J20: =+(J18+$A$18)/J19 -> #DIV/0! | K20: =+(K18+$A$18)/K19 -> #DIV/0!
A21: 100 | B21: grade B FOB BRZ | C21: =+C20+($A$21/C19) -> #DIV/0! | D21: =+D20+($A$21/D19) -> #DIV/0! | E21: =+E20+($A$21/E19) -> #DIV/0! | F21: =+F20+($A$21/F19) -> #DIV/0! | G21: =+G20+($A$21/G19) -> #DIV/0! | H21: =+H20+($A$21/H19) -> #DIV/0! | I21: =+I20+($A$21/I19) -> #DIV/0! | J21: =+J20+($A$21/J19) -> #DIV/0! | K21: =+K20+($A$21/K19) -> #DIV/0!
A22: 1.12 | B22: anhydrous FOB BRZ | C22: =+C20*$A$22 -> #DIV/0! | D22: =+D20*$A$22 -> #DIV/0! | E22: =+E20*$A$22 -> #DIV/0! | F22: =+F20*$A$22 -> #DIV/0! | G22: =+G20*$A$22 -> #DIV/0! | H22: =+H20*$A$22 -> #DIV/0! | I22: =+I20*$A$22 -> #DIV/0! | J22: =+J20*$A$22 -> #DIV/0! | K22: =+K20*$A$22 -> #DIV/0!
B24: CIF China | C24: =+C22+$D$3 -> #DIV/0! | D24: =+D22+$D$3 -> #DIV/0! | E24: =+E22+$D$3 -> #DIV/0! | F24: =+F22+$D$3 -> #DIV/0! | G24: =+G22+$D$3 -> #DIV/0! | H24: =+H22+$D$3 -> #DIV/0! | I24: =+I22+$D$3 -> #DIV/0! | J24: =+J22+$D$3 -> #DIV/0! | K24: =+K22+$D$3 -> #DIV/0!
A25: 1.3 | B25: Import duty | C25: =+C24*$A$25 -> #DIV/0! | D25: =+D24*$A$25 -> #DIV/0! | E25: =+E24*$A$25 -> #DIV/0! | F25: =+F24*$A$25 -> #DIV/0! | G25: =+G24*$A$25 -> #DIV/0! | H25: =+H24*$A$25 -> #DIV/0! | I25: =+I24*$A$25 -> #DIV/0! | J25: =+J24*$A$25 -> #DIV/0! | K25: =+K24*$A$25 -> #DIV/0!
B27: CIF usd/mt | C27: =+C25/$A$4 -> #DIV/0! | D27: =+D25/$A$4 -> #DIV/0! | E27: =+E25/$A$4 -> #DIV/0! | F27: =+F25/$A$4 -> #DIV/0! | G27: =+G25/$A$4 -> #DIV/0! | H27: =+H25/$A$4 -> #DIV/0! | I27: =+I25/$A$4 -> #DIV/0! | J27: =+J25/$A$4 -> #DIV/0! | K27: =+K25/$A$4 -> #DIV/0!
B31: China domestic price

Sheet USA
C3: 264.172
B4: Arbitrage Brazil to California | H4: 3000
B5: Updated: | C5: 44286 | H5: =+H4/I5 -> #DIV/0! | I5: =+'settlement day'!H30 -> 0
B7: Volume | C7: 40000 | D7: m3 | E7: =(+C7*C3)/1000 -> 10566.88 | F7: mln gal | Q7: 2.4825
B8: FOB Santos | C8: 545 | D8: per m3 | E8: JUNE | F8: loading | I8: FREIGHT | Q8: 0.365
B9: FOB Santos | C9: =C8/264.172 -> 2.0630498 | D9: per gallon | I9: 05/02/2021: spi: $1.7-1.75 m as a guide | Q9: =+Q7+Q8 -> 2.8475
B10: Frt ($/mT) | C10: =E10/334 -> 0.16601777 | D10: per gallon | E10: =+I12 -> 55.449937 | F10: usd/mt | I10: 1750000 | J10: usd lps | K10: 400/400 | Q10: =+Q9*264.172 -> 752.22977
B11: CIF Cali | C11: =C9+C10 -> 2.2290676 | D11: per gallon | I11: =40000*0.789 -> 31560 | J11: mt | P11: FOB | Q11: =+Q10/1.1 -> 683.84525 | R11: eur/cbm
B12: CIF Cali ME importer of record | C12: =C11*1.025 -> 2.2847943 | D12: per gallon | E12: =+C12*C3 -> 603.57868 | F12: USD/cbm | I12: =+I10/I11 -> 55.449937 | J12: usd/mt
L13: =+I12*0.789 -> 43.75
B15: LCSF Baseline | C15: 79.9 | D15: CI value
B16: LCFS (Brazil) | C16: 58 | D16: CI value | I16: CIF SALE TO ME
B17: LCFS CI value | C17: =+'settlement day'!BJ34 -> 0 | D17: per gallon | I17: =+C9 -> 2.0630498 | J17: FOB Santos
B18: LCFS ( Brazilian producer) | C18: =(C15-C16)*C17 -> 0 | D18: per gallon | I18: 0.005 | J18: Costings
B19: D6 2021 | C19: =+'settlement day'!BG34 -> 0 | D19: per gallon | I19: =+C10 -> 0.16601777 | J19: Freight
B20: D5 2021 | C20: =+'settlement day'!BI34 -> 0 | D20: per gallon | I20: 0.01 | J20: Demurrage
B21: D5-D6 | C21: =C20-C19 -> 0 | D21: per gallon | I21: 0.01 | J21: MEG
B22: Total CI+RIN pick-up | C22: =(C21+C18)*E22 -> 0 | D22: per gallon | E22: 1 | I22: =SUM(I17:I21) -> 2.2540676 | J22: =+I22*C3 -> 595.46155 | K22: USD/cbm
B23: Total CI+RIN pick-up | C23: =C22*$C$3 -> 0 | D23: per m3
E24: OPIS spot | G24: Platts
B25: CIF Cali with Credit | C25: =C12-C22 -> 2.2847943 | E25: Argo | F25: =+'settlement day'!AY34 -> 0
B26: Cali delivered (CHIP + differential) | C26: =+F28+G27 -> 0.18 | E26: LA | F26: =+'settlement day'!AY38 -> 0 | H26: =+F25+G27 -> 0.18
F27: =+F26-F25 -> 0 | G27: 0.18
E28: CHIP | F28: =+'settlement day'!I9 -> 0 | G28: JULY | H28: arrival
B29: Bzl /Cali arb | C29: =C26-C25 -> -2.1047943 | D29: =+C29*C3 -> -556.02772 | F29: =+F28-C25 -> -2.2847943
B31: Duty Drawback (2.5%) | C31: =C11*0.025 -> 0.05572669 | D31: per gallon
B32: Duty Drawback (2.5%) | C32: =C31*264.172 -> 14.721431 | D32: per m3
B39: FLORIDA / USGC
B40: 0.12 | D40: usd/cbm
B41: LYB / Florida ind bid | D41: =(+'settlement day'!I9+B40)*C3 -> 31.70064 | F41: JULY arrival
B42: CIF USGC/USEC | C42: =+D41-D42 -> #REF! | D42: =+('FOB origin'!#REF!)+('Freight matrix'!H16*0.789) -> #REF! | E42: b3
C43: =+D41-D43 -> #REF! | D43: =+'FOB origin'!#REF!+('Freight matrix'!$H$16*0.789) -> #REF! | E43: phys

Sheet Freight matrix
B1: Last update | C1: April 21
B3: Freight rates in USD/MT
B4: ex USGC | C4: 5kt | E4: 10kt | G4: 20kt | I4: 30kt | K4: 40kt
B5: ARA | C5: 57 | D5: 60 | E5: 47 | F5: 55 | G5: 39 | H5: 42 | I5: 32 | J5: 35 | K5: 29 | L5: 32
B6: France | C6: 57 | D6: 60 | E6: 47 | F6: 55 | G6: 39 | H6: 42 | I6: 32 | J6: 35 | K6: 29 | L6: 32
B7: Baltics | C7: 57 | D7: 60 | E7: 47 | F7: 60 | G7: 39 | H7: 42 | I7: 32 | J7: 35 | K7: 29 | L7: 32
B8: North Brazil | C8: 65 | D8: 68 | E8: 55 | F8: 57 | G8: 40 | H8: 42 | I8: 37 | J8: 39 | K8: 30 | L8: 33
B9: Southeast Brazil | C9: - | D9: - | E9: - | F9: - | G9: 47 | H9: 49 | I9: 44 | J9: 46 | K9: 37 | L9: 40
B10: Colombia / Caribe | D10: 60 | F10: 50
B11: Far East | C11: 80 | D11: 83 | E11: 72 | F11: 75 | G11: 62 | H11: 65 | I11: 52 | J11: 55 | K11: 47 | L11: 50 | P11: 35
B12: WCI/AG | C12: 81 | D12: 85 | E12: 74 | F12: 78 | G12: 65 | H12: 70 | I12: 60 | J12: 65 | K12: 55 | L12: 60 | P12: =+P11*0.789 -> 27.615
B13: CHINA
B15: ex BRAZIL | C15: 5kt | E15: 10kt | G15: 20kt | I15: 30kt | K15: 40kt
B16: USG/USEC | C16: 50 | D16: 53 | E16: 43 | F16: 46 | G16: 32 | H16: 35 | I16: 26 | J16: 28 | K16: 22 | L16: 25
B17: USWC | C17: - | D17: - | E17: - | F17: - | G17: 70 | H17: 73 | I17: 53 | J17: 56 | K17: 39 | L17: 41
B18: ARA | C18: 65 | D18: 68 | E18: 50 | F18: 53 | G18: 40 | H18: 43 | I18: 32 | J18: 35 | K18: - | L18: -
B19: France | C19: 65 | D19: 68 | E19: 50 | F19: 53 | G19: 40 | H19: 43 | I19: 32 | J19: 35 | K19: - | L19: -
B20: Baltics | C20: 65 | D20: 68 | E20: 50 | F20: 53 | G20: 40 | H20: 43 | I20: 32 | J20: 35 | K20: - | L20: -
B21: Colombia / Caribe
B22: Far East | C22: 80 | D22: 83 | E22: 85 | F22: 90 | G22: 64 | H22: 68 | I22: 52 | J22: 55 | K22: 46 | L22: 49
B23: WCI/AG | C23: - | D23: - | E23: 70 | F23: 73 | G23: 53 | H23: 56 | I23: 55 | J23: 58 | K23: 48 | L23: 51
B24: CHINA | H24: 58 | J24: 55
B26: ex KARACHI | C26: 5kt | E26: 10kt | G26: 20kt | I26: 30kt | K26: 40kt
B27: ARA | C27: 85 | D27: 88 | E27: 73 | F27: 76 | G27: 65 | H27: 68 | I27: 55 | J27: 58 | K27: 45 | L27: 48
B28: FAR EAST | C28: 57 | D28: 60 | E28: 50 | F28: 53 | G28: 42 | H28: 45 | I28: 36 | J28: 39 | K28: 31 | L28: 33
B30: ex WCCAM/SAM | C30: 5kt | E30: 10kt | G30: 20kt | I30: 30kt | K30: 40kt
B31: North Brazil | C31: 71 | D31: 73 | E31: 60 | F31: 63 | G31: 49 | H31: 52 | I31: - | J31: - | K31: - | L31: -
B32: ARA | C32: 83 | D32: 86 | E32: 73 | F32: 76 | G32: 63 | H32: 66 | I32: 53 | J32: 56 | K32: 41 | L32: 45
B33: FAR EAST | C33: 85 | D33: 88 | E33: 75 | F33: 79 | G33: 67 | H33: 70 | I33: 59 | J33: 62 | K33: 50 | L33: 53

Sheet BRAZIL domestic
D2: BRAZILIAN DOMESTIC MARKET
I3: Date | J3: =+'settlement day'!B3 -> 45946
E4: Anhydrous premium over Hydrous | F4: =100%-(+E12/I12) -> 0.078169014 | I4: FX | J4: ='settlement day'!BA30 -> 5.7416
C6: EXPORTS | K6: IMPORTS
E7: BRL/cbm | F7: USD/cbm | H7: CS | I7: BRL/cbm | J7: USD/cbm | L7: NE | M7: BRL/cbm | N7: USD/cbm | O7: =470/0.867 -> 542.09919 | P7: 470 s/ICMS | Q7: 190 | R7: RS | S7: BRL/cbm | T7: USD/cbm
D8: HYDROUS | E8: =+'settlement day'!AY45 -> 0 | H8: ANHYDROUS | I8: =+'settlement day'!AY44 -> 0 | L8: ANHYDROUS | M8: =+'PLATTS&OPIS'!I256 -> 3900 | Q8: https://covid19.apple.com/mobility | R8: ANHYDROUS | S8: =+I8+Q7 -> 190
D9: (-) INSS 2,85% | E9: =+E8*2.85% -> 0 | I9: =+I8*2.85% -> 0 | M9: 0 | O9: (-) INSS 2,85% | S9: 0
D10: (-) ICMS 12% | E10: =+E8*12% -> 0 | I10: 122 | O10: (-) ICMS XX%
B11: 130.9 | D11: (-) PIS/COFINS | E11: 130.9 | I11: 20 | L11: 131 | M11: 0 | O11: (-) PIS/COFINS | S11: 149
E12: =+E8-(E9+E10+E11) -> -130.9 | I12: =+I8-(I9+I10+I11) -> -142 | J12: =+I12/E12 -> 1.0847976 | M12: =+M8-(M9+M10+M11) -> 3900 | S12: =+S8-(S9+S10+S11) -> 41
C13: 1 | D13: (+) CBIOS | E13: =+'settlement day'!BK34*'BRAZIL domestic'!C13 -> 41.25 | G13: 1.2 | I13: =+'settlement day'!BK34*'BRAZIL domestic'!G13 -> 49.5
D15: (+) Inland freight to port | E15: =+'mkt data'!G5 -> 300 | I15: =+E15 -> 300 | M15: 50 | O15: (+) Inland freight to hub | S15: 0
D16: (+) Terminal port | E16: =+'mkt data'!H8 -> 100 | I16: =+E16 -> 100 | M16: 0 | S16: 0
D18: (=) TOTAL | E18: =+E12+E13+E15+E16 -> 310.35 | F18: =+E18/$J$4 -> 54.052877 | I18: =+I12+I13+I15+I16 -> 307.5 | J18: =+I18/$J$4 -> 53.5565 | M18: =+M12+M15+M16 -> 3950 | N18: =+M18/$J$4 -> 687.96154 | S18: =+S12+S15+S16 -> 41 | T18: =+S18/$J$4 -> 7.1408667
D20: (+) Port costs | E20: 10 | F20: =+E20/J4 -> 1.7416748 | J20: =+F20 -> 1.7416748 | M20: 70 | N20: =+M20/$J$4 -> 12.191724 | O20: (+) Port costs | S20: 65 | T20: =+S20/$J$4 -> 11.320886
D21: (+) Inspection | E21: 5 | F21: =+E21/J4 -> 0.8708374 | J21: =+F21 -> 0.8708374 | M21: 15 | N21: =+M21/$J$4 -> 2.6125122 | O21: (+) Inspection | S21: 36 | T21: =+S21/$J$4 -> 6.2700293
D22: (+) EXPORT premium B grade | E22: =+'mkt data'!G4 -> 150 | F22: =+E22/J4 -> 26.125122 | J22: 0 | M22: 25 | N22: =+M22/$J$4 -> 4.354187 | O22: (+) Inland freight to hub | S22: 65 | T22: =+S22/$J$4 -> 11.320886
K23: 44593 | M23: =+N23*J4 -> 5.7416 | N23: 1 | O23: (+) other costs | S23: 10 | T23: =+S23/J4 -> 1.7416748
E24: FOB Santos | F24: =+F18+F20+F21+F22 -> 82.790511 | I24: FOB Santos | J24: =+J18+J20+J21+J22 -> 56.169012 | K24: 765 | M24: =+N24*J4 -> 516.09807 | N24: =+K24*K25 -> 89.8875 | O24: (+) PIS/COFINS on CFR | R24: =(+'settlement day'!M9+0.33+0.03)*264.172 -> 95.10192 | S24: =+T24*J4 -> 64.159369 | T24: =+R24*R25 -> 11.174476
K25: 0.1175 | M25: 100 | N25: =+M25/$J$4 -> 17.416748 | O25: (+) margin | R25: 0.1175 | S25: 100 | T25: =+S25/$J$4 -> 17.416748
M26: =SUM(M20:M25) -> 731.83967
N27: =+N18-(N20+N21+N22+N23+N24+N25) -> 560.49887 | O27: Suape Value with TRQ | T27: =+T18-(T20+T21+T22+T23+T24+T25) -> -52.103833
N28: =+N18-(N20+N21+N22+N23+N24+N25)-N29 -> 560.49887 | O28: Suape Value w/o TRQ | T28: =+T18-(T20+T21+T22+T23+T24+T25)-T29 -> -71.124217
K29: 0 | M29: =+N29*J4 -> 0 | N29: =+K29*K24 -> 0 | O29: Import duty | Q29: 0.2 | S29: =+T29*J4 -> 109.20744 | T29: =+Q29*R24 -> 19.020384
C32: BRAZILIAN DOMESTIC MARKET -- basis B3
E34: Frete | F34: 65 | G34: R$/cbm | H34: 65 | I34: 75 frete 14/6/21
E35: PIS/COFINS | F35: 130.9 | G35: R$/cbm
D36: 30 | E36: ICMS | F36: 0.133 | G36: 0.867
E37: anh/hydrous | F37: 0.14 | G37: 1.14
U39: 264.172
D40: 44621 | E40: 44652 | F40: 44682 | G40: 44713 | H40: 44743 | I40: 44774 | J40: 44805 | K40: 44835 | L40: 44866 | M40: 44896 | N40: 44927 | O40: 44958 | P40: 44986 | S40: 750
C41: B3 | D41: =+'settlement day'!Q13 -> 0 | E41: =+'settlement day'!R13 -> 0 | F41: =+'settlement day'!S13 -> 0 | G41: =+'settlement day'!T13 -> 0 | H41: =+'settlement day'!U13 -> 0 | I41: =+'settlement day'!V13 -> 0 | J41: =+'settlement day'!W13 -> 0 | K41: =+'settlement day'!X13 -> 0 | ... P41: =+'settlement day'!AC13 -> 0 | S41: =+S40/U39 -> 2.8390594
C42: ESALQ P | D42: =+'settlement day'!BI42 -> 2856.5
D43: =+D41-D42 -> -2856.5
C45: Ex plant | D45: =+(D41-$F$34+$F$35)/$G$36 -> 76.009227 | E45: =+(E41-$F$34+$F$35)/$G$36 -> 76.009227 | F45: =+(F41-$F$34+$F$35)/$G$36 -> 76.009227 | G45: =+(G41-$F$34+$F$35)/$G$36 -> 76.009227 | H45: =+(H41-$F$34+$F$35)/$G$36 -> 76.009227 | I45: =+(I41-$F$34+$F$35)/$G$36 -> 76.009227 | J45: =+(J41-$F$34+$F$35)/$G$36 -> 76.009227 | K45: =+(K41-$F$34+$F$35)/$G$36 -> 76.009227 | ... P45: =+(P41-$F$34+$F$35)/$G$36 -> 76.009227
C46: net tax | D46: =D41-$F$34 -> -65
C47: Anhydrous ex mill equivalent | D47: =((D41-$F$34)*$G$37)+$F$35 -> 56.8 | E47: =((E41-$F$34)*$G$37)+$F$35 -> 56.8 | F47: =((F41-$F$34)*$G$37)+$F$35 -> 56.8 | G47: =((G41-$F$34)*$G$37)+$F$35 -> 56.8 | H47: =((H41-$F$34)*$G$37)+$F$35 -> 56.8 | I47: =((I41-$F$34)*$G$37)+$F$35 -> 56.8 | J47: =((J41-$F$34)*$G$37)+$F$35 -> 56.8 | K47: =((K41-$F$34)*$G$37)+$F$35 -> 56.8 | ... P47: =((P41-$F$34)*$G$37)+$F$35 -> 56.8
C49: ESALQ RB | D49: =+'settlement day'!$BI$43 -> 0
D50: =+D46-D49 -> -65
D52: =+((D49+$F$35)/$G$36)+H34 -> 215.98039

Sheet INDIA
A1: ='settlement day'!B3 -> 45946 | B1: INDIA
B2: ST ROSE | C2: Freight | D2: =F2/$A$5 -> 0 | E2: usd/cbm | G2: pmt
B3: GALVESTON | C3: Freight | D3: =F3/$A$5 -> 82.382763 | E3: usd/cbm | F3: 65 | G3: pmt
A4: 264.172 | B4: SANTOS | C4: Freight | D4: =F4/$A$5 -> 0 | E4: usd/cbm | G4: pmt
A5: 0.789 | C5: Volume | D5: 20000 | E5: cbm | F5: =D5*A5 -> 15780 | G5: mt
A7: 0.18 | B7: cpg
A8: Basis | B8: US | C8: 45992 | D8: 46023 | E8: 46054 | F8: 46082 | G8: 46113 | H8: 46143 | I8: 46174 | J8: 46204 | K8: 46235 | L8: 46266 | M8: 46296 | N8: 46327 | O8: 46357
B9: CHIP | C9: ='settlement day'!BJ9 -> 1.63 | D9: ='settlement day'!BK9 -> 1.5775 | E9: ='settlement day'!BL9 -> 1.5825 | F9: ='settlement day'!BM9 -> 1.6075 | G9: ='settlement day'!BN9 -> 1.6325 | H9: ='settlement day'!BO9 -> 1.655 | I9: ='settlement day'!BP9 -> 1.6675 | J9: ='settlement day'!BQ9 -> 1.6725 | ... O9: ='settlement day'!BV9 -> 1.5825
B11: FOB US usd/cbm | C11: =+(C9+$A$7)*$A$4 -> 478.15132 | D11: =+(D9+$A$7)*$A$4 -> 464.28229 | E11: =+(E9+$A$7)*$A$4 -> 465.60315 | F11: =+(F9+$A$7)*$A$4 -> 472.20745 | G11: =+(G9+$A$7)*$A$4 -> 478.81175 | H11: =+(H9+$A$7)*$A$4 -> 484.75562 | I11: =+(I9+$A$7)*$A$4 -> 488.05777 | J11: =+(J9+$A$7)*$A$4 -> 489.37863 | ... O11: =+(O9+$A$7)*$A$4 -> 465.60315
B13: CIF INDIA usd/cbm | C13: =+C11+$D$2 -> 478.15132 | D13: =+D11+$D$2 -> 464.28229 | E13: =+E11+$D$2 -> 465.60315 | F13: =+F11+$D$2 -> 472.20745 | G13: =+G11+$D$2 -> 478.81175 | H13: =+H11+$D$2 -> 484.75562 | I13: =+I11+$D$2 -> 488.05777 | J13: =+J11+$D$2 -> 489.37863 | ... O13: =+O11+$D$2 -> 465.60315
B14: Anhydrous CIF INDIA usd/mt | C14: =+C13/$A$5 -> 606.02195 | D14: =+D13/$A$5 -> 588.44397 | E14: =+E13/$A$5 -> 590.11806 | F14: =+F13/$A$5 -> 598.48853 | G14: =+G13/$A$5 -> 606.859 | H14: =+H13/$A$5 -> 614.39242 | I14: =+I13/$A$5 -> 618.57766 | J14: =+J13/$A$5 -> 620.25175 | ... O14: =+O13/$A$5 -> 590.11806
A17: inland
A18: =+'mkt data'!G6+'mkt data'!G8 -> 90 | B18: BRAZIL | C18: 45992 | D18: 46023 | E18: 46054 | F18: 46082 | G18: 46113 | H18: 46143 | I18: 46174 | J18: 46204 | K18: 46235 | L18: 46266 | M18: 46296 | N18: 46327 | O18: 46357
A19: brl/cbm | B19: B3 | C19: ='settlement day'!BJ13 -> 2904.5 | D19: ='settlement day'!BK13 -> 2930 | E19: ='settlement day'!BL13 -> 2950 | F19: ='settlement day'!BM13 -> 2975 | G19: ='settlement day'!BN13 -> 2700 | H19: ='settlement day'!BO13 -> 2420 | I19: ='settlement day'!BP13 -> 2390 | J19: ='settlement day'!BQ13 -> 2485 | ... O19: ='settlement day'!BV13 -> 2605
B20: BRL/USD | C20: ='settlement day'!BJ30 -> 5.5005501 | D20: ='settlement day'!BK30 -> 5.538632 | E20: ='settlement day'!BL30 -> 5.574136 | F20: ='settlement day'!BM30 -> 5.6132473 | G20: ='settlement day'!BN30 -> 5.6561086 | H20: ='settlement day'!BO30 -> 5.6963828 | I20: ='settlement day'!BP30 -> 5.7355893 | J20: ='settlement day'!BQ30 -> 5.7786767 | ... O20: ='settlement day'!BV30 -> 5.9772863
B22: hydrous FOB BRZ | C22: ='FOB origin'!BF20 -> 553.27324 | D22: ='FOB origin'!BG20 -> 554.13414 | E22: ='FOB origin'!BH20 -> 554.24914 | F22: ='FOB origin'!BI20 -> 554.90289 | G22: ='FOB origin'!BJ20 -> 502.14514 | H22: ='FOB origin'!BK20 -> 449.50364 | I22: ='FOB origin'!BL20 -> 441.26114 | J22: ='FOB origin'!BM20 -> 454.47689 | ... O22: ='FOB origin'!BR20 -> 459.74664
A23: 100 | B23: grade B FOB BRZ | C23: ='FOB origin'!BF21 -> 636.90124 | D23: ='FOB origin'!BG21 -> 637.18714 | E23: ='FOB origin'!BH21 -> 636.77314 | F23: ='FOB origin'!BI21 -> 636.85189 | G23: ='FOB origin'!BJ21 -> 583.47314 | H23: ='FOB origin'!BK21 -> 530.25664 | I23: ='FOB origin'!BL21 -> 521.46214 | J23: ='FOB origin'!BM21 -> 534.07989 | ... O23: ='FOB origin'!BR21 -> 536.70464
A24: 1.125 | B24: anhydrous FOB BRZ | C24: ='FOB origin'!BF22 -> 622.50922 | D24: ='FOB origin'!BG22 -> 623.47773 | E24: ='FOB origin'!BH22 -> 623.60711 | F24: ='FOB origin'!BI22 -> 624.34257 | G24: ='FOB origin'!BJ22 -> 564.99011 | H24: ='FOB origin'!BK22 -> 505.76842 | I24: ='FOB origin'!BL22 -> 496.49561 | J24: ='FOB origin'!BM22 -> 511.36332 | ... O24: ='FOB origin'!BR22 -> 517.29179
B26: CIF INDIA usd/cbm | C26: =+C22+$D$4 -> 553.27324 | D26: =+D22+$D$4 -> 554.13414 | E26: =+E22+$D$4 -> 554.24914 | F26: =+F22+$D$4 -> 554.90289 | G26: =+G22+$D$4 -> 502.14514 | H26: =+H22+$D$4 -> 449.50364 | I26: =+I22+$D$4 -> 441.26114 | J26: =+J22+$D$4 -> 454.47689 | ... O26: =+O22+$D$4 -> 459.74664
B27: hydrous CIF INDIA usd/mt | C27: =+C26/$A$5 -> 701.23352 | D27: =+D26/$A$5 -> 702.32464 | E27: =+E26/$A$5 -> 702.4704 | F27: =+F26/$A$5 -> 703.29898 | G27: =+G26/$A$5 -> 636.43238 | H27: =+H26/$A$5 -> 569.71311 | I27: =+I26/$A$5 -> 559.26634 | J27: =+J26/$A$5 -> 576.01634 | ... O27: =+O26/$A$5 -> 582.69537
A29: 1.07 | B29: water discount
B30: hydrous net back value compared to anhydrous US | C30: =C11/$A$29 -> 446.87039 | D30: =D11/$A$29 -> 433.90868 | E30: =E11/$A$29 -> 435.14313 | F30: =F11/$A$29 -> 441.31537 | G30: =G11/$A$29 -> 447.48762 | H30: =H11/$A$29 -> 453.04264 | I30: =I11/$A$29 -> 456.12876 | J30: =J11/$A$29 -> 457.36321 | ... O30: =O11/$A$29 -> 435.14313
B31: diff Brazilian FOB vs US | C31: =C22-C30 -> 106.40285 | D31: =D22-D30 -> 120.22546 | E31: =E22-E30 -> 119.10601 | F31: =F22-F30 -> 113.58752 | G31: =G22-G30 -> 54.657528 | H31: =H22-H30 -> -3.5389907 | I31: =I22-I30 -> -14.867612 | J31: =J22-J30 -> -2.8863108 | ... O31: =O22-O30 -> 24.603514
B34: CIF vs CIF pmt | C34: =C27-C14 -> 95.211565 | D34: =D27-D14 -> 113.88068 | E34: =E27-E14 -> 112.35234 | F34: =F27-F14 -> 104.81045 | G34: =G27-G14 -> 29.573377 | H34: =H27-H14 -> -44.679309 | I34: =I27-I14 -> -59.311312 | J34: =J27-J14 -> -44.235406 | ... O34: =O27-O14 -> -7.4226935
A39: 100 | B39: bid premium pmt
A40: 9 | B40: costs
B41: India indicative bid anhydrous
B42: CIF India usd/mt | C42: =((C9*$A$4)/$A$5)+$A$39 -> 645.75458 | D42: =((D9*$A$4)/$A$5)+$A$39 -> 628.17659 | E42: =((E9*$A$4)/$A$5)+$A$39 -> 629.85068 | F42: =((F9*$A$4)/$A$5)+$A$39 -> 638.22115 | G42: =((G9*$A$4)/$A$5)+$A$39 -> 646.59162 | H42: =((H9*$A$4)/$A$5)+$A$39 -> 654.12504 | I42: =((I9*$A$4)/$A$5)+$A$39 -> 658.31028 | J42: =((J9*$A$4)/$A$5)+$A$39 -> 659.98437 | ... O42: =((O9*$A$4)/$A$5)+$A$39 -> 629.85068
B43: FOB US usd/mt | C43: =C42+$A$40+$F$3 -> 719.75458 | D43: =D42+$A$40+$F$3 -> 702.17659 | E43: =E42+$A$40+$F$3 -> 703.85068 | F43: =F42+$A$40+$F$3 -> 712.22115 | G43: =G42+$A$40+$F$3 -> 720.59162 | H43: =H42+$A$40+$F$3 -> 728.12504 | I43: =I42+$A$40+$F$3 -> 732.31028 | J43: =J42+$A$40+$F$3 -> 733.98437 | ... O43: =O42+$A$40+$F$3 -> 703.85068
B44: FOB US usd/cbm | C44: =C43*$A$5 -> 567.88636 | D44: =D43*$A$5 -> 554.01733 | E44: =E43*$A$5 -> 555.33819 | F44: =F43*$A$5 -> 561.94249 | G44: =G43*$A$5 -> 568.54679 | H44: =H43*$A$5 -> 574.49066 | I44: =I43*$A$5 -> 577.79281 | J44: =J43*$A$5 -> 579.11367 | ... O44: =O43*$A$5 -> 555.33819
B45: FOB US cpg CHIP | C45: =(C44/$A$4)-C9 -> 0.51968415 | D45: =(D44/$A$4)-D9 -> 0.51968415 | E45: =(E44/$A$4)-E9 -> 0.51968415 | F45: =(F44/$A$4)-F9 -> 0.51968415 | G45: =(G44/$A$4)-G9 -> 0.51968415 | H45: =(H44/$A$4)-H9 -> 0.51968415 | I45: =(I44/$A$4)-I9 -> 0.51968415 | J45: =(J44/$A$4)-J9 -> 0.51968415 | ... O45: =(O44/$A$4)-O9 -> 0.51968415
A47: 1.07 | B47: water discount
B48: India indicative bid hydrous
B49: FOB BRZ usd/cbm | C49: =C44/$A$47 -> 530.73492 | D49: =D44/$A$47 -> 517.77321 | E49: =E44/$A$47 -> 519.00765 | F49: =F44/$A$47 -> 525.1799 | G49: =G44/$A$47 -> 531.35214 | H49: =H44/$A$47 -> 536.90716 | I49: =I44/$A$47 -> 539.99328 | J49: =J44/$A$47 -> 541.22773 | ... O49: =O44/$A$47 -> 519.00765
C59: 0.789
C60: 264.172 | E60: june | I60: Raizen 22/4/21 -- FX 5.44
C61: chip cbm | D61: =+E61*C60 -> 418.05219 | E61: =+E9 -> 1.5825 | I61: 629 | J61: usd/cbm FOB
C62: chip pmt | D62: =+D61/C59 -> 529.85068 | I62: =+I61/A5 -> 797.21166 | J62: usd/mt FOB
C63: bid premium pmt | D63: 100 | I63: =+I62+45 -> 842.21166 | J63: usd/mt CIF
C64: bid CIF WCI | D64: =+D62+D63 -> 629.85068 | E64: pmt
D65: =+'Freight matrix'!G12 -> 65 | E65: pmt
D66: 9 | E66: pmt
D67: =+D64-D65-D66 -> 555.85068 | E67: pmt fob
C69: anhydrous | D69: =+D67*0.789 -> 438.56619 | E69: cbm fob | F69: =+D69/C60 -> 1.660154
F70: =+F69-E61 -> 0.077653953
C71: hydrous | D71: =+D69/1.07 -> 409.87494 | E71: cbm fob
D73: =130/5.65 -> 23.00885

Sheet FOB origin
C1: FOB ORIGIN
B2: 264.172
B3: 0.789
B4: 0.1 | AH4: =+(AH9+$B$4)*$B$2 -> 26.4172 | AI4: =+(AI9+$B$4)*$B$2 -> 26.4172 | AJ4: =+(AJ9+$B$4)*$B$2 -> 26.4172 | AK4: =+(AK9+$B$4)*$B$2 -> 26.4172 | AL4: =+(AL9+$B$4)*$B$2 -> 26.4172 | AM4: =+(AM9+$B$4)*$B$2 -> 26.4172 | AN4: =+(AN9+$B$4)*$B$2 -> 26.4172 | AO4: =+(AO9+$B$4)*$B$2 -> 26.4172 | ... BR4: =+(BR9+$B$4)*$B$2 -> 444.46939
C6: FOB ORIGIN | D6: 44317 | E6: 44378 | F6: 44409 | G6: 44440 | H6: 44470 | I6: 44501 | J6: 44531 | K6: 44562 | L6: 44593 | M6: 44621 | N6: 44652 | O6: 44682 | P6: 44713 | Q6: 44743 | R6: 44774 | S6: 44805 | T6: 44835 | U6: 44866 | V6: 44896 | W6: 44927 | X6: 44958 | Y6: 44986 | Z6: 45017 | AA6: 45047 | AB6: 45078 | AC6: 45108 | AD6: 45139 | AE6: 45170 | AF6: 45200 | AG6: 45231 | AH6: 45261 | AI6: 45292 | AJ6: 45323 | AK6: 45352 | AL6: 45383 | AM6: 45413 | AN6: 45444 | AO6: 45474 | AP6: 45505 | AQ6: 45536 | AR6: 45566 | AS6: 45597 | AT6: 45627 | AU6: 45658 | AV6: 45689 | AW6: 45717 | AX6: 45748 | AY6: 45778 | AZ6: 45809 | BA6: 45839 | BB6: 45870 | BC6: 45901 | BD6: 45931 | BE6: 45962 | BF6: 45992 | BG6: 46023 | BH6: 46054 | BI6: 46082 | BJ6: 46113 | BK6: 46143 | BL6: 46174 | BM6: 46204 | BN6: 46235 | BO6: 46266 | BP6: 46296 | BQ6: 46327 | BR6: 46357 | BT6: Cbios | BU6: CBio unit | BV6: per vol HYD | BW6: per vol ANH
C7: USGC | BT7: R$ | BU7: =+'settlement day'!BO42 -> 41.25 | BV7: =+'settlement day'!BP42 -> 44.212219 | BW7: =+'settlement day'!BQ42 -> 50.121507
C8: D-1 | D8: =+'settlement day'!G11 -> 0 | E8: =+'settlement day'!I11 -> 0 | F8: =+'settlement day'!J11 -> 0 | G8: =+'settlement day'!K11 -> 0 | H8: =+'settlement day'!L11 -> 0 | I8: =+'settlement day'!M11 -> 0 | J8: =+'settlement day'!N11 -> 0 | K8: =+'settlement day'!O11 -> 0 | L8: =+'settlement day'!P11 -> 0 | ... BR8: =+'settlement day'!BV11 -> 0 | BT8: U$ | BU8: =+'settlement day'!BO43 -> 8.2786441 | BV8: =+'settlement day'!BP43 -> 8.8731448 | BW8: =+'settlement day'!BQ43 -> 10.059106
C9: CHIP | D9: =+'settlement day'!G9 -> 0 | E9: =+'settlement day'!I9 -> 0 | F9: =+'settlement day'!J9 -> 0 | G9: =+'settlement day'!K9 -> 0 | H9: =+'settlement day'!L9 -> 0 | I9: =+'settlement day'!M9 -> 0 | J9: =+'settlement day'!N9 -> 0 | K9: =+'settlement day'!O9 -> 0 | L9: =+'settlement day'!P9 -> 0 | ... BR9: =+'settlement day'!BV9 -> 1.5825 | BV9: =+BW8-BV8 -> 1.185961
B11: 0.1 | C11: FOB US IMTT - D12 | D11: =+(D9+$B$11)*$B$2 -> 26.4172 | E11: =+(E9+$B$11)*$B$2 -> 26.4172 | F11: =+(F9+$B$11)*$B$2 -> 26.4172 | G11: =+(G9+$B$11)*$B$2 -> 26.4172 | H11: =+(H9+$B$11)*$B$2 -> 26.4172 | I11: =+(I9+$B$11)*$B$2 -> 26.4172 | J11: =+(J9+$B$11)*$B$2 -> 26.4172 | K11: =+(K9+$B$11)*$B$2 -> 26.4172 | ... BR11: =+(BR9+$B$11)*$B$2 -> 444.46939
A12: 0.08 | B12: =+'mkt data'!G14 -> 0.27 | C12: FOB US IMTT - U3 | D12: =+(D9+$B$12)*$B$2 -> 71.32644 | E12: =+(E9+$B$12)*$B$2 -> 71.32644 | F12: =+(F9+$B$12)*$B$2 -> 71.32644 | G12: =+(G9+$B$12)*$B$2 -> 71.32644 | H12: =+(H9+$B$12)*$B$2 -> 71.32644 | I12: =+(I9+$B$12)*$B$2 -> 71.32644 | J12: =+(J9+$B$12)*$B$2 -> 71.32644 | K12: =+(K9+$B$12)*$B$2 -> 71.32644 | ... BF12: =+(BF9+$B$12)*$B$2 -> 501.9268 | BG12: =+(BG9+$B$12+$A$12)*$B$2 -> 509.19153 | BH12: =+(BH9+$B$12+$A$12)*$B$2 -> 510.51239 | BI12: =+(BI9+$B$12+$A$12)*$B$2 -> 517.11669 | BJ12: =+(BJ9+$B$12+$A$12)*$B$2 -> 523.72099 | BK12: =+(BK9+$B$12+$A$12)*$B$2 -> 529.66486 | BL12: =+(BL9+$B$12+$A$12)*$B$2 -> 532.96701 | BM12: =+(BM9+$B$12+$A$12)*$B$2 -> 534.28787 | BN12: =+(BN9+$B$12+$A$12)*$B$2 -> 532.96701 | ... BR12: =+(BR9+$B$12+$A$12)*$B$2 -> 510.51239
C14: BRAZIL CS
B15: inland | C15: D-1 | D15: =+'settlement day'!G15 -> 0 | E15: =+'settlement day'!I15 -> 0 | F15: =+'settlement day'!J15 -> 0 | G15: =+'settlement day'!K15 -> 0 | H15: =+'settlement day'!L15 -> 0 | I15: =+'settlement day'!M15 -> 0 | J15: =+'settlement day'!N15 -> 0 | K15: =+'settlement day'!O15 -> 0 | L15: =+'settlement day'!P15 -> 0 | ... BR15: =+'settlement day'!BV15 -> 0
B16: =+'mkt data'!G23 -> 90 | C16: B3 ETH Brazil | D16: =+'settlement day'!G13 -> 0 | E16: =+'settlement day'!I13 -> 0 | F16: =+'settlement day'!J13 -> 0 | G16: =+'settlement day'!K13 -> 0 | H16: =+'settlement day'!L13 -> 0 | I16: =+'settlement day'!M13 -> 0 | J16: =+'settlement day'!N13 -> 0 | K16: =+'settlement day'!O13 -> 0 | L16: =+'settlement day'!P13 -> 0 | ... BR16: =+'settlement day'!BV13 -> 2605
B17: brl/cbm | C17: BRL/USD | D17: =+'settlement day'!G30 -> 0 | E17: =+'settlement day'!I30 -> 0 | F17: =+'settlement day'!J30 -> 0 | G17: =+'settlement day'!K30 -> 0 | H17: =+'settlement day'!L30 -> 0 | I17: =+'settlement day'!M30 -> 0 | J17: =+'settlement day'!N30 -> 0 | K17: =+'settlement day'!O30 -> 0 | L17: =+'settlement day'!P30 -> 0 | ... BR17: =+'settlement day'!BV30 -> 5.9772863 | BT17: ADD CBIO VALUE , factor for HYDROUS and ANHYDROUS
BV18: HYD | BW18: ANH
B20: =+(B31+B32)-B16 -> 460 | C20: Hydrous FOB BRZ | D20: =+(D16+$B$16)/D17 -> #DIV/0! | E20: =+(E16+$B$16)/E17 -> #DIV/0! | F20: =+(F16+$B$16)/F17 -> #DIV/0! | G20: =+(G16+$B$16)/G17 -> #DIV/0! | H20: =+(H16+$B$16)/H17 -> #DIV/0! | I20: =+(I16+$B$16)/I17 -> #DIV/0! | J20: =+(J16+$B$16)/J17 -> #DIV/0! | K20: =+(K16+$B$16)/K17 -> #DIV/0! | L20: =+((L16+$B$16)/L17)+BV8 -> #DIV/0! | M20: =+((M16+$B$16)/M17)+$BV$8 -> #DIV/0! | N20: =+((N16+$B$16)/N17)+$BV$8 -> #DIV/0! | O20: =+((O16+$B$16)/O17)+$BV$8 -> #DIV/0! | P20: =+((P16+$B$16)/P17)+$BV$8 -> #DIV/0! | Q20: =+((Q16+$B$16)/Q17)+$BV$8 -> #DIV/0! | R20: =+((R16+$B$16)/R17)+$BV$8 -> #DIV/0! | S20: =+((S16+$B$16)/S17)+$BV$8 -> #DIV/0! | T20: =+((T16+$B$16)/T17)+$BV$8 -> #DIV/0! | ... BR20: =+((BR16+$B$16)/BR17)+$BV$8 -> 459.74664 | BU20: cbio $/cbm | BV20: 23.533119 | BW20: 24.609798
B21: =+'mkt data'!H2 -> 1.125 | C21: Grade B FOB BRZ | D21: =+D20+($B$20/D17) -> #DIV/0! | E21: =+E20+($B$20/E17) -> #DIV/0! | F21: =+F20+($B$20/F17) -> #DIV/0! | G21: =+G20+($B$20/G17) -> #DIV/0! | H21: =+H20+($B$20/H17) -> #DIV/0! | I21: =+I20+($B$20/I17) -> #DIV/0! | J21: =+J20+($B$20/J17) -> #DIV/0! | K21: =+K20+($B$20/K17) -> #DIV/0! | ... BR21: =+BR20+($B$20/BR17) -> 536.70464
B22: =+EU!BG3 -> 0 | C22: Anhydrous FOB BRZ | D22: =+D20*$B$21 -> #DIV/0! | E22: =+E20*$B$21 -> #DIV/0! | F22: =+F20*$B$21 -> #DIV/0! | G22: =+G20*$B$21 -> #DIV/0! | H22: =+H20*$B$21+$B$22 -> #DIV/0! | I22: =+I20*$B$21+$B$22 -> #DIV/0! | J22: =+J20*$B$21+$B$22 -> #DIV/0! | K22: =+K20*$B$21+$B$22 -> #DIV/0! | L22: =+L20*$B$21+$B$22+$BW$8 -> #DIV/0! | M22: =+M20*$B$21+$B$22+$BW$8 -> #DIV/0! | N22: =+N20*$B$21+$B$22+$BW$8 -> #DIV/0! | O22: =+O20*$B$21+$B$22+$BW$8 -> #DIV/0! | P22: =+P20*$B$21+$B$22+$BW$8 -> #DIV/0! | Q22: =+Q20*$B$21+$B$22+$BW$8 -> #DIV/0! | R22: =+R20*$B$21+$B$22+$BW$8 -> #DIV/0! | S22: =+S20*$B$21+$B$22+$BW$8 -> #DIV/0! | ... W22: =+W20*$B$21+$B$22+$BW$8 -> #DIV/0! | X22: =+(X20-$BV$8)*$B$21+$B$22+$BW$8 -> #DIV/0! | Y22: =+(Y20-$BV$8)*$B$21+$B$22+$BW$8 -> #DIV/0! | Z22: =+(Z20-$BV$8)*$B$21+$B$22+$BW$8 -> #DIV/0! | AA22: =+(AA20-$BV$8)*$B$21+$B$22+$BW$8 -> #DIV/0! | AB22: =+(AB20-$BV$8)*$B$21+$B$22+$BW$8 -> #DIV/0! | AC22: =+(AC20-$BV$8)*$B$21+$B$22+$BW$8 -> #DIV/0! | AD22: =+(AD20-$BV$8)*$B$21+$B$22+$BW$8 -> #DIV/0! | AE22: =+(AE20-$BV$8)*$B$21+$B$22+$BW$8 -> #DIV/0! | ... BR22: =+(BR20-$BV$8)*$B$21+$B$22+$BW$8 -> 517.29179 | BY22: 520
C23: hyd CHIP basis net back cpg | AI23: =+((AI20/264.172)-AI9)*100 -> 10.23739 | AJ23: =+((AJ20/264.172)-AJ9)*100 -> 10.196251 | AK23: =+((AK20/264.172)-AK9)*100 -> 10.178595 | AL23: =+((AL20/264.172)-AL9)*100 -> 9.9470152 | AM23: =+((AM20/264.172)-AM9)*100 -> 9.8592736 | AN23: =+((AN20/264.172)-AN9)*100 -> 9.4881918 | AO23: =+((AO20/264.172)-AO9)*100 -> 9.3764638 | AP23: =+((AP20/264.172)-AP9)*100 -> 9.3827415 | ... BR23: =+((BR20/264.172)-BR9)*100 -> 15.783071 | BY23: =40*0.789 -> 31.56
B24: 1 | C24: Anhydrous FOB- flat hyd | D24: =+D22*$B$21 -> #DIV/0! | E24: =+E22*$B$21 -> #DIV/0! | F24: =+F22*$B$21 -> #DIV/0! | G24: =+G22*$B$21 -> #DIV/0! | H24: =+H22*$B$21+$B$22 -> #DIV/0! | I24: =+I22*$B$21+$B$22 -> #DIV/0! | J24: =+J22*$B$21+$B$22 -> #DIV/0! | K24: =+K22*$B$21+$B$22 -> #DIV/0! | L24: =+L22*$B$21+$B$22+$BW$8 -> #DIV/0! | M24: =+M22*$B$21+$B$22+$BW$8 -> #DIV/0! | N24: =+N22*$B$21+$B$22+$BW$8 -> #DIV/0! | O24: =+O22*$B$21+$B$22+$BW$8 -> #DIV/0! | P24: =+P22*$B$21+$B$22+$BW$8 -> #DIV/0! | Q24: =+Q22*$B$21+$B$22+$BW$8 -> #DIV/0! | R24: =+R22*$B$21+$B$22+$BW$8 -> #DIV/0! | S24: =+S22*$B$21+$B$22+$BW$8 -> #DIV/0! | ... W24: =+W22*$B$21+$B$22+$BW$8 -> #DIV/0! | X24: =+(X22-$BV$8)*$B$21+$B$22+$BW$8 -> #DIV/0! | Y24: =+(Y22-$BV$8)*$B$21+$B$22+$BW$8 -> #DIV/0! | Z24: =+(Z22-$BV$8)*$B$21+$B$22+$BW$8 -> #DIV/0! | AA24: =+(AA22-$BV$8)*$B$21+$B$22+$BW$8 -> #DIV/0! | AB24: =+(AB22-$BV$8)*$B$21+$B$22+$BW$8 -> #DIV/0! | AC24: =+(AC22-$BV$8)*$B$21+$B$22+$BW$8 -> #DIV/0! | AD24: =+(AD22-$BV$8)*$B$21+$B$22+$BW$8 -> #DIV/0! | AE24: =+(AE22-$BV$8)*$B$21+$B$22+$BW$8 -> #DIV/0! | ... AK24: =+(AK22-$BV$8)*$B$21+$B$22+$BW$8 -> 34.194627 | AL24: =+(AL20-$BV$8)*$B$24+$B$22+$BW$8 -> 27.46319 | AM24: =+(AM20-$BV$8)*$B$24+$B$22+$BW$8 -> 27.231401 | AN24: =+(AN20-$BV$8)*$B$24+$B$22+$BW$8 -> 26.251107 | AO24: =+(AO20-$BV$8)*$B$24+$B$22+$BW$8 -> 25.955953 | AP24: =+(AP20-$BV$8)*$B$24+$B$22+$BW$8 -> 25.972537 | AQ24: =+(AQ20-$BV$8)*$B$24+$B$22+$BW$8 -> 26.580446 | AR24: =+(AR20-$BV$8)*$B$24+$B$22+$BW$8 -> 25.558443 | AS24: =+(AS20-$BV$8)*$B$24+$B$22+$BW$8 -> 24.928012 | ... BR24: =+(BR20-$BV$8)*$B$24+$B$22+$BW$8 -> 460.93261 | BY24: =+BY22+BY23 -> 551.56
BY25: =+BY24/264.172 -> 2.0878821
C26: diff anhydrous/hydrous | AM26: =+AM22-AM20 -> 3.332498 | AN26: =+AN22-AN20 -> 3.2099612 | AO26: =+AO22-AO20 -> 3.1730669 | AP26: =+AP22-AP20 -> 3.1751399 | AQ26: =+AQ22-AQ20 -> 3.2511285 | AR26: =+AR22-AR20 -> 3.1233782 | AS26: =+AS22-AS20 -> 3.0445743 | AT26: =+AT22-AT20 -> 3.0029095 | ... AW26: =+AW22-AW20 -> 3.1453452 | AZ26: =AZ22-AZ12 -> -42.711483 | BA26: =BA22-BA12 -> -43.191819 | BB26: =BB22-BB12 -> -42.645617 | BC26: =BC22-BC12 -> -42.228222 | BK26: =BK12-BK22 -> 23.896442 | BL26: =BL12-BL22 -> 36.471404 | BM26: =BM12-BM22 -> 22.924545 | BN26: =BN12-BN22 -> 25.079935 | BO26: =BO12-BO22 -> 27.235325 | BP26: =BP12-BP22 -> 6.8005567 | BQ26: =BQ12-BQ22 -> -0.38159584 | BR26: =BR12-BR22 -> -6.7794033 | BY26: =+BY25-BK9 -> 0.43288214
BU27: ANH EU | BV27: =750+BW20 -> 774.6098 | BW27: =+BV27/264.172 -> 2.9322176
K28: 44562 | L28: 44593 | M28: 44621 | N28: 44652 | O28: 44682 | P28: 44713 | Q28: 44743 | R28: 44774 | S28: 44805 | T28: 44835 | U28: 44866 | V28: 44896 | W28: 44927 | X28: 44958 | Y28: 44986 | Z28: 45017 | AA28: 45047 | AB28: 45078 | AC28: 45108 | AD28: 45139 | AE28: 45170 | AF28: 45200 | AG28: 45231 | AH28: 45261 | AI28: 45292 | AJ28: 45323 | AK28: 45352 | AL28: 45383 | AM28: 45413 | AN28: 45444 | AO28: 45474 | AP28: 45505 | AQ28: 45536 | AR28: 45566 | AS28: 45597 | AT28: 45627 | AU28: 45658 | AV28: 45689 | AW28: 45717 | AX28: 45748 | AY28: 45778 | AZ28: 45809 | BA28: 45839 | BB28: 45870 | BC28: 45901 | BD28: 45931 | BE28: 45962 | BF28: 45992 | BG28: 46023 | BH28: 46054 | BI28: 46082 | BJ28: 46113 | BK28: 46143 | BL28: 46174 | BM28: 46204 | BN28: 46235 | BO28: 46266 | BP28: 46296 | BQ28: 46327 | BR28: 46357
C29: Grade B ind offer
C30: B3 | K30: =+K16 -> 0 | L30: =+L16 -> 0 | M30: =+M16 -> 0 | N30: =+N16 -> 0 | O30: =+O16 -> 0 | P30: =+P16 -> 0 | Q30: =+Q16 -> 0 | R30: =+R16 -> 0 | ... BR30: =+BR16 -> 2605
B31: 300 | C31: Fobbing | K31: =+$B$31 -> 300 | L31: =+$B$31 -> 300 | M31: =+$B$31 -> 300 | N31: =+$B$31 -> 300 | O31: =+$B$31 -> 300 | P31: =+$B$31 -> 300 | Q31: =+$B$31 -> 300 | R31: =+$B$31 -> 300 | ... BR31: =+$B$31 -> 300
B32: 250 | C32: Premium | K32: =+$B$32 -> 250 | L32: =+$B$32 -> 250 | M32: =+$B$32 -> 250 | N32: =+$B$32 -> 250 | O32: =+$B$32 -> 250 | P32: =+$B$32 -> 250 | Q32: =+$B$32 -> 250 | R32: =+$B$32 -> 250 | ... BR32: =+$B$32 -> 250
B33: =+BV7 -> 44.212219 | C33: Cbios | L33: =+$B$33 -> 44.212219 | M33: =+$B$33 -> 44.212219 | N33: =+$B$33 -> 44.212219 | O33: =+$B$33 -> 44.212219 | P33: =+$B$33 -> 44.212219 | Q33: =+$B$33 -> 44.212219 | R33: =+$B$33 -> 44.212219 | S33: =+$B$33 -> 44.212219 | ... BR33: =+$B$33 -> 44.212219
C34: FOB Sts R$/cbm | K34: =SUM(K30:K32) -> 550 | L34: =SUM(L30:L33) -> 594.21222 | M34: =SUM(M30:M33) -> 594.21222 | N34: =SUM(N30:N33) -> 594.21222 | O34: =SUM(O30:O33) -> 594.21222 | P34: =SUM(P30:P33) -> 594.21222 | Q34: =SUM(Q30:Q33) -> 594.21222 | R34: =SUM(R30:R33) -> 594.21222 | S34: =SUM(S30:S33) -> 594.21222 | ... BR34: =SUM(BR30:BR33) -> 3199.2122
C36: FOB Sts usd/cbm | K36: =+K34/K17 -> #DIV/0! | L36: =+L34/L17 -> #DIV/0! | M36: =+M34/M17 -> #DIV/0! | N36: =+N34/N17 -> #DIV/0! | O36: =+O34/O17 -> #DIV/0! | P36: =+P34/P17 -> #DIV/0! | Q36: =+Q34/Q17 -> #DIV/0! | R36: =+R34/R17 -> #DIV/0! | ... BR36: =+BR34/BR17 -> 535.2282 | BT36: =AVERAGE(Q36:S36) -> #DIV/0! | BU36: =+BT36/264.172 -> #DIV/0!
C37: FOB Sts usd/gal | K37: =+K36/$B$2 -> #DIV/0! | L37: =+L36/$B$2 -> #DIV/0! | M37: =+M36/$B$2 -> #DIV/0! | N37: =+N36/$B$2 -> #DIV/0! | O37: =+O36/$B$2 -> #DIV/0! | P37: =+P36/$B$2 -> #DIV/0! | Q37: =+Q36/$B$2 -> #DIV/0! | R37: =+R36/$B$2 -> #DIV/0! | ... BR37: =+BR36/$B$2 -> 2.0260596
C38: CHIP | K38: =+K9 -> 0 | L38: =+L9 -> 0 | M38: =+M9 -> 0 | N38: =+N9 -> 0 | O38: =+O9 -> 0 | P38: =+P9 -> 0 | Q38: =+Q9 -> 0 | R38: =+R9 -> 0 | ... BR38: =+BR9 -> 1.5825
C39: grade b basis usg | K39: =+K37-K38 -> #DIV/0! | L39: =+L37-L38 -> #DIV/0! | M39: =+M37-M38 -> #DIV/0! | N39: =+N37-N38 -> #DIV/0! | O39: =+O37-O38 -> #DIV/0! | P39: =+P37-P38 -> #DIV/0! | Q39: =+Q37-Q38 -> #DIV/0! | R39: =+R37-R38 -> #DIV/0! | ... BR39: =+BR37-BR38 -> 0.44355955
B41: =+'mkt data'!G18 -> 0.3 | C41: Grade B USA
C42: CHIP | K42: =+K9 -> 0 | L42: =+L9 -> 0 | M42: =+M9 -> 0 | N42: =+N9 -> 0 | O42: =+O9 -> 0 | P42: =+P9 -> 0 | Q42: =+Q9 -> 0 | R42: =+R9 -> 0 | ... BR42: =+BR9 -> 1.5825
C43: FOB USG usd/gal | K43: =+K42+$B$41 -> 0.3 | L43: =+L42+$B$41 -> 0.3 | M43: =+M42+$B$41 -> 0.3 | N43: =+N42+$B$41 -> 0.3 | O43: =+O42+$B$41 -> 0.3 | P43: =+P42+$B$41 -> 0.3 | Q43: =+Q42+$B$41 -> 0.3 | R43: =+R42+$B$41 -> 0.3 | ... BR43: =+BR42+$B$41 -> 1.8825
C44: FOB USG usd/cbm | K44: =+K43*$B$2 -> 79.2516 | L44: =+L43*$B$2 -> 79.2516 | M44: =+M43*$B$2 -> 79.2516 | N44: =+N43*$B$2 -> 79.2516 | O44: =+O43*$B$2 -> 79.2516 | P44: =+P43*$B$2 -> 79.2516 | Q44: =+Q43*$B$2 -> 79.2516 | R44: =+R43*$B$2 -> 79.2516 | ... BR44: =+BR43*$B$2 -> 497.30379
A47: pmt | B47: $/cbm | C47: Anhydrous CIF USGC | L47: 44593 | M47: 44621 | N47: 44652 | O47: 44682 | P47: 44713 | Q47: 44743 | R47: 44774 | S47: 44805 | T47: 44835 | U47: 44866 | V47: 44896 | AB47: pmt | AC47: $/cbm | AD47: 10kcbm = USD 45-48 pmt
A48: 48 | B48: =+A48*$B$3 -> 37.872 | C48: 10kcbm | L48: =+$L$22+B48 -> #DIV/0! | M48: =+$M$22+B48 -> #DIV/0! | N48: =+$N$22+$B$48 -> #DIV/0! | O48: =+$O$22+$B$48 -> #DIV/0! | P48: =+$P$22+$B$48 -> #DIV/0! | Q48: =+$Q$22+$B$48 -> #DIV/0! | R48: =+$R$22+$B$48 -> #DIV/0! | S48: =+$S$22+$B$48 -> #DIV/0! | T48: =+$T$22+$B$48 -> #DIV/0! | U48: =+$U$22+$B$48 -> #DIV/0! | V48: =+$V$22+$B$48 -> #DIV/0! | AB48: 48 | AC48: =+AB48*$B$3 -> 37.872 | AD48: 20kcbm = USD 33-35 pmt
A49: 35 | B49: =+A49*$B$3 -> 27.615 | C49: 20kcbm | L49: =+$L$22+B49 -> #DIV/0! | M49: =+$M$22+B49 -> #DIV/0! | N49: =+$N$22+$B$49 -> #DIV/0! | O49: =+$O$22+$B$49 -> #DIV/0! | P49: =+$P$22+$B$49 -> #DIV/0! | Q49: =+$Q$22+$B$49 -> #DIV/0! | R49: =+$R$22+$B$49 -> #DIV/0! | S49: =+$S$22+$B$49 -> #DIV/0! | T49: =+$T$22+$B$49 -> #DIV/0! | U49: =+$U$22+$B$49 -> #DIV/0! | V49: =+$V$22+$B$49 -> #DIV/0! | AB49: 35 | AC49: =+AB49*$B$3 -> 27.615 | AD49: 40kcbm = USD 25-27 pmt (right now looking like low 30s pmt) *MR market fluctuates more
A50: 27 | B50: =+A50*$B$3 -> 21.303 | C50: 40kcbm | L50: =+$L$22+B50 -> #DIV/0! | M50: =+$M$22+B50 -> #DIV/0! | N50: =+$N$22+$B$50 -> #DIV/0! | O50: =+$O$22+$B$50 -> #DIV/0! | P50: =+$P$22+$B$50 -> #DIV/0! | Q50: =+$Q$22+$B$50 -> #DIV/0! | R50: =+$R$22+$B$50 -> #DIV/0! | S50: =+$S$22+$B$50 -> #DIV/0! | T50: =+$T$22+$B$50 -> #DIV/0! | U50: =+$U$22+$B$50 -> #DIV/0! | V50: =+$V$22+$B$50 -> #DIV/0! | AB50: 27 | AC50: =+AB50*$B$3 -> 21.303

Sheet EU
B1: 264.172
B2: 0.789 | BF2: Cbios | BG2: =+'FOB origin'!BW8 -> 10.059106 | BH2: usd/cbm
C3: usd/cbm | AV3: FREIGHT | BC3: pmt | BF3: Export + BonSucro premium | BG3: 0 | BH3: usd/cbm
B4: USA | C4: =+BC4*B2 -> 35.505 | AV4: ST ROSE | BC4: 45 | BF4: Premiun EN Grade USA | BG4: =+'mkt data'!G14 -> 0.27 | BH4: usd/gal | BI4: ='FOB origin'!A12 -> 0.08 | BJ4: =BG4+BI4 -> 0.35
B5: BRZ | C5: =+BC5*B2 -> 43.395 | AV5: SANTOS | BC5: 55 | BF5: T2 CIF discount | BG5: 0 | BH5: eur/cbm
C6: 20000 | BC6: cbm | BF6: EU import duty (den) | BG6: 102 | BH6: eur/cbm
BF7: EU import duty (und) | BG7: 192 | BH7: eur/cbm
C10: CHIP | D10: =+'settlement day'!I9 -> 0 | E10: =+'settlement day'!J9 -> 0 | F10: =+'settlement day'!K9 -> 0 | G10: =+'settlement day'!L9 -> 0 | H10: =+'settlement day'!M9 -> 0 | I10: =+'settlement day'!N9 -> 0 | J10: =+'settlement day'!O9 -> 0 | K10: =+'settlement day'!P9 -> 0 | ... BQ10: =+'settlement day'!BV9 -> 1.5825
D11: JUL | E11: AUG | F11: SEP | G11: OCT | H11: NOV | I11: DEC | J11: JAN | K11: FEB | L11: MAR | M11: APR | N11: MAY | O11: JUN | P11: JUL | Q11: AUG | R11: SEP | S11: OCT | T11: NOV | U11: DEC | V11: JAN | W11: FEB | X11: MAR | Y11: APR | Z11: MAY | AA11: JUN | AB11: JUL | AC11: AUG | AD11: SEP | AE11: OCT | AF11: NOV | AG11: DEC | AH11: JAN | AI11: FEB | AJ11: MAR | AK11: APR | AL11: MAY | AM11: JUN | AN11: JUL | AO11: AUG | AP11: SEP | AQ11: OCT | AR11: NOV | AS11: DEC | AT11: JAN | AU11: FEB | AV11: MAR | AW11: APR | AX11: MAY | AY11: JUN | AZ11: JUL | BA11: AUG | BB11: SEP | BC11: OCT | BD11: NOV | BE11: DEC | BF11: JAN | BG11: FEB | BH11: MAR | BI11: APR | BJ11: MAY | BK11: JUN | BL11: JUL | BM11: AUG | BN11: SEPT | BO11: OCT | BP11: NOV | BQ11: DEC
C12: T2 eur/cbm | D12: =+'settlement day'!I5 -> 0 | E12: =+'settlement day'!J5 -> 0 | F12: =+'settlement day'!K5 -> 0 | G12: =+'settlement day'!L5 -> 0 | H12: =+'settlement day'!M5 -> 0 | I12: =+'settlement day'!N5 -> 0 | J12: =+'settlement day'!O5 -> 0 | K12: =+'settlement day'!P5 -> 0 | ... BQ12: =+'settlement day'!BV5 -> 610
C13: T1 eur/cbm - ind bid | D13: =+D12-$BG$6-$BG$5 -> -102 | E13: =+E12-$BG$6-$BG$5 -> -102 | F13: =+F12-$BG$6-$BG$5 -> -102 | G13: =+G12-$BG$6-$BG$5 -> -102 | H13: =+H12-$BG$6-$BG$5 -> -102 | I13: =+I12-$BG$6-$BG$5 -> -102 | J13: =+J12-$BG$6-$BG$5 -> -102 | K13: =+K12-$BG$6-$BG$5 -> -102 | ... BQ13: =+BQ12-$BG$6-$BG$5 -> 508
C14: eur/usd | D14: =+'settlement day'!I29 -> 0 | E14: =+F14 -> 0 | F14: =+'settlement day'!K29 -> 0 | G14: =+I14 -> 0 | H14: =+I14 -> 0 | I14: =+'settlement day'!O29 -> 0 | J14: =+I14 -> 0 | K14: =+L14 -> 0 | L14: =+'settlement day'!Q29 -> 0 | M14: =+'settlement day'!R29 -> 0 | N14: =+'settlement day'!S29 -> 0 | O14: =+'settlement day'!T29 -> 0 | P14: =+'settlement day'!U29 -> 0 | Q14: =+R14 -> 0 | R14: =+'settlement day'!W29 -> 0 | S14: =+'settlement day'!W29 -> 0 | T14: =+'settlement day'!W29 -> 0 | U14: =+'settlement day'!Z29 -> 0 | V14: =+'settlement day'!AA29 -> 0 | W14: =+'settlement day'!AB29 -> 0 | X14: =+'settlement day'!AC29 -> 0 | Y14: =+'settlement day'!AD29 -> 0 | Z14: =+'settlement day'!AE29 -> 0 | AA14: =+'settlement day'!AF29 -> 0 | AB14: =+'settlement day'!AG29 -> 0 | ... BQ14: =+'settlement day'!BV29 -> 1.1866
C15: T1 usd/cbm - ind bid | D15: =+D14*D13 -> 0 | E15: =+D14*E13 -> 0 | F15: =+F14*F13 -> 0 | G15: =+F14*G13 -> 0 | H15: =+F14*H13 -> 0 | I15: =+I14*I13 -> 0 | J15: =+J14*J13 -> 0 | K15: =+K14*K13 -> 0 | L15: =+L14*L13 -> 0 | M15: =+M14*M13 -> 0 | N15: =+N14*N13 -> 0 | O15: =+O14*O13 -> 0 | P15: =+P14*P13 -> 0 | ... BQ15: =+BQ14*BQ13 -> 602.7928
C18: CIF ARA - shipment from origin
C19: eur/usd | D19: =+'settlement day'!I34 -> 0 | E19: =+F19 -> 0 | F19: =+'settlement day'!K34 -> 0 | G19: =+I19 -> 0 | H19: =+I19 -> 0 | I19: =+'settlement day'!O34 -> 0 | J19: =+I19 -> 0 | K19: =+L19 -> 0 | L19: =+'settlement day'!Q34 -> 0 | M19: =+'settlement day'!R34 -> 0 | N19: =+'settlement day'!S34 -> 0 | O19: =+'settlement day'!T34 -> 0 | P19: =+'settlement day'!U34 -> 0 | Q19: =+R19 -> 0 | R19: =+'settlement day'!W34 -> 0 | S19: =+'settlement day'!W34 -> 0 | T19: =+T14 -> 0 | U19: =+U14 -> 0 | V19: =+V14 -> 0 | W19: =+W14 -> 0 | X19: =+X14 -> 0 | Y19: =+Y14 -> 0 | Z19: =+Z14 -> 0 | AA19: =+AA14 -> 0 | ... BQ19: =+BQ14 -> 1.1866
D20: JUL | E20: AUG | F20: SEP | G20: OCT | H20: NOV | I20: DEC | J20: JAN | K20: FEB | L20: MAR | M20: APR | N20: MAY | O20: JUN | P20: JUL | Q20: AUG | R20: SEP | S20: OCT | T20: NOV | U20: DEC | V20: JAN | W20: FEB | X20: MAR | Y20: APR | Z20: MAY | AA20: JUN | AB20: JUL | AC20: AUG | AD20: SEP | AE20: OCT | AF20: NOV | AG20: DEC | AH20: JAN'24 | AI20: FEB'24 | AJ20: MAR'24 | AK20: APR'24 | AL20: 45413 | AM20: 45444 | AN20: 45474 | AO20: 45505 | AP20: 45536 | AQ20: 45566 | AR20: 45597 | AS20: 45627 | AT20: 45658 | AU20: 45689 | AV20: 45717 | AW20: 45748 | AX20: 45778 | AY20: 45809 | AZ20: 45839 | BA20: 45870 | BB20: 45901 | BC20: 45931 | BD20: 45962 | BE20: 45992 | BF20: 46023 | BG20: 46054 | BH20: 46082 | BI20: 46113 | BJ20: 46143 | BK20: 46174 | BL20: 46204 | BM20: 46235 | BN20: 46266 | BO20: 46296 | BP20: 46327 | BQ20: 46357
C21: T2 eur/cbm flat | D21: =+D12-$BG$5 -> 0 | E21: =+E12-$BG$5 -> 0 | F21: =+F12-$BG$5 -> 0 | G21: =+G12-$BG$5 -> 0 | H21: =+H12-$BG$5 -> 0 | I21: =+I12-$BG$5 -> 0 | J21: =+J12-$BG$5-$BI$5 -> 0 | K21: =+K12-$BG$5-$BI$5 -> 0 | L21: =+L12-$BG$5-$BI$5 -> 0 | M21: =+M12-$BG$5-$BI$5 -> 0 | N21: =+N12-$BG$5-$BI$5 -> 0 | O21: =+O12-$BG$5-$BI$5 -> 0 | P21: =+P12-$BG$5-$BI$5 -> 0 | Q21: =+Q12-$BG$5-$BI$5 -> 0 | ... BQ21: =+BQ12-$BG$5-$BI$5 -> 610
C22: D-1 | H22: =+'settlement day'!M7 -> 0 | I22: =+'settlement day'!N7 -> 0 | J22: =+'settlement day'!O7 -> 0 | K22: =+'settlement day'!P7 -> 0 | L22: =+'settlement day'!Q7 -> 0 | M22: =+'settlement day'!R7 -> 0 | N22: =+'settlement day'!S7 -> 0 | O22: =+'settlement day'!T7 -> 0 | ... BQ22: =+'settlement day'!BV7 -> 6
C23: BRZ Origin
C24: Anhydrous BS FOB usd/cbm | D24: =+'FOB origin'!E22+$BG$3 -> #DIV/0! | E24: =+'FOB origin'!F22+$BG$3 -> #DIV/0! | F24: =+'FOB origin'!G22+$BG$3 -> #DIV/0! | G24: =+'FOB origin'!H22+$BG$3 -> #DIV/0! | H24: =+'FOB origin'!I22+$BG$3 -> #DIV/0! | I24: =+'FOB origin'!J22+$BG$3 -> #DIV/0! | J24: =+'FOB origin'!K22+$BG$3 -> #DIV/0! | K24: =+'FOB origin'!L22+$BG$3 -> #DIV/0! | ... BQ24: =+'FOB origin'!BR22+$BG$3 -> 517.29179
C25: CIF ARA - T1 usd/cbm | D25: =+D24+$C$5 -> #DIV/0! | E25: =+E24+$C$5 -> #DIV/0! | F25: =+F24+$C$5 -> #DIV/0! | G25: =+G24+$C$5 -> #DIV/0! | H25: =+H24+$C$5 -> #DIV/0! | I25: =+I24+$C$5 -> #DIV/0! | J25: =+J24+$C$5 -> #DIV/0! | K25: =+K24+$C$5 -> #DIV/0! | ... BQ25: =+BQ24+$C$5 -> 560.68679
C26: CIF ARA eur/cbm T2 DEN. | D26: =+(D25/D14)+$BG$6 -> #DIV/0! | E26: =+(E25/E14)+$BG$6 -> #DIV/0! | F26: =+(F25/F14)+$BG$6 -> #DIV/0! | G26: =+(G25/G14)+$BG$6 -> #DIV/0! | H26: =+(H25/H14)+$BG$6 -> #DIV/0! | I26: =+(I25/I14)+$BG$6 -> #DIV/0! | J26: =+(J25/J14)+$BG$6 -> #DIV/0! | K26: =+(K25/K14)+$BG$6 -> #DIV/0! | ... BQ26: =+(BQ25/BQ14)+$BG$6 -> 574.51542
C27: BRZ DEN Arb M0 vs T2 M+1 | T27: =+U21-T26 -> #DIV/0! | U27: =+V21-U26 -> #DIV/0! | V27: =+W21-V26 -> #DIV/0! | W27: =+X21-W26 -> #DIV/0! | X27: =+Y21-X26 -> #DIV/0! | Y27: =+Z21-Y26 -> #DIV/0! | Z27: =+AA21-Z26 -> #DIV/0! | AA27: =+AB21-AA26 -> #DIV/0! | ... BG27: =+BH21-BG26 -> -47.058113 | BH27: =+BI12-BH26 -> -35.683379 | BI27: =+BJ12-BI26 -> 16.500207 | BJ27: =+BK12-BJ26 -> 66.777555 | BK27: =+BL12-BK26 -> 69.64988 | BL27: =+BM12-BL26 -> 56.859768 | BM27: =+BN12-BM26 -> 57.799514 | BN27: =+BO12-BN26 -> 49.73926 | BO27: =+BP12-BO26 -> 34.684398 | BP27: =+BQ12-BP26 -> 35.867136 | BQ27: =+BQ12-BQ26 -> 35.484583
C28: **CIF ARA eur/cbm T2 DEN. | D28: =+(D26/D15)+$BG$6 -> #DIV/0! | E28: =+(E26/E15)+$BG$6 -> #DIV/0! | F28: =+(F26/F15)+$BG$6 -> #DIV/0! | G28: =+(G26/G15)+$BG$6 -> #DIV/0! | H28: =+(H26/H15)+$BG$6 -> #DIV/0! | I28: =+(I26/I15)+$BG$6 -> #DIV/0! | J28: =+(J26/J15)+$BG$6 -> #DIV/0! | K28: =+(K26/K15)+$BG$6 -> #DIV/0! | ... AJ28: =+(AJ26/AJ15)+$BG$6 -> 100.45662 | AK28: =((('FOB origin'!AL24+EU!$C$5)/AK14)+$BG$6) -> 168.11139 | AL28: =((('FOB origin'!AM24+EU!$C$5)/AL14)+$BG$6) -> 167.08146 | AM28: =((('FOB origin'!AN24+EU!$C$5)/AM14)+$BG$6) -> 167.05942 | AN28: =((('FOB origin'!AO24+EU!$C$5)/AN14)+$BG$6) -> 166.0478 | AO28: =((('FOB origin'!AP24+EU!$C$5)/AO14)+$BG$6) -> 164.86138 | AP28: =((('FOB origin'!AQ24+EU!$C$5)/AP14)+$BG$6) -> 164.5004 | AQ28: =((('FOB origin'!AR24+EU!$C$5)/AQ14)+$BG$6) -> 165.36468 | AR28: =((('FOB origin'!AS24+EU!$C$5)/AR14)+$BG$6) -> 166.68757 | ... BQ28: =((('FOB origin'!BR24+EU!$C$5)/BQ14)+$BG$6) -> 527.01905
C29: **BRZ DEN Arb M0 vs T2 M+1 | AK29: =+AL21-AK28 -> -168.11139 | AL29: =+AM21-AL28 -> -167.08146 | AM29: =+AN21-AM28 -> -167.05942 | AN29: =+AO21-AN28 -> -166.0478 | AO29: =+AP21-AO28 -> -164.86138 | AP29: =+AQ21-AP28 -> -164.5004 | AQ29: =+AR21-AQ28 -> -165.36468 | AR29: =+AS21-AR28 -> -166.68757 | ... AU29: =+AV21-AU28 -> -168.12569 | AV29: =+AV21-AV28 -> -165.91972 | AW29: =+AW21-AW28 -> -162.9818 | AX29: =+AX21-AX28 -> -163.04698 | AY29: =+AY21-AY28 -> -161.68276 | AZ29: =+AZ21-AZ28 -> -162.73845 | BA29: =+BA21-BA28 -> -161.75821 | BB29: =+BB21-BB28 -> -161.94188 | BC29: =+BC21-BC28 -> 168.75768 | ... BQ29: =+BQ21-BQ28 -> 82.980949
C30: US Origin
C31: FOB IMTT usd/cbm (M0) | D31: =+(D10+$BG$4)*$B$1 -> 71.32644 | E31: =+(E10+$BG$4)*$B$1 -> 71.32644 | F31: =+(F10+$BG$4)*$B$1 -> 71.32644 | G31: =+(G10+$BG$4)*$B$1 -> 71.32644 | H31: =+(H10+$BG$4)*$B$1 -> 71.32644 | I31: =+(I10+$BG$4)*$B$1 -> 71.32644 | J31: =+(J10+$BG$4)*$B$1 -> 71.32644 | K31: =+(K10+$BG$4)*$B$1 -> 71.32644 | ... BE31: =+(BE10+$BG$4)*$B$1 -> 501.9268 | BF31: =+(BF10+$BG$4+$BI$4)*$B$1 -> 509.19153 | BG31: =+(BG10+$BG$4+$BI$4)*$B$1 -> 510.51239 | BH31: =+(BH10+$BG$4+$BI$4)*$B$1 -> 517.11669 | BI31: =+(BI10+$BG$4+$BI$4)*$B$1 -> 523.72099 | BJ31: =+(BJ10+$BG$4+$BI$4)*$B$1 -> 529.66486 | BK31: =+(BK10+$BG$4+$BI$4)*$B$1 -> 532.96701 | BL31: =+(BL10+$BG$4+$BI$4)*$B$1 -> 534.28787 | BM31: =+(BM10+$BG$4+$BI$4)*$B$1 -> 532.96701 | ... BQ31: =+(BQ10+$BG$4+$BI$4)*$B$1 -> 510.51239
C32: CIF ARA - T1 usd/cbm | D32: =+D31+$C$4 -> 106.83144 | E32: =+E31+$C$4 -> 106.83144 | F32: =+F31+$C$4 -> 106.83144 | G32: =+G31+$C$4 -> 106.83144 | H32: =+H31+$C$4 -> 106.83144 | I32: =+I31+$C$4 -> 106.83144 | J32: =+J31+$C$4 -> 106.83144 | K32: =+K31+$C$4 -> 106.83144 | ... BQ32: =+BQ31+$C$4 -> 546.01739
C33: CIF ARA eur/cbm T2 DEN. | D33: =+(D32/D14)+$BG$6 -> #DIV/0! | E33: =+(E32/E14)+$BG$6 -> #DIV/0! | F33: =+(F32/F14)+$BG$6 -> #DIV/0! | G33: =+(G32/G14)+$BG$6 -> #DIV/0! | H33: =+(H32/H14)+$BG$6 -> #DIV/0! | I33: =+(I32/I14)+$BG$6 -> #DIV/0! | J33: =+(J32/J14)+$BG$6 -> #DIV/0! | K33: =+(K32/K14)+$BG$6 -> #DIV/0! | ... BQ33: =+(BQ32/BQ14)+$BG$6 -> 562.15287
C34: USA DEN Arb M0 vs T2 M+1 | T34: =+U26-T33 -> #DIV/0! | U34: =+V21-U33 -> #DIV/0! | V34: =+W21-V33 -> #DIV/0! | W34: =+X21-W33 -> #DIV/0! | X34: =+Y21-X33 -> #DIV/0! | Y34: =+Z21-Y33 -> #DIV/0! | Z34: =+AA21-Z33 -> #DIV/0! | AA34: =+AB21-AA33 -> #DIV/0! | AB34: =+AC21-AB33 -> #DIV/0! | ... BE34: =+BF21-BE33 -> 43.733703 | BF34: =+BF21-BF33 -> 38.389029 | BG34: =+BG21-BG33 -> 45.798181 | BH34: =+BI12-BH33 -> 62.183473 | BI34: =+BJ12-BI33 -> 58.234748 | BJ34: =+BK12-BJ33 -> 53.18859 | BK34: =+BL12-BK33 -> 45.385169 | BL34: =+BM12-BL33 -> 44.145564 | BM34: =+BN12-BM33 -> 43.262571 | BN34: =+BO12-BN33 -> 33.379577 | BO34: =+BP12-BO33 -> 35.60252 | BP34: =+BQ12-BP33 -> 42.837974 | BQ34: =+BQ12-BQ33 -> 47.847135
B36: 1.25 | AV36: =AV32*$B$36 -> 133.5393 | AW36: =AW32*$B$36 -> 133.5393 | AX36: =AX32*$B$36 -> 133.5393 | AY36: =AY32*$B$36 -> 133.5393 | AZ36: =AZ32*$B$36 -> 133.5393 | BA36: =BA32*$B$36 -> 133.5393 | BB36: =BB32*$B$36 -> 133.5393 | BC36: =BC32*$B$36 -> 734.5306 | ... BQ36: =BQ32*$B$36 -> 682.52174
C37: USD vs BRZ | AV37: =AV36-AV25 -> 62.450737 | AW37: =AW36-AW25 -> 62.197134 | AX37: =AX36-AX25 -> 62.347243 | AY37: =AY36-AY25 -> 61.529343 | AZ37: =AZ36-AZ25 -> 62.009679 | BA37: =BA36-BA25 -> 61.463477 | BB37: =BB36-BB25 -> 61.046082 | BC37: =BC36-BC25 -> 73.843937 | ... BQ37: =BQ36-BQ25 -> 121.83494
AV38: =AV37/264.172 -> 0.2364018 | AW38: =AW37/264.172 -> 0.23544181 | AX38: =AX37/264.172 -> 0.23601003 | AY38: =AY37/264.172 -> 0.23291395 | AZ38: =AZ37/264.172 -> 0.23473221 | BA38: =BA37/264.172 -> 0.23266462 | BB38: =BB37/264.172 -> 0.2310846 | BC38: =BC37/264.172 -> 0.27952977 | ... BQ38: =BQ37/264.172 -> 0.46119552
C39: ** Anhydrous flat Hydrous
BB40: 45901 | BC40: 45931 | BD40: 45962 | BE40: 45992 | BF40: 46023 | BG40: 46054 | BH40: 46082 | BI40: 46113 | BJ40: 46143 | BK40: 46174 | BL40: 46204 | BM40: 46235 | BN40: 46266 | BO40: 46296 | BP40: 46327 | BQ40: 46357
C41: ARB FAVORABLE TO: | BC41: =IF(BC26>BC33, "USA", "BRZ") -> USA | BD41: =IF(BD26>BD33, "USA", "BRZ") -> USA | BE41: =IF(BE26>BE33, "USA", "BRZ") -> USA | BF41: =IF(BF26>BF33, "USA", "BRZ") -> USA | BG41: =IF(BG26>BG33, "USA", "BRZ") -> USA | BH41: =IF(BH26>BH33, "USA", "BRZ") -> USA | BI41: =IF(BI26>BI33, "USA", "BRZ") -> USA | BJ41: =IF(BJ26>BJ33, "USA", "BRZ") -> BRZ | ... BQ41: =IF(BQ26>BQ33, "USA", "BRZ") -> USA
C43: Brazil premium over USA | AI43: =AI26-AI33 -> -30.534847 | AJ43: =AJ26-AJ33 -> -30.62575 | AK43: =AK26-AK33 -> -31.533625 | AL43: =AL26-AL33 -> -31.384539 | AM43: =AM26-AM33 -> -32.84571 | AN43: =AN26-AN33 -> -32.779259 | AO43: =AO26-AO33 -> -32.147462 | AP43: =AP26-AP33 -> -31.074336 | ... BQ43: =BQ26-BQ33 -> 12.362551
BB44: =BB43/264.172 -> -0.11070976 | BC44: =BC43/264.172 -> 0.23741995 | BD44: =BD43/264.172 -> 0.37359548 | BE44: =BE43/264.172 -> 0.41468438 | BF44: =BF43/264.172 -> 0.39363973 | BG44: =BG43/264.172 -> 0.3893535 | BH44: =BH43/264.172 -> 0.37046641 | BI44: =BI43/264.172 -> 0.15798245 | ... BQ44: =BQ43/264.172 -> 0.046797357
C46: T2 M+1 eur/cbm disc | K46: =+L10 -> 0 | L46: =+M10 -> 0 | M46: =+N10 -> 0 | N46: =+O10 -> 0 | O46: =+P10 -> 0 | P46: =+Q10 -> 0 | Q46: =+R21+$C$47 -> -130 | R46: =+S21+$C$47 -> -130 | S46: =+T21+$C$47 -> -130 | T46: =+U21+$C$47 -> -130 | U46: =+V21+$C$47 -> -130 | V46: =+W21+$C$47 -> -130 | W46: =+X21+$C$47 -> -130 | X46: =+Y21+$C$47 -> -130 | ... BQ46: =+BR21+$C$47 -> -130
C47: -130
C48: ARB UISA/EU Denatured | K48: =+K46-K45 -> 0 | L48: =+L46-L45 -> 0 | M48: =+M46-M45 -> 0 | N48: =+N46-N45 -> 0 | O48: =+O46-O45 -> 0 | P48: =+P46-P45 -> 0 | Q48: =+Q46-Q33 -> #DIV/0! | R48: =+R46-R33 -> #DIV/0! | S48: =+S46-S33 -> #DIV/0! | T48: =+T46-T33 -> #DIV/0! | U48: =+U46-U33 -> #DIV/0! | V48: =+V46-V33 -> #DIV/0! | W48: =+W46-W33 -> #DIV/0! | X48: =+X46-X33 -> #DIV/0! | ... BQ48: =+BQ46-BQ33 -> -692.15287
C51: ARB BRZ/EU, Bon Sucro | K51: FEB | L51: MAR | M51: APR | N51: MAY | O51: JUN | P51: JUL | Q51: AUG | R51: SEP | S51: OCT | T51: NOV | U51: DEC | V51: JAN | W51: FEB | X51: MAR | Y51: APR | Z51: MAY | AA51: JUN | AB51: JUL | AC51: AUG | AD51: SEP | AE51: OCT | AF51: NOV | AG51: DEC | AH51: JAN'24 | AI51: FEB'24 | AJ51: MAR'24 | AK51: APR'24 | AL51: 45413 | AM51: 45444 | AN51: 45474 | AO51: 45505 | AP51: 45536 | AQ51: 45566 | AR51: 45597 | AS51: 45627 | AT51: 45658 | AU51: 45689 | AV51: 45717 | AW51: 45748 | AX51: 45778 | AY51: 45809 | AZ51: 45839 | BA51: 45870 | BB51: 45901 | BC51: 45931 | BD51: 45962 | BE51: 45992 | BF51: 46023 | BG51: 46054 | BH51: 46082 | BI51: 46113 | BJ51: 46143 | BK51: 46174 | BL51: 46204 | BM51: 46235 | BN51: 46266 | BO51: 46296 | BP51: 46327 | BQ51: 46357
C52: FOB Brazil, usd/cbm | K52: =+K24 -> #DIV/0! | L52: =+L24 -> #DIV/0! | M52: =+M24 -> #DIV/0! | N52: =+N24 -> #DIV/0! | O52: =+O24 -> #DIV/0! | P52: =+P24 -> #DIV/0! | Q52: =+Q24 -> #DIV/0! | R52: =+R24 -> #DIV/0! | ... BQ52: =+BQ24 -> 517.29179
C54: CIF ARA "T2" UND eur/cbm | K54: =+((K52+$C$5)/K14)+$BG$7 -> #DIV/0! | L54: =+((L52+$C$5)/L14)+$BG$7 -> #DIV/0! | M54: =+((M52+$C$5)/M14)+$BG$7 -> #DIV/0! | N54: =+((N52+$C$5)/N14)+$BG$7 -> #DIV/0! | O54: =+((O52+$C$5)/O14)+$BG$7 -> #DIV/0! | P54: =+((P52+$C$5)/P14)+$BG$7 -> #DIV/0! | Q54: =+((Q52+$C$5)/Q14)+$BG$7 -> #DIV/0! | R54: =+((R52+$C$5)/R14)+$BG$7 -> #DIV/0! | ... BQ54: =+((BQ52+$C$5)/BQ14)+$BG$7 -> 664.51542
C55: T2 M+1 eur/cbm flat | K55: =+L21 -> 0 | L55: =+M21 -> 0 | M55: =+N21 -> 0 | N55: =+O21 -> 0 | O55: =+P21 -> 0 | P55: =+Q21 -> 0 | Q55: =+R21 -> 0 | R55: =+S21 -> 0 | ... BG55: =+BH21 -> 622 | BH55: =+BI12 -> 634 | BI55: =+BJ12 -> 635 | BJ55: =+BK12 -> 635 | BK55: =+BL12 -> 630 | BL55: =+BM12 -> 628 | BM55: =+BN12 -> 626 | BN55: =+BO12 -> 615 | BO55: =+BP12 -> 610 | BP55: =+BQ12 -> 610 | BQ55: =+BQ12 -> 610
C57: ARB BRZ/EU Undenatured | K57: =+K55-K54 -> #DIV/0! | L57: =+L55-L54 -> #DIV/0! | M57: =+M55-M54 -> #DIV/0! | N57: =+N55-N54 -> #DIV/0! | O57: =+O55-O54 -> #DIV/0! | P57: =+P55-P54 -> #DIV/0! | Q57: =+Q55-Q54 -> #DIV/0! | R57: =+R55-R54 -> #DIV/0! | ... BQ57: =+BQ55-BQ54 -> -54.515417
C60: T2 M+1 eur/cbm disc | K60: =+L25 -> #DIV/0! | L60: =+M25 -> #DIV/0! | M60: =+N25 -> #DIV/0! | N60: =+O25 -> #DIV/0! | O60: =+P25 -> #DIV/0! | P60: =+Q25 -> #DIV/0! | Q60: =+R21+$C$61 -> -130 | R60: =+S21+$C$61 -> -130 | S60: =+T21+$C$61 -> -130 | T60: =+U21+$C$61 -> -130 | U60: =+V21+$C$61 -> -130 | V60: =+W21+$C$61 -> -130 | W60: =+X21+$C$61 -> -130 | X60: =+Y21+$C$61 -> -130 | ... BQ60: =+BR21+$C$61 -> -130
C61: =+C47 -> -130
C62: ARB BRZ/EU Undenatured | K62: =+K60-K59 -> #DIV/0! | L62: =+L60-L59 -> #DIV/0! | M62: =+M60-M59 -> #DIV/0! | N62: =+N60-N59 -> #DIV/0! | O62: =+O60-O59 -> #DIV/0! | P62: =+P60-P59 -> #DIV/0! | Q62: =+Q60-Q54 -> #DIV/0! | R62: =+R60-R54 -> #DIV/0! | S62: =+S60-S54 -> #DIV/0! | T62: =+T60-T54 -> #DIV/0! | U62: =+U60-U54 -> #DIV/0! | V62: =+V60-V54 -> #DIV/0! | W62: =+W60-W54 -> #DIV/0! | X62: =+X60-X54 -> #DIV/0! | ... BQ62: =+BQ60-BQ54 -> -794.51542
C64: T2 M+1 eur/cbm disc | K64: =+L32 -> 106.83144 | L64: =+M32 -> 106.83144 | M64: =+N32 -> 106.83144 | N64: =+O32 -> 106.83144 | O64: =+P32 -> 106.83144 | P64: =+Q32 -> 106.83144 | Q64: =+R21+$C$61 -> -130 | R64: =+S21+$C$61 -> -130 | S64: =+T21+$C$61 -> -130 | T64: =+U21+$C$61 -> -130 | U64: =+V21+$C$61 -> -130 | V64: =+W21+$C$61 -> -130 | W64: =+X21+$C$61 -> -130 | X64: =+Y21+$C$61 -> -130 | ... BQ64: =+BR21+$C$61 -> -130
C65: =+C47 -> -130
C66: ARB BRZ/EU Denatured | K66: =+K64-K63 -> 106.83144 | L66: =+L64-L63 -> 106.83144 | M66: =+M64-M63 -> 106.83144 | N66: =+N64-N63 -> 106.83144 | O66: =+O64-O63 -> 106.83144 | P66: =+P64-P63 -> 106.83144 | Q66: =+Q64-(Q54-$BG$7+$BG$6) -> #DIV/0! | R66: =+R64-(R54-$BG$7+$BG$6) -> #DIV/0! | S66: =+S64-(S54-$BG$7+$BG$6) -> #DIV/0! | T66: =+T64-(T54-$BG$7+$BG$6) -> #DIV/0! | U66: =+U64-(U54-$BG$7+$BG$6) -> #DIV/0! | V66: =+V64-(V54-$BG$7+$BG$6) -> #DIV/0! | W66: =+W64-(W54-$BG$7+$BG$6) -> #DIV/0! | X66: =+X64-(X54-$BG$7+$BG$6) -> #DIV/0! | ... BQ66: =+BQ64-(BQ54-$BG$7+$BG$6) -> -704.51542
N72: eur/usd | Q72: =+J14 -> 0 | T72: =+Q72 -> 0 | U72: eur/usd | AI72: =+M14 -> 0 | AJ72: eur/usd
C73: Paraguay | Q73: Brasil
C74: =+E21 -> 0 | H74: AUG | I74: T2 | K74: eur/cbm | M74: JUL | N74: T2 | Q74: =+R21 -> 0 | R74: eur/cbm | T74: 710 | AI74: 820 | AJ74: 1H MAR | AK74: >>> ind offer from Green/Brazil
C75: -150 | Q75: -102 | T75: =+-Q78 -> 47.34 | U75: freight | AI75: =+-Q78 -> 47.34 | AJ75: freight
C76: =+C74+C75 -> -150 | Q76: =+Q74+Q75 -> -102 | T76: =+T74+T75 -> 757.34 | U76: CIF T1 | AI76: =+AI74+AI75 -> 867.34 | AJ76: CIF T1
C77: =+C76*D14 -> 0 | I77: T1 CIF | K77: usd/cbm | N77: T1 CIF | Q77: =+Q76*Q72 -> 0 | R77: usd/cbm
C78: =-(70*0.789) -> -55.23 | M78: 60pmt | N78: freight | Q78: =-(60*0.789) -> -47.34 | T78: =+T76/Q72 -> #DIV/0! | U78: CIF T2 | AI78: =+AI76/AI72 -> #DIV/0! | AJ78: CIF T2
C79: =+C77+C78 -> -55.23 | H79: JUL | I79: FOB ARG | K79: usd/cbm | M79: JUN | N79: FOB STS | Q79: =+Q77+Q78 -> -47.34 | R79: usd/cbm | T79: 102 | AI79: 102
C80: =-(0.05*264.172) -> -13.2086 | Q80: =-(0.03*264.172) -> -7.92516 | T80: =+T78+T79 -> #DIV/0! | U80: AUG arrival | AI80: =+AI78+AI79 -> #DIV/0! | AJ80: 2H MAR arrival - CIF T2
C81: =+C79+C80 -> -68.4386 | I81: MEG ind bid | N81: MEG ind bid | Q81: =+Q79+Q80 -> -55.26516 | R81: usd/cbm | T81: =+R21 -> 0 | U81: SEP T2
T82: -35 | AI82: =+M21 -> 0 | AJ82: APR T2
T83: =+T81+T82 -> -35 | AI83: =+AI82-AI80 -> #DIV/0! | AJ83: spread T1/T2 CIF vs T2
N84: 15000 | Q84: =+N84*-Q80 -> 118877.4 | T84: =+T83-T80 -> #DIV/0!
AL88: Sucden
AK89: JUNE load | AL89: 2.3825 | AM89: =+'settlement day'!T9 -> 0 | AN89: settle 28/3
AK90: FOB basis | AL90: 0.365
AK91: cost | AL91: 0.01
AK92: demurrage | AL92: 0.01
AJ93: =SUM(AL90:AL93) -> 0.405 | AK93: margin | AL93: 0.02
AK94: freight | AL94: =+AP94/264.172 -> 0.19883447 | AO94: 65 | AP94: =+AO94*0.8081 -> 52.5265
AK95: CIF Rdam | AL95: =SUM(AL89:AL94) -> 2.9863345 | AM95: usd/gal
AL96: =+AL95*264.172 -> 788.90595 | AM96: usd/cbm
AO97: =+AL98-AL96 -> 1.09405 | AP97: =+AO97/264.172 -> 0.0041414306
AK98: offer CIF | AL98: 790 | AM98: usd/cbm
AK99: =+O14 -> 0 | AL99: =+AL98/AK99 -> #DIV/0! | AM99: eur/cbm
AK100: 0.06 | AL100: 192 | AM100: eur/cbm
AL101: =+AL99+AL100 -> #DIV/0! | AM101: eur/cbm
AK103: ref price PAK FOB | AL103: 900 | AM103: usd/ton
AK104: PAK FOB | AL104: =+AL103*0.8081 -> 727.29 | AM104: usd/cbm
AK105: freight | AL105: =+AN105*0.8081 -> 64.648 | AM105: usd/cbm | AN105: 80
AK106: CIF ARA | AL106: =+AL104+AL105 -> 791.938 | AM106: usd/cbm
AL107: =+AL106/AK99 -> #DIV/0! | AM107: eur/cbm
AK110: replacement vs PAK | AL110: =+AL107-AL101 -> #DIV/0!

Sheet ARB BRZ 2022
A1: 0.789 | E1: =+'settlement day'!M30 -> 0
A2: 264.172 | C2: FX | D2: =+'settlement day'!M30 -> 0 | E2: =+'settlement day'!N30 -> 0 | F2: =+'settlement day'!O30 -> 0 | G2: =+'settlement day'!P30 -> 0 | H2: =+'settlement day'!Q30 -> 0 | I2: =+'settlement day'!R30 -> 0 | J2: =+'settlement day'!S30 -> 0 | K2: =+'settlement day'!T30 -> 0 | ... T2: =+'settlement day'!AC30 -> 0
D3: 44501 | E3: 44531 | F3: 44562 | G3: 44593 | H3: 44621 | I3: 44652 | J3: 44682 | K3: 44713 | L3: 44743 | M3: 44774 | N3: 44805 | O3: 44835 | P3: 44866 | Q3: 44896 | R3: 44927 | S3: 44958 | T3: 44986
C4: CHIP | D4: =+'settlement day'!M9 -> 0 | E4: =+'settlement day'!N9 -> 0 | F4: =+'settlement day'!O9 -> 0 | G4: =+'settlement day'!P9 -> 0 | H4: =+'settlement day'!Q9 -> 0 | I4: =+'settlement day'!R9 -> 0 | J4: =+'settlement day'!S9 -> 0 | K4: =+'settlement day'!T9 -> 0 | ... T4: =+'settlement day'!AC9 -> 0
B5: 0.13 | C5: FOB (usd/gal) | D5: =+D4+$B$5 -> 0.13 | E5: =+E4+$B$5 -> 0.13 | F5: =+F4+$B$5 -> 0.13 | G5: =+G4+$B$5 -> 0.13 | H5: =+H4+$B$5 -> 0.13 | I5: =+I4+$B$5 -> 0.13 | J5: =+J4+$B$5 -> 0.13 | K5: =+K4+$B$5 -> 0.13 | ... T5: =+T4+$B$5 -> 0.13
C6: FOB usd/cbm | D6: =+D5*$A$2 -> 34.34236 | E6: =+E5*$A$2 -> 34.34236 | F6: =+F5*$A$2 -> 34.34236 | G6: =+G5*$A$2 -> 34.34236 | H6: =+H5*$A$2 -> 34.34236 | I6: =+I5*$A$2 -> 34.34236 | J6: =+J5*$A$2 -> 34.34236 | K6: =+K5*$A$2 -> 34.34236 | ... T6: =+T5*$A$2 -> 34.34236
B8: 0.02 | C8: cost (usd/cbm) | D8: =+$B$8*$A$2 -> 5.28344 | E8: =+D8 -> 5.28344 | F8: =+E8 -> 5.28344 | G8: =+F8 -> 5.28344 | H8: =+G8 -> 5.28344 | I8: =+H8 -> 5.28344 | J8: =+I8 -> 5.28344 | K8: =+J8 -> 5.28344 | L8: =+K8 -> 5.28344 | ... T8: =+S8 -> 5.28344
A9: 20kcbm | B9: 85 | C9: freight usd/cbm | D9: =+$B$9*$A$1 -> 67.065 | E9: =+D9 -> 67.065 | F9: =+E9 -> 67.065 | G9: =+F9 -> 67.065 | H9: =+G9 -> 67.065 | I9: =+H9 -> 67.065 | J9: =+I9 -> 67.065 | K9: =+J9 -> 67.065 | L9: =+K9 -> 67.065 | ... T9: =+S9 -> 67.065
C10: CIF usd/cbm | D10: =SUM(D6:D9) -> 106.6908 | E10: =SUM(E6:E9) -> 106.6908 | F10: =SUM(F6:F9) -> 106.6908 | G10: =SUM(G6:G9) -> 106.6908 | H10: =SUM(H6:H9) -> 106.6908 | I10: =SUM(I6:I9) -> 106.6908 | J10: =SUM(J6:J9) -> 106.6908 | K10: =SUM(K6:K9) -> 106.6908 | ... T10: =SUM(T6:T9) -> 106.6908
C11: CIF brl/cbm | E11: =+E10*E2 -> 0 | F11: =+F10*F2 -> 0 | G11: =+G10*G2 -> 0 | H11: =+H10*H2 -> 0 | I11: =+I10*I2 -> 0 | J11: =+J10*J2 -> 0 | K11: =+K10*K2 -> 0 | L11: =+L10*L2 -> 0 | ... T11: =+T10*T2 -> 0
B13: 0 | C13: Import duly | D13: =+D10*$B$13 -> 0 | E13: =+E11*$B$13 -> 0 | F13: =+F11*$B$13 -> 0 | G13: =+G11*$B$13 -> 0 | H13: =+H11*$B$13 -> 0 | I13: =+I11*$B$13 -> 0 | J13: =+J11*$B$13 -> 0 | K13: =+K11*$B$13 -> 0 | L13: =+L11*$B$13 -> 0 | ... T13: =+T11*$B$13 -> 0
A14: antes 11.75% | B14: 0 | C14: PIS/COFINS | D14: =+D10*$B$14 -> 0 | E14: =+E11*$B$14 -> 0 | F14: =+F11*$B$14 -> 0 | G14: =+G11*$B$14 -> 0 | H14: =+H11*$B$14 -> 0 | I14: =+I11*$B$14 -> 0 | J14: =+J11*$B$14 -> 0 | K14: =+K11*$B$14 -> 0 | L14: =+L11*$B$14 -> 0 | ... T14: =+T11*$B$14 -> 0
C15: ICMS | D15: 0 | E15: 0 | F15: 0 | G15: 0 | H15: 0 | I15: 0 | J15: 0 | K15: 0 | L15: 0 | M15: 0 | N15: 0 | O15: 0 | P15: 0 | Q15: 0 | R15: 1 | S15: 2 | T15: 3
B16: 0.08 | C16: AFRMM | D16: 0 | E16: 0 | F16: 0 | G16: 0 | H16: =+H9*$B$16 -> 5.3652 | I16: =+I9*$B$16 -> 5.3652 | J16: =+J9*$B$16 -> 5.3652 | K16: =+K9*$B$16 -> 5.3652 | L16: =+L9*$B$16 -> 5.3652 | M16: =+M9*$B$16 -> 5.3652 | N16: =+N9*$B$16 -> 5.3652 | O16: =+O9*$B$16 -> 5.3652 | ... T16: =+T9*$B$16 -> 5.3652
C17: Cargo Cleared usd/cbm | D17: =SUM(D10:D16) -> 106.6908 | E17: =SUM(E11:E16) -> 0 | F17: =SUM(F11:F16) -> 0 | G17: =SUM(G11:G16) -> 0 | H17: =SUM(H11:H16) -> 5.3652 | I17: =SUM(I11:I16) -> 5.3652 | J17: =SUM(J11:J16) -> 5.3652 | K17: =SUM(K11:K16) -> 5.3652 | L17: =SUM(L11:L16) -> 5.3652 | ... T17: =SUM(T11:T16) -> 8.3652
C19: Terminal cost (brl/cbm) | D19: 80 | E19: 80 | F19: 80 | G19: 80 | H19: 80 | I19: 80 | J19: 80 | K19: 80 | L19: 80 | M19: 80 | N19: 80 | O19: 80 | P19: 80 | Q19: 80 | R19: 80 | S19: 80 | T19: 80
C20: Inspection (brl/cbm) | D20: 15 | E20: 15 | F20: 15 | G20: 15 | H20: 15 | I20: 15 | J20: 15 | K20: 15 | L20: 15 | M20: 15 | N20: 15 | O20: 15 | P20: 15 | Q20: 15 | R20: 15 | S20: 15 | T20: 15
C21: Inland freight (brl/cbm) | D21: 25 | E21: 25 | F21: 25 | G21: 25 | H21: 25 | I21: 25 | J21: 25 | K21: 25 | L21: 25 | M21: 25 | N21: 25 | O21: 25 | P21: 25 | Q21: 25 | R21: 25 | S21: 25 | T21: 25
C22: Other costs (brl/cbm)
C23: Margin (brl/cbm)
C25: EX Tank disport (brl/cbm) | D25: =SUM(D19:D24) -> 120 | E25: =SUM(E17:E24) -> 120 | F25: =SUM(F17:F24) -> 120 | G25: =SUM(G17:G24) -> 120 | H25: =SUM(H17:H24) -> 125.3652 | I25: =SUM(I17:I24) -> 125.3652 | J25: =SUM(J17:J24) -> 125.3652 | K25: =SUM(K17:K24) -> 125.3652 | L25: =SUM(L17:L24) -> 125.3652 | ... T25: =SUM(T17:T24) -> 128.3652
C26: EX Tank disport (usd/cbm) | E26: =+E25/E2 -> #DIV/0! | F26: =+F25/F2 -> #DIV/0! | G26: =+G25/G2 -> #DIV/0! | H26: =+H25/H2 -> #DIV/0! | I26: =+I25/I2 -> #DIV/0! | J26: =+J25/J2 -> #DIV/0! | K26: =+K25/K2 -> #DIV/0! | L26: =+L25/L2 -> #DIV/0! | ... T26: =+T25/T2 -> #DIV/0!
C28: NE BRZ (brl/cbm) | D28: =+'PLATTS&OPIS'!I156 -> 4470 | E28: =+'PLATTS&OPIS'!I171 -> 4480 | G28: =+'PLATTS&OPIS'!I236 -> 3565 | H28: =+'PLATTS&OPIS'!I266 -> 4150 | I28: =+'PLATTS&OPIS'!I285 -> 4195 | J28: =+'PLATTS&OPIS'!I305 -> 4445 | K28: =+'PLATTS&OPIS'!I330 -> 4045 | L28: =+'PLATTS&OPIS'!I350 -> 4095 | M28: =+'PLATTS&OPIS'!I370 -> 3495 | N28: =+'PLATTS&OPIS'!I400 -> 3160 | O28: =+'PLATTS&OPIS'!I415 -> 3245 | P28: =+'PLATTS&OPIS'!I579 -> 3595 | Q28: =+P28 -> 3595 | R28: =+Q28 -> 3595 | S28: =+R28 -> 3595 | T28: =+S28 -> 3595
C29: 0% import tax | D29: 44501 | E29: 44531 | F29: 44562 | G29: 44593 | H29: 44621 | I29: 44652 | J29: 44682 | K29: 44713 | L29: 44743 | M29: 44774 | N29: 44805 | O29: 44835 | P29: 44866 | Q29: 44896 | R29: 44927 | S29: 44958 | T29: 44986
C30: ARB (brl/cbm) | D30: =+D28-D25 -> 4350 | E30: =+E28-E25 -> 4360 | F30: =+F28-F25 -> -120 | G30: =+G28-G25 -> 3445 | H30: =+H28-H25 -> 4024.6348 | I30: =+I28-I25 -> 4069.6348 | J30: =+J28-J25 -> 4319.6348 | K30: =+K28-K25 -> 3919.6348 | ... T30: =+T28-T25 -> 3466.6348
C31: ARB (usd/cbm) | D31: =+D30/$E$1 -> #DIV/0! | E31: =+E30/E2 -> #DIV/0! | F31: =+F30/F2 -> #DIV/0! | G31: =+G30/G2 -> #DIV/0! | H31: =+H30/H2 -> #DIV/0! | I31: =+I30/I2 -> #DIV/0! | J31: =+J30/J2 -> #DIV/0! | K31: =+K30/K2 -> #DIV/0! | L31: =+L30/L2 -> #DIV/0! | ... T31: =+T30/T2 -> #DIV/0!
C32: ARB (usd/gal) | H32: =+H31/264.172 -> #DIV/0! | I32: =+I31/264.172 -> #DIV/0! | J32: =+J31/264.172 -> #DIV/0! | K32: =+K31/264.172 -> #DIV/0! | L32: =+L31/264.172 -> #DIV/0! | M32: =+M31/264.172 -> #DIV/0! | N32: =+N31/264.172 -> #DIV/0! | O32: =+O31/264.172 -> #DIV/0! | ... T32: =+T31/264.172 -> #DIV/0!
C34: load mth+1 | D34: 44531 | E34: 44562 | F34: 44593 | G34: 44621 | I34: 44652 | J34: 44682 | K34: 44713 | L34: 44743 | M34: 44774 | N34: 44805 | O34: 44835 | P34: 44866 | Q34: 44896 | R34: 44927 | S34: 44958 | T34: 44986
C35: B3 hyd | D35: =+'settlement day'!N13 -> 0 | E35: =+'settlement day'!O13 -> 0 | F35: =+'settlement day'!P13 -> 0 | G35: =+'settlement day'!Q13 -> 0 | I35: =+'settlement day'!R13 -> 0 | J35: =+'settlement day'!S13 -> 0 | K35: =+'settlement day'!T13 -> 0 | L35: =+'settlement day'!U13 -> 0 | M35: =+'settlement day'!V13 -> 0 | N35: =+'settlement day'!W13 -> 0 | O35: =+'settlement day'!X13 -> 0 | P35: =+'settlement day'!Y13 -> 0 | ... T35: =+'settlement day'!AC13 -> 0
C36: B3 hyd ex plant | D36: =+(D35-'mkt data'!$G$23+'mkt data'!$G$24)/'mkt data'!$H$25 -> -99.524494 | E36: =+(E35-'mkt data'!$G$23+'mkt data'!$G$24)/'mkt data'!$H$25 -> -99.524494 | F36: =+(F35-'mkt data'!$G$23+'mkt data'!$G$24)/'mkt data'!$H$25 -> -99.524494 | G36: =+(G35-'mkt data'!$G$23+'mkt data'!$G$24)/'mkt data'!$H$25 -> -99.524494 | I36: =+(I35-'mkt data'!$G$23+'mkt data'!$G$24)/'mkt data'!$H$25 -> -99.524494 | J36: =+(J35-'mkt data'!$G$23+'mkt data'!$G$24)/'mkt data'!$H$25 -> -99.524494 | K36: =+(K35-'mkt data'!$G$23+'mkt data'!$G$24)/'mkt data'!$H$25 -> -99.524494 | L36: =+(L35-'mkt data'!$G$23+'mkt data'!$G$24)/'mkt data'!$H$25 -> -99.524494 | M36: =+(M35-'mkt data'!$G$23+'mkt data'!$G$24)/'mkt data'!$H$25 -> -99.524494 | N36: =+(N35-'mkt data'!$G$23+'mkt data'!$G$24)/'mkt data'!$H$25 -> -99.524494 | O36: =+(O35-'mkt data'!$G$23+'mkt data'!$G$24)/'mkt data'!$H$25 -> -99.524494 | P36: =+(P35-'mkt data'!$G$23+'mkt data'!$G$24)/'mkt data'!$H$25 -> -99.524494 | ... T36: =+(T35-'mkt data'!$G$23+'mkt data'!$G$24)/'mkt data'!$H$25 -> -99.524494
B38: =+'mkt data'!G26 -> 0.12 | C38: B3 anydrous ex plant | D38: =+((D35-'mkt data'!$G$23)*'mkt data'!$H$26)+('mkt data'!$G$24) -> -100.8 | E38: =+((E35-'mkt data'!$G$23)*'mkt data'!$H$26)+('mkt data'!$G$24) -> -100.8 | F38: =+((F35-'mkt data'!$G$23)*'mkt data'!$H$26)+('mkt data'!$G$24) -> -100.8 | G38: =+((G35-'mkt data'!$G$23)*'mkt data'!$H$26)+('mkt data'!$G$24) -> -100.8 | I38: =+((I35-'mkt data'!$G$23)*'mkt data'!$H$26)+('mkt data'!$G$24) -> -100.8 | J38: =+((J35-'mkt data'!$G$23)*'mkt data'!$H$26)+('mkt data'!$G$24) -> -100.8 | K38: =+((K35-'mkt data'!$G$23)*'mkt data'!$H$26)+('mkt data'!$G$24) -> -100.8 | L38: =+((L35-'mkt data'!$G$23)*'mkt data'!$H$26)+('mkt data'!$G$24) -> -100.8 | M38: =+((M35-'mkt data'!$G$23)*'mkt data'!$H$26)+('mkt data'!$G$24) -> -100.8 | N38: =+((N35-'mkt data'!$G$23)*'mkt data'!$H$26)+('mkt data'!$G$24) -> -100.8 | O38: =+((O35-'mkt data'!$G$23)*'mkt data'!$H$26)+('mkt data'!$G$24) -> -100.8 | P38: =+((P35-'mkt data'!$G$23)*'mkt data'!$H$26)+('mkt data'!$G$24) -> -100.8 | ... T38: =+((T35-'mkt data'!$G$23)*'mkt data'!$H$26)+('mkt data'!$G$24) -> -100.8
B40: =470/0.867 -> 542.09919 | C40: B3 CS to NE (brl/cbm) | D40: =+D38+$B$40 -> 441.29919 | E40: =+E38+$B$40 -> 441.29919 | F40: =+F38+$B$40 -> 441.29919 | G40: =+G38+$B$40 -> 441.29919 | I40: =+I38+$B$40 -> 441.29919 | J40: =+J38+$B$40 -> 441.29919 | K40: =+K38+$B$40 -> 441.29919 | L40: =+L38+$B$40 -> 441.29919 | M40: =+M38+$B$40 -> 441.29919 | N40: =+N38+$B$40 -> 441.29919 | O40: =+O38+$B$40 -> 441.29919 | P40: =+P38+$B$40 -> 441.29919 | ... T40: =+T38+$B$40 -> 441.29919
D41: 44531 | E41: 44562 | F41: 44593 | G41: 44621 | I41: 44652 | J41: 44682 | K41: 44713 | L41: 44743 | M41: 44774 | N41: 44805 | O41: 44835 | P41: 44866 | Q41: 44896 | R41: 44927 | S41: 44958 | T41: 44986
C42: ARB (brl/cbm) | D42: =+D40-D25 -> 321.29919 | E42: =+E40-E25 -> 321.29919 | F42: =+F40-F25 -> 321.29919 | G42: =+G40-G25 -> 321.29919 | I42: =+I40-I25 -> 315.93399 | J42: =+J40-J25 -> 315.93399 | K42: =+K40-K25 -> 315.93399 | L42: =+L40-L25 -> 315.93399 | M42: =+M40-M25 -> 315.93399 | N42: =+N40-N25 -> 315.93399 | O42: =+O40-O25 -> 315.93399 | P42: =+P40-P25 -> 315.93399 | ... T42: =+T40-T25 -> 312.93399
C43: ARB (usd/cbm) | D43: =+D42/$E$1 -> #DIV/0! | E43: =+E42/E2 -> #DIV/0! | F43: =+F42/F2 -> #DIV/0! | G43: =+G42/G2 -> #DIV/0! | I43: =+I42/H2 -> #DIV/0! | J43: =+J42/I2 -> #DIV/0! | K43: =+K42/J2 -> #DIV/0! | L43: =+L42/L2 -> #DIV/0! | M43: =+M42/M2 -> #DIV/0! | N43: =+N42/N2 -> #DIV/0! | O43: =+O42/O2 -> #DIV/0! | P43: =+P42/P2 -> #DIV/0! | Q43: =+Q42/Q2 -> #DIV/0! | R43: =+R42/R2 -> #DIV/0! | S43: =+S42/S2 -> #DIV/0! | T43: =+T42/T2 -> #DIV/0!
C44: ARB (usd/gal) | I44: =+I43/264.172 -> #DIV/0! | J44: =+J43/264.172 -> #DIV/0! | K44: =+K43/264.172 -> #DIV/0! | L44: =+L43/264.172 -> #DIV/0! | M44: =+M43/264.172 -> #DIV/0! | N44: =+N43/264.172 -> #DIV/0! | O44: =+O43/264.172 -> #DIV/0! | P44: =+P43/264.172 -> #DIV/0! | ... T44: =+T43/264.172 -> #DIV/0!

Sheet ARB BRZ 2024_25
A1: 0.789 | E1: =+'settlement day'!M30 -> 0
A2: 264.172 | C2: BRL/USD | D2: =+'settlement day'!M30 -> 0 | E2: =+'settlement day'!N30 -> 0 | F2: =+'settlement day'!O30 -> 0 | G2: =+'settlement day'!P30 -> 0 | H2: =+'settlement day'!Q30 -> 0 | I2: =+'settlement day'!R30 -> 0 | J2: =+'settlement day'!S30 -> 0 | K2: =+'settlement day'!T30 -> 0 | ... BM2: =+'settlement day'!BV30 -> 5.9772863
D3: 44501 | E3: 44531 | F3: 44562 | G3: 44593 | H3: 44621 | I3: 44652 | J3: 44682 | K3: 44713 | L3: 44743 | M3: 44774 | N3: 44805 | O3: 44835 | P3: 44866 | Q3: 44896 | R3: 44927 | S3: 44958 | T3: 44986 | U3: 45017 | V3: 45047 | W3: 45078 | X3: 45108 | Y3: 45139 | Z3: 45170 | AA3: 45200 | AB3: 45231 | AC3: 45261 | AD3: 45292 | AE3: 45323 | AF3: 45352 | AG3: 45383 | AH3: 45413 | AI3: 45444 | AJ3: 45474 | AK3: 45505 | AL3: 45536 | AM3: 45566 | AN3: 45597 | AO3: 45627 | AP3: 45658 | AQ3: 45689 | AR3: 45717 | AS3: 45748 | AT3: 45778 | AU3: 45809 | AV3: 45839 | AW3: 45870 | AX3: 45901 | AY3: 45931 | AZ3: 45962 | BA3: 45992 | BB3: 46023 | BC3: 46054 | BD3: 46082 | BE3: 46113 | BF3: 46143 | BG3: 46174 | BH3: 46204 | BI3: 46235 | BJ3: 46266 | BK3: 46296 | BL3: 46327 | BM3: 46357
C4: CHIP | D4: =+'settlement day'!M9 -> 0 | E4: =+'settlement day'!N9 -> 0 | F4: =+'settlement day'!O9 -> 0 | G4: =+'settlement day'!P9 -> 0 | H4: =+'settlement day'!Q9 -> 0 | I4: =+'settlement day'!R9 -> 0 | J4: =+'settlement day'!S9 -> 0 | K4: =+'settlement day'!T9 -> 0 | ... U4: =+'settlement day'!AD9 -> 0 | V4: =+'settlement day'!AE8 -> 2.43773 | W4: =+'settlement day'!AF8 -> 2.50714 | X4: =+'settlement day'!AG8 -> 2.44342 | Y4: =+'settlement day'!AH8 -> 2.1663 | Z4: =+'settlement day'!AI9 -> 0 | AA4: =+'settlement day'!AJ9 -> 0 | AB4: =+'settlement day'!AK9 -> 0 | AC4: =+'settlement day'!AL9 -> 0 | AD4: =+'settlement day'!AM9 -> 0 | AE4: =+'settlement day'!AN9 -> 0 | AF4: =+'settlement day'!AO9 -> 0 | AG4: =+'settlement day'!AP9 -> 0 | ... BM4: =+'settlement day'!BV9 -> 1.5825
B5: ='mkt data'!G16 -> 0.12 | C5: FOB (usd/gal) | D5: =+D4+$B$5 -> 0.12 | E5: =+E4+$B$5 -> 0.12 | F5: =+F4+$B$5 -> 0.12 | G5: =+G4+$B$5 -> 0.12 | H5: =+H4+$B$5 -> 0.12 | I5: =+I4+$B$5 -> 0.12 | J5: =+J4+$B$5 -> 0.12 | K5: =+K4+$B$5 -> 0.12 | ... BM5: =+BM4+$B$5 -> 1.7025
C6: FOB usd/cbm | D6: =+D5*$A$2 -> 31.70064 | E6: =+E5*$A$2 -> 31.70064 | F6: =+F5*$A$2 -> 31.70064 | G6: =+G5*$A$2 -> 31.70064 | H6: =+H5*$A$2 -> 31.70064 | I6: =+I5*$A$2 -> 31.70064 | J6: =+J5*$A$2 -> 31.70064 | K6: =+K5*$A$2 -> 31.70064 | ... BM6: =+BM5*$A$2 -> 449.75283
B8: 0.02 | C8: cost (usd/cbm) | D8: =+$B$8*$A$2 -> 5.28344 | E8: =+D8 -> 5.28344 | F8: =+E8 -> 5.28344 | G8: =+F8 -> 5.28344 | H8: =+G8 -> 5.28344 | I8: =+H8 -> 5.28344 | J8: =+I8 -> 5.28344 | K8: =+J8 -> 5.28344 | L8: =+K8 -> 5.28344 | ... BM8: =+BL8 -> 5.28344
A9: 20kcbm | B9: =75*0.789 -> 59.175 | C9: freight usd/cbm | D9: =+$B$9*$A$1 -> 46.689075 | E9: =+$B$9*$A$1 -> 46.689075 | F9: =+$B$9*$A$1 -> 46.689075 | G9: =+$B$9*$A$1 -> 46.689075 | H9: =+$B$9*$A$1 -> 46.689075 | I9: =+$B$9*$A$1 -> 46.689075 | J9: =+$B$9*$A$1 -> 46.689075 | K9: =+$B$9*$A$1 -> 46.689075 | ... AG9: =+$B$9*$A$1 -> 46.689075 | AH9: =+B9 -> 59.175 | AI9: =+$B$9 -> 59.175 | AJ9: =+$B$9 -> 59.175 | AK9: =+$B$9 -> 59.175 | AL9: =+$B$9 -> 59.175 | AM9: =+$B$9 -> 59.175 | AN9: =+$B$9 -> 59.175 | AO9: =+$B$9 -> 59.175 | AP9: =+$B$9 -> 59.175 | ... BM9: =+$B$9 -> 59.175
C10: CIF usd/cbm | D10: =SUM(D6:D9) -> 83.673155 | E10: =SUM(E6:E9) -> 83.673155 | F10: =SUM(F6:F9) -> 83.673155 | G10: =SUM(G6:G9) -> 83.673155 | H10: =SUM(H6:H9) -> 83.673155 | I10: =SUM(I6:I9) -> 83.673155 | J10: =SUM(J6:J9) -> 83.673155 | K10: =SUM(K6:K9) -> 83.673155 | ... BM10: =SUM(BM6:BM9) -> 514.21127
C11: CIF brl/cbm | E11: =+E10*E2 -> 0 | F11: =+F10*F2 -> 0 | G11: =+G10*G2 -> 0 | H11: =+H10*H2 -> 0 | I11: =+I10*I2 -> 0 | J11: =+J10*J2 -> 0 | K11: =+K10*K2 -> 0 | L11: =+L10*L2 -> 0 | ... BM11: =+BM10*BM2 -> 3073.588
B13: 0.18 | C13: Import duly | D13: =+D10*$B$13 -> 15.061168 | E13: =+E11*$B$13 -> 0 | F13: =+F11*$B$13 -> 0 | G13: =+G11*$B$13 -> 0 | H13: =+H11*$B$13 -> 0 | I13: =+I11*$B$13 -> 0 | J13: =+J11*$B$13 -> 0 | K13: =+K11*$B$13 -> 0 | L13: =+L11*$B$13 -> 0 | ... BM13: =+BM11*$B$13 -> 553.24584
A14: antes 11.75% | B14: 0.1175 | C14: PIS/COFINS | D14: =+D10*$B$14 -> 9.8315957 | E14: =+E11*$B$14 -> 0 | F14: =+F11*$B$14 -> 0 | G14: =+G11*$B$14 -> 0 | H14: =+H11*$B$14 -> 0 | I14: =+I11*$B$14 -> 0 | J14: =+J11*$B$14 -> 0 | K14: =+K11*$B$14 -> 0 | L14: =+L11*$B$14 -> 0 | ... R14: =+R11*$B$14 -> 0 | S14: 20 | T14: 20 | U14: 20 | V14: 20 | W14: 20 | X14: 20 | Y14: 20 | Z14: 20 | AA14: 20 | AB14: 20 | AC14: 20 | AD14: 20 | AE14: 20 | AF14: =AF11*$B$14 -> 49.11472 | AG14: =AG11*$B$14 -> 50.841148 | AH14: =AH11*$B$14 -> 59.216444 | AI14: =AI11*$B$14 -> 62.801519 | AJ14: =AJ11*$B$14 -> 63.967544 | AK14: =AK11*$B$14 -> 63.900882 | AL14: =AL11*$B$14 -> 61.549624 | AM14: =AM11*$B$14 -> 65.608114 | ... BM14: =BM11*$B$14 -> 361.14659
C15: ICMS | D15: 0 | E15: 0 | F15: 0 | G15: 0 | H15: 0 | I15: 0 | J15: 0 | K15: 0 | L15: 0 | M15: 0 | N15: 0 | O15: 0 | P15: 0 | Q15: 0 | R15: 1 | S15: 0 | T15: 0 | U15: 0 | V15: 0 | W15: 0 | X15: 0 | Y15: 0 | Z15: 0 | AA15: 0 | AB15: 0 | AC15: 0 | AD15: 0 | AE15: 0 | AF15: 0 | AG15: 0 | AH15: 0 | AI15: 0 | AJ15: 0 | AK15: 0 | AL15: 0 | AM15: 0 | AN15: 0 | AO15: 0 | AP15: 0 | AQ15: 0 | AR15: 0 | AS15: 0 | AT15: 0 | AU15: 0 | AV15: 0 | AW15: 0 | AX15: 0 | AY15: 0 | AZ15: 0 | BA15: 0 | BB15: 0 | BC15: 0 | BD15: 0 | BE15: 0 | BF15: 0 | BG15: 0 | BH15: 0 | BI15: 0 | BJ15: 0 | BK15: 0 | BL15: 0 | BM15: 0
B16: 0.08 | C16: AFRMM | D16: 0 | E16: 0 | F16: 0 | G16: 0 | H16: =+H9*$B$16 -> 3.735126 | I16: =+I9*$B$16 -> 3.735126 | J16: =+J9*$B$16 -> 3.735126 | K16: =+K9*$B$16 -> 3.735126 | L16: =+L9*$B$16 -> 3.735126 | M16: =+M9*$B$16 -> 3.735126 | N16: =+N9*$B$16 -> 3.735126 | O16: =+O9*$B$16 -> 3.735126 | ... BM16: =+BM9*$B$16 -> 4.734
C17: Cargo Cleared usd/cbm | D17: =SUM(D10:D16) -> 108.56592 | E17: =SUM(E11:E16) -> 0 | F17: =SUM(F11:F16) -> 0 | G17: =SUM(G11:G16) -> 0 | H17: =SUM(H11:H16) -> 3.735126 | I17: =SUM(I11:I16) -> 3.735126 | J17: =SUM(J11:J16) -> 3.735126 | K17: =SUM(K11:K16) -> 3.735126 | L17: =SUM(L11:L16) -> 3.735126 | ... BM17: =SUM(BM11:BM16) -> 3992.7144
C19: Terminal cost (brl/cbm) | D19: 80 | E19: 80 | F19: 80 | G19: 80 | H19: 80 | I19: 80 | J19: 80 | K19: 80 | L19: 80 | M19: 80 | N19: 80 | O19: 80 | P19: 80 | Q19: 80 | R19: 80 | S19: 80 | T19: 80 | U19: 80 | V19: 80 | W19: 80 | X19: 80 | Y19: 80 | Z19: 80 | AA19: 80 | AB19: 80 | AC19: 80 | AD19: 80 | AE19: 80 | AF19: 80 | AG19: 80 | AH19: 80 | AI19: 80 | AJ19: 80 | AK19: 80 | AL19: 80 | AM19: 80 | AN19: 80 | AO19: 80 | AP19: 80 | AQ19: 80 | AR19: 80 | AS19: 80 | AT19: 80 | AU19: 80 | AV19: 80 | AW19: 80 | AX19: 80 | AY19: 80 | AZ19: 80 | BA19: 80 | BB19: 80 | BC19: 80 | BD19: 80 | BE19: 80 | BF19: 80 | BG19: 80 | BH19: 80 | BI19: 80 | BJ19: 80 | BK19: 80 | BL19: 80 | BM19: 80
C20: Inspection (brl/cbm) | D20: 15 | E20: 15 | F20: 15 | G20: 15 | H20: 15 | I20: 15 | J20: 15 | K20: 15 | L20: 15 | M20: 15 | N20: 15 | O20: 15 | P20: 15 | Q20: 15 | R20: 15 | S20: 15 | T20: 15 | U20: 15 | V20: 15 | W20: 15 | X20: 15 | Y20: 15 | Z20: 15 | AA20: 15 | AB20: 15 | AC20: 15 | AD20: 15 | AE20: 15 | AF20: 15 | AG20: 15 | AH20: 15 | AI20: 15 | AJ20: 15 | AK20: 15 | AL20: 15 | AM20: 15 | AN20: 15 | AO20: 15 | AP20: 15 | AQ20: 15 | AR20: 15 | AS20: 15 | AT20: 15 | AU20: 15 | AV20: 15 | AW20: 15 | AX20: 15 | AY20: 15 | AZ20: 15 | BA20: 15 | BB20: 15 | BC20: 15 | BD20: 15 | BE20: 15 | BF20: 15 | BG20: 15 | BH20: 15 | BI20: 15 | BJ20: 15 | BK20: 15 | BL20: 15 | BM20: 15
C21: Inland freight (brl/cbm) | D21: 25 | E21: 25 | F21: 25 | G21: 25 | H21: 25 | I21: 25 | J21: 25 | K21: 25 | L21: 25 | M21: 25 | N21: 25 | O21: 25 | P21: 25 | Q21: 25 | R21: 25 | S21: 25 | T21: 25 | U21: 25 | V21: 25 | W21: 25 | X21: 25 | Y21: 25 | Z21: 25 | AA21: 25 | AB21: 25 | AC21: 25 | AD21: 25 | AE21: 25 | AF21: 25 | AG21: 25 | AH21: 25 | AI21: 25 | AJ21: 25 | AK21: 25 | AL21: 25 | AM21: 25 | AN21: 25 | AO21: 25 | AP21: 25 | AQ21: 25 | AR21: 25 | AS21: 25 | AT21: 25 | AU21: 25 | AV21: 25 | AW21: 25 | AX21: 25 | AY21: 25 | AZ21: 25 | BA21: 25 | BB21: 25 | BC21: 25 | BD21: 25 | BE21: 25 | BF21: 25 | BG21: 25 | BH21: 25 | BI21: 25 | BJ21: 25 | BK21: 25 | BL21: 25 | BM21: 25
C22: Other costs (brl/cbm)
C23: Margin (brl/cbm)
C25: EX Tank disport (brl/cbm) | D25: =SUM(D19:D24) -> 120 | E25: =SUM(E17:E24) -> 120 | F25: =SUM(F17:F24) -> 120 | G25: =SUM(G17:G24) -> 120 | H25: =SUM(H17:H24) -> 123.73513 | I25: =SUM(I17:I24) -> 123.73513 | J25: =SUM(J17:J24) -> 123.73513 | K25: =SUM(K17:K24) -> 123.73513 | L25: =SUM(L17:L24) -> 123.73513 | ... BM25: =SUM(BM17:BM24) -> 4112.7144
C26: EX Tank disport (usd/cbm) | E26: =+E25/E2 -> #DIV/0! | F26: =+F25/F2 -> #DIV/0! | G26: =+G25/G2 -> #DIV/0! | H26: =+H25/H2 -> #DIV/0! | I26: =+I25/I2 -> #DIV/0! | J26: =+J25/J2 -> #DIV/0! | K26: =+K25/K2 -> #DIV/0! | L26: =+L25/L2 -> #DIV/0! | ... BM26: =+BM25/BM2 -> 688.05712
C28: NE BRZ (brl/cbm) | D28: =+'PLATTS&OPIS'!I156 -> 4470 | E28: =+'PLATTS&OPIS'!I171 -> 4480 | G28: =+'PLATTS&OPIS'!I236 -> 3565 | H28: =+'PLATTS&OPIS'!I266 -> 4150 | I28: =+'PLATTS&OPIS'!I285 -> 4195 | J28: =+'PLATTS&OPIS'!I305 -> 4445 | K28: =+'PLATTS&OPIS'!I330 -> 4045 | L28: =+'PLATTS&OPIS'!I350 -> 4095 | M28: =+'PLATTS&OPIS'!I350 -> 4095 | N28: =+M28 -> 4095 | O28: =+N28 -> 4095 | P28: =+O28 -> 4095 | Q28: =+P28 -> 4095 | R28: =+'PLATTS&OPIS'!I485 -> 3450 | S28: =+'PLATTS&OPIS'!I505 -> 3580 | T28: =+'PLATTS&OPIS'!I520 -> 3575 | U28: =+'PLATTS&OPIS'!I544 -> 3945 | V28: =+'PLATTS&OPIS'!I559 -> 3445 | W28: =+'PLATTS&OPIS'!I589 -> 3650 | X28: =+'PLATTS&OPIS'!I609 -> 3140 | Y28: =+'PLATTS&OPIS'!I634 -> 3265 | Z28: =+'PLATTS&OPIS'!I654 -> 3295 | AA28: =+'PLATTS&OPIS'!I676 -> 2895 | AB28: =+'PLATTS&OPIS'!I697 -> 2815 | AC28: =+'PLATTS&OPIS'!I713 -> 2800 | AD28: =+'PLATTS&OPIS'!I740 -> 3065 | AE28: =+'PLATTS&OPIS'!I761 -> 3245 | AF28: =+'PLATTS&OPIS'!I781 -> 3205 | AG28: =+'PLATTS&OPIS'!I803 -> 3175 | AH28: =+'PLATTS&OPIS'!I827 -> 3200 | AI28: =+'PLATTS&OPIS'!I846 -> 3225 | AJ28: =+'PLATTS&OPIS'!I869 -> 3640 | AK28: =+'PLATTS&OPIS'!I892 -> 3495 | AL28: =+'PLATTS&OPIS'!I912 -> 3150 | AM28: =+'PLATTS&OPIS'!I936 -> 3030 | AN28: =+'PLATTS&OPIS'!I956 -> 3100 | AO28: =+'PLATTS&OPIS'!I968 -> 3370 | AP28: =+'PLATTS&OPIS'!I1000 -> 3655 | AQ28: =+'PLATTS&OPIS'!I1019 -> 3545 | AR28: =+'PLATTS&OPIS'!I1040 -> 3395 | AS28: =+'PLATTS&OPIS'!I1063 -> 3560 | AT28: =+'PLATTS&OPIS'!I1083 -> 3640 | AU28: =+'PLATTS&OPIS'!I1104 -> 3560 | AV28: =+'PLATTS&OPIS'!I1127 -> 3550 | AW28: =+'PLATTS&OPIS'!I1148 -> 3760 | AX28: =+'PLATTS&OPIS'!I1170 -> 3545 | AY28: =+'PLATTS&OPIS'!I1182 -> 3380 | AZ28: =+AY28 -> 3380 | BA28: =+AZ28 -> 3380 | BB28: =+BA28 -> 3380 | BC28: =+BB28 -> 3380 | BD28: =+BC28 -> 3380 | BE28: =+BD28 -> 3380 | BF28: =+BE28 -> 3380 | BG28: =+BF28 -> 3380 | ... BM28: =+BL28 -> 3380
D29: 44501 | E29: 44531 | F29: 44562 | G29: 44593 | H29: 44621 | I29: 44652 | J29: 44682 | K29: 44713 | L29: 44743 | M29: 44774 | N29: 44805 | O29: 44835 | P29: 44866 | Q29: 44896 | R29: 44927 | S29: 44958 | T29: 44986 | U29: 45017 | V29: 45047 | W29: 45078 | X29: 45108 | Y29: 45139 | Z29: 45170 | AA29: 45200 | AB29: 45231 | AC29: 45261 | AD29: 45292 | AE29: 45323 | AF29: 45352 | AG29: 45383 | AH29: 45413 | AI29: 45444 | AJ29: 45474 | AK29: 45505 | AL29: 45536 | AM29: 45566 | AN29: 45597 | AO29: 45627 | AP29: 45658 | AQ29: 45689 | AR29: 45717 | AS29: 45748 | AT29: 45778 | AU29: 45809 | AV29: 45839 | AW29: 45870 | AX29: 45901 | AY29: 45931 | AZ29: 45962 | BA29: 45992 | BB29: 46023 | BC29: 46054 | BD29: 46082 | BE29: 46113 | BF29: 46143 | BG29: 46174 | BH29: 46204 | BI29: 46235 | BJ29: 46266 | BK29: 46296 | BL29: 46327 | BM29: 46357
C30: ARB (brl/cbm) | D30: =+D28-D25 -> 4350 | E30: =+E28-E25 -> 4360 | F30: =+F28-F25 -> -120 | G30: =+G28-G25 -> 3445 | H30: =+H28-H25 -> 4026.2649 | I30: =+I28-I25 -> 4071.2649 | J30: =+J28-J25 -> 4321.2649 | K30: =+K28-K25 -> 3921.2649 | ... BM30: =+BM28-BM25 -> -732.71441
C31: ARB (usd/cbm) | D31: =+D30/$E$1 -> #DIV/0! | E31: =+E30/E2 -> #DIV/0! | F31: =+F30/F2 -> #DIV/0! | G31: =+G30/G2 -> #DIV/0! | H31: =+H30/H2 -> #DIV/0! | I31: =+I30/I2 -> #DIV/0! | J31: =+J30/J2 -> #DIV/0! | K31: =+K30/K2 -> #DIV/0! | L31: =+L30/L2 -> #DIV/0! | ... BM31: =+BM30/BM2 -> -122.58312
C32: ARB (usd/gal) | H32: =+H31/264.172 -> #DIV/0! | I32: =+I31/264.172 -> #DIV/0! | J32: =+J31/264.172 -> #DIV/0! | K32: =+K31/264.172 -> #DIV/0! | L32: =+L31/264.172 -> #DIV/0! | M32: =+M31/264.172 -> #DIV/0! | N32: =+N31/264.172 -> #DIV/0! | O32: =+O31/264.172 -> #DIV/0! | ... BM32: =+BM31/264.172 -> -0.46402768
A34: -80 | B34: 350 | C34: NE based B3 -80+350 | AV34: =AV48+$A$34+$B$34 -> 270 | AW34: =AW48+$A$34+$B$34 -> 270 | AX34: =AX48+$A$34+$B$34 -> 270 | AY34: =AY48+$A$34+$B$34 -> 3113.5 | AZ34: =AZ48+$A$34+$B$34 -> 3170 | BA34: =BA48+$A$34+$B$34 -> 3174.5 | BB34: =BB48+$A$34+$B$34 -> 3200 | BC34: =BC48+$A$34+$B$34 -> 3220 | ... BM34: =BM48+$A$34+$B$34 -> 2875
C36: USA / NNE Brazil arbitrage
A37: NE incl mkt structure | C37: NE BRZ (brl/cbm) | D37: =+'PLATTS&OPIS'!I162 -> 0 | E37: =+'PLATTS&OPIS'!I177 -> 0 | G37: =+'PLATTS&OPIS'!I242 -> 0 | H37: =+'PLATTS&OPIS'!I272 -> 0 | I37: =+'PLATTS&OPIS'!I291 -> 0 | J37: =+'PLATTS&OPIS'!I311 -> 0 | K37: =+'PLATTS&OPIS'!I336 -> 0 | L37: =+'PLATTS&OPIS'!I356 -> 0 | M37: =+'PLATTS&OPIS'!I356 -> 0 | N37: =+M37 -> 0 | O37: =+N37 -> 0 | P37: =+O37 -> 0 | Q37: =+P37 -> 0 | R37: =+'PLATTS&OPIS'!I491 -> 0 | S37: =+'PLATTS&OPIS'!I511 -> 0 | T37: =+T28+T46 -> 6401 | U37: =+U28+U46 -> 7026 | V37: =+V28+V46 -> 3445 | W37: =+W28+W46 -> 3650 | X37: =+X28+X46 -> 3140 | Y37: =+Y28+Y46 -> 3265 | Z37: =+Z28+Z46 -> 3295 | AA37: =+Z37+AA46 -> 3295 | AB37: =+AB28+AB46 -> 2815 | AC37: =+AB37+AC46 -> 2815 | AD37: =+AC37+AD46 -> 2815 | AE37: =+AD37+AE46 -> 2815 | AF37: =AF28+AF46 -> 3205 | AG37: =+AG28+AG46 -> 3175 | AH37: =+AH28+AH46 -> 3200 | AI37: =+AI28+AI46 -> 3225 | AJ37: =+AJ28+AJ46 -> 3640 | AK37: =+AK28+AK46 -> 3495 | AL37: =+AL28+AL46 -> 3150 | AM37: =+AM28+AM46 -> 3030 | AN37: =+AN28+AN46 -> 3100 | ... AQ37: =+AQ28+AQ46 -> 3545 | AR37: =+AR28 -> 3395 | AS37: =+AS28+AS46 -> 3560 | AT37: =+AT28+AT46 -> 3640 | AU37: =+AU28+AU46 -> 3560 | AV37: =+AV28+AV46 -> 3550 | AW37: =+AW28+AW46 -> 3760 | AX37: =+AX28+AX46 -> 3545 | AY37: =+AY28+AY46 -> 3380 | AZ37: =+AY37+AZ46 -> 3436.5 | BA37: =+AZ37+BA46 -> 3441 | BB37: =+BA37+BB46 -> 3466.5 | BC37: =+BB37+BC46 -> 3486.5 | BD37: =+BC37+BD46 -> 3511.5 | BE37: =+BD37+BE46 -> 3236.5 | BF37: =+BE37+BF46 -> 2956.5 | BG37: =+BF37+BG46 -> 2926.5 | ... BM37: =+BL37+BM46 -> 3141.5
C38: BRL/USD | D38: =+'settlement day'!M66 -> 0 | E38: =+'settlement day'!N66 -> 0 | F38: =+'settlement day'!O66 -> 0 | G38: =+'settlement day'!P66 -> 0 | H38: =+'settlement day'!Q66 -> 0 | I38: =+'settlement day'!R66 -> 0 | J38: =+'settlement day'!S66 -> 0 | K38: =+'settlement day'!T66 -> 0 | ... U38: =+'settlement day'!AD66 -> 0 | V38: =V2 -> 0 | W38: =W2 -> 0 | X38: =X2 -> 0 | Y38: =Y2 -> 0 | Z38: =Z2 -> 0 | AA38: =AA2 -> 0 | AB38: =AB2 -> 0 | AC38: =AC2 -> 4.8412998 | ... BM38: =BM2 -> 5.9772863
D39: 44501 | E39: 44531 | F39: 44562 | G39: 44593 | H39: 44621 | I39: 44652 | J39: 44682 | K39: 44713 | L39: 44743 | M39: 44774 | N39: 44805 | O39: 44835 | P39: 44866 | Q39: 44896 | R39: 44927 | S39: 44958 | T39: 44986 | U39: 45017 | V39: 45047 | W39: 45078 | X39: 45108 | Y39: 45139 | Z39: 45170 | AA39: 45200 | AB39: 45231 | AC39: 45261 | AD39: 45292 | AE39: 45323 | AF39: 45352 | AG39: 45383 | AH39: 45413 | AI39: 45444 | AJ39: 45474 | AK39: 45505 | AL39: 45536 | AM39: 45566 | AN39: 45597 | AO39: 45627 | AP39: 45658 | AQ39: 45689 | AR39: 45717 | AS39: 45748 | AT39: 45778 | AU39: 45809 | AV39: 45839 | AW39: 45870 | AX39: 45901 | AY39: 45931 | AZ39: 45962 | BA39: 45992 | BB39: 46023 | BC39: 46054 | BD39: 46082 | BE39: 46113 | BF39: 46143 | BG39: 46174 | BH39: 46204 | BI39: 46235 | BJ39: 46266 | BK39: 46296 | BL39: 46327 | BM39: 46357
C40: ARB (brl/cbm) | D40: =+D37-D31 -> #DIV/0! | E40: =+E37-E31 -> #DIV/0! | F40: =+F37-F31 -> #DIV/0! | G40: =+G37-G31 -> #DIV/0! | H40: =+H37-H31 -> #DIV/0! | I40: =+I37-I31 -> #DIV/0! | J40: =+J37-J31 -> #DIV/0! | K40: =+K37-K31 -> #DIV/0! | ... S40: =+S37-S31 -> #DIV/0! | T40: =+T37-T25 -> 6257.2649 | U40: =+U37-U25 -> 6882.2649 | V40: =+V37-V25 -> 3301.2649 | W40: =+W37-W25 -> 3506.2649 | X40: =+X37-X25 -> 2996.2649 | Y40: =+Y37-Y25 -> 3121.2649 | Z40: =+Z37-Z25 -> 3151.2649 | AA40: =+AA37-AA25 -> 3151.2649 | ... BM40: =+BM37-BM25 -> -971.21441
C41: ARB (usd/cbm) | D41: =+D40/$E$1 -> #DIV/0! | E41: =+E40/E8 -> #DIV/0! | F41: =+F40/F8 -> #DIV/0! | G41: =+G40/G8 -> #DIV/0! | H41: =+H40/H8 -> #DIV/0! | I41: =+I40/I8 -> #DIV/0! | J41: =+J40/J8 -> #DIV/0! | K41: =+K40/K8 -> #DIV/0! | L41: =+L40/L8 -> #DIV/0! | ... S41: =+S40/S8 -> #DIV/0! | T41: =+T40/T2 -> #DIV/0! | U41: =+U40/U2 -> #DIV/0! | V41: =+V40/V2 -> #DIV/0! | W41: =+W40/W2 -> #DIV/0! | X41: =+X40/X2 -> #DIV/0! | Y41: =+Y40/Y2 -> #DIV/0! | Z41: =+Z40/Z2 -> #DIV/0! | AA41: =+AA40/AA2 -> #DIV/0! | ... BM41: =+BM40/BM2 -> -162.48417
C42: ARB (usd/gal) - 18% import duty | H42: =+H41/264.172 -> #DIV/0! | I42: =+I41/264.172 -> #DIV/0! | J42: =+J41/264.172 -> #DIV/0! | K42: =+K41/264.172 -> #DIV/0! | L42: =+L41/264.172 -> #DIV/0! | M42: =+M41/264.172 -> #DIV/0! | N42: =+N41/264.172 -> #DIV/0! | O42: =+O41/264.172 -> #DIV/0! | ... BM42: =+BM41/264.172 -> -0.61506962
C43: ARB (usd/gal) - 0% import duty | T43: ='ARB BRZ 2023 (no tax)'!T38 -> #DIV/0! | U43: ='ARB BRZ 2023 (no tax)'!U38 -> #DIV/0! | V43: ='ARB BRZ 2023 (no tax)'!V38 -> #DIV/0! | W43: ='ARB BRZ 2023 (no tax)'!W38 -> #DIV/0! | X43: ='ARB BRZ 2023 (no tax)'!X38 -> #DIV/0! | Y43: ='ARB BRZ 2023 (no tax)'!Y38 -> #DIV/0! | Z43: ='ARB BRZ 2023 (no tax)'!Z38 -> #DIV/0! | AA43: ='ARB BRZ 2023 (no tax)'!AA38 -> #DIV/0! | ... BM43: ='ARB BRZ 2023 (no tax)'!BM38 -> -0.21403529
AL44: =AL43*264.172 -> 524.62288 | AM44: =AM43*264.172 -> 406.26086 | AN44: =AN43*264.172 -> 397.46815 | AO44: =AO43*264.172 -> 430.05242 | AP44: =AP43*264.172 -> 511.51667 | AQ44: =AQ43*264.172 -> 490.77054 | AR44: =AR43*264.172 -> 475.50673 | AS44: =AS43*264.172 -> 512.85112 | ... BM44: =BM43*264.172 -> -56.54213
T46: ='settlement day'!AC12 -> 2826 | U46: ='settlement day'!AD12 -> 3081 | V46: 0 | W46: 0 | X46: 0 | Z46: 0 | AR46: 0 | AZ46: =AZ48-AY48 -> 56.5 | BA46: =BA48-AZ48 -> 4.5 | BB46: =BB48-BA48 -> 25.5 | BC46: =BC48-BB48 -> 20 | BD46: =BD48-BC48 -> 25 | BE46: =BE48-BD48 -> -275 | BF46: =BF48-BE48 -> -280 | BG46: =BG48-BF48 -> -30 | ... BM46: =BM48-BL48 -> 20
C47: load mth+1 | D47: 44531 | E47: 44562 | F47: 44593 | G47: 44621 | I47: 44652 | J47: 44682 | K47: 44713 | L47: 44743 | M47: 44774 | N47: 44805 | O47: 44835 | P47: 44866 | Q47: 44896 | R47: 44927 | S47: 44958 | T47: 44986 | U47: 45017 | V47: 45047 | W47: 45078 | X47: 45108 | Y47: 45139 | Z47: 45170 | AA47: 45200 | AB47: 45231 | AC47: 45261 | AD47: 45292 | AE47: 45323 | AF47: 45352 | AG47: 45383 | AH47: 45413 | AI47: 45444 | AJ47: 45474 | AK47: 45505 | AL47: 45536 | AM47: 45566 | AN47: 45597 | AO47: 45627 | AP47: 45658 | AQ47: 45689 | AR47: 45717 | AS47: 45748 | AT47: 45778 | AU47: 45809 | AV47: 45839 | AW47: 45870 | AX47: 45901 | AY47: 45931 | AZ47: 45962 | BA47: 45992 | BB47: 46023 | BC47: 46054 | BD47: 46082 | BE47: 46113 | BF47: 46143 | BG47: 46174 | BH47: 46204 | BI47: 46235 | BJ47: 46266 | BK47: 46296 | BL47: 46327 | BM47: 46357
C48: B3 hyd | D48: =+'settlement day'!N13 -> 0 | E48: =+'settlement day'!O13 -> 0 | F48: =+'settlement day'!P13 -> 0 | G48: =+'settlement day'!Q13 -> 0 | I48: =+'settlement day'!R13 -> 0 | J48: =+'settlement day'!S13 -> 0 | K48: =+'settlement day'!T13 -> 0 | L48: =+'settlement day'!U13 -> 0 | M48: =+'settlement day'!V13 -> 0 | N48: =+'settlement day'!W13 -> 0 | O48: =+'settlement day'!X13 -> 0 | P48: =+'settlement day'!Y13 -> 0 | ... BM48: =+'settlement day'!BV13 -> 2605
C49: B3 hyd ex plant | D49: =+(D48-'mkt data'!$G$23+'mkt data'!$G$24)/'mkt data'!$H$25 -> -99.524494 | E49: =+(E48-'mkt data'!$G$23+'mkt data'!$G$24)/'mkt data'!$H$25 -> -99.524494 | F49: =+(F48-'mkt data'!$G$23+'mkt data'!$G$24)/'mkt data'!$H$25 -> -99.524494 | G49: =+(G48-'mkt data'!$G$23+'mkt data'!$G$24)/'mkt data'!$H$25 -> -99.524494 | I49: =+(I48-'mkt data'!$G$23+'mkt data'!$G$24)/'mkt data'!$H$25 -> -99.524494 | J49: =+(J48-'mkt data'!$G$23+'mkt data'!$G$24)/'mkt data'!$H$25 -> -99.524494 | K49: =+(K48-'mkt data'!$G$23+'mkt data'!$G$24)/'mkt data'!$H$25 -> -99.524494 | L49: =+(L48-'mkt data'!$G$23+'mkt data'!$G$24)/'mkt data'!$H$25 -> -99.524494 | M49: =+(M48-'mkt data'!$G$23+'mkt data'!$G$24)/'mkt data'!$H$25 -> -99.524494 | N49: =+(N48-'mkt data'!$G$23+'mkt data'!$G$24)/'mkt data'!$H$25 -> -99.524494 | O49: =+(O48-'mkt data'!$G$23+'mkt data'!$G$24)/'mkt data'!$H$25 -> -99.524494 | P49: =+(P48-'mkt data'!$G$23+'mkt data'!$G$24)/'mkt data'!$H$25 -> -99.524494 | ... BM49: =+(BM48-'mkt data'!$G$23+'mkt data'!$G$24)/'mkt data'!$H$25 -> 2781.1567
B51: =+'mkt data'!G26 -> 0.12 | C51: B3 anydrous ex plant | D51: =+((D48-'mkt data'!$G$23)*'mkt data'!$H$26)+('mkt data'!$G$24) -> -100.8 | E51: =+((E48-'mkt data'!$G$23)*'mkt data'!$H$26)+('mkt data'!$G$24) -> -100.8 | F51: =+((F48-'mkt data'!$G$23)*'mkt data'!$H$26)+('mkt data'!$G$24) -> -100.8 | G51: =+((G48-'mkt data'!$G$23)*'mkt data'!$H$26)+('mkt data'!$G$24) -> -100.8 | I51: =+((I48-'mkt data'!$G$23)*'mkt data'!$H$26)+('mkt data'!$G$24) -> -100.8 | J51: =+((J48-'mkt data'!$G$23)*'mkt data'!$H$26)+('mkt data'!$G$24) -> -100.8 | K51: =+((K48-'mkt data'!$G$23)*'mkt data'!$H$26)+('mkt data'!$G$24) -> -100.8 | L51: =+((L48-'mkt data'!$G$23)*'mkt data'!$H$26)+('mkt data'!$G$24) -> -100.8 | M51: =+((M48-'mkt data'!$G$23)*'mkt data'!$H$26)+('mkt data'!$G$24) -> -100.8 | N51: =+((N48-'mkt data'!$G$23)*'mkt data'!$H$26)+('mkt data'!$G$24) -> -100.8 | O51: =+((O48-'mkt data'!$G$23)*'mkt data'!$H$26)+('mkt data'!$G$24) -> -100.8 | P51: =+((P48-'mkt data'!$G$23)*'mkt data'!$H$26)+('mkt data'!$G$24) -> -100.8 | ... BM51: =+((BM48-'mkt data'!$G$23)*'mkt data'!$H$26)+('mkt data'!$G$24) -> 2816.8
B53: =470/0.867 -> 542.09919 | C53: B3 CS to NE (brl/cbm) | D53: =+D51+$B$53 -> 441.29919 | E53: =+E51+$B$53 -> 441.29919 | F53: =+F51+$B$53 -> 441.29919 | G53: =+G51+$B$53 -> 441.29919 | I53: =+I51+$B$53 -> 441.29919 | J53: =+J51+$B$53 -> 441.29919 | K53: =+K51+$B$53 -> 441.29919 | L53: =+L51+$B$53 -> 441.29919 | M53: =+M51+$B$53 -> 441.29919 | N53: =+N51+$B$53 -> 441.29919 | O53: =+O51+$B$53 -> 441.29919 | P53: =+P51+$B$53 -> 441.29919 | ... BM53: =+BM51+$B$53 -> 3358.8992
D54: 44531 | E54: 44562 | F54: 44593 | G54: 44621 | I54: 44652 | J54: 44682 | K54: 44713 | L54: 44743 | M54: 44774 | N54: 44805 | O54: 44835 | P54: 44866 | Q54: 44896 | R54: 44927 | S54: 44958 | T54: 44986 | U54: 45017 | V54: 45047 | W54: 45078 | X54: 45108 | Y54: 45139 | Z54: 45170 | AA54: 45200 | AB54: 45231 | AC54: 45261 | AD54: 45292 | AE54: 45323 | AF54: 45352 | AG54: 45383 | AH54: 45413 | AI54: 45444 | AJ54: 45474 | AK54: 45505 | AL54: 45536 | AM54: 45566 | AN54: 45597 | AO54: 45627 | AP54: 45658 | AQ54: 45689 | AR54: 45717 | AS54: 45748 | AT54: 45778 | AU54: 45809 | AV54: 45839 | AW54: 45870 | AX54: 45901 | AY54: 45931 | AZ54: 45962 | BA54: 45992 | BB54: 46023 | BC54: 46054 | BD54: 46082 | BE54: 46113 | BF54: 46143 | BG54: 46174 | BH54: 46204 | BI54: 46235 | BJ54: 46266 | BK54: 46296 | BL54: 46327 | BM54: 46357
C55: ARB (brl/cbm) | D55: =+D53-D25 -> 321.29919 | E55: =+E53-E25 -> 321.29919 | F55: =+F53-F25 -> 321.29919 | G55: =+G53-G25 -> 321.29919 | I55: =+I53-I25 -> 317.56407 | J55: =+J53-J25 -> 317.56407 | K55: =+K53-K25 -> 317.56407 | L55: =+L53-L25 -> 317.56407 | M55: =+M53-M25 -> 317.56407 | N55: =+N53-N25 -> 317.56407 | O55: =+O53-O25 -> 317.56407 | P55: =+P53-P25 -> 317.56407 | ... BM55: =+BM53-BM25 -> -753.81522
C56: ARB (usd/cbm) | D56: =+D55/$E$1 -> #DIV/0! | E56: =+E55/E2 -> #DIV/0! | F56: =+F55/F2 -> #DIV/0! | G56: =+G55/G2 -> #DIV/0! | I56: =+I55/H2 -> #DIV/0! | J56: =+J55/I2 -> #DIV/0! | K56: =+K55/J2 -> #DIV/0! | L56: =+L55/L2 -> #DIV/0! | M56: =+M55/M2 -> #DIV/0! | N56: =+N55/N2 -> #DIV/0! | O56: =+O55/O2 -> #DIV/0! | P56: =+P55/P2 -> #DIV/0! | Q56: =+Q55/Q2 -> #DIV/0! | R56: =+R55/R2 -> #DIV/0! | S56: =+S55/S2 -> #DIV/0! | ... BM56: =+BM55/BM2 -> -126.11329
C57: ARB (usd/gal) | I57: =+I56/264.172 -> #DIV/0! | J57: =+J56/264.172 -> #DIV/0! | K57: =+K56/264.172 -> #DIV/0! | L57: =+L56/264.172 -> #DIV/0! | M57: =+M56/264.172 -> #DIV/0! | N57: =+N56/264.172 -> #DIV/0! | O57: =+O56/264.172 -> #DIV/0! | P57: =+P56/264.172 -> #DIV/0! | ... BM57: =+BM56/264.172 -> -0.47739081

Sheet ARB BRZ 2023 (no tax)
A1: 0.789 | E1: =+'settlement day'!M30 -> 0
A2: 264.172 | C2: FX | D2: =+'settlement day'!M30 -> 0 | E2: =+'settlement day'!N30 -> 0 | F2: =+'settlement day'!O30 -> 0 | G2: =+'settlement day'!P30 -> 0 | H2: =+'settlement day'!Q30 -> 0 | I2: =+'settlement day'!R30 -> 0 | J2: =+'settlement day'!S30 -> 0 | K2: =+'settlement day'!T30 -> 0 | ... BM2: =+'settlement day'!BV30 -> 5.9772863
D3: 44501 | E3: 44531 | F3: 44562 | G3: 44593 | H3: 44621 | I3: 44652 | J3: 44682 | K3: 44713 | L3: 44743 | M3: 44774 | N3: 44805 | O3: 44835 | P3: 44866 | Q3: 44896 | R3: 44927 | S3: 44958 | T3: 44986 | U3: 45017 | V3: 45047 | W3: 45078 | X3: 45108 | Y3: 45139 | Z3: 45170 | AA3: 45200 | AB3: 45231 | AC3: 45261 | AD3: 45292 | AE3: 45323 | AF3: 45352 | AG3: 45383 | AH3: 45413 | AI3: 45444 | AJ3: 45474 | AK3: 45505 | AL3: 45536 | AM3: 45566 | AN3: 45597 | AO3: 45627 | AP3: 45658 | AQ3: 45689 | AR3: 45717 | AS3: 45748 | AT3: 45778 | AU3: 45809 | AV3: 45839 | AW3: 45870 | AX3: 45901 | AY3: 45931 | AZ3: 45962 | BA3: 45992 | BB3: 46023 | BC3: 46054 | BD3: 46082 | BE3: 46113 | BF3: 46143 | BG3: 46174 | BH3: 46204 | BI3: 46235 | BJ3: 46266 | BK3: 46296 | BL3: 46327 | BM3: 46357
C4: CHIP | D4: =+'settlement day'!M9 -> 0 | E4: =+'settlement day'!N9 -> 0 | F4: =+'settlement day'!O9 -> 0 | G4: =+'settlement day'!P9 -> 0 | H4: =+'settlement day'!Q9 -> 0 | I4: =+'settlement day'!R9 -> 0 | J4: =+'settlement day'!S9 -> 0 | K4: =+'settlement day'!T9 -> 0 | ... BM4: =+'settlement day'!BV9 -> 1.5825
B5: ='ARB BRZ 2024_25'!B5 -> 0.12 | C5: FOB (usd/gal) | D5: =+D4+$B$5 -> 0.12 | E5: =+E4+$B$5 -> 0.12 | F5: =+F4+$B$5 -> 0.12 | G5: =+G4+$B$5 -> 0.12 | H5: =+H4+$B$5 -> 0.12 | I5: =+I4+$B$5 -> 0.12 | J5: =+J4+$B$5 -> 0.12 | K5: =+K4+$B$5 -> 0.12 | ... BM5: =+BM4+$B$5 -> 1.7025
C6: FOB usd/cbm | D6: =+D5*$A$2 -> 31.70064 | E6: =+E5*$A$2 -> 31.70064 | F6: =+F5*$A$2 -> 31.70064 | G6: =+G5*$A$2 -> 31.70064 | H6: =+H5*$A$2 -> 31.70064 | I6: =+I5*$A$2 -> 31.70064 | J6: =+J5*$A$2 -> 31.70064 | K6: =+K5*$A$2 -> 31.70064 | ... BM6: =+BM5*$A$2 -> 449.75283
B8: 0.02 | C8: cost (usd/cbm) | D8: =+$B$8*$A$2 -> 5.28344 | E8: =+D8 -> 5.28344 | F8: =+E8 -> 5.28344 | G8: =+F8 -> 5.28344 | H8: =+G8 -> 5.28344 | I8: =+H8 -> 5.28344 | J8: =+I8 -> 5.28344 | K8: =+J8 -> 5.28344 | L8: =+K8 -> 5.28344 | ... BM8: =+BL8 -> 5.28344
A9: 20kcbm | B9: =60*0.789 -> 47.34 | C9: freight usd/cbm | D9: =+$B$9*$A$1 -> 37.35126 | E9: =+D9 -> 37.35126 | F9: =+E9 -> 37.35126 | G9: =+F9 -> 37.35126 | H9: =+G9 -> 37.35126 | I9: =+H9 -> 37.35126 | J9: =+I9 -> 37.35126 | K9: =+J9 -> 37.35126 | L9: =+K9 -> 37.35126 | ... AG9: =+AF9 -> 37.35126 | AH9: =+B9 -> 47.34 | AI9: =+AH9 -> 47.34 | AJ9: =+AI9 -> 47.34 | AK9: =+AJ9 -> 47.34 | AL9: =+AK9 -> 47.34 | AM9: =+AL9 -> 47.34 | AN9: =+AM9 -> 47.34 | AO9: =+AN9 -> 47.34 | AP9: =+AO9 -> 47.34 | ... BM9: =+BL9 -> 47.34
C10: CIF usd/cbm | D10: =SUM(D6:D9) -> 74.33534 | E10: =SUM(E6:E9) -> 74.33534 | F10: =SUM(F6:F9) -> 74.33534 | G10: =SUM(G6:G9) -> 74.33534 | H10: =SUM(H6:H9) -> 74.33534 | I10: =SUM(I6:I9) -> 74.33534 | J10: =SUM(J6:J9) -> 74.33534 | K10: =SUM(K6:K9) -> 74.33534 | ... BM10: =SUM(BM6:BM9) -> 502.37627
C11: CIF brl/cbm | E11: =+E10*E2 -> 0 | F11: =+F10*F2 -> 0 | G11: =+G10*G2 -> 0 | H11: =+H10*H2 -> 0 | I11: =+I10*I2 -> 0 | J11: =+J10*J2 -> 0 | K11: =+K10*K2 -> 0 | L11: =+L10*L2 -> 0 | ... BM11: =+BM10*BM2 -> 3002.8468
A12: da cfr value
B13: 0 | C13: Import duly | D13: =+D10*$B$13 -> 0 | E13: =+E11*$B$13 -> 0 | F13: =+F11*$B$13 -> 0 | G13: =+G11*$B$13 -> 0 | H13: =+H11*$B$13 -> 0 | I13: =+I11*$B$13 -> 0 | J13: =+J11*$B$13 -> 0 | K13: =+K11*$B$13 -> 0 | L13: =+L11*$B$13 -> 0 | ... BM13: =+BM11*$B$13 -> 0
A14: antes 11.75% | B14: 0.1175 | C14: PIS/COFINS | D14: =+D10*$B$14 -> 8.7344024 | E14: =+E11*$B$14 -> 0 | F14: =+F11*$B$14 -> 0 | G14: =+G11*$B$14 -> 0 | H14: =+H11*$B$14 -> 0 | I14: =+I11*$B$14 -> 0 | J14: =+J11*$B$14 -> 0 | K14: =+K11*$B$14 -> 0 | L14: =+L11*$B$14 -> 0 | ... R14: =+R11*$B$14 -> 0 | S14: 20 | T14: 20 | U14: 20 | V14: 20 | W14: 20 | X14: 20 | Y14: 20 | Z14: 20 | AA14: 20 | AB14: 20 | AC14: 20 | AD14: 20 | AE14: 20 | AF14: =AF11*$B$14 -> 43.633581 | AG14: =AG11*$B$14 -> 45.167342 | AH14: =AH11*$B$14 -> 51.928244 | AI14: =AI11*$B$14 -> 55.072078 | AJ14: =AJ11*$B$14 -> 56.094592 | AK14: =AK11*$B$14 -> 56.036134 | AL14: =AL11*$B$14 -> 53.974263 | AM14: =AM11*$B$14 -> 57.533245 | ... BM14: =BM11*$B$14 -> 352.8345
C15: ICMS | D15: 0 | E15: 0 | F15: 0 | G15: 0 | H15: 0 | I15: 0 | J15: 0 | K15: 0 | L15: 0 | M15: 0 | N15: 0 | O15: 0 | P15: 0 | Q15: 0 | R15: 1 | S15: 0 | T15: 0 | U15: 0 | V15: 0 | W15: 0 | X15: 0 | Y15: 0 | Z15: 0 | AA15: 0 | AB15: 0 | AC15: 0 | AD15: 0 | AE15: 0 | AF15: 0 | AG15: 0 | AH15: 0 | AI15: 0 | AJ15: 0 | AK15: 0 | AL15: 0 | AM15: 0 | AN15: 0 | AO15: 0 | AP15: 0 | AQ15: 0 | AR15: 0 | AS15: 0 | AT15: 0 | AU15: 0 | AV15: 0 | AW15: 0 | AX15: 0 | AY15: 0 | AZ15: 0 | BA15: 0 | BB15: 0 | BC15: 0 | BD15: 0 | BE15: 0 | BF15: 0 | BG15: 0 | BH15: 0 | BI15: 0 | BJ15: 0 | BK15: 0 | BL15: 0 | BM15: 0
B16: 0.08 | C16: AFRMM | D16: 0 | E16: 0 | F16: 0 | G16: 0 | H16: =+H9*$B$16 -> 2.9881008 | I16: =+I9*$B$16 -> 2.9881008 | J16: =+J9*$B$16 -> 2.9881008 | K16: =+K9*$B$16 -> 2.9881008 | L16: =+L9*$B$16 -> 2.9881008 | M16: =+M9*$B$16 -> 2.9881008 | N16: =+N9*$B$16 -> 2.9881008 | O16: =+O9*$B$16 -> 2.9881008 | ... BM16: =+BM9*$B$16 -> 3.7872
C17: Cargo Cleared usd/cbm | D17: =SUM(D10:D16) -> 83.069742 | E17: =SUM(E11:E16) -> 0 | F17: =SUM(F11:F16) -> 0 | G17: =SUM(G11:G16) -> 0 | H17: =SUM(H11:H16) -> 2.9881008 | I17: =SUM(I11:I16) -> 2.9881008 | J17: =SUM(J11:J16) -> 2.9881008 | K17: =SUM(K11:K16) -> 2.9881008 | L17: =SUM(L11:L16) -> 2.9881008 | ... BM17: =SUM(BM11:BM16) -> 3359.4685
C19: Terminal cost (brl/cbm) | D19: 80 | E19: 80 | F19: 80 | G19: 80 | H19: 80 | I19: 80 | J19: 80 | K19: 80 | L19: 80 | M19: 80 | N19: 80 | O19: 80 | P19: 80 | Q19: 80 | R19: 80 | S19: 80 | T19: 80 | U19: 80 | V19: 80 | W19: 80 | X19: 80 | Y19: 80 | Z19: 80 | AA19: 80 | AB19: 80 | AC19: 80 | AD19: 80 | AE19: 80 | AF19: 80 | AG19: 80 | AH19: 80 | AI19: 80 | AJ19: 80 | AK19: 80 | AL19: 80 | AM19: 80 | AN19: 80 | AO19: 80 | AP19: 80 | AQ19: 80 | AR19: 80 | AS19: 80 | AT19: 80 | AU19: 80 | AV19: 80 | AW19: 80 | AX19: 80 | AY19: 80 | AZ19: 80 | BA19: 80 | BB19: 80 | BC19: 80 | BD19: 80 | BE19: 80 | BF19: 80 | BG19: 80 | BH19: 80 | BI19: 80 | BJ19: 80 | BK19: 80 | BL19: 80 | BM19: 80
C20: Inspection (brl/cbm) | D20: 15 | E20: 15 | F20: 15 | G20: 15 | H20: 15 | I20: 15 | J20: 15 | K20: 15 | L20: 15 | M20: 15 | N20: 15 | O20: 15 | P20: 15 | Q20: 15 | R20: 15 | S20: 15 | T20: 15 | U20: 15 | V20: 15 | W20: 15 | X20: 15 | Y20: 15 | Z20: 15 | AA20: 15 | AB20: 15 | AC20: 15 | AD20: 15 | AE20: 15 | AF20: 15 | AG20: 15 | AH20: 15 | AI20: 15 | AJ20: 15 | AK20: 15 | AL20: 15 | AM20: 15 | AN20: 15 | AO20: 15 | AP20: 15 | AQ20: 15 | AR20: 15 | AS20: 15 | AT20: 15 | AU20: 15 | AV20: 15 | AW20: 15 | AX20: 15 | AY20: 15 | AZ20: 15 | BA20: 15 | BB20: 15 | BC20: 15 | BD20: 15 | BE20: 15 | BF20: 15 | BG20: 15 | BH20: 15 | BI20: 15 | BJ20: 15 | BK20: 15 | BL20: 15 | BM20: 15
C21: Inland freight (brl/cbm) | D21: 25 | E21: 25 | F21: 25 | G21: 25 | H21: 25 | I21: 25 | J21: 25 | K21: 25 | L21: 25 | M21: 25 | N21: 25 | O21: 25 | P21: 25 | Q21: 25 | R21: 25 | S21: 25 | T21: 25 | U21: 25 | V21: 25 | W21: 25 | X21: 25 | Y21: 25 | Z21: 25 | AA21: 25 | AB21: 25 | AC21: 25 | AD21: 25 | AE21: 25 | AF21: 25 | AG21: 25 | AH21: 25 | AI21: 25 | AJ21: 25 | AK21: 25 | AL21: 25 | AM21: 25 | AN21: 25 | AO21: 25 | AP21: 25 | AQ21: 25 | AR21: 25 | AS21: 25 | AT21: 25 | AU21: 25 | AV21: 25 | AW21: 25 | AX21: 25 | AY21: 25 | AZ21: 25 | BA21: 25 | BB21: 25 | BC21: 25 | BD21: 25 | BE21: 25 | BF21: 25 | BG21: 25 | BH21: 25 | BI21: 25 | BJ21: 25 | BK21: 25 | BL21: 25 | BM21: 25
C22: Other costs (brl/cbm)
C23: Margin (brl/cbm)
C25: EX Tank disport (brl/cbm) | D25: =SUM(D19:D24) -> 120 | E25: =SUM(E17:E24) -> 120 | F25: =SUM(F17:F24) -> 120 | G25: =SUM(G17:G24) -> 120 | H25: =SUM(H17:H24) -> 122.9881 | I25: =SUM(I17:I24) -> 122.9881 | J25: =SUM(J17:J24) -> 122.9881 | K25: =SUM(K17:K24) -> 122.9881 | L25: =SUM(L17:L24) -> 122.9881 | ... BM25: =SUM(BM17:BM24) -> 3479.4685
C26: EX Tank disport (usd/cbm) | E26: =+E25/E2 -> #DIV/0! | F26: =+F25/F2 -> #DIV/0! | G26: =+G25/G2 -> #DIV/0! | H26: =+H25/H2 -> #DIV/0! | I26: =+I25/I2 -> #DIV/0! | J26: =+J25/J2 -> #DIV/0! | K26: =+K25/K2 -> #DIV/0! | L26: =+L25/L2 -> #DIV/0! | ... BM26: =+BM25/BM2 -> 582.11508
C28: NE BRZ (brl/cbm) | D28: =+'PLATTS&OPIS'!I156 -> 4470 | E28: =+'PLATTS&OPIS'!I171 -> 4480 | G28: =+'PLATTS&OPIS'!I236 -> 3565 | H28: =+'PLATTS&OPIS'!I266 -> 4150 | I28: =+'PLATTS&OPIS'!I285 -> 4195 | J28: =+'PLATTS&OPIS'!I305 -> 4445 | K28: =+'PLATTS&OPIS'!I330 -> 4045 | L28: =+'PLATTS&OPIS'!I350 -> 4095 | M28: =+'PLATTS&OPIS'!I350 -> 4095 | N28: =+M28 -> 4095 | O28: =+N28 -> 4095 | P28: =+O28 -> 4095 | Q28: =+P28 -> 4095 | R28: =+'PLATTS&OPIS'!I485 -> 3450 | S28: =+'PLATTS&OPIS'!I505 -> 3580 | T28: =+'PLATTS&OPIS'!I554 -> 3895 | U28: =+T28 -> 3895 | V28: =+U28 -> 3895 | W28: =+'PLATTS&OPIS'!I584 -> 3600 | X28: =+'PLATTS&OPIS'!I609 -> 3140 | Y28: =+'PLATTS&OPIS'!I641 -> 3300 | Z28: =+'PLATTS&OPIS'!I654 -> 3295 | AA28: =+'PLATTS&OPIS'!I677 -> 2895 | AB28: =+'PLATTS&OPIS'!I699 -> 2720 | AC28: =+'PLATTS&OPIS'!I713 -> 2800 | AD28: =+'PLATTS&OPIS'!I740 -> 3065 | AE28: =+'PLATTS&OPIS'!I761 -> 3245 | AF28: =+'PLATTS&OPIS'!I781 -> 3205 | AG28: =+'PLATTS&OPIS'!I804 -> 3175 | AH28: =+'PLATTS&OPIS'!I827 -> 3200 | AI28: =+'PLATTS&OPIS'!I846 -> 3225 | AJ28: =+'PLATTS&OPIS'!I869 -> 3640 | AK28: =+'PLATTS&OPIS'!I892 -> 3495 | AL28: =+'PLATTS&OPIS'!I912 -> 3150 | AM28: =+'PLATTS&OPIS'!I936 -> 3030 | AN28: =+'PLATTS&OPIS'!I956 -> 3100 | AO28: =+'PLATTS&OPIS'!I968 -> 3370 | AP28: =+'PLATTS&OPIS'!I1000 -> 3655 | AQ28: =+'PLATTS&OPIS'!I1019 -> 3545 | AR28: =+'PLATTS&OPIS'!I1040 -> 3395 | AS28: =+'PLATTS&OPIS'!I1063 -> 3560 | AT28: =+'PLATTS&OPIS'!I1083 -> 3640 | AU28: =+'PLATTS&OPIS'!I1104 -> 3560 | AV28: =+'PLATTS&OPIS'!I1127 -> 3550 | AW28: =+'PLATTS&OPIS'!I1148 -> 3760 | AX28: =+'PLATTS&OPIS'!I1170 -> 3545 | AY28: =+'PLATTS&OPIS'!I1182 -> 3380 | AZ28: =+AY28 -> 3380 | BA28: =+AZ28 -> 3380 | BB28: =+BA28 -> 3380 | BC28: =+BB28 -> 3380 | BD28: =+BC28 -> 3380 | BE28: =+BD28 -> 3380 | BF28: =+BE28 -> 3380 | BG28: =+BF28 -> 3380 | ... BM28: =+BL28 -> 3380
C29: 0% import tax | D29: 44501 | E29: 44531 | F29: 44562 | G29: 44593 | H29: 44621 | I29: 44652 | J29: 44682 | K29: 44713 | L29: 44743 | M29: 44774 | N29: 44805 | O29: 44835 | P29: 44866 | Q29: 44896 | R29: 44927 | S29: 44958 | T29: 44986 | U29: 45017 | V29: 45047 | W29: 45078 | X29: 45108 | Y29: 45139 | Z29: 45170 | AA29: 45200 | AB29: 45231 | AC29: 45261 | AD29: 45292 | AE29: 45323 | AF29: 45352 | AG29: 45383 | AH29: 45413 | AI29: 45444 | AJ29: 45474 | AK29: 45505 | AL29: 45536 | AM29: 45566 | AN29: 45597 | AO29: 45627 | AP29: 45658 | AQ29: 45689 | AR29: 45717 | AS29: 45748 | AT29: 45778 | AU29: 45809 | AV29: 45839 | AW29: 45870 | AX29: 45901 | AY29: 45931 | AZ29: 45962 | BA29: 45992 | BB29: 46023 | BC29: 46054 | BD29: 46082 | BE29: 46113 | BF29: 46143 | BG29: 46174 | BH29: 46204 | BI29: 46235 | BJ29: 46266 | BK29: 46296 | BL29: 46327 | BM29: 46357
C30: ARB (brl/cbm) | D30: =+D28-D25 -> 4350 | E30: =+E28-E25 -> 4360 | F30: =+F28-F25 -> -120 | G30: =+G28-G25 -> 3445 | H30: =+H28-H25 -> 4027.0119 | I30: =+I28-I25 -> 4072.0119 | J30: =+J28-J25 -> 4322.0119 | K30: =+K28-K25 -> 3922.0119 | ... BM30: =+BM28-BM25 -> -99.468501
C31: ARB (usd/cbm) | D31: =+D30/$E$1 -> #DIV/0! | E31: =+E30/E2 -> #DIV/0! | F31: =+F30/F2 -> #DIV/0! | G31: =+G30/G2 -> #DIV/0! | H31: =+H30/H2 -> #DIV/0! | I31: =+I30/I2 -> #DIV/0! | J31: =+J30/J2 -> #DIV/0! | K31: =+K30/K2 -> #DIV/0! | L31: =+L30/L2 -> #DIV/0! | ... BM31: =+BM30/BM2 -> -16.64108
C32: ARB (usd/gal) | H32: =+H31/264.172 -> #DIV/0! | I32: =+I31/264.172 -> #DIV/0! | J32: =+J31/264.172 -> #DIV/0! | K32: =+K31/264.172 -> #DIV/0! | L32: =+L31/264.172 -> #DIV/0! | M32: =+M31/264.172 -> #DIV/0! | N32: =+N31/264.172 -> #DIV/0! | O32: =+O31/264.172 -> #DIV/0! | ... BM32: =+BM31/264.172 -> -0.062993354
A34: NE incl mkt structure | C34: NE BRZ (brl/cbm) | D34: =+'PLATTS&OPIS'!I162 -> 0 | E34: =+'PLATTS&OPIS'!I177 -> 0 | G34: =+'PLATTS&OPIS'!I242 -> 0 | H34: =+'PLATTS&OPIS'!I272 -> 0 | I34: =+'PLATTS&OPIS'!I291 -> 0 | J34: =+'PLATTS&OPIS'!I311 -> 0 | K34: =+'PLATTS&OPIS'!I336 -> 0 | L34: =+'PLATTS&OPIS'!I356 -> 0 | M34: =+'PLATTS&OPIS'!I356 -> 0 | N34: =+M34 -> 0 | O34: =+N34 -> 0 | P34: =+O34 -> 0 | Q34: =+P34 -> 0 | R34: =+'PLATTS&OPIS'!I491 -> 0 | S34: =+'PLATTS&OPIS'!I511 -> 0 | T34: =+T28+T40 -> 6721 | U34: =+U28+U40 -> 6976 | V34: =+V28+V40 -> 6546.5 | W34: =+W28+W40 -> 3600 | X34: =+X28+X40 -> 5375.5 | Y34: =+Y28+Y40 -> 3300 | Z34: =+Y34+Z40 -> 3300 | AA34: =+Z34+AA40 -> 3300 | AB34: =+AB28+AB40 -> 2720 | AC34: =+AB34+AC40 -> 2720 | AD34: =+AC34+AD40 -> 2720 | AE34: =+AD34+AE40 -> 2720 | AF34: =+AF28+AF40 -> 3205 | AG34: =+AG28+AG40 -> 3175 | AH34: =+AH28+AH40 -> 3200 | AI34: =+AI28+AI40 -> 3225 | AJ34: =+AJ28+AJ40 -> 3640 | AK34: =+AK28+AK40 -> 3495 | AL34: =+AK34+AL40 -> 3495 | AM34: =+AM28+AM40 -> 3030 | AN34: =+AN28+AN40 -> 3100 | AO34: =+AO28+AO40 -> 3370 | AP34: =+AP28+AP40 -> 3655 | AQ34: =+AQ28+AQ40 -> 3545 | AR34: =+AR28+AR40 -> 3395 | AS34: =+AS28+AS40 -> 3560 | AT34: =+AT28+AT40 -> 3640 | AU34: =+AU28+AU40 -> 3560 | AV34: =+AU34+AV40 -> 3560 | AW34: =+AW28+AW40 -> 3760 | AX34: =+AX28+AX40 -> 3545 | AY34: =+AY28+AY40 -> 3380 | AZ34: =+AY34+AZ40 -> 3436.5 | BA34: =+AZ34+BA40 -> 3441 | BB34: =+BA34+BB40 -> 3466.5 | BC34: =+BB34+BC40 -> 3486.5 | BD34: =+BC34+BD40 -> 3511.5 | BE34: =+BD34+BE40 -> 3236.5 | BF34: =+BE34+BF40 -> 2956.5 | BG34: =+BF34+BG40 -> 2926.5 | ... BM34: =+BL34+BM40 -> 3141.5
C35: 0% import tax | D35: 44501 | E35: 44531 | F35: 44562 | G35: 44593 | H35: 44621 | I35: 44652 | J35: 44682 | K35: 44713 | L35: 44743 | M35: 44774 | N35: 44805 | O35: 44835 | P35: 44866 | Q35: 44896 | R35: 44927 | S35: 44958 | T35: 44986 | U35: 45017 | V35: 45047 | W35: 45078 | X35: 45108 | Y35: 45139 | Z35: 45170 | AA35: 45200 | AB35: 45231 | AC35: 45261 | AD35: 45292 | AE35: 45323 | AF35: 45352 | AG35: 45383 | AH35: 45413 | AI35: 45444 | AJ35: 45474 | AK35: 45505 | AL35: 45536 | AM35: 45566 | AN35: 45597 | AO35: 45627 | AP35: 45658 | AQ35: 45689 | AR35: 45717 | AS35: 45748 | AT35: 45778 | AU35: 45809 | AV35: 45839 | AW35: 45870 | AX35: 45901 | AY35: 45931 | AZ35: 45962 | BA35: 45992 | BB35: 46023 | BC35: 46054 | BD35: 46082 | BE35: 46113 | BF35: 46143 | BG35: 46174 | BH35: 46204 | BI35: 46235 | BJ35: 46266 | BK35: 46296 | BL35: 46327 | BM35: 46357
C36: ARB (brl/cbm) | D36: =+D34-D31 -> #DIV/0! | E36: =+E34-E31 -> #DIV/0! | F36: =+F34-F31 -> #DIV/0! | G36: =+G34-G31 -> #DIV/0! | H36: =+H34-H31 -> #DIV/0! | I36: =+I34-I31 -> #DIV/0! | J36: =+J34-J31 -> #DIV/0! | K36: =+K34-K31 -> #DIV/0! | ... S36: =+S34-S31 -> #DIV/0! | T36: =+T34-T25 -> 6578.0119 | U36: =+U34-U25 -> 6833.0119 | V36: =+V34-V25 -> 6403.5119 | W36: =+W34-W25 -> 3457.0119 | X36: =+X34-X25 -> 5232.5119 | Y36: =+Y34-Y25 -> 3157.0119 | Z36: =+Z34-Z25 -> 3157.0119 | AA36: =+AA34-AA25 -> 3157.0119 | ... BM36: =+BM34-BM25 -> -337.9685
C37: ARB (usd/cbm) | D37: =+D36/$E$1 -> #DIV/0! | E37: =+E36/E8 -> #DIV/0! | F37: =+F36/F8 -> #DIV/0! | G37: =+G36/G8 -> #DIV/0! | H37: =+H36/H8 -> #DIV/0! | I37: =+I36/I8 -> #DIV/0! | J37: =+J36/J8 -> #DIV/0! | K37: =+K36/K8 -> #DIV/0! | L37: =+L36/L8 -> #DIV/0! | ... S37: =+S36/S8 -> #DIV/0! | T37: =+T36/T2 -> #DIV/0! | U37: =+U36/U2 -> #DIV/0! | V37: =+V36/V2 -> #DIV/0! | W37: =+W36/W2 -> #DIV/0! | X37: =+X36/X2 -> #DIV/0! | Y37: =+Y36/Y2 -> #DIV/0! | Z37: =+Z36/Z2 -> #DIV/0! | AA37: =+AA36/AA2 -> #DIV/0! | ... BM37: =+BM36/BM2 -> -56.54213
C38: ARB (usd/gal) | H38: =+H37/264.172 -> #DIV/0! | I38: =+I37/264.172 -> #DIV/0! | J38: =+J37/264.172 -> #DIV/0! | K38: =+K37/264.172 -> #DIV/0! | L38: =+L37/264.172 -> #DIV/0! | M38: =+M37/264.172 -> #DIV/0! | N38: =+N37/264.172 -> #DIV/0! | O38: =+O37/264.172 -> #DIV/0! | ... BM38: =+BM37/264.172 -> -0.21403529
T40: ='settlement day'!AC12 -> 2826 | U40: ='settlement day'!AD12 -> 3081 | V40: ='settlement day'!AE12 -> 2651.5 | W40: 0 | X40: ='settlement day'!AG12 -> 2235.5 | Z40: 0 | AZ40: =AZ42-AY42 -> 56.5 | BA40: =BA42-AZ42 -> 4.5 | BB40: =BB42-BA42 -> 25.5 | BC40: =BC42-BB42 -> 20 | BD40: =BD42-BC42 -> 25 | BE40: =BE42-BD42 -> -275 | BF40: =BF42-BE42 -> -280 | BG40: =BG42-BF42 -> -30 | ... BM40: =BM42-BL42 -> 20
C41: load mth+1 | D41: 44531 | E41: 44562 | F41: 44593 | G41: 44621 | I41: 44652 | J41: 44682 | K41: 44713 | L41: 44743 | M41: 44774 | N41: 44805 | O41: 44835 | P41: 44866 | Q41: 44896 | R41: 44927 | S41: 44958 | T41: 44986 | U41: 45017 | V41: 45047 | W41: 45078 | X41: 45108 | Y41: 45139 | Z41: 45170 | AA41: 45200 | AB41: 45231 | AC41: 45261 | AD41: 45292 | AE41: 45323 | AF41: 45352 | AG41: 45383 | AH41: 45413 | AI41: 45444 | AJ41: 45474 | AK41: 45505 | AL41: 45536 | AM41: 45566 | AN41: 45597 | AO41: 45627 | AP41: 45658 | AQ41: 45689 | AR41: 45717 | AS41: 45748 | AT41: 45778 | AU41: 45809 | AV41: 45839 | AW41: 45870 | AX41: 45901 | AY41: 45931 | AZ41: 45962 | BA41: 45992 | BB41: 46023 | BC41: 46054 | BD41: 46082 | BE41: 46113 | BF41: 46143 | BG41: 46174 | BH41: 46204 | BI41: 46235 | BJ41: 46266 | BK41: 46296 | BL41: 46327 | BM41: 46357
C42: B3 hyd | D42: =+'settlement day'!N13 -> 0 | E42: =+'settlement day'!O13 -> 0 | F42: =+'settlement day'!P13 -> 0 | G42: =+'settlement day'!Q13 -> 0 | I42: =+'settlement day'!R13 -> 0 | J42: =+'settlement day'!S13 -> 0 | K42: =+'settlement day'!T13 -> 0 | L42: =+'settlement day'!U13 -> 0 | M42: =+'settlement day'!V13 -> 0 | N42: =+'settlement day'!W13 -> 0 | O42: =+'settlement day'!X13 -> 0 | P42: =+'settlement day'!Y13 -> 0 | ... BM42: =+'settlement day'!BV13 -> 2605
C43: B3 hyd ex plant | D43: =+(D42-'mkt data'!$G$23+'mkt data'!$G$24)/'mkt data'!$H$25 -> -99.524494 | E43: =+(E42-'mkt data'!$G$23+'mkt data'!$G$24)/'mkt data'!$H$25 -> -99.524494 | F43: =+(F42-'mkt data'!$G$23+'mkt data'!$G$24)/'mkt data'!$H$25 -> -99.524494 | G43: =+(G42-'mkt data'!$G$23+'mkt data'!$G$24)/'mkt data'!$H$25 -> -99.524494 | I43: =+(I42-'mkt data'!$G$23+'mkt data'!$G$24)/'mkt data'!$H$25 -> -99.524494 | J43: =+(J42-'mkt data'!$G$23+'mkt data'!$G$24)/'mkt data'!$H$25 -> -99.524494 | K43: =+(K42-'mkt data'!$G$23+'mkt data'!$G$24)/'mkt data'!$H$25 -> -99.524494 | L43: =+(L42-'mkt data'!$G$23+'mkt data'!$G$24)/'mkt data'!$H$25 -> -99.524494 | M43: =+(M42-'mkt data'!$G$23+'mkt data'!$G$24)/'mkt data'!$H$25 -> -99.524494 | N43: =+(N42-'mkt data'!$G$23+'mkt data'!$G$24)/'mkt data'!$H$25 -> -99.524494 | O43: =+(O42-'mkt data'!$G$23+'mkt data'!$G$24)/'mkt data'!$H$25 -> -99.524494 | P43: =+(P42-'mkt data'!$G$23+'mkt data'!$G$24)/'mkt data'!$H$25 -> -99.524494 | ... BM43: =+(BM42-'mkt data'!$G$23+'mkt data'!$G$24)/'mkt data'!$H$25 -> 2781.1567
B45: =+'mkt data'!G26 -> 0.12 | C45: B3 anydrous ex plant | D45: =+((D42-'mkt data'!$G$23)*'mkt data'!$H$26)+('mkt data'!$G$24) -> -100.8 | E45: =+((E42-'mkt data'!$G$23)*'mkt data'!$H$26)+('mkt data'!$G$24) -> -100.8 | F45: =+((F42-'mkt data'!$G$23)*'mkt data'!$H$26)+('mkt data'!$G$24) -> -100.8 | G45: =+((G42-'mkt data'!$G$23)*'mkt data'!$H$26)+('mkt data'!$G$24) -> -100.8 | I45: =+((I42-'mkt data'!$G$23)*'mkt data'!$H$26)+('mkt data'!$G$24) -> -100.8 | J45: =+((J42-'mkt data'!$G$23)*'mkt data'!$H$26)+('mkt data'!$G$24) -> -100.8 | K45: =+((K42-'mkt data'!$G$23)*'mkt data'!$H$26)+('mkt data'!$G$24) -> -100.8 | L45: =+((L42-'mkt data'!$G$23)*'mkt data'!$H$26)+('mkt data'!$G$24) -> -100.8 | M45: =+((M42-'mkt data'!$G$23)*'mkt data'!$H$26)+('mkt data'!$G$24) -> -100.8 | N45: =+((N42-'mkt data'!$G$23)*'mkt data'!$H$26)+('mkt data'!$G$24) -> -100.8 | O45: =+((O42-'mkt data'!$G$23)*'mkt data'!$H$26)+('mkt data'!$G$24) -> -100.8 | P45: =+((P42-'mkt data'!$G$23)*'mkt data'!$H$26)+('mkt data'!$G$24) -> -100.8 | ... BM45: =+((BM42-'mkt data'!$G$23)*'mkt data'!$H$26)+('mkt data'!$G$24) -> 2816.8
B47: =470/0.867 -> 542.09919 | C47: B3 CS to NE (brl/cbm) | D47: =+D45+$B$47 -> 441.29919 | E47: =+E45+$B$47 -> 441.29919 | F47: =+F45+$B$47 -> 441.29919 | G47: =+G45+$B$47 -> 441.29919 | I47: =+I45+$B$47 -> 441.29919 | J47: =+J45+$B$47 -> 441.29919 | K47: =+K45+$B$47 -> 441.29919 | L47: =+L45+$B$47 -> 441.29919 | M47: =+M45+$B$47 -> 441.29919 | N47: =+N45+$B$47 -> 441.29919 | O47: =+O45+$B$47 -> 441.29919 | P47: =+P45+$B$47 -> 441.29919 | ... BM47: =+BM45+$B$47 -> 3358.8992
D48: 44531 | E48: 44562 | F48: 44593 | G48: 44621 | I48: 44652 | J48: 44682 | K48: 44713 | L48: 44743 | M48: 44774 | N48: 44805 | O48: 44835 | P48: 44866 | Q48: 44896 | R48: 44927 | S48: 44958 | T48: 44986 | U48: 45017 | V48: 45047 | W48: 45078 | X48: 45108 | Y48: 45139 | Z48: 45170 | AA48: 45200 | AB48: 45231 | AC48: 45261 | AD48: 45292 | AE48: 45323 | AF48: 45352 | AG48: 45383 | AH48: 45413 | AI48: 45444 | AJ48: 45474 | AK48: 45505 | AL48: 45536 | AM48: 45566 | AN48: 45597 | AO48: 45627 | AP48: 45658 | AQ48: 45689 | AR48: 45717 | AS48: 45748 | AT48: 45778 | AU48: 45809 | AV48: 45839 | AW48: 45870 | AX48: 45901 | AY48: 45931 | AZ48: 45962 | BA48: 45992 | BB48: 46023 | BC48: 46054 | BD48: 46082 | BE48: 46113 | BF48: 46143 | BG48: 46174 | BH48: 46204 | BI48: 46235 | BJ48: 46266 | BK48: 46296 | BL48: 46327 | BM48: 46357
C49: ARB (brl/cbm) | D49: =+D47-D25 -> 321.29919 | E49: =+E47-E25 -> 321.29919 | F49: =+F47-F25 -> 321.29919 | G49: =+G47-G25 -> 321.29919 | I49: =+I47-I25 -> 318.31109 | J49: =+J47-J25 -> 318.31109 | K49: =+K47-K25 -> 318.31109 | L49: =+L47-L25 -> 318.31109 | M49: =+M47-M25 -> 318.31109 | N49: =+N47-N25 -> 318.31109 | O49: =+O47-O25 -> 318.31109 | P49: =+P47-P25 -> 318.31109 | ... BM49: =+BM47-BM25 -> -120.56931
C50: ARB (usd/cbm) | D50: =+D49/$E$1 -> #DIV/0! | E50: =+E49/E2 -> #DIV/0! | F50: =+F49/F2 -> #DIV/0! | G50: =+G49/G2 -> #DIV/0! | I50: =+I49/H2 -> #DIV/0! | J50: =+J49/I2 -> #DIV/0! | K50: =+K49/J2 -> #DIV/0! | L50: =+L49/L2 -> #DIV/0! | M50: =+M49/M2 -> #DIV/0! | N50: =+N49/N2 -> #DIV/0! | O50: =+O49/O2 -> #DIV/0! | P50: =+P49/P2 -> #DIV/0! | Q50: =+Q49/Q2 -> #DIV/0! | R50: =+R49/R2 -> #DIV/0! | S50: =+S49/S2 -> #DIV/0! | ... BM50: =+BM49/BM2 -> -20.171245
C51: ARB (usd/gal) | I51: =+I50/264.172 -> #DIV/0! | J51: =+J50/264.172 -> #DIV/0! | K51: =+K50/264.172 -> #DIV/0! | L51: =+L50/264.172 -> #DIV/0! | M51: =+M50/264.172 -> #DIV/0! | N51: =+N50/264.172 -> #DIV/0! | O51: =+O50/264.172 -> #DIV/0! | P51: =+P50/264.172 -> #DIV/0! | ... BM51: =+BM50/264.172 -> -0.076356485

Sheet mkt data
E2: BRAZIL | F2: A/H spread | G2: 0.125 | H2: 1.125 | K2: EU T1 bid (eur/cbm) | L2: -150
F3: Anhydrous CARB/ISCC premium (usd/cbm) | G3: 35 | K3: EU T2 bid (eur/cbm) | L3: 0
F4: Grade B qlt premium (brl/cbm) | G4: 150 | H4: 150 | K4: EU import duty (eur/cbm) | L4: 102
F5: Freight RB-Santos (brl/cbm) | G5: 300 | K5: EU extra import duty for US (eur/cbm) | L5: 0
F6: Freight RB-Paulinia (brl/cbm) | G6: 90
F7: Freight Paulinia-Santos (brl/cbm) | G7: 80
F8: Storage load port (brl/cbm) | G8: 0 | H8: 100 | K8: CS BRZ import cost (brl/cbm) | L8: =+L9+20 -> 130
F9: PIS COFINS | G9: 130.9 | K9: NE BRZ import cost (brl/cbm) | L9: 110
F10: ICMS SP | G10: 0.12 | H10: =+(100-12)/100 -> 0.88 | K10: Extra PIS/COFINS on imports BRZ (%) | L10: 0.1175
F11: INSS | G11: 0.0285
F12: Port Costs + Inspection BRZ (brl/cbm) | G12: 15 | H12: =10+5 -> 15
F14: USA basis U3 cert (cpg) | G14: 0.27 | K14: Conversion factor gallons to cbm | L14: 264.172
F15: USA basis ASTM (cpg) | G15: 0.08 | K15: Conversion usd/mt to usd/cbm (anhydrous) | L15: 0.789
F16: USA basis U5 (cpg) | G16: 0.12 | K16: Conversion usd/mt to usd/cbm (hydrous) | L16: 0.805
F17: USA basis PNS (cpg) | G17: 0.11
F18: USA basis GRADE B (cpg) | G18: 0.3
F22: B3
F23: Frete | G23: 90 | H23: R$/cbm
F24: PIS/COFINS | G24: 0 | H24: R$/cbm | I24: 130.9 | J24: >> PEC 15-16, no Pis/COFINS?
F25: ICMS | G25: 0.0957 | H25: 0.9043
F26: anh/hydrous | G26: 0.12 | H26: 1.12

Sheet settlement day
AM1: =+AM8*264.172/AM29 -> 387.34338
B2: Last settlement date:
B3: 45946 | C3: 44197 | D3: 44228 | E3: 44256 | F3: 44287 | G3: 44317 | H3: 44348 | I3: 44378 | J3: 44409 | K3: 44440 | L3: 44470 | M3: 44501 | N3: 44531 | O3: 44562 | P3: 44593 | Q3: 44621 | R3: 44652 | S3: 44682 | T3: 44713 | U3: 44743 | V3: 44774 | W3: 44805 | X3: 44835 | Y3: 44866 | Z3: 44896 | AA3: 44927 | AB3: 44958 | AC3: 44986 | AD3: 45017 | AE3: 45047 | AF3: 45078 | AG3: 45108 | AH3: 45139 | AI3: 45170 | AJ3: 45200 | AK3: 45231 | AL3: 45261 | AM3: 45292 | AN3: 45323 | AO3: 45352 | AP3: 45383 | AQ3: 45413 | AR3: 45444 | AS3: 45474 | AT3: 45505 | AU3: 45536 | AV3: 45566 | AW3: 45597 | AX3: 45627 | AY3: 45658 | AZ3: 45689 | BA3: 45717 | BB3: 45748 | BC3: 45778 | BD3: 45809 | BE3: 45839 | BF3: 45870 | BG3: 45901 | BH3: 45931 | BI3: 45962 | BJ3: 45992 | BK3: 46023 | BL3: 46054 | BM3: 46082 | BN3: 46113 | BO3: 46143 | BP3: 46174 | BQ3: 46204 | BR3: 46235 | BS3: 46266 | BT3: 46296 | BU3: 46327 | BV3: 46357 | BW3: Q4 25 | BX3: CAL 26 | BY3: Q1 26 | BZ3: Q2 26 | CA3: Q3 26 | CB3: Q4 26
B4: EU T2 CME (Eur/cbm) | F4: =+(AVERAGE('[1]PLATTt & OPIt'!C6:C26)) -> #REF! | G4: =+(AVERAGE('PLATTS&OPIS'!C28:C46)) -> 635.15789 | H4: =+(AVERAGE('PLATTS&OPIS'!C48:C69)) -> 656.59091 | I4: 656.591 | J4: 660.56 | K4: 792.716 | L4: 987.179 | M4: 1276.807 | N4: 1060.917 | O4: 938.775 | P4: 946.188 | Q4: 1143.152 | R4: 1189.013 | S4: 1138.583 | T4: 1273.825 | U4: 1199.5 | V4: 1039.591 | W4: 997.405 | X4: 862.19 | Y4: 785.955 | Z4: 722.163 | AA4: 751.75 | AB4: 835.488 | AC4: 899.63 | AD4: 866.806 | AE4: 756.563 | AF4: 775.773 | AG4: 736.012 | AH4: 726.841 | AI4: 785.869 | AJ4: 813.386 | AK4: 685.023 | AL4: 601.987 | AM4: 605.795 | AN4: 633.667 | AO4: 676.85 | AP4: 685.095 | AQ4: 691.964 | AR4: 745.688 | AS4: 715.793 | AT4: 669.56 | AU4: 629.988 | AV4: 652.424 | AW4: 670.012 | AX4: 662.988 | AY4: 671.466 | AZ4: 688.088 | BA4: 671.56 | BB4: 645.275 | BC4: 596.288 | BD4: 595.345 | BE4: 602.5 | BF4: 601.813 | BG4: 658.352 | BI4: =+BH5-BI5 -> 100 | BJ4: =+BI5-BJ5 -> 52 | BK4: =+BJ5-BK5 -> 24 | BL4: =+BK5-BL5 -> -8 | BM4: =+BL5-BM5 -> -10 | BN4: =+BM5-BN5 -> -12 | BO4: =+BN5-BO5 -> -1 | BP4: =+BO5-BP5 -> 0 | ... BV4: =+BU5-BV5 -> 0 | BY4: =+BW5-BY5 -> 83.333333 | BZ4: =+BY5-BZ5 -> -22
B5: Settlement | C5: =+'T2'!C27 -> 0 | D5: =+'T2'!D27 -> 0 | E5: =+'T2'!E27 -> 0 | F5: =+'T2'!F70 -> 0 | G5: =+'T2'!G91 -> 0 | H5: =+'T2'!H139 -> 0 | I5: =+'T2'!I139 -> 0 | J5: =+'T2'!J139 -> 0 | K5: =+'T2'!K160 -> 0 | L5: =+'T2'!L202 -> 0 | M5: =+'T2'!M202 -> 0 | N5: =+'T2'!N244 -> 0 | O5: =+'T2'!O244 -> 0 | P5: =+'T2'!P270 -> 0 | Q5: =+'T2'!Q286 -> 0 | R5: =+'T2'!R310 -> 0 | S5: =INDEX('T2'!$A$4:$BB$1048576,MATCH('settlement day'!$B$3,'T2'!$A$4:$A$1048576,0),MATCH('settlement day'!S$3,'T2'!$A$4:$BB$4,0)) -> 0 | T5: =INDEX('T2'!$A$4:$BB$1048576,MATCH('settlement day'!$B$3,'T2'!$A$4:$A$1048576,0),MATCH('settlement day'!T$3,'T2'!$A$4:$BB$4,0)) -> 0 | U5: =INDEX('T2'!$A$4:$BB$1048576,MATCH('settlement day'!$B$3,'T2'!$A$4:$A$1048576,0),MATCH('settlement day'!U$3,'T2'!$A$4:$BB$4,0)) -> 0 | V5: =INDEX('T2'!$A$4:$BB$1048576,MATCH('settlement day'!$B$3,'T2'!$A$4:$A$1048576,0),MATCH('settlement day'!V$3,'T2'!$A$4:$BB$4,0)) -> 0 | W5: =INDEX('T2'!$A$4:$BB$1048576,MATCH('settlement day'!$B$3,'T2'!$A$4:$A$1048576,0),MATCH('settlement day'!W$3,'T2'!$A$4:$BB$4,0)) -> 0 | X5: =INDEX('T2'!$A$4:$BB$1048576,MATCH('settlement day'!$B$3,'T2'!$A$4:$A$1048576,0),MATCH('settlement day'!X$3,'T2'!$A$4:$BB$4,0)) -> 0 | Y5: =INDEX('T2'!$A$4:$BB$1048576,MATCH('settlement day'!$B$3,'T2'!$A$4:$A$1048576,0),MATCH('settlement day'!Y$3,'T2'!$A$4:$BB$4,0)) -> 0 | Z5: =INDEX('T2'!$A$4:$BB$1048576,MATCH('settlement day'!$B$3,'T2'!$A$4:$A$1048576,0),MATCH('settlement day'!Z$3,'T2'!$A$4:$BB$4,0)) -> 0 | ... BB5: =INDEX('T2'!$A$4:$BB$1048576,MATCH('settlement day'!$B$3,'T2'!$A$4:$A$1048576,0),MATCH('settlement day'!BB$3,'T2'!$A$4:$BB$4,0)) -> 0 | BC5: =INDEX('T2'!$A$4:$CC$1048576,MATCH('settlement day'!$B$3,'T2'!$A$4:$A$1048576,0),MATCH('settlement day'!BC$3,'T2'!$A$4:$CC$4,0)) -> 0 | BD5: =INDEX('T2'!$A$4:$CC$1048576,MATCH('settlement day'!$B$3,'T2'!$A$4:$A$1048576,0),MATCH('settlement day'!BD$3,'T2'!$A$4:$CC$4,0)) -> 0 | BE5: =INDEX('T2'!$A$4:$CC$1048576,MATCH('settlement day'!$B$3,'T2'!$A$4:$A$1048576,0),MATCH('settlement day'!BE$3,'T2'!$A$4:$CC$4,0)) -> 0 | BF5: =INDEX('T2'!$A$4:$CC$1048576,MATCH('settlement day'!$B$3,'T2'!$A$4:$A$1048576,0),MATCH('settlement day'!BF$3,'T2'!$A$4:$CC$4,0)) -> 0 | BG5: =INDEX('T2'!$A$4:$CC$1048576,MATCH('settlement day'!$B$3,'T2'!$A$4:$A$1048576,0),MATCH('settlement day'!BG$3,'T2'!$A$4:$CC$4,0)) -> 0 | BH5: =INDEX('T2'!$A$4:$CC$1048576,MATCH('settlement day'!$B$3,'T2'!$A$4:$A$1048576,0),MATCH('settlement day'!BH$3,'T2'!$A$4:$CC$4,0)) -> 780 | BI5: =INDEX('T2'!$A$4:$CC$1048576,MATCH('settlement day'!$B$3,'T2'!$A$4:$A$1048576,0),MATCH('settlement day'!BI$3,'T2'!$A$4:$CC$4,0)) -> 680 | BJ5: =INDEX('T2'!$A$4:$CC$1048576,MATCH('settlement day'!$B$3,'T2'!$A$4:$A$1048576,0),MATCH('settlement day'!BJ$3,'T2'!$A$4:$CC$4,0)) -> 628 | ... BV5: =INDEX('T2'!$A$4:$CC$1048576,MATCH('settlement day'!$B$3,'T2'!$A$4:$A$1048576,0),MATCH('settlement day'!BV$3,'T2'!$A$4:$CC$4,0)) -> 610 | BW5: =SUM(BH5:BJ5)/3 -> 696 | BX5: =SUM(BK5:BV5)/12 -> 621.75 | BY5: =SUM(BK5:BM5)/3 -> 612.66667 | BZ5: =SUM(BN5:BP5)/3 -> 634.66667 | CA5: =SUM(BQ5:BS5)/3 -> 628 | CB5: =SUM(BT5:BV5)/3 -> 611.66667
B6: D-1 | C6: =+'T2'!C26 -> 0 | D6: =+'T2'!D26 -> 0 | E6: =+'T2'!E26 -> 0 | F6: =+'T2'!F69 -> 0 | G6: =+'T2'!G90 -> 0 | H6: =+'T2'!H138 -> 0 | I6: =+'T2'!I138 -> 0 | J6: =+'T2'!J138 -> 0 | K6: =+'T2'!K159 -> 0 | L6: =+'T2'!L201 -> 0 | M6: =+'T2'!M201 -> 0 | N6: =+'T2'!N243 -> 0 | O6: =+'T2'!O243 -> 0 | P6: =+'T2'!P269 -> 0 | Q6: =+'T2'!Q285 -> 0 | R6: =+'T2'!R309 -> 0 | S6: =OFFSET(INDEX('T2'!$A$4:$BB$1048576,MATCH('settlement day'!$B$3,'T2'!$A$4:$A$1048576,0),MATCH('settlement day'!S$3,'T2'!$A$4:$BB$4,0)),-1,0) -> 0 | T6: =OFFSET(INDEX('T2'!$A$4:$BB$1048576,MATCH('settlement day'!$B$3,'T2'!$A$4:$A$1048576,0),MATCH('settlement day'!T$3,'T2'!$A$4:$BB$4,0)),-1,0) -> 0 | U6: =OFFSET(INDEX('T2'!$A$4:$BB$1048576,MATCH('settlement day'!$B$3,'T2'!$A$4:$A$1048576,0),MATCH('settlement day'!U$3,'T2'!$A$4:$BB$4,0)),-1,0) -> 0 | V6: =OFFSET(INDEX('T2'!$A$4:$BB$1048576,MATCH('settlement day'!$B$3,'T2'!$A$4:$A$1048576,0),MATCH('settlement day'!V$3,'T2'!$A$4:$BB$4,0)),-1,0) -> 0 | W6: =OFFSET(INDEX('T2'!$A$4:$BB$1048576,MATCH('settlement day'!$B$3,'T2'!$A$4:$A$1048576,0),MATCH('settlement day'!W$3,'T2'!$A$4:$BB$4,0)),-1,0) -> 0 | X6: =OFFSET(INDEX('T2'!$A$4:$BB$1048576,MATCH('settlement day'!$B$3,'T2'!$A$4:$A$1048576,0),MATCH('settlement day'!X$3,'T2'!$A$4:$BB$4,0)),-1,0) -> 0 | Y6: =OFFSET(INDEX('T2'!$A$4:$BB$1048576,MATCH('settlement day'!$B$3,'T2'!$A$4:$A$1048576,0),MATCH('settlement day'!Y$3,'T2'!$A$4:$BB$4,0)),-1,0) -> 0 | Z6: =OFFSET(INDEX('T2'!$A$4:$BB$1048576,MATCH('settlement day'!$B$3,'T2'!$A$4:$A$1048576,0),MATCH('settlement day'!Z$3,'T2'!$A$4:$BB$4,0)),-1,0) -> 0 | ... BB6: =OFFSET(INDEX('T2'!$A$4:$BB$1048576,MATCH('settlement day'!$B$3,'T2'!$A$4:$A$1048576,0),MATCH('settlement day'!BB$3,'T2'!$A$4:$BB$4,0)),-1,0) -> 0 | BC6: =OFFSET(INDEX('T2'!$A$4:$CC$1048576,MATCH('settlement day'!$B$3,'T2'!$A$4:$A$1048576,0),MATCH('settlement day'!BC$3,'T2'!$A$4:$CC$4,0)),-1,0) -> 0 | BD6: =OFFSET(INDEX('T2'!$A$4:$CC$1048576,MATCH('settlement day'!$B$3,'T2'!$A$4:$A$1048576,0),MATCH('settlement day'!BD$3,'T2'!$A$4:$CC$4,0)),-1,0) -> 0 | BE6: =OFFSET(INDEX('T2'!$A$4:$CC$1048576,MATCH('settlement day'!$B$3,'T2'!$A$4:$A$1048576,0),MATCH('settlement day'!BE$3,'T2'!$A$4:$CC$4,0)),-1,0) -> 0 | BF6: =OFFSET(INDEX('T2'!$A$4:$CC$1048576,MATCH('settlement day'!$B$3,'T2'!$A$4:$A$1048576,0),MATCH('settlement day'!BF$3,'T2'!$A$4:$CC$4,0)),-1,0) -> 0 | BG6: =OFFSET(INDEX('T2'!$A$4:$CC$1048576,MATCH('settlement day'!$B$3,'T2'!$A$4:$A$1048576,0),MATCH('settlement day'!BG$3,'T2'!$A$4:$CC$4,0)),-1,0) -> 0 | BH6: =OFFSET(INDEX('T2'!$A$4:$CC$1048576,MATCH('settlement day'!$B$3,'T2'!$A$4:$A$1048576,0),MATCH('settlement day'!BH$3,'T2'!$A$4:$CC$4,0)),-1,0) -> 770 | BI6: =OFFSET(INDEX('T2'!$A$4:$CC$1048576,MATCH('settlement day'!$B$3,'T2'!$A$4:$A$1048576,0),MATCH('settlement day'!BI$3,'T2'!$A$4:$CC$4,0)),-1,0) -> 672 | BJ6: =OFFSET(INDEX('T2'!$A$4:$CC$1048576,MATCH('settlement day'!$B$3,'T2'!$A$4:$A$1048576,0),MATCH('settlement day'!BJ$3,'T2'!$A$4:$CC$4,0)),-1,0) -> 630 | ... BV6: =OFFSET(INDEX('T2'!$A$4:$CC$1048576,MATCH('settlement day'!$B$3,'T2'!$A$4:$A$1048576,0),MATCH('settlement day'!BV$3,'T2'!$A$4:$CC$4,0)),-1,0) -> 604 | BW6: =SUM(BH6:BJ6)/3 -> 690.66667 | BX6: =SUM(BK6:BV6)/12 -> 619 | BY6: =SUM(BK6:BM6)/3 -> 612 | BZ6: =SUM(BN6:BP6)/3 -> 634 | CA6: =SUM(BQ6:BS6)/3 -> 626 | CB6: =SUM(BT6:BV6)/3 -> 604
B7: Variation | C7: =C5-C6 -> 0 | D7: =D5-D6 -> 0 | E7: =E5-E6 -> 0 | F7: =F5-F6 -> 0 | G7: =G5-G6 -> 0 | H7: =H5-H6 -> 0 | I7: =I5-I6 -> 0 | J7: =J5-J6 -> 0 | ... CB7: =CB5-CB6 -> 7.6666667
B8: US CU CME (US$/gal) | F8: =AVERAGE('PLATTS&OPIS'!B6:B26)/100 -> 2.1193095 | G8: =AVERAGE('PLATTS&OPIS'!B28:B46)/100 -> 2.551 | H8: =AVERAGE('PLATTS&OPIS'!B48:B69)/100 -> 2.3812045 | I8: 2.23 | J8: 2.24732 | K8: 2.41169 | L8: 2.60193 | M8: 3.4042 | N8: 2.973 | O8: 2.15903 | P8: 2.15674 | Q8: 2.46807 | R8: 2.63575 | S8: 2.75574 | T8: 2.78986 | U8: 2.51938 | V8: 2.54667 | W8: 2.44292 | X8: 2.46457 | Y8: 2.57873 | Z8: 2.20306 | AA8: 2.19058 | AB8: 2.17318 | AC8: 2.24302 | AD8: 2.42224 | AE8: 2.43773 | AF8: 2.50714 | AG8: 2.44342 | AH8: 2.1663 | AI8: 2.35293 | AJ8: 2.27059 | AK8: 1.86235 | AL8: 1.66878 | AM8: 1.58898 | AN8: 1.50218 | AO8: 1.5776 | AP8: 1.65439 | AQ8: 1.78299 | AR8: 1.92958 | AS8: 1.90324 | AT8: 1.826 | AU8: 1.69903 | AV8: 1.56505 | AW8: 1.62655 | AX8: 1.62131 | AY8: 1.68214 | AZ8: 1.75087 | BA8: 1.7022 | BB8: 1.77026 | BC8: 1.73208 | BD8: 1.657 | BE8: 1.7473 | BF8: 1.79381 | BG8: 1.98583 | BI8: =+BH9-BI9 -> 0.13 | BJ8: =+BI9-BJ9 -> 0.06 | BK8: =+BJ9-BK9 -> 0.0525 | BL8: =+BK9-BL9 -> -0.005 | BM8: =+BL9-BM9 -> -0.025 | BN8: =+BM9-BN9 -> -0.025 | BO8: =+BN9-BO9 -> -0.0225 | BP8: =+BO9-BP9 -> -0.0125 | ... BV8: =+BU9-BV9 -> 0.0225
B9: Last settlement | C9: =+CU!D27 -> 0 | D9: =+CU!E27 -> 0 | E9: =+CU!F27 -> 0 | F9: =+CU!G70 -> 0 | G9: =+CU!H91 -> 0 | H9: =+CU!I139 -> 0 | I9: =+CU!J139 -> 0 | J9: =+CU!K139 -> 0 | K9: =+CU!L160 -> 0 | L9: =+CU!M202 -> 0 | M9: =+CU!N202 -> 0 | N9: =+CU!O244 -> 0 | O9: =+CU!P244 -> 0 | P9: =+CU!Q269 -> 0 | Q9: =+CU!R286 -> 0 | R9: =+CU!S310 -> 0 | S9: =INDEX(CU!$A$4:$BB$1048576,MATCH('settlement day'!$B$3,CU!$A$4:$A$1048576,0),MATCH('settlement day'!S$3,CU!$A$4:$BB$4,0)) -> 0 | T9: =INDEX(CU!$A$4:$BB$1048576,MATCH('settlement day'!$B$3,CU!$A$4:$A$1048576,0),MATCH('settlement day'!T$3,CU!$A$4:$BB$4,0)) -> 0 | U9: =INDEX(CU!$A$4:$BB$1048576,MATCH('settlement day'!$B$3,CU!$A$4:$A$1048576,0),MATCH('settlement day'!U$3,CU!$A$4:$BB$4,0)) -> 0 | V9: =INDEX(CU!$A$4:$BB$1048576,MATCH('settlement day'!$B$3,CU!$A$4:$A$1048576,0),MATCH('settlement day'!V$3,CU!$A$4:$BB$4,0)) -> 0 | W9: =INDEX(CU!$A$4:$BB$1048576,MATCH('settlement day'!$B$3,CU!$A$4:$A$1048576,0),MATCH('settlement day'!W$3,CU!$A$4:$BB$4,0)) -> 0 | X9: =INDEX(CU!$A$4:$BB$1048576,MATCH('settlement day'!$B$3,CU!$A$4:$A$1048576,0),MATCH('settlement day'!X$3,CU!$A$4:$BB$4,0)) -> 0 | Y9: =INDEX(CU!$A$4:$BB$1048576,MATCH('settlement day'!$B$3,CU!$A$4:$A$1048576,0),MATCH('settlement day'!Y$3,CU!$A$4:$BB$4,0)) -> 0 | Z9: =INDEX(CU!$A$4:$BB$1048576,MATCH('settlement day'!$B$3,CU!$A$4:$A$1048576,0),MATCH('settlement day'!Z$3,CU!$A$4:$BB$4,0)) -> 0 | ... BA9: =INDEX(CU!$A$4:$BB$1048576,MATCH('settlement day'!$B$3,CU!$A$4:$A$1048576,0),MATCH('settlement day'!BA$3,CU!$A$4:$BB$4,0)) -> 0 | BB9: =INDEX(CU!$A$4:$CC$1048576,MATCH('settlement day'!$B$3,CU!$A$4:$A$1048576,0),MATCH('settlement day'!BB$3,CU!$A$4:$CC$4,0)) -> 0 | BC9: =INDEX(CU!$A$4:$CC$1048576,MATCH('settlement day'!$B$3,CU!$A$4:$A$1048576,0),MATCH('settlement day'!BC$3,CU!$A$4:$CC$4,0)) -> 0 | BD9: =INDEX(CU!$A$4:$CC$1048576,MATCH('settlement day'!$B$3,CU!$A$4:$A$1048576,0),MATCH('settlement day'!BD$3,CU!$A$4:$CC$4,0)) -> 0 | BE9: =INDEX(CU!$A$4:$CC$1048576,MATCH('settlement day'!$B$3,CU!$A$4:$A$1048576,0),MATCH('settlement day'!BE$3,CU!$A$4:$CC$4,0)) -> 0 | BF9: =INDEX(CU!$A$4:$CC$1048576,MATCH('settlement day'!$B$3,CU!$A$4:$A$1048576,0),MATCH('settlement day'!BF$3,CU!$A$4:$CC$4,0)) -> 0 | BG9: =INDEX(CU!$A$4:$CC$1048576,MATCH('settlement day'!$B$3,CU!$A$4:$A$1048576,0),MATCH('settlement day'!BG$3,CU!$A$4:$CC$4,0)) -> 0 | BH9: =INDEX(CU!$A$4:$CC$1048576,MATCH('settlement day'!$B$3,CU!$A$4:$A$1048576,0),MATCH('settlement day'!BH$3,CU!$A$4:$CC$4,0)) -> 1.82 | BI9: =INDEX(CU!$A$4:$CC$1048576,MATCH('settlement day'!$B$3,CU!$A$4:$A$1048576,0),MATCH('settlement day'!BI$3,CU!$A$4:$CC$4,0)) -> 1.69 | ... BV9: =INDEX(CU!$A$4:$CC$1048576,MATCH('settlement day'!$B$3,CU!$A$4:$A$1048576,0),MATCH('settlement day'!BV$3,CU!$A$4:$CC$4,0)) -> 1.5825 | BW9: =SUM(BH9:BJ9)/3 -> 1.7133333 | BX9: =SUM(BK9:BV9)/12 -> 1.6291667 | BY9: =SUM(BK9:BM9)/3 -> 1.5891667 | BZ9: =SUM(BN9:BP9)/3 -> 1.6516667 | CA9: =SUM(BQ9:BS9)/3 -> 1.6675 | CB9: =SUM(BT9:BV9)/3 -> 1.6083333
B10: day before D-1 | C10: =+CU!D26 -> 0 | D10: =+CU!E26 -> 0 | E10: =+CU!F26 -> 0 | F10: =+CU!G69 -> 0 | G10: =+CU!H90 -> 0 | H10: =+CU!I138 -> 0 | I10: =+CU!J138 -> 0 | J10: =+CU!K138 -> 0 | K10: =+CU!L159 -> 0 | L10: =+CU!M201 -> 0 | M10: =+CU!N201 -> 0 | N10: =+CU!O243 -> 0 | O10: =+CU!P243 -> 0 | P10: =+CU!Q267 -> 0 | Q10: =+CU!R285 -> 0 | R10: =+CU!S309 -> 0 | S10: =OFFSET(INDEX(CU!$A$4:$BB$1048576,MATCH('settlement day'!$B$3,CU!$A$4:$A$1048576,0),MATCH('settlement day'!S$3,CU!$A$4:$BB$4,0)),-1,0) -> 0 | T10: =OFFSET(INDEX(CU!$A$4:$BB$1048576,MATCH('settlement day'!$B$3,CU!$A$4:$A$1048576,0),MATCH('settlement day'!T$3,CU!$A$4:$BB$4,0)),-1,0) -> 0 | U10: =OFFSET(INDEX(CU!$A$4:$BB$1048576,MATCH('settlement day'!$B$3,CU!$A$4:$A$1048576,0),MATCH('settlement day'!U$3,CU!$A$4:$BB$4,0)),-1,0) -> 0 | V10: =OFFSET(INDEX(CU!$A$4:$BB$1048576,MATCH('settlement day'!$B$3,CU!$A$4:$A$1048576,0),MATCH('settlement day'!V$3,CU!$A$4:$BB$4,0)),-1,0) -> 0 | W10: =OFFSET(INDEX(CU!$A$4:$BB$1048576,MATCH('settlement day'!$B$3,CU!$A$4:$A$1048576,0),MATCH('settlement day'!W$3,CU!$A$4:$BB$4,0)),-1,0) -> 0 | X10: =OFFSET(INDEX(CU!$A$4:$BB$1048576,MATCH('settlement day'!$B$3,CU!$A$4:$A$1048576,0),MATCH('settlement day'!X$3,CU!$A$4:$BB$4,0)),-1,0) -> 0 | Y10: =OFFSET(INDEX(CU!$A$4:$BB$1048576,MATCH('settlement day'!$B$3,CU!$A$4:$A$1048576,0),MATCH('settlement day'!Y$3,CU!$A$4:$BB$4,0)),-1,0) -> 0 | Z10: =OFFSET(INDEX(CU!$A$4:$BB$1048576,MATCH('settlement day'!$B$3,CU!$A$4:$A$1048576,0),MATCH('settlement day'!Z$3,CU!$A$4:$BB$4,0)),-1,0) -> 0 | ... BA10: =OFFSET(INDEX(CU!$A$4:$BB$1048576,MATCH('settlement day'!$B$3,CU!$A$4:$A$1048576,0),MATCH('settlement day'!BA$3,CU!$A$4:$BB$4,0)),-1,0) -> 0 | BB10: =OFFSET(INDEX(CU!$A$4:$CC$1048576,MATCH('settlement day'!$B$3,CU!$A$4:$A$1048576,0),MATCH('settlement day'!BB$3,CU!$A$4:$CC$4,0)),-1,0) -> 0 | BC10: =OFFSET(INDEX(CU!$A$4:$CC$1048576,MATCH('settlement day'!$B$3,CU!$A$4:$A$1048576,0),MATCH('settlement day'!BC$3,CU!$A$4:$CC$4,0)),-1,0) -> 0 | BD10: =OFFSET(INDEX(CU!$A$4:$CC$1048576,MATCH('settlement day'!$B$3,CU!$A$4:$A$1048576,0),MATCH('settlement day'!BD$3,CU!$A$4:$CC$4,0)),-1,0) -> 0 | BE10: =OFFSET(INDEX(CU!$A$4:$CC$1048576,MATCH('settlement day'!$B$3,CU!$A$4:$A$1048576,0),MATCH('settlement day'!BE$3,CU!$A$4:$CC$4,0)),-1,0) -> 0 | BF10: =OFFSET(INDEX(CU!$A$4:$CC$1048576,MATCH('settlement day'!$B$3,CU!$A$4:$A$1048576,0),MATCH('settlement day'!BF$3,CU!$A$4:$CC$4,0)),-1,0) -> 0 | BG10: =OFFSET(INDEX(CU!$A$4:$CC$1048576,MATCH('settlement day'!$B$3,CU!$A$4:$A$1048576,0),MATCH('settlement day'!BG$3,CU!$A$4:$CC$4,0)),-1,0) -> 0 | BH10: =OFFSET(INDEX(CU!$A$4:$CC$1048576,MATCH('settlement day'!$B$3,CU!$A$4:$A$1048576,0),MATCH('settlement day'!BH$3,CU!$A$4:$CC$4,0)),-1,0) -> 1.8275 | BI10: =OFFSET(INDEX(CU!$A$4:$CC$1048576,MATCH('settlement day'!$B$3,CU!$A$4:$A$1048576,0),MATCH('settlement day'!BI$3,CU!$A$4:$CC$4,0)),-1,0) -> 1.71 | ... BV10: =OFFSET(INDEX(CU!$A$4:$CC$1048576,MATCH('settlement day'!$B$3,CU!$A$4:$A$1048576,0),MATCH('settlement day'!BV$3,CU!$A$4:$CC$4,0)),-1,0) -> 1.5825 | BW10: =SUM(BH10:BJ10)/3 -> 1.7258333 | BX10: =SUM(BK10:BV10)/12 -> 1.63 | BY10: =SUM(BK10:BM10)/3 -> 1.5916667 | BZ10: =SUM(BN10:BP10)/3 -> 1.6525 | CA10: =SUM(BQ10:BS10)/3 -> 1.6675 | CB10: =SUM(BT10:BV10)/3 -> 1.6083333
B11: Variation | C11: =C9-C10 -> 0 | D11: =D9-D10 -> 0 | E11: =E9-E10 -> 0 | F11: =F9-F10 -> 0 | G11: =G9-G10 -> 0 | H11: =H9-H10 -> 0 | I11: =I9-I10 -> 0 | J11: =J9-J10 -> 0 | ... BV11: =BV9-BV10 -> 0 | BW11: =+BW9-BW10 -> -0.0125 | BX11: =+BX9-BX10 -> -0.00083333333 | BY11: =+BY9-BY10 -> -0.0025 | BZ11: =+BZ9-BZ10 -> -0.00083333333 | CA11: =+CA9-CA10 -> 0 | CB11: =+CB9-CB10 -> 0
B12: B3 ETH (R$/cbm) | F12: =AVERAGE('B3 ETH'!H22:H26) -> 2726.8 | G12: =AVERAGE('[2]ESALr Paulinia'!B2808:B2812) -> #REF! | H12: =+'ESALQ Paulinia'!E2834 -> 2873.9 | I12: 3023 | J12: 3273 | K12: 3365.5 | L12: 3897.5 | M12: 3587.5 | N12: 3403 | O12: 3179 | P12: 2936 | Q12: 3478.5 | R12: 3594.5 | S12: 3244 | T12: 3080 | U12: 3035 | V12: 2478 | W12: 2580.5 | X12: 2795 | Y12: 2895 | Z12: 2971.5 | AA12: 2852 | AB12: 2819.5 | AC12: 2826 | AD12: 3081 | AE12: 2651.5 | AF12: 2613 | AG12: 2235.5 | AH12: 2303 | AI12: 2276 | AJ12: 2317.5 | AK12: 2177 | AL12: 2004 | AM12: 2247.5 | AN12: 2235 | AO12: 2380 | AP12: 2427.5 | AQ12: 2406.5 | AR12: 2564 | AS12: 2692.5 | AT12: 2677 | AU12: 2600.5 | AV12: 2705.5 | AW12: 2726.5 | AX12: 2745.5 | AY12: 2986 | AZ12: 2945 | BA12: 2834 | BB12: 2807 | BC12: 2705 | BD12: 2718 | BE12: 2715 | BF12: 2815 | BG12: 2830.5 | BH12: =+BG13-BH13 -> -2843.5 | BI12: =+BH13-BI13 -> -56.5 | BJ12: =+BI13-BJ13 -> -4.5 | BK12: =+BJ13-BK13 -> -25.5 | BL12: =+BK13-BL13 -> -20 | BM12: =+BL13-BM13 -> -25 | BN12: =+BM13-BN13 -> 275 | BO12: =+BN13-BO13 -> 280 | ... BV12: =+BU13-BV13 -> -20
B13: Last settlement | C13: =+'B3 ETH'!E27 -> 0 | D13: =+'B3 ETH'!F27 -> 0 | E13: =+'B3 ETH'!G27 -> 0 | F13: =+'B3 ETH'!H70 -> 0 | G13: =+'B3 ETH'!I91 -> 0 | H13: =+'B3 ETH'!J139 -> 0 | I13: =+'B3 ETH'!K139 -> 0 | J13: =+'B3 ETH'!L139 -> 0 | K13: =+'B3 ETH'!M160 -> 0 | L13: =+'B3 ETH'!N202 -> 0 | M13: =+'B3 ETH'!O202 -> 0 | N13: =+'B3 ETH'!P244 -> 0 | O13: =+'B3 ETH'!Q244 -> 0 | P13: =+'B3 ETH'!R268 -> 0 | Q13: =+'B3 ETH'!S286 -> 0 | R13: =+'B3 ETH'!T310 -> 0 | S13: =INDEX('B3 ETH'!$A$4:$BB$1048576,MATCH('settlement day'!$B$3,'B3 ETH'!$A$4:$A$1048576,0),MATCH('settlement day'!S$3,'B3 ETH'!$A$4:$BB$4,0)) -> 0 | T13: =INDEX('B3 ETH'!$A$4:$BB$1048576,MATCH('settlement day'!$B$3,'B3 ETH'!$A$4:$A$1048576,0),MATCH('settlement day'!T$3,'B3 ETH'!$A$4:$BB$4,0)) -> 0 | U13: =INDEX('B3 ETH'!$A$4:$BB$1048576,MATCH('settlement day'!$B$3,'B3 ETH'!$A$4:$A$1048576,0),MATCH('settlement day'!U$3,'B3 ETH'!$A$4:$BB$4,0)) -> 0 | V13: =INDEX('B3 ETH'!$A$4:$BB$1048576,MATCH('settlement day'!$B$3,'B3 ETH'!$A$4:$A$1048576,0),MATCH('settlement day'!V$3,'B3 ETH'!$A$4:$BB$4,0)) -> 0 | W13: =INDEX('B3 ETH'!$A$4:$BB$1048576,MATCH('settlement day'!$B$3,'B3 ETH'!$A$4:$A$1048576,0),MATCH('settlement day'!W$3,'B3 ETH'!$A$4:$BB$4,0)) -> 0 | X13: =INDEX('B3 ETH'!$A$4:$BB$1048576,MATCH('settlement day'!$B$3,'B3 ETH'!$A$4:$A$1048576,0),MATCH('settlement day'!X$3,'B3 ETH'!$A$4:$BB$4,0)) -> 0 | Y13: =INDEX('B3 ETH'!$A$4:$BB$1048576,MATCH('settlement day'!$B$3,'B3 ETH'!$A$4:$A$1048576,0),MATCH('settlement day'!Y$3,'B3 ETH'!$A$4:$BB$4,0)) -> 0 | Z13: =INDEX('B3 ETH'!$A$4:$BB$1048576,MATCH('settlement day'!$B$3,'B3 ETH'!$A$4:$A$1048576,0),MATCH('settlement day'!Z$3,'B3 ETH'!$A$4:$BB$4,0)) -> 0 | ... AZ13: =INDEX('B3 ETH'!$A$4:$BB$1048576,MATCH('settlement day'!$B$3,'B3 ETH'!$A$4:$A$1048576,0),MATCH('settlement day'!AZ$3,'B3 ETH'!$A$4:$BB$4,0)) -> 0 | BA13: =INDEX('B3 ETH'!$A$4:$CC$1048576,MATCH('settlement day'!$B$3,'B3 ETH'!$A$4:$A$1048576,0),MATCH('settlement day'!BA$3,'B3 ETH'!$A$4:$CC$4,0)) -> 0 | BB13: =INDEX('B3 ETH'!$A$4:$CC$1048576,MATCH('settlement day'!$B$3,'B3 ETH'!$A$4:$A$1048576,0),MATCH('settlement day'!BB$3,'B3 ETH'!$A$4:$CC$4,0)) -> 0 | BC13: =INDEX('B3 ETH'!$A$4:$CC$1048576,MATCH('settlement day'!$B$3,'B3 ETH'!$A$4:$A$1048576,0),MATCH('settlement day'!BC$3,'B3 ETH'!$A$4:$CC$4,0)) -> 0 | BD13: =INDEX('B3 ETH'!$A$4:$CC$1048576,MATCH('settlement day'!$B$3,'B3 ETH'!$A$4:$A$1048576,0),MATCH('settlement day'!BD$3,'B3 ETH'!$A$4:$CC$4,0)) -> 0 | BE13: =INDEX('B3 ETH'!$A$4:$CC$1048576,MATCH('settlement day'!$B$3,'B3 ETH'!$A$4:$A$1048576,0),MATCH('settlement day'!BE$3,'B3 ETH'!$A$4:$CC$4,0)) -> 0 | BF13: =INDEX('B3 ETH'!$A$4:$CC$1048576,MATCH('settlement day'!$B$3,'B3 ETH'!$A$4:$A$1048576,0),MATCH('settlement day'!BF$3,'B3 ETH'!$A$4:$CC$4,0)) -> 0 | BG13: =INDEX('B3 ETH'!$A$4:$CC$1048576,MATCH('settlement day'!$B$3,'B3 ETH'!$A$4:$A$1048576,0),MATCH('settlement day'!BG$3,'B3 ETH'!$A$4:$CC$4,0)) -> 0 | BH13: =INDEX('B3 ETH'!$A$4:$CC$1048576,MATCH('settlement day'!$B$3,'B3 ETH'!$A$4:$A$1048576,0),MATCH('settlement day'!BH$3,'B3 ETH'!$A$4:$CC$4,0)) -> 2843.5 | ... BV13: =INDEX('B3 ETH'!$A$4:$CC$1048576,MATCH('settlement day'!$B$3,'B3 ETH'!$A$4:$A$1048576,0),MATCH('settlement day'!BV$3,'B3 ETH'!$A$4:$CC$4,0)) -> 2605 | BW13: =SUM(BH13:BJ13)/3 -> 2882.6667 | BX13: =SUM(BK13:BV13)/12 -> 2632.0833 | BY13: =SUM(BK13:BM13)/3 -> 2951.6667 | BZ13: =SUM(BN13:BP13)/3 -> 2503.3333 | CA13: =SUM(BQ13:BS13)/3 -> 2485 | CB13: =SUM(BT13:BV13)/3 -> 2588.3333
B14: day before D-1 | C14: =+'B3 ETH'!E26 -> 0 | D14: =+'B3 ETH'!F26 -> 0 | E14: =+'B3 ETH'!G26 -> 0 | F14: =+'B3 ETH'!H69 -> 0 | G14: =+'B3 ETH'!I90 -> 0 | H14: =+'B3 ETH'!J138 -> 0 | I14: =+'B3 ETH'!K138 -> 0 | J14: =+'B3 ETH'!L138 -> 0 | K14: =+'B3 ETH'!M159 -> 0 | L14: =+'B3 ETH'!N201 -> 0 | M14: =+'B3 ETH'!O201 -> 0 | N14: =+'B3 ETH'!P243 -> 0 | O14: =+'B3 ETH'!Q243 -> 0 | P14: =+'B3 ETH'!R267 -> 0 | Q14: =+'B3 ETH'!S285 -> 0 | R14: =+'B3 ETH'!T309 -> 0 | S14: =OFFSET(INDEX('B3 ETH'!$A$4:$BB$1048576,MATCH('settlement day'!$B$3,'B3 ETH'!$A$4:$A$1048576,0),MATCH('settlement day'!S$3,'B3 ETH'!$A$4:$BB$4,0)),-1,0) -> 0 | T14: =OFFSET(INDEX('B3 ETH'!$A$4:$BB$1048576,MATCH('settlement day'!$B$3,'B3 ETH'!$A$4:$A$1048576,0),MATCH('settlement day'!T$3,'B3 ETH'!$A$4:$BB$4,0)),-1,0) -> 0 | U14: =OFFSET(INDEX('B3 ETH'!$A$4:$BB$1048576,MATCH('settlement day'!$B$3,'B3 ETH'!$A$4:$A$1048576,0),MATCH('settlement day'!U$3,'B3 ETH'!$A$4:$BB$4,0)),-1,0) -> 0 | V14: =OFFSET(INDEX('B3 ETH'!$A$4:$BB$1048576,MATCH('settlement day'!$B$3,'B3 ETH'!$A$4:$A$1048576,0),MATCH('settlement day'!V$3,'B3 ETH'!$A$4:$BB$4,0)),-1,0) -> 0 | W14: =OFFSET(INDEX('B3 ETH'!$A$4:$BB$1048576,MATCH('settlement day'!$B$3,'B3 ETH'!$A$4:$A$1048576,0),MATCH('settlement day'!W$3,'B3 ETH'!$A$4:$BB$4,0)),-1,0) -> 0 | X14: =OFFSET(INDEX('B3 ETH'!$A$4:$BB$1048576,MATCH('settlement day'!$B$3,'B3 ETH'!$A$4:$A$1048576,0),MATCH('settlement day'!X$3,'B3 ETH'!$A$4:$BB$4,0)),-1,0) -> 0 | Y14: =OFFSET(INDEX('B3 ETH'!$A$4:$BB$1048576,MATCH('settlement day'!$B$3,'B3 ETH'!$A$4:$A$1048576,0),MATCH('settlement day'!Y$3,'B3 ETH'!$A$4:$BB$4,0)),-1,0) -> 0 | Z14: =OFFSET(INDEX('B3 ETH'!$A$4:$BB$1048576,MATCH('settlement day'!$B$3,'B3 ETH'!$A$4:$A$1048576,0),MATCH('settlement day'!Z$3,'B3 ETH'!$A$4:$BB$4,0)),-1,0) -> 0 | ... AZ14: =OFFSET(INDEX('B3 ETH'!$A$4:$BB$1048576,MATCH('settlement day'!$B$3,'B3 ETH'!$A$4:$A$1048576,0),MATCH('settlement day'!AZ$3,'B3 ETH'!$A$4:$BB$4,0)),-1,0) -> 0 | BA14: =OFFSET(INDEX('B3 ETH'!$A$4:$CC$1048576,MATCH('settlement day'!$B$3,'B3 ETH'!$A$4:$A$1048576,0),MATCH('settlement day'!BA$3,'B3 ETH'!$A$4:$CC$4,0)),-1,0) -> 0 | BB14: =OFFSET(INDEX('B3 ETH'!$A$4:$CC$1048576,MATCH('settlement day'!$B$3,'B3 ETH'!$A$4:$A$1048576,0),MATCH('settlement day'!BB$3,'B3 ETH'!$A$4:$CC$4,0)),-1,0) -> 0 | BC14: =OFFSET(INDEX('B3 ETH'!$A$4:$CC$1048576,MATCH('settlement day'!$B$3,'B3 ETH'!$A$4:$A$1048576,0),MATCH('settlement day'!BC$3,'B3 ETH'!$A$4:$CC$4,0)),-1,0) -> 0 | BD14: =OFFSET(INDEX('B3 ETH'!$A$4:$CC$1048576,MATCH('settlement day'!$B$3,'B3 ETH'!$A$4:$A$1048576,0),MATCH('settlement day'!BD$3,'B3 ETH'!$A$4:$CC$4,0)),-1,0) -> 0 | BE14: =OFFSET(INDEX('B3 ETH'!$A$4:$CC$1048576,MATCH('settlement day'!$B$3,'B3 ETH'!$A$4:$A$1048576,0),MATCH('settlement day'!BE$3,'B3 ETH'!$A$4:$CC$4,0)),-1,0) -> 0 | BF14: =OFFSET(INDEX('B3 ETH'!$A$4:$CC$1048576,MATCH('settlement day'!$B$3,'B3 ETH'!$A$4:$A$1048576,0),MATCH('settlement day'!BF$3,'B3 ETH'!$A$4:$CC$4,0)),-1,0) -> 0 | BG14: =OFFSET(INDEX('B3 ETH'!$A$4:$CC$1048576,MATCH('settlement day'!$B$3,'B3 ETH'!$A$4:$A$1048576,0),MATCH('settlement day'!BG$3,'B3 ETH'!$A$4:$CC$4,0)),-1,0) -> 0 | BH14: =OFFSET(INDEX('B3 ETH'!$A$4:$CC$1048576,MATCH('settlement day'!$B$3,'B3 ETH'!$A$4:$A$1048576,0),MATCH('settlement day'!BH$3,'B3 ETH'!$A$4:$CC$4,0)),-1,0) -> 2840.5 | ... BV14: =OFFSET(INDEX('B3 ETH'!$A$4:$CC$1048576,MATCH('settlement day'!$B$3,'B3 ETH'!$A$4:$A$1048576,0),MATCH('settlement day'!BV$3,'B3 ETH'!$A$4:$CC$4,0)),-1,0) -> 2605 | BW14: =SUM(BH14:BJ14)/3 -> 2883.3333 | BX14: =SUM(BK14:BV14)/12 -> 2632.0833 | BY14: =SUM(BK14:BM14)/3 -> 2951.6667 | BZ14: =SUM(BN14:BP14)/3 -> 2503.3333 | CA14: =SUM(BQ14:BS14)/3 -> 2485 | CB14: =SUM(BT14:BV14)/3 -> 2588.3333
B15: Variation | C15: =C13-C14 -> 0 | D15: =D13-D14 -> 0 | E15: =E13-E14 -> 0 | F15: =F13-F14 -> 0 | G15: =G13-G14 -> 0 | H15: =H13-H14 -> 0 | I15: =I13-I14 -> 0 | J15: =J13-J14 -> 0 | ... BV15: =BV13-BV14 -> 0 | BW15: =+BW13-BW14 -> -0.66666667 | BX15: =+BX13-BX14 -> 0 | BY15: =+BY13-BY14 -> 0 | BZ15: =+BZ13-BZ14 -> 0 | CA15: =+CA13-CA14 -> 0 | CB15: =+CB13-CB14 -> 0
B16: RBOB (US$/gal) | N16: 1.9801 | O16: 2.2285 | P16: 2.5543 | Q16: 2.797 | R16: 3.1896 | S16: 3.4721 | T16: 4.0804 | U16: 3.6498 | V16: 3.4881 | W16: 2.6059 | X16: 2.4726 | Y16: 2.8107 | Z16: 2.4185 | AA16: 2.4595 | AB16: 2.5435 | AC16: 2.4343 | AD16: 2.7005 | AE16: 2.578 | AF16: 2.5599 | AG16: 2.634 | AH16: 2.929 | AI16: 2.7664 | AJ16: 2.4399 | AK16: 2.2227 | AL16: 2.1998 | AM16: 2.1026 | AN16: 2.1833 | AO16: 2.3043 | AP16: 2.7611 | AQ16: 2.7108 | AR16: 2.426 | AS16: 2.5291 | AT16: 2.482 | AU16: 2.2117 | AV16: 1.9621 | AW16: 2.0035 | AX16: 1.9437 | AY16: 2.0015 | AZ16: 2.0365 | BA16: 1.9703 | BB16: 2.2831 | BC16: 2.037 | BD16: 2.0384 | BE16: 2.0798 | BF16: 2.2156 | BG16: 2.1876 | BH16: 1.9729 | BJ16: =+BI17-BJ17 -> 0.0513 | BK16: =+BJ17-BK17 -> 0.0226 | BL16: =+BK17-BL17 -> -0.0058 | BM16: =+BL17-BM17 -> -0.0194 | BN16: =+BM17-BN17 -> -0.2044 | BO16: =+BN17-BO17 -> -0.0039 | BP16: =+BO17-BP17 -> 0.0091 | BQ16: =+BP17-BQ17 -> 0.0184 | ... BV16: =+BU17-BV17 -> 0.0209
B17: Last settlement | C17: =+RBOB!C26 -> 0 | D17: =+RBOB!D26 -> 0 | E17: =+RBOB!E26 -> 0 | F17: =+RBOB!F70 -> 0 | G17: =+RBOB!G91 -> 0 | H17: =+RBOB!H139 -> 0 | I17: =+RBOB!I139 -> 0 | J17: =+RBOB!J139 -> 0 | K17: =+RBOB!K160 -> 0 | L17: =+RBOB!L202 -> 0 | M17: =+RBOB!M202 -> 0 | N17: =+RBOB!N244 -> 0 | O17: =+RBOB!O244 -> 0 | P17: =+RBOB!P268 -> 0 | Q17: =+RBOB!Q286 -> 0 | R17: =+RBOB!R310 -> 0 | S17: =INDEX(RBOB!$A$4:$BB$1048576,MATCH('settlement day'!$B$3,RBOB!$A$4:$A$1048576,0),MATCH('settlement day'!S$3,RBOB!$A$4:$BB$4,0)) -> 0 | T17: =INDEX(RBOB!$A$4:$BB$1048576,MATCH('settlement day'!$B$3,RBOB!$A$4:$A$1048576,0),MATCH('settlement day'!T$3,RBOB!$A$4:$BB$4,0)) -> 0 | U17: =INDEX(RBOB!$A$4:$BB$1048576,MATCH('settlement day'!$B$3,RBOB!$A$4:$A$1048576,0),MATCH('settlement day'!U$3,RBOB!$A$4:$BB$4,0)) -> 0 | V17: =INDEX(RBOB!$A$4:$BB$1048576,MATCH('settlement day'!$B$3,RBOB!$A$4:$A$1048576,0),MATCH('settlement day'!V$3,RBOB!$A$4:$BB$4,0)) -> 0 | W17: =INDEX(RBOB!$A$4:$BB$1048576,MATCH('settlement day'!$B$3,RBOB!$A$4:$A$1048576,0),MATCH('settlement day'!W$3,RBOB!$A$4:$BB$4,0)) -> 0 | X17: =INDEX(RBOB!$A$4:$BB$1048576,MATCH('settlement day'!$B$3,RBOB!$A$4:$A$1048576,0),MATCH('settlement day'!X$3,RBOB!$A$4:$BB$4,0)) -> 0 | Y17: =INDEX(RBOB!$A$4:$BB$1048576,MATCH('settlement day'!$B$3,RBOB!$A$4:$A$1048576,0),MATCH('settlement day'!Y$3,RBOB!$A$4:$BB$4,0)) -> 0 | Z17: =INDEX(RBOB!$A$4:$BB$1048576,MATCH('settlement day'!$B$3,RBOB!$A$4:$A$1048576,0),MATCH('settlement day'!Z$3,RBOB!$A$4:$BB$4,0)) -> 0 | ... BB17: =INDEX(RBOB!$A$4:$BB$1048576,MATCH('settlement day'!$B$3,RBOB!$A$4:$A$1048576,0),MATCH('settlement day'!BB$3,RBOB!$A$4:$BB$4,0)) -> 0 | BC17: =INDEX(RBOB!$A$4:$CC$1048576,MATCH('settlement day'!$B$3,RBOB!$A$4:$A$1048576,0),MATCH('settlement day'!BC$3,RBOB!$A$4:$CC$4,0)) -> 0 | BD17: =INDEX(RBOB!$A$4:$CC$1048576,MATCH('settlement day'!$B$3,RBOB!$A$4:$A$1048576,0),MATCH('settlement day'!BD$3,RBOB!$A$4:$CC$4,0)) -> 0 | BE17: =INDEX(RBOB!$A$4:$CC$1048576,MATCH('settlement day'!$B$3,RBOB!$A$4:$A$1048576,0),MATCH('settlement day'!BE$3,RBOB!$A$4:$CC$4,0)) -> 0 | BF17: =INDEX(RBOB!$A$4:$CC$1048576,MATCH('settlement day'!$B$3,RBOB!$A$4:$A$1048576,0),MATCH('settlement day'!BF$3,RBOB!$A$4:$CC$4,0)) -> 0 | BG17: =INDEX(RBOB!$A$4:$CC$1048576,MATCH('settlement day'!$B$3,RBOB!$A$4:$A$1048576,0),MATCH('settlement day'!BG$3,RBOB!$A$4:$CC$4,0)) -> 0 | BH17: =INDEX(RBOB!$A$4:$CC$1048576,MATCH('settlement day'!$B$3,RBOB!$A$4:$A$1048576,0),MATCH('settlement day'!BH$3,RBOB!$A$4:$CC$4,0)) -> 0 | BI17: =INDEX(RBOB!$A$4:$CC$1048576,MATCH('settlement day'!$B$3,RBOB!$A$4:$A$1048576,0),MATCH('settlement day'!BI$3,RBOB!$A$4:$CC$4,0)) -> 1.8117 | BJ17: =INDEX(RBOB!$A$4:$CC$1048576,MATCH('settlement day'!$B$3,RBOB!$A$4:$A$1048576,0),MATCH('settlement day'!BJ$3,RBOB!$A$4:$CC$4,0)) -> 1.7604 | ... BV17: =INDEX(RBOB!$A$4:$CC$1048576,MATCH('settlement day'!$B$3,RBOB!$A$4:$A$1048576,0),MATCH('settlement day'!BV$3,RBOB!$A$4:$CC$4,0)) -> 1.6998 | BW17: =SUM(BH17:BJ17)/3 -> 1.1907 | BX17: =SUM(BK17:BV17)/12 -> 1.839225 | BY17: =SUM(BK17:BM17)/3 -> 1.7481333 | BZ17: =SUM(BN17:BP17)/3 -> 1.9669667 | CA17: =SUM(BQ17:BS17)/3 -> 1.9173333 | CB17: =SUM(BT17:BV17)/3 -> 1.7244667
B18: day before D-1 | C18: =+RBOB!C25 -> 0 | D18: =+RBOB!D25 -> 0 | E18: =+RBOB!E25 -> 0 | F18: =+RBOB!F69 -> 0 | G18: =+RBOB!G90 -> 0 | H18: =+RBOB!H138 -> 0 | I18: =+RBOB!I138 -> 0 | J18: =+RBOB!J138 -> 0 | K18: =+RBOB!K159 -> 0 | L18: =+RBOB!L201 -> 0 | M18: =+RBOB!M201 -> 0 | N18: =+RBOB!N243 -> 0 | O18: =+RBOB!O243 -> 0 | P18: =+RBOB!P267 -> 0 | Q18: =+RBOB!Q285 -> 0 | R18: =+RBOB!R309 -> 0 | S18: =OFFSET(INDEX(RBOB!$A$4:$BB$1048576,MATCH('settlement day'!$B$3,RBOB!$A$4:$A$1048576,0),MATCH('settlement day'!S$3,RBOB!$A$4:$BB$4,0)),-1,0) -> 0 | T18: =OFFSET(INDEX(RBOB!$A$4:$BB$1048576,MATCH('settlement day'!$B$3,RBOB!$A$4:$A$1048576,0),MATCH('settlement day'!T$3,RBOB!$A$4:$BB$4,0)),-1,0) -> 0 | U18: =OFFSET(INDEX(RBOB!$A$4:$BB$1048576,MATCH('settlement day'!$B$3,RBOB!$A$4:$A$1048576,0),MATCH('settlement day'!U$3,RBOB!$A$4:$BB$4,0)),-1,0) -> 0 | V18: =OFFSET(INDEX(RBOB!$A$4:$BB$1048576,MATCH('settlement day'!$B$3,RBOB!$A$4:$A$1048576,0),MATCH('settlement day'!V$3,RBOB!$A$4:$BB$4,0)),-1,0) -> 0 | W18: =OFFSET(INDEX(RBOB!$A$4:$BB$1048576,MATCH('settlement day'!$B$3,RBOB!$A$4:$A$1048576,0),MATCH('settlement day'!W$3,RBOB!$A$4:$BB$4,0)),-1,0) -> 0 | X18: =OFFSET(INDEX(RBOB!$A$4:$BB$1048576,MATCH('settlement day'!$B$3,RBOB!$A$4:$A$1048576,0),MATCH('settlement day'!X$3,RBOB!$A$4:$BB$4,0)),-1,0) -> 0 | Y18: =OFFSET(INDEX(RBOB!$A$4:$BB$1048576,MATCH('settlement day'!$B$3,RBOB!$A$4:$A$1048576,0),MATCH('settlement day'!Y$3,RBOB!$A$4:$BB$4,0)),-1,0) -> 0 | Z18: =OFFSET(INDEX(RBOB!$A$4:$BB$1048576,MATCH('settlement day'!$B$3,RBOB!$A$4:$A$1048576,0),MATCH('settlement day'!Z$3,RBOB!$A$4:$BB$4,0)),-1,0) -> 0 | ... BB18: =OFFSET(INDEX(RBOB!$A$4:$BB$1048576,MATCH('settlement day'!$B$3,RBOB!$A$4:$A$1048576,0),MATCH('settlement day'!BB$3,RBOB!$A$4:$BB$4,0)),-1,0) -> 0 | BC18: =OFFSET(INDEX(RBOB!$A$4:$CC$1048576,MATCH('settlement day'!$B$3,RBOB!$A$4:$A$1048576,0),MATCH('settlement day'!BC$3,RBOB!$A$4:$CC$4,0)),-1,0) -> 0 | BD18: =OFFSET(INDEX(RBOB!$A$4:$CC$1048576,MATCH('settlement day'!$B$3,RBOB!$A$4:$A$1048576,0),MATCH('settlement day'!BD$3,RBOB!$A$4:$CC$4,0)),-1,0) -> 0 | BE18: =OFFSET(INDEX(RBOB!$A$4:$CC$1048576,MATCH('settlement day'!$B$3,RBOB!$A$4:$A$1048576,0),MATCH('settlement day'!BE$3,RBOB!$A$4:$CC$4,0)),-1,0) -> 0 | BF18: =OFFSET(INDEX(RBOB!$A$4:$CC$1048576,MATCH('settlement day'!$B$3,RBOB!$A$4:$A$1048576,0),MATCH('settlement day'!BF$3,RBOB!$A$4:$CC$4,0)),-1,0) -> 0 | BG18: =OFFSET(INDEX(RBOB!$A$4:$CC$1048576,MATCH('settlement day'!$B$3,RBOB!$A$4:$A$1048576,0),MATCH('settlement day'!BG$3,RBOB!$A$4:$CC$4,0)),-1,0) -> 0 | BH18: =OFFSET(INDEX(RBOB!$A$4:$CC$1048576,MATCH('settlement day'!$B$3,RBOB!$A$4:$A$1048576,0),MATCH('settlement day'!BH$3,RBOB!$A$4:$CC$4,0)),-1,0) -> 0 | BI18: =OFFSET(INDEX(RBOB!$A$4:$CC$1048576,MATCH('settlement day'!$B$3,RBOB!$A$4:$A$1048576,0),MATCH('settlement day'!BI$3,RBOB!$A$4:$CC$4,0)),-1,0) -> 1.8344 | BJ18: =OFFSET(INDEX(RBOB!$A$4:$CC$1048576,MATCH('settlement day'!$B$3,RBOB!$A$4:$A$1048576,0),MATCH('settlement day'!BJ$3,RBOB!$A$4:$CC$4,0)),-1,0) -> 1.7841 | ... BV18: =OFFSET(INDEX(RBOB!$A$4:$CC$1048576,MATCH('settlement day'!$B$3,RBOB!$A$4:$A$1048576,0),MATCH('settlement day'!BV$3,RBOB!$A$4:$CC$4,0)),-1,0) -> 1.7157 | BW18: =SUM(BH18:BJ18)/3 -> 1.2061667 | BX18: =SUM(BK18:BV18)/12 -> 1.8570583 | BY18: =SUM(BK18:BM18)/3 -> 1.7696667 | BZ18: =SUM(BN18:BP18)/3 -> 1.9843333 | CA18: =SUM(BQ18:BS18)/3 -> 1.9339 | CB18: =SUM(BT18:BV18)/3 -> 1.7403333
B19: Variation | C19: =C17-C18 -> 0 | D19: =D17-D18 -> 0 | E19: =E17-E18 -> 0 | F19: =F17-F18 -> 0 | G19: =G17-G18 -> 0 | H19: =H17-H18 -> 0 | I19: =I17-I18 -> 0 | J19: =J17-J18 -> 0 | ... CB19: =CB17-CB18 -> -0.015866667
B20: US CORN Fut. (US$/bu) | AC20: =+Z21-AC21 -> 0 | AE20: =+AC21-AE21 -> 0 | AG20: =+AE21-AG21 -> 0 | AI20: =+AG21-AI21 -> 0 | AL20: =+AI21-AL21 -> 0 | AO20: =+AL21-AO21 -> 0 | AQ20: =+AO21-AQ21 -> 0 | AS20: =+AQ21-AS21 -> 0 | AU20: =+AS21-AU21 -> 0 | AX20: =+AU21-AX21 -> 0 | BA20: =+AX21-BA21 -> 0 | BC20: =+AZ21-BC21 -> 0 | BE20: =+BB21-BE21 -> 0 | BG20: =+BD21-BG21 -> 0 | BJ20: =+BG21-BJ21 -> -4.216 | BM20: =+BJ21-BM21 -> -0.138 | BO20: =+BM21-BO21 -> -0.082 | BQ20: =+BO21-BQ21 -> -0.058 | BS20: =+BQ21-BS21 -> 0.032 | BV20: =+BS21-BV21 -> -0.11
B21: Last settlement | E21: =+CORN!C26 -> 0 | G21: =+CORN!D83 -> 0 | I21: =+CORN!E83 -> 0 | J21: =+K21-I21 -> 0 | K21: =+CORN!F125 -> 0 | L21: =+N21-K21 -> 0 | M21: =+N21-I21 -> 0 | N21: =+CORN!G192 -> 0 | Q21: =+CORN!H270 -> 0 | S21: =IFERROR(INDEX(CORN!$A$4:$BB$1048576,MATCH('settlement day'!$B$3,CORN!$A$4:$A$1048576,0),MATCH('settlement day'!S$3,CORN!$A$4:$BB$4,0)),"") -> 0 | T21: =IFERROR(INDEX(CORN!$A$4:$BB$1048576,MATCH('settlement day'!$B$3,CORN!$A$4:$A$1048576,0),MATCH('settlement day'!T$3,CORN!$A$4:$BB$4,0)),"") | U21: =IFERROR(INDEX(CORN!$A$4:$BB$1048576,MATCH('settlement day'!$B$3,CORN!$A$4:$A$1048576,0),MATCH('settlement day'!U$3,CORN!$A$4:$BB$4,0)),"") -> 0 | V21: =IFERROR(INDEX(CORN!$A$4:$BB$1048576,MATCH('settlement day'!$B$3,CORN!$A$4:$A$1048576,0),MATCH('settlement day'!V$3,CORN!$A$4:$BB$4,0)),"") | W21: =IFERROR(INDEX(CORN!$A$4:$BB$1048576,MATCH('settlement day'!$B$3,CORN!$A$4:$A$1048576,0),MATCH('settlement day'!W$3,CORN!$A$4:$BB$4,0)),"") -> 0 | X21: =IFERROR(INDEX(CORN!$A$4:$BB$1048576,MATCH('settlement day'!$B$3,CORN!$A$4:$A$1048576,0),MATCH('settlement day'!X$3,CORN!$A$4:$BB$4,0)),"") | Y21: =IFERROR(INDEX(CORN!$A$4:$BB$1048576,MATCH('settlement day'!$B$3,CORN!$A$4:$A$1048576,0),MATCH('settlement day'!Y$3,CORN!$A$4:$BB$4,0)),"") | Z21: =IFERROR(INDEX(CORN!$A$4:$BB$1048576,MATCH('settlement day'!$B$3,CORN!$A$4:$A$1048576,0),MATCH('settlement day'!Z$3,CORN!$A$4:$BB$4,0)),"") -> 0 | ... AE21: =IFERROR(INDEX(CORN!$A$4:$BB$1048576,MATCH('settlement day'!$B$3,CORN!$A$4:$A$1048576,0),MATCH('settlement day'!AE$3,CORN!$A$4:$BB$4,0)),"") -> 0 | AG21: =IFERROR(INDEX(CORN!$A$4:$BB$1048576,MATCH('settlement day'!$B$3,CORN!$A$4:$A$1048576,0),MATCH('settlement day'!AG$3,CORN!$A$4:$BB$4,0)),"") -> 0 | AI21: =IFERROR(INDEX(CORN!$A$4:$BB$1048576,MATCH('settlement day'!$B$3,CORN!$A$4:$A$1048576,0),MATCH('settlement day'!AI$3,CORN!$A$4:$BB$4,0)),"") -> 0 | AL21: =IFERROR(INDEX(CORN!$A$4:$BB$1048576,MATCH('settlement day'!$B$3,CORN!$A$4:$A$1048576,0),MATCH('settlement day'!AL$3,CORN!$A$4:$BB$4,0)),"") -> 0 | AO21: =IFERROR(INDEX(CORN!$A$4:$BB$1048576,MATCH('settlement day'!$B$3,CORN!$A$4:$A$1048576,0),MATCH('settlement day'!AO$3,CORN!$A$4:$BB$4,0)),"") -> 0 | AQ21: =IFERROR(INDEX(CORN!$A$4:$BB$1048576,MATCH('settlement day'!$B$3,CORN!$A$4:$A$1048576,0),MATCH('settlement day'!AQ$3,CORN!$A$4:$BB$4,0)),"") -> 0 | AS21: =IFERROR(INDEX(CORN!$A$4:$BB$1048576,MATCH('settlement day'!$B$3,CORN!$A$4:$A$1048576,0),MATCH('settlement day'!AS$3,CORN!$A$4:$BB$4,0)),"") -> 0 | AU21: =IFERROR(INDEX(CORN!$A$4:$BB$1048576,MATCH('settlement day'!$B$3,CORN!$A$4:$A$1048576,0),MATCH('settlement day'!AU$3,CORN!$A$4:$BB$4,0)),"") -> 0 | AX21: =IFERROR(INDEX(CORN!$A$4:$BB$1048576,MATCH('settlement day'!$B$3,CORN!$A$4:$A$1048576,0),MATCH('settlement day'!AX$3,CORN!$A$4:$BB$4,0)),"") -> 0 | BA21: =IFERROR(INDEX(CORN!$A$4:$BB$1048576,MATCH('settlement day'!$B$3,CORN!$A$4:$A$1048576,0),MATCH('settlement day'!BA$3,CORN!$A$4:$BB$4,0)),"") -> 0 | BC21: =IFERROR(INDEX(CORN!$A$4:$CC$1048576,MATCH('settlement day'!$B$3,CORN!$A$4:$A$1048576,0),MATCH('settlement day'!BC$3,CORN!$A$4:$CC$4,0)),"") -> 0 | BE21: =IFERROR(INDEX(CORN!$A$4:$CC$1048576,MATCH('settlement day'!$B$3,CORN!$A$4:$A$1048576,0),MATCH('settlement day'!BE$3,CORN!$A$4:$CC$4,0)),"") -> 0 | BG21: =IFERROR(INDEX(CORN!$A$4:$CC$1048576,MATCH('settlement day'!$B$3,CORN!$A$4:$A$1048576,0),MATCH('settlement day'!BG$3,CORN!$A$4:$CC$4,0)),"") -> 0 | BJ21: =IFERROR(INDEX(CORN!$A$4:$CC$1048576,MATCH('settlement day'!$B$3,CORN!$A$4:$A$1048576,0),MATCH('settlement day'!BJ$3,CORN!$A$4:$CC$4,0)),"") -> 4.216 | BM21: =IFERROR(INDEX(CORN!$A$4:$BB$1048576,MATCH('settlement day'!$B$3,CORN!$A$4:$A$1048576,0),MATCH('settlement day'!BM$3,CORN!$A$4:$BB$4,0)),"") -> 4.354 | BO21: =IFERROR(INDEX(CORN!$A$4:$BB$1048576,MATCH('settlement day'!$B$3,CORN!$A$4:$A$1048576,0),MATCH('settlement day'!BO$3,CORN!$A$4:$BB$4,0)),"") -> 4.436 | BQ21: =IFERROR(INDEX(CORN!$A$4:$BB$1048576,MATCH('settlement day'!$B$3,CORN!$A$4:$A$1048576,0),MATCH('settlement day'!BQ$3,CORN!$A$4:$BB$4,0)),"") -> 4.494 | BS21: =IFERROR(INDEX(CORN!$A$4:$BB$1048576,MATCH('settlement day'!$B$3,CORN!$A$4:$A$1048576,0),MATCH('settlement day'!BS$3,CORN!$A$4:$BB$4,0)),"") -> 4.462 | BV21: =IFERROR(INDEX(CORN!$A$4:$BB$1048576,MATCH('settlement day'!$B$3,CORN!$A$4:$A$1048576,0),MATCH('settlement day'!BV$3,CORN!$A$4:$BB$4,0)),"") -> 4.572
B22: day before D-1 | E22: =+CORN!C25 -> 0 | G22: =+CORN!D82 -> 0 | I22: =+CORN!E82 -> 0 | K22: =+CORN!F124 -> 0 | N22: =+CORN!G191 -> 0 | Q22: =+CORN!H269 -> 0 | S22: =IFERROR(OFFSET(INDEX(CORN!$A$4:$BB$1048576,MATCH('settlement day'!$B$3,CORN!$A$4:$A$1048576,0),MATCH('settlement day'!S$3,CORN!$A$4:$BB$4,0)),-1,0),"") -> 0 | T22: =IFERROR(OFFSET(INDEX(CORN!$A$4:$BB$1048576,MATCH('settlement day'!$B$3,CORN!$A$4:$A$1048576,0),MATCH('settlement day'!T$3,CORN!$A$4:$BB$4,0)),-1,0),"") | U22: =IFERROR(OFFSET(INDEX(CORN!$A$4:$BB$1048576,MATCH('settlement day'!$B$3,CORN!$A$4:$A$1048576,0),MATCH('settlement day'!U$3,CORN!$A$4:$BB$4,0)),-1,0),"") -> 0 | V22: =IFERROR(OFFSET(INDEX(CORN!$A$4:$BB$1048576,MATCH('settlement day'!$B$3,CORN!$A$4:$A$1048576,0),MATCH('settlement day'!V$3,CORN!$A$4:$BB$4,0)),-1,0),"") | W22: =IFERROR(OFFSET(INDEX(CORN!$A$4:$BB$1048576,MATCH('settlement day'!$B$3,CORN!$A$4:$A$1048576,0),MATCH('settlement day'!W$3,CORN!$A$4:$BB$4,0)),-1,0),"") -> 0 | X22: =IFERROR(OFFSET(INDEX(CORN!$A$4:$BB$1048576,MATCH('settlement day'!$B$3,CORN!$A$4:$A$1048576,0),MATCH('settlement day'!X$3,CORN!$A$4:$BB$4,0)),-1,0),"") | Y22: =IFERROR(OFFSET(INDEX(CORN!$A$4:$BB$1048576,MATCH('settlement day'!$B$3,CORN!$A$4:$A$1048576,0),MATCH('settlement day'!Y$3,CORN!$A$4:$BB$4,0)),-1,0),"") | Z22: =IFERROR(OFFSET(INDEX(CORN!$A$4:$BB$1048576,MATCH('settlement day'!$B$3,CORN!$A$4:$A$1048576,0),MATCH('settlement day'!Z$3,CORN!$A$4:$BB$4,0)),-1,0),"") -> 0 | ... AE22: =IFERROR(OFFSET(INDEX(CORN!$A$4:$BB$1048576,MATCH('settlement day'!$B$3,CORN!$A$4:$A$1048576,0),MATCH('settlement day'!AE$3,CORN!$A$4:$BB$4,0)),-1,0),"") -> 0 | AG22: =IFERROR(OFFSET(INDEX(CORN!$A$4:$BB$1048576,MATCH('settlement day'!$B$3,CORN!$A$4:$A$1048576,0),MATCH('settlement day'!AG$3,CORN!$A$4:$BB$4,0)),-1,0),"") -> 0 | AI22: =IFERROR(OFFSET(INDEX(CORN!$A$4:$BB$1048576,MATCH('settlement day'!$B$3,CORN!$A$4:$A$1048576,0),MATCH('settlement day'!AI$3,CORN!$A$4:$BB$4,0)),-1,0),"") -> 0 | AL22: =IFERROR(OFFSET(INDEX(CORN!$A$4:$BB$1048576,MATCH('settlement day'!$B$3,CORN!$A$4:$A$1048576,0),MATCH('settlement day'!AL$3,CORN!$A$4:$BB$4,0)),-1,0),"") -> 0 | AO22: =IFERROR(OFFSET(INDEX(CORN!$A$4:$BB$1048576,MATCH('settlement day'!$B$3,CORN!$A$4:$A$1048576,0),MATCH('settlement day'!AO$3,CORN!$A$4:$BB$4,0)),-1,0),"") -> 0 | AQ22: =IFERROR(OFFSET(INDEX(CORN!$A$4:$BB$1048576,MATCH('settlement day'!$B$3,CORN!$A$4:$A$1048576,0),MATCH('settlement day'!AQ$3,CORN!$A$4:$BB$4,0)),-1,0),"") -> 0 | AS22: =IFERROR(OFFSET(INDEX(CORN!$A$4:$BB$1048576,MATCH('settlement day'!$B$3,CORN!$A$4:$A$1048576,0),MATCH('settlement day'!AS$3,CORN!$A$4:$BB$4,0)),-1,0),"") -> 0 | AU22: =IFERROR(OFFSET(INDEX(CORN!$A$4:$BB$1048576,MATCH('settlement day'!$B$3,CORN!$A$4:$A$1048576,0),MATCH('settlement day'!AU$3,CORN!$A$4:$BB$4,0)),-1,0),"") -> 0 | AX22: =IFERROR(OFFSET(INDEX(CORN!$A$4:$BB$1048576,MATCH('settlement day'!$B$3,CORN!$A$4:$A$1048576,0),MATCH('settlement day'!AX$3,CORN!$A$4:$BB$4,0)),-1,0),"") -> 0 | BA22: =IFERROR(OFFSET(INDEX(CORN!$A$4:$BB$1048576,MATCH('settlement day'!$B$3,CORN!$A$4:$A$1048576,0),MATCH('settlement day'!BA$3,CORN!$A$4:$BB$4,0)),-1,0),"") -> 0 | BC22: =IFERROR(OFFSET(INDEX(CORN!$A$4:$CC$1048576,MATCH('settlement day'!$B$3,CORN!$A$4:$A$1048576,0),MATCH('settlement day'!BC$3,CORN!$A$4:$CC$4,0)),-1,0),"") -> 0 | BE22: =IFERROR(OFFSET(INDEX(CORN!$A$4:$CC$1048576,MATCH('settlement day'!$B$3,CORN!$A$4:$A$1048576,0),MATCH('settlement day'!BE$3,CORN!$A$4:$CC$4,0)),-1,0),"") -> 0 | BG22: =IFERROR(OFFSET(INDEX(CORN!$A$4:$CC$1048576,MATCH('settlement day'!$B$3,CORN!$A$4:$A$1048576,0),MATCH('settlement day'!BG$3,CORN!$A$4:$CC$4,0)),-1,0),"") -> 0 | BJ22: =IFERROR(OFFSET(INDEX(CORN!$A$4:$CC$1048576,MATCH('settlement day'!$B$3,CORN!$A$4:$A$1048576,0),MATCH('settlement day'!BJ$3,CORN!$A$4:$CC$4,0)),-1,0),"") -> 4.166 | BM22: =IFERROR(OFFSET(INDEX(CORN!$A$4:$BB$1048576,MATCH('settlement day'!$B$3,CORN!$A$4:$A$1048576,0),MATCH('settlement day'!BM$3,CORN!$A$4:$BB$4,0)),-1,0),"") -> 4.322 | BO22: =IFERROR(OFFSET(INDEX(CORN!$A$4:$BB$1048576,MATCH('settlement day'!$B$3,CORN!$A$4:$A$1048576,0),MATCH('settlement day'!BO$3,CORN!$A$4:$BB$4,0)),-1,0),"") -> 4.41 | BQ22: =IFERROR(OFFSET(INDEX(CORN!$A$4:$BB$1048576,MATCH('settlement day'!$B$3,CORN!$A$4:$A$1048576,0),MATCH('settlement day'!BQ$3,CORN!$A$4:$BB$4,0)),-1,0),"") -> 4.47 | BS22: =IFERROR(OFFSET(INDEX(CORN!$A$4:$BB$1048576,MATCH('settlement day'!$B$3,CORN!$A$4:$A$1048576,0),MATCH('settlement day'!BS$3,CORN!$A$4:$BB$4,0)),-1,0),"") -> 4.434 | BV22: =IFERROR(OFFSET(INDEX(CORN!$A$4:$BB$1048576,MATCH('settlement day'!$B$3,CORN!$A$4:$A$1048576,0),MATCH('settlement day'!BV$3,CORN!$A$4:$BB$4,0)),-1,0),"") -> 4.546
B23: Variation | E23: =E21-E22 -> 0 | G23: =G21-G22 -> 0 | I23: =I21-I22 -> 0 | K23: =K21-K22 -> 0 | N23: =N21-N22 -> 0 | Q23: =Q21-Q22 -> 0 | S23: =S21-S22 -> 0 | U23: =U21-U22 -> 0 | W23: =W21-W22 -> 0 | Z23: =Z21-Z22 -> 0 | AC23: =AC21-AC22 -> 0 | AE23: =AE21-AE22 -> 0 | AG23: =AG21-AG22 -> 0 | AI23: =AI21-AI22 -> 0 | AL23: =AL21-AL22 -> 0 | AO23: =AO21-AO22 -> 0 | AQ23: =AQ21-AQ22 -> 0 | AS23: =AS21-AS22 -> 0 | AU23: =AU21-AU22 -> 0 | AX23: =AX21-AX22 -> 0 | BA23: =BA21-BA22 -> 0 | BC23: =BC21-BC22 -> 0 | BE23: =BE21-BE22 -> 0 | BG23: =BG21-BG22 -> 0 | BJ23: =BJ21-BJ22 -> 0.05 | BM23: =BM21-BM22 -> 0.032 | BO23: =BO21-BO22 -> 0.026 | BQ23: =BQ21-BQ22 -> 0.024 | BS23: =BS21-BS22 -> 0.028 | BV23: =BV21-BV22 -> 0.026
B24: Sugar #11 (US$/pound)
B25: Last settlement | E25: =+'Sugar 11'!B26 -> 0 | G25: =+'Sugar 11'!C83 -> 0 | I25: =+'Sugar 11'!D83 -> 0 | L25: =+'Sugar 11'!E137 -> 0 | Q25: =+'Sugar 11'!F282 -> 0 | S25: =IFERROR(INDEX('Sugar 11'!$A$4:$BB$1048576,MATCH('settlement day'!$B$3,'Sugar 11'!$A$4:$A$1048576,0),MATCH('settlement day'!S$3,'Sugar 11'!$A$4:$BB$4,0)),"") -> 0 | T25: =IFERROR(INDEX('Sugar 11'!$A$4:$BB$1048576,MATCH('settlement day'!$B$3,'Sugar 11'!$A$4:$A$1048576,0),MATCH('settlement day'!T$3,'Sugar 11'!$A$4:$BB$4,0)),"") | U25: 0 | V25: =IFERROR(INDEX('Sugar 11'!$A$4:$BB$1048576,MATCH('settlement day'!$B$3,'Sugar 11'!$A$4:$A$1048576,0),MATCH('settlement day'!V$3,'Sugar 11'!$A$4:$BB$4,0)),"") | W25: =IFERROR(INDEX('Sugar 11'!$A$4:$BB$1048576,MATCH('settlement day'!$B$3,'Sugar 11'!$A$4:$A$1048576,0),MATCH('settlement day'!W$3,'Sugar 11'!$A$4:$BB$4,0)),"") | X25: =IFERROR(INDEX('Sugar 11'!$A$4:$BB$1048576,MATCH('settlement day'!$B$3,'Sugar 11'!$A$4:$A$1048576,0),MATCH('settlement day'!X$3,'Sugar 11'!$A$4:$BB$4,0)),"") -> 0 | Y25: =IFERROR(INDEX('Sugar 11'!$A$4:$BB$1048576,MATCH('settlement day'!$B$3,'Sugar 11'!$A$4:$A$1048576,0),MATCH('settlement day'!Y$3,'Sugar 11'!$A$4:$BB$4,0)),"") | Z25: =IFERROR(INDEX('Sugar 11'!$A$4:$BB$1048576,MATCH('settlement day'!$B$3,'Sugar 11'!$A$4:$A$1048576,0),MATCH('settlement day'!Z$3,'Sugar 11'!$A$4:$BB$4,0)),"") | AA25: =IFERROR(INDEX('Sugar 11'!$A$4:$BB$1048576,MATCH('settlement day'!$B$3,'Sugar 11'!$A$4:$A$1048576,0),MATCH('settlement day'!AA$3,'Sugar 11'!$A$4:$BB$4,0)),"") | AB25: =IFERROR(INDEX('Sugar 11'!$A$4:$BB$1048576,MATCH('settlement day'!$B$3,'Sugar 11'!$A$4:$A$1048576,0),MATCH('settlement day'!AB$3,'Sugar 11'!$A$4:$BB$4,0)),"") | AC25: =IFERROR(INDEX('Sugar 11'!$A$4:$BB$1048576,MATCH('settlement day'!$B$3,'Sugar 11'!$A$4:$A$1048576,0),MATCH('settlement day'!AC$3,'Sugar 11'!$A$4:$BB$4,0)),"") -> 0 | ... AM25: =IFERROR(INDEX('Sugar 11'!$A$4:$BB$1048576,MATCH('settlement day'!$B$3,'Sugar 11'!$A$4:$A$1048576,0),MATCH('settlement day'!AM$3,'Sugar 11'!$A$4:$BB$4,0)),"") | AO25: =IFERROR(INDEX('Sugar 11'!$A$4:$BB$1048576,MATCH('settlement day'!$B$3,'Sugar 11'!$A$4:$A$1048576,0),MATCH('settlement day'!AO$3,'Sugar 11'!$A$4:$BB$4,0)),"") -> 0 | AQ25: =IFERROR(INDEX('Sugar 11'!$A$4:$BB$1048576,MATCH('settlement day'!$B$3,'Sugar 11'!$A$4:$A$1048576,0),MATCH('settlement day'!AQ$3,'Sugar 11'!$A$4:$BB$4,0)),"") -> 0 | AS25: =IFERROR(INDEX('Sugar 11'!$A$4:$BB$1048576,MATCH('settlement day'!$B$3,'Sugar 11'!$A$4:$A$1048576,0),MATCH('settlement day'!AS$3,'Sugar 11'!$A$4:$BB$4,0)),"") -> 0 | AV25: =IFERROR(INDEX('Sugar 11'!$A$4:$CC$1048576,MATCH('settlement day'!$B$3,'Sugar 11'!$A$4:$A$1048576,0),MATCH('settlement day'!AV$3,'Sugar 11'!$A$4:$CC$4,0)),"") -> 0 | AX25: 20 | BA25: =IFERROR(INDEX('Sugar 11'!$A$4:$CC$1048576,MATCH('settlement day'!$B$3,'Sugar 11'!$A$4:$A$1048576,0),MATCH('settlement day'!BA$3,'Sugar 11'!$A$4:$CC$4,0)),"") -> 0 | BC25: =IFERROR(INDEX('Sugar 11'!$A$4:$CC$1048576,MATCH('settlement day'!$B$3,'Sugar 11'!$A$4:$A$1048576,0),MATCH('settlement day'!BC$3,'Sugar 11'!$A$4:$CC$4,0)),"") -> 0 | BE25: =IFERROR(INDEX('Sugar 11'!$A$4:$CC$1048576,MATCH('settlement day'!$B$3,'Sugar 11'!$A$4:$A$1048576,0),MATCH('settlement day'!BE$3,'Sugar 11'!$A$4:$CC$4,0)),"") -> 0 | BH25: =IFERROR(INDEX('Sugar 11'!$A$4:$CC$1048576,MATCH('settlement day'!$B$3,'Sugar 11'!$A$4:$A$1048576,0),MATCH('settlement day'!BH$3,'Sugar 11'!$A$4:$CC$4,0)),"") -> 0 | BM25: =IFERROR(INDEX('Sugar 11'!$A$4:$CC$1048576,MATCH('settlement day'!$B$3,'Sugar 11'!$A$4:$A$1048576,0),MATCH('settlement day'!BM$3,'Sugar 11'!$A$4:$CC$4,0)),"") -> 0.158 | BO25: =IFERROR(INDEX('Sugar 11'!$A$4:$CC$1048576,MATCH('settlement day'!$B$3,'Sugar 11'!$A$4:$A$1048576,0),MATCH('settlement day'!BO$3,'Sugar 11'!$A$4:$CC$4,0)),"") -> 0.1527 | BQ25: =IFERROR(INDEX('Sugar 11'!$A$4:$CC$1048576,MATCH('settlement day'!$B$3,'Sugar 11'!$A$4:$A$1048576,0),MATCH('settlement day'!BQ$3,'Sugar 11'!$A$4:$CC$4,0)),"") -> 0.1511 | BT25: =IFERROR(INDEX('Sugar 11'!$A$4:$CC$1048576,MATCH('settlement day'!$B$3,'Sugar 11'!$A$4:$A$1048576,0),MATCH('settlement day'!BT$3,'Sugar 11'!$A$4:$CC$4,0)),"") -> 0.1531
B26: day before D-1 | E26: =+'Sugar 11'!B25 -> 0 | G26: =+'Sugar 11'!C82 -> 0 | I26: =+'Sugar 11'!D82 -> 0 | L26: =+'Sugar 11'!E136 -> 0 | Q26: =+'Sugar 11'!F271 -> 0 | S26: =IFERROR(INDEX('Sugar 11'!$A$4:$BB$1048576,MATCH('settlement day'!$B$3,'Sugar 11'!$A$4:$A$1048576,0),MATCH('settlement day'!S$3,'Sugar 11'!$A$4:$BB$4,0)),"") -> 0 | T26: =IFERROR(INDEX('Sugar 11'!$A$4:$BB$1048576,MATCH('settlement day'!$B$3,'Sugar 11'!$A$4:$A$1048576,0),MATCH('settlement day'!T$3,'Sugar 11'!$A$4:$BB$4,0)),"") | U26: 0 | V26: =IFERROR(INDEX('Sugar 11'!$A$4:$BB$1048576,MATCH('settlement day'!$B$3,'Sugar 11'!$A$4:$A$1048576,0),MATCH('settlement day'!V$3,'Sugar 11'!$A$4:$BB$4,0)),"") | W26: =IFERROR(INDEX('Sugar 11'!$A$4:$BB$1048576,MATCH('settlement day'!$B$3,'Sugar 11'!$A$4:$A$1048576,0),MATCH('settlement day'!W$3,'Sugar 11'!$A$4:$BB$4,0)),"") | X26: =IFERROR(OFFSET(INDEX('Sugar 11'!$A$4:$BB$1048576,MATCH('settlement day'!$B$3,'Sugar 11'!$A$4:$A$1048576,0),MATCH('settlement day'!X$3,'Sugar 11'!$A$4:$BB$4,0)),-1,0),"") -> 0 | Y26: =IFERROR(OFFSET(INDEX('Sugar 11'!$A$4:$BB$1048576,MATCH('settlement day'!$B$3,'Sugar 11'!$A$4:$A$1048576,0),MATCH('settlement day'!Y$3,'Sugar 11'!$A$4:$BB$4,0)),-1,0),"") | Z26: =IFERROR(OFFSET(INDEX('Sugar 11'!$A$4:$BB$1048576,MATCH('settlement day'!$B$3,'Sugar 11'!$A$4:$A$1048576,0),MATCH('settlement day'!Z$3,'Sugar 11'!$A$4:$BB$4,0)),-1,0),"") | AA26: =IFERROR(OFFSET(INDEX('Sugar 11'!$A$4:$BB$1048576,MATCH('settlement day'!$B$3,'Sugar 11'!$A$4:$A$1048576,0),MATCH('settlement day'!AA$3,'Sugar 11'!$A$4:$BB$4,0)),-1,0),"") | AB26: =IFERROR(OFFSET(INDEX('Sugar 11'!$A$4:$BB$1048576,MATCH('settlement day'!$B$3,'Sugar 11'!$A$4:$A$1048576,0),MATCH('settlement day'!AB$3,'Sugar 11'!$A$4:$BB$4,0)),-1,0),"") | AC26: =IFERROR(OFFSET(INDEX('Sugar 11'!$A$4:$BB$1048576,MATCH('settlement day'!$B$3,'Sugar 11'!$A$4:$A$1048576,0),MATCH('settlement day'!AC$3,'Sugar 11'!$A$4:$BB$4,0)),-1,0),"") -> 0 | AD26: =IFERROR(OFFSET(INDEX('Sugar 11'!$A$4:$BB$1048576,MATCH('settlement day'!$B$3,'Sugar 11'!$A$4:$A$1048576,0),MATCH('settlement day'!AD$3,'Sugar 11'!$A$4:$BB$4,0)),-1,0),"") | AE26: =IFERROR(OFFSET(INDEX('Sugar 11'!$A$4:$BB$1048576,MATCH('settlement day'!$B$3,'Sugar 11'!$A$4:$A$1048576,0),MATCH('settlement day'!AE$3,'Sugar 11'!$A$4:$BB$4,0)),-1,0),"") -> 0 | ... AM26: =IFERROR(OFFSET(INDEX('Sugar 11'!$A$4:$BB$1048576,MATCH('settlement day'!$B$3,'Sugar 11'!$A$4:$A$1048576,0),MATCH('settlement day'!AM$3,'Sugar 11'!$A$4:$BB$4,0)),-1,0),"") | AO26: =IFERROR(OFFSET(INDEX('Sugar 11'!$A$4:$BB$1048576,MATCH('settlement day'!$B$3,'Sugar 11'!$A$4:$A$1048576,0),MATCH('settlement day'!AO$3,'Sugar 11'!$A$4:$BB$4,0)),-1,0),"") -> 0 | AQ26: =IFERROR(OFFSET(INDEX('Sugar 11'!$A$4:$BB$1048576,MATCH('settlement day'!$B$3,'Sugar 11'!$A$4:$A$1048576,0),MATCH('settlement day'!AQ$3,'Sugar 11'!$A$4:$BB$4,0)),-1,0),"") -> 0 | AS26: =IFERROR(OFFSET(INDEX('Sugar 11'!$A$4:$BB$1048576,MATCH('settlement day'!$B$3,'Sugar 11'!$A$4:$A$1048576,0),MATCH('settlement day'!AS$3,'Sugar 11'!$A$4:$BB$4,0)),-1,0),"") -> 0 | AV26: =IFERROR(OFFSET(INDEX('Sugar 11'!$A$4:$CC$1048576,MATCH('settlement day'!$B$3,'Sugar 11'!$A$4:$A$1048576,0),MATCH('settlement day'!AV$3,'Sugar 11'!$A$4:$CC$4,0)),-1,0),"") -> 0 | BA26: =IFERROR(OFFSET(INDEX('Sugar 11'!$A$4:$CC$1048576,MATCH('settlement day'!$B$3,'Sugar 11'!$A$4:$A$1048576,0),MATCH('settlement day'!BA$3,'Sugar 11'!$A$4:$CC$4,0)),-1,0),"") -> 0 | BC26: =IFERROR(OFFSET(INDEX('Sugar 11'!$A$4:$CC$1048576,MATCH('settlement day'!$B$3,'Sugar 11'!$A$4:$A$1048576,0),MATCH('settlement day'!BC$3,'Sugar 11'!$A$4:$CC$4,0)),-1,0),"") -> 0 | BE26: =IFERROR(OFFSET(INDEX('Sugar 11'!$A$4:$CC$1048576,MATCH('settlement day'!$B$3,'Sugar 11'!$A$4:$A$1048576,0),MATCH('settlement day'!BE$3,'Sugar 11'!$A$4:$CC$4,0)),-1,0),"") -> 0 | BH26: =IFERROR(OFFSET(INDEX('Sugar 11'!$A$4:$CC$1048576,MATCH('settlement day'!$B$3,'Sugar 11'!$A$4:$A$1048576,0),MATCH('settlement day'!BH$3,'Sugar 11'!$A$4:$CC$4,0)),-1,0),"") -> 0 | BM26: =IFERROR(OFFSET(INDEX('Sugar 11'!$A$4:$CC$1048576,MATCH('settlement day'!$B$3,'Sugar 11'!$A$4:$A$1048576,0),MATCH('settlement day'!BM$3,'Sugar 11'!$A$4:$CC$4,0)),-1,0),"") -> 0.1569 | BO26: =IFERROR(OFFSET(INDEX('Sugar 11'!$A$4:$CC$1048576,MATCH('settlement day'!$B$3,'Sugar 11'!$A$4:$A$1048576,0),MATCH('settlement day'!BO$3,'Sugar 11'!$A$4:$CC$4,0)),-1,0),"") -> 0.1517 | BQ26: =IFERROR(OFFSET(INDEX('Sugar 11'!$A$4:$CC$1048576,MATCH('settlement day'!$B$3,'Sugar 11'!$A$4:$A$1048576,0),MATCH('settlement day'!BQ$3,'Sugar 11'!$A$4:$CC$4,0)),-1,0),"") -> 0.1501 | BT26: =IFERROR(OFFSET(INDEX('Sugar 11'!$A$4:$CC$1048576,MATCH('settlement day'!$B$3,'Sugar 11'!$A$4:$A$1048576,0),MATCH('settlement day'!BT$3,'Sugar 11'!$A$4:$CC$4,0)),-1,0),"") -> 0.152
B27: Variation | E27: =E25-E26 -> 0 | G27: =G25-G26 -> 0 | I27: =I25-I26 -> 0 | L27: =L25-L26 -> 0 | Q27: =Q25-Q26 -> 0 | S27: =S25-S26 -> 0 | U27: =U25-U26 -> 0 | X27: =X25-X26 -> 0 | AC27: =AC25-AC26 -> 0 | AE27: =AE25-AE26 -> 0 | AG27: =AG25-AG26 -> 0 | AJ27: =AJ25-AJ26 -> 0 | AO27: =AO25-AO26 -> 0 | AQ27: =AQ25-AQ26 -> 0 | AS27: =AS25-AS26 -> 0 | AV27: =AV25-AV26 -> 0 | BA27: =BA25-BA26 -> 0 | BC27: =BC25-BC26 -> 0 | BE27: =BE25-BE26 -> 0 | BH27: =BH25-BH26 -> 0 | BM27: =BM25-BM26 -> 0.0011 | BO27: =BO25-BO26 -> 0.001 | BQ27: =BQ25-BQ26 -> 0.001 | BT27: =BT25-BT26 -> 0.0011
B28: FX
B29: USD/EUR | F29: =+'EUR USD'!B30 -> 0 | G29: =+'EUR USD'!C48 -> 0 | H29: =+'EUR USD'!D713 -> 0 | I29: =+'EUR USD'!E93 -> 0 | J29: =+'EUR USD'!F116 -> 0 | K29: =+'EUR USD'!G140 -> 0 | L29: =+'EUR USD'!H166 -> 0 | N29: =+'EUR USD'!J193 -> 0 | O29: =+'EUR USD'!K230 -> 0 | P29: =+'EUR USD'!L242 -> 0 | Q29: =+R29 -> 0 | R29: =+S29 -> 0 | S29: =IFERROR(INDEX('EUR USD'!$A$4:$BY$1048576,MATCH('settlement day'!$B$3,'EUR USD'!$A$4:$A$1048576,0),MATCH('settlement day'!S$3,'EUR USD'!$A$4:$BY$4,0)),"") -> 0 | T29: =IFERROR(INDEX('EUR USD'!$A$4:$BY$1048576,MATCH('settlement day'!$B$3,'EUR USD'!$A$4:$A$1048576,0),MATCH('settlement day'!T$3,'EUR USD'!$A$4:$BY$4,0)),"") -> 0 | U29: =+V29 -> 0 | V29: =+W29 -> 0 | W29: =+X29 -> 0 | X29: =+Y29 -> 0 | Y29: =+Z29 -> 0 | Z29: =AA29 -> 0 | AA29: =INDEX('EUR USD'!$A$4:$BY$1048576,MATCH('settlement day'!$B$3,'EUR USD'!$A$4:$A$1048576,0),MATCH('settlement day'!AA$3,'EUR USD'!$A$4:$BY$4,0)) -> 0 | AB29: =INDEX('EUR USD'!$A$4:$BY$1048576,MATCH('settlement day'!$B$3,'EUR USD'!$A$4:$A$1048576,0),MATCH('settlement day'!AB$3,'EUR USD'!$A$4:$BY$4,0)) -> 0 | AC29: =INDEX('EUR USD'!$A$4:$BY$1048576,MATCH('settlement day'!$B$3,'EUR USD'!$A$4:$A$1048576,0),MATCH('settlement day'!AC$3,'EUR USD'!$A$4:$BY$4,0)) -> 0 | AD29: =INDEX('EUR USD'!$A$4:$BY$1048576,MATCH('settlement day'!$B$3,'EUR USD'!$A$4:$A$1048576,0),MATCH('settlement day'!AD$3,'EUR USD'!$A$4:$BY$4,0)) -> 0 | AE29: =INDEX('EUR USD'!$A$4:$BY$1048576,MATCH('settlement day'!$B$3,'EUR USD'!$A$4:$A$1048576,0),MATCH('settlement day'!AE$3,'EUR USD'!$A$4:$BY$4,0)) -> 0 | AF29: =INDEX('EUR USD'!$A$4:$BY$1048576,MATCH('settlement day'!$B$3,'EUR USD'!$A$4:$A$1048576,0),MATCH('settlement day'!AF$3,'EUR USD'!$A$4:$BY$4,0)) -> 0 | AG29: =INDEX('EUR USD'!$A$4:$BY$1048576,MATCH('settlement day'!$B$3,'EUR USD'!$A$4:$A$1048576,0),MATCH('settlement day'!AG$3,'EUR USD'!$A$4:$BY$4,0)) -> 0 | AH29: =INDEX('EUR USD'!$A$4:$BY$1048576,MATCH('settlement day'!$B$3,'EUR USD'!$A$4:$A$1048576,0),MATCH('settlement day'!AH$3,'EUR USD'!$A$4:$BY$4,0)) -> 0 | ... AU29: =INDEX('EUR USD'!$A$4:$BY$1048576,MATCH('settlement day'!$B$3,'EUR USD'!$A$4:$A$1048576,0),MATCH('settlement day'!AU$3,'EUR USD'!$A$4:$BY$4,0)) -> 1.1196 | AV29: =INDEX('EUR USD'!$A$4:$CM$1048576,MATCH('settlement day'!$B$3,'EUR USD'!$A$4:$A$1048576,0),MATCH('settlement day'!AV$3,'EUR USD'!$A$4:$CM$4,0)) -> 1.0882 | AW29: =INDEX('EUR USD'!$A$4:$CM$1048576,MATCH('settlement day'!$B$3,'EUR USD'!$A$4:$A$1048576,0),MATCH('settlement day'!AW$3,'EUR USD'!$A$4:$CM$4,0)) -> 1.0562 | AX29: =INDEX('EUR USD'!$A$4:$CM$1048576,MATCH('settlement day'!$B$3,'EUR USD'!$A$4:$A$1048576,0),MATCH('settlement day'!AX$3,'EUR USD'!$A$4:$CM$4,0)) -> 1.0389 | AY29: =INDEX('EUR USD'!$A$4:$CM$1048576,MATCH('settlement day'!$B$3,'EUR USD'!$A$4:$A$1048576,0),MATCH('settlement day'!AY$3,'EUR USD'!$A$4:$CM$4,0)) -> 1.0393 | AZ29: =INDEX('EUR USD'!$A$4:$CM$1048576,MATCH('settlement day'!$B$3,'EUR USD'!$A$4:$A$1048576,0),MATCH('settlement day'!AZ$3,'EUR USD'!$A$4:$CM$4,0)) -> 1.0411 | BA29: =INDEX('EUR USD'!$A$4:$CM$1048576,MATCH('settlement day'!$B$3,'EUR USD'!$A$4:$A$1048576,0),MATCH('settlement day'!BA$3,'EUR USD'!$A$4:$CM$4,0)) -> 1.0815 | BB29: =INDEX('EUR USD'!$A$4:$CM$1048576,MATCH('settlement day'!$B$3,'EUR USD'!$A$4:$A$1048576,0),MATCH('settlement day'!BB$3,'EUR USD'!$A$4:$CM$4,0)) -> 1.1373 | BC29: =INDEX('EUR USD'!$A$4:$CM$1048576,MATCH('settlement day'!$B$3,'EUR USD'!$A$4:$A$1048576,0),MATCH('settlement day'!BC$3,'EUR USD'!$A$4:$CM$4,0)) -> 1.1339 | ... BK29: =INDEX('EUR USD'!$A$4:$CM$1048576,MATCH('settlement day'!$B$3,'EUR USD'!$A$4:$A$1048576,0),MATCH('settlement day'!BK$3,'EUR USD'!$A$4:$CM$4,0)) -> 1.1749 | BL29: =BM29 -> 1.17625 | BM29: =INDEX('EUR USD'!$A$4:$CM$1048576,MATCH('settlement day'!$B$3,'EUR USD'!$A$4:$A$1048576,0),MATCH('settlement day'!BM$3,'EUR USD'!$A$4:$CM$4,0)) -> 1.17625 | BN29: =BP29 -> 1.1779 | BO29: =BP29 -> 1.1779 | BP29: =INDEX('EUR USD'!$A$4:$CM$1048576,MATCH('settlement day'!$B$3,'EUR USD'!$A$4:$A$1048576,0),MATCH('settlement day'!BP$3,'EUR USD'!$A$4:$CM$4,0)) -> 1.1779 | BQ29: =BS29 -> 1.1825 | BR29: =BS29 -> 1.1825 | BS29: =INDEX('EUR USD'!$A$4:$CM$1048576,MATCH('settlement day'!$B$3,'EUR USD'!$A$4:$A$1048576,0),MATCH('settlement day'!BS$3,'EUR USD'!$A$4:$CM$4,0)) -> 1.1825 | BT29: =BV29 -> 1.1866 | BU29: =BV29 -> 1.1866 | BV29: =INDEX('EUR USD'!$A$4:$CM$1048576,MATCH('settlement day'!$B$3,'EUR USD'!$A$4:$A$1048576,0),MATCH('settlement day'!BV$3,'EUR USD'!$A$4:$CM$4,0)) -> 1.1866
B30: BRL/USD | C30: =+'BRL USD'!C8 -> 0 | D30: =+'BRL USD'!D7 -> 0 | E30: =+'BRL USD'!E7 -> 0 | F30: 0 | G30: 0 | H30: 0 | I30: 0 | J30: =+K30 -> 0 | K30: =+L30 -> 0 | M30: =+N30 -> 0 | N30: =+O30 -> 0 | O30: =+P30 -> 0 | P30: =+Q30 -> 0 | Q30: =+R30 -> 0 | R30: =+S30 -> 0 | S30: =+T30 -> 0 | T30: =+U30 -> 0 | ... Y30: =+Z30 -> 0 | Z30: =AA30 -> 0 | AA30: =AB30 -> 0 | AB30: =AC30 -> 0 | AC30: =AD30 -> 0 | AD30: =INDEX('BRL USD'!$A$4:$BB$1048576,MATCH('settlement day'!$B$3,'BRL USD'!$A$4:$A$1048576,0),MATCH('settlement day'!AD$3,'BRL USD'!$A$4:$BB$4,0)) -> 0 | AE30: =INDEX('BRL USD'!$A$4:$BB$1048576,MATCH('settlement day'!$B$3,'BRL USD'!$A$4:$A$1048576,0),MATCH('settlement day'!AE$3,'BRL USD'!$A$4:$BB$4,0)) -> 0 | AF30: =INDEX('BRL USD'!$A$4:$BB$1048576,MATCH('settlement day'!$B$3,'BRL USD'!$A$4:$A$1048576,0),MATCH('settlement day'!AF$3,'BRL USD'!$A$4:$BB$4,0)) -> 0 | AG30: =INDEX('BRL USD'!$A$4:$BB$1048576,MATCH('settlement day'!$B$3,'BRL USD'!$A$4:$A$1048576,0),MATCH('settlement day'!AG$3,'BRL USD'!$A$4:$BB$4,0)) -> 0 | AH30: =INDEX('BRL USD'!$A$4:$BB$1048576,MATCH('settlement day'!$B$3,'BRL USD'!$A$4:$A$1048576,0),MATCH('settlement day'!AH$3,'BRL USD'!$A$4:$BB$4,0)) -> 0 | AI30: =INDEX('BRL USD'!$A$4:$BB$1048576,MATCH('settlement day'!$B$3,'BRL USD'!$A$4:$A$1048576,0),MATCH('settlement day'!AI$3,'BRL USD'!$A$4:$BB$4,0)) -> 0 | AJ30: =INDEX('BRL USD'!$A$4:$BB$1048576,MATCH('settlement day'!$B$3,'BRL USD'!$A$4:$A$1048576,0),MATCH('settlement day'!AJ$3,'BRL USD'!$A$4:$BB$4,0)) -> 0 | AK30: =INDEX('BRL USD'!$A$4:$BB$1048576,MATCH('settlement day'!$B$3,'BRL USD'!$A$4:$A$1048576,0),MATCH('settlement day'!AK$3,'BRL USD'!$A$4:$BB$4,0)) -> 0 | ... BA30: =INDEX('BRL USD'!$A$4:$BB$1048576,MATCH('settlement day'!$B$3,'BRL USD'!$A$4:$A$1048576,0),MATCH('settlement day'!BA$3,'BRL USD'!$A$4:$BB$4,0)) -> 5.7416 | BB30: =INDEX('BRL USD'!$A$4:$CC$1048576,MATCH('settlement day'!$B$3,'BRL USD'!$A$4:$A$1048576,0),MATCH('settlement day'!BB$3,'BRL USD'!$A$4:$CC$4,0)) -> 5.6602 | BC30: =INDEX('BRL USD'!$A$4:$CC$1048576,MATCH('settlement day'!$B$3,'BRL USD'!$A$4:$A$1048576,0),MATCH('settlement day'!BC$3,'BRL USD'!$A$4:$CC$4,0)) -> 5.7081 | BD30: =INDEX('BRL USD'!$A$4:$CC$1048576,MATCH('settlement day'!$B$3,'BRL USD'!$A$4:$A$1048576,0),MATCH('settlement day'!BD$3,'BRL USD'!$A$4:$CC$4,0)) -> 5.4565 | BE30: =INDEX('BRL USD'!$A$4:$CC$1048576,MATCH('settlement day'!$B$3,'BRL USD'!$A$4:$A$1048576,0),MATCH('settlement day'!BE$3,'BRL USD'!$A$4:$CC$4,0)) -> 5.6015 | BF30: =INDEX('BRL USD'!$A$4:$CC$1048576,MATCH('settlement day'!$B$3,'BRL USD'!$A$4:$A$1048576,0),MATCH('settlement day'!BF$3,'BRL USD'!$A$4:$CC$4,0)) -> 5.4372 | BG30: =INDEX('BRL USD'!$A$4:$CC$1048576,MATCH('settlement day'!$B$3,'BRL USD'!$A$4:$A$1048576,0),MATCH('settlement day'!BG$3,'BRL USD'!$A$4:$CC$4,0)) -> 5.318 | BH30: =INDEX('BRL USD'!$A$4:$CC$1048576,MATCH('settlement day'!$B$3,'BRL USD'!$A$4:$A$1048576,0),MATCH('settlement day'!BH$3,'BRL USD'!$A$4:$CC$4,0)) -> 5.4348 | BI30: =INDEX('BRL USD'!$A$4:$CC$1048576,MATCH('settlement day'!$B$3,'BRL USD'!$A$4:$A$1048576,0),MATCH('settlement day'!BI$3,'BRL USD'!$A$4:$CC$4,0)) -> 5.4659743 | ... BV30: =INDEX('BRL USD'!$A$4:$CC$1048576,MATCH('settlement day'!$B$3,'BRL USD'!$A$4:$A$1048576,0),MATCH('settlement day'!BV$3,'BRL USD'!$A$4:$CC$4,0)) -> 5.9772863
B33: SPOT PHYS | AY33: Last | AZ33: D-1 | BA33: Variation | BC33: Phys Spread CHICAGO | BF33: RIN Opis | BG33: D6 | BH33: D4 | BI33: D5 | BJ33: CARB ($/CI) | BK33: Cbio (R$/Cb) | BN33: RIN Platts | BO33: D6-P | BP33: D4-P | BQ33: D5-P | BR33: CARB ($/ton)
B34: OPIS Chicago | AY34: =INDEX('PLATTS&OPIS'!$A$4:$BB$1048576,MATCH('settlement day'!$B$3,'PLATTS&OPIS'!$A$4:$A$1048576,0),MATCH(B34,'PLATTS&OPIS'!$A$4:$BB$4,0)) -> 0 | AZ34: =OFFSET(INDEX('PLATTS&OPIS'!$A$4:$BB$1048576,MATCH('settlement day'!$B$3,'PLATTS&OPIS'!$A$4:$A$1048576,0),MATCH(B34,'PLATTS&OPIS'!$A$4:$BB$4,0)),-1,0) -> 0 | BA34: =(+AY34-AZ34) -> 0 | BC34: New York | BD34: =+AY35-AY34 -> 0 | BF34: D-1 | BG34: =INDEX('PLATTS&OPIS'!$A$4:$BB$1048576,MATCH('settlement day'!$B$3,'PLATTS&OPIS'!$A$4:$A$1048576,0),MATCH(BG33,'PLATTS&OPIS'!$A$4:$BB$4,0)) -> 0 | BH34: =INDEX('PLATTS&OPIS'!$A$4:$BB$1048576,MATCH('settlement day'!$B$3,'PLATTS&OPIS'!$A$4:$A$1048576,0),MATCH(BH33,'PLATTS&OPIS'!$A$4:$BB$4,0)) -> 0 | BI34: =INDEX('PLATTS&OPIS'!$A$4:$BB$1048576,MATCH('settlement day'!$B$3,'PLATTS&OPIS'!$A$4:$A$1048576,0),MATCH(BI33,'PLATTS&OPIS'!$A$4:$BB$4,0)) -> 0 | BJ34: =INDEX('PLATTS&OPIS'!$A$4:$BB$1048576,MATCH('settlement day'!$B$3,'PLATTS&OPIS'!$A$4:$A$1048576,0),MATCH(BJ33,'PLATTS&OPIS'!$A$4:$BB$4,0)) -> 0 | BK34: =OFFSET(INDEX('PLATTS&OPIS'!$A$4:$BB$1048576,MATCH('settlement day'!$B$3,'PLATTS&OPIS'!$A$4:$A$1048576,0),MATCH(BK33,'PLATTS&OPIS'!$A$4:$BB$4,0)),-1,0) -> 41.25 | BN34: Last | BO34: =INDEX('PLATTS&OPIS'!$A$4:$BB$1048576,MATCH('settlement day'!$B$3,'PLATTS&OPIS'!$A$4:$A$1048576,0),MATCH(BO33,'PLATTS&OPIS'!$A$4:$BB$4,0)) -> 0 | BP34: =INDEX('PLATTS&OPIS'!$A$4:$BB$1048576,MATCH('settlement day'!$B$3,'PLATTS&OPIS'!$A$4:$A$1048576,0),MATCH(BP33,'PLATTS&OPIS'!$A$4:$BB$4,0)) -> 0 | BQ34: =INDEX('PLATTS&OPIS'!$A$4:$BB$1048576,MATCH('settlement day'!$B$3,'PLATTS&OPIS'!$A$4:$A$1048576,0),MATCH(BQ33,'PLATTS&OPIS'!$A$4:$BB$4,0)) -> 0 | BR34: =INDEX('PLATTS&OPIS'!$A$4:$BB$1048576,MATCH('settlement day'!$B$3,'PLATTS&OPIS'!$A$4:$A$1048576,0),MATCH(BR33,'PLATTS&OPIS'!$A$4:$BB$4,0)) -> 0
B35: OPIS New York | AY35: =INDEX('PLATTS&OPIS'!$A$4:$BB$1048576,MATCH('settlement day'!$B$3,'PLATTS&OPIS'!$A$4:$A$1048576,0),MATCH(B35,'PLATTS&OPIS'!$A$4:$BB$4,0)) -> 0 | AZ35: =OFFSET(INDEX('PLATTS&OPIS'!$A$4:$BB$1048576,MATCH('settlement day'!$B$3,'PLATTS&OPIS'!$A$4:$A$1048576,0),MATCH(B35,'PLATTS&OPIS'!$A$4:$BB$4,0)),-1,0) -> 0 | BA35: =(+AY35-AZ35) -> 0 | BC35: Gulf Coast | BD35: =+AY36-AY34 -> 0 | BF35: D-2 | BG35: =OFFSET(INDEX('PLATTS&OPIS'!$A$4:$BB$1048576,MATCH('settlement day'!$B$3,'PLATTS&OPIS'!$A$4:$A$1048576,0),MATCH(BG33,'PLATTS&OPIS'!$A$4:$BB$4,0)),-1,0) -> 0 | BH35: =OFFSET(INDEX('PLATTS&OPIS'!$A$4:$BB$1048576,MATCH('settlement day'!$B$3,'PLATTS&OPIS'!$A$4:$A$1048576,0),MATCH(BH33,'PLATTS&OPIS'!$A$4:$BB$4,0)),-1,0) -> 0 | BI35: =OFFSET(INDEX('PLATTS&OPIS'!$A$4:$BB$1048576,MATCH('settlement day'!$B$3,'PLATTS&OPIS'!$A$4:$A$1048576,0),MATCH(BI33,'PLATTS&OPIS'!$A$4:$BB$4,0)),-1,0) -> 0 | BJ35: =OFFSET(INDEX('PLATTS&OPIS'!$A$4:$BB$1048576,MATCH('settlement day'!$B$3,'PLATTS&OPIS'!$A$4:$A$1048576,0),MATCH(BJ33,'PLATTS&OPIS'!$A$4:$BB$4,0)),-1,0) -> 0 | BK35: =OFFSET(INDEX('PLATTS&OPIS'!$A$4:$BB$1048576,MATCH('settlement day'!$B$3,'PLATTS&OPIS'!$A$4:$A$1048576,0),MATCH(BK33,'PLATTS&OPIS'!$A$4:$BB$4,0)),-2,0) -> 41.25 | BN35: D-1 | BO35: =OFFSET(INDEX('PLATTS&OPIS'!$A$4:$BB$1048576,MATCH('settlement day'!$B$3,'PLATTS&OPIS'!$A$4:$A$1048576,0),MATCH(BO33,'PLATTS&OPIS'!$A$4:$BB$4,0)),-1,0) -> 0 | BP35: =OFFSET(INDEX('PLATTS&OPIS'!$A$4:$BB$1048576,MATCH('settlement day'!$B$3,'PLATTS&OPIS'!$A$4:$A$1048576,0),MATCH(BP33,'PLATTS&OPIS'!$A$4:$BB$4,0)),-1,0) -> 0 | BQ35: =OFFSET(INDEX('PLATTS&OPIS'!$A$4:$BB$1048576,MATCH('settlement day'!$B$3,'PLATTS&OPIS'!$A$4:$A$1048576,0),MATCH(BQ33,'PLATTS&OPIS'!$A$4:$BB$4,0)),-1,0) -> 0 | BR35: =OFFSET(INDEX('PLATTS&OPIS'!$A$4:$BB$1048576,MATCH('settlement day'!$B$3,'PLATTS&OPIS'!$A$4:$A$1048576,0),MATCH(BR33,'PLATTS&OPIS'!$A$4:$BB$4,0)),-1,0) -> 0
B36: OPIS Gulf Coast | AY36: =INDEX('PLATTS&OPIS'!$A$4:$BB$1048576,MATCH('settlement day'!$B$3,'PLATTS&OPIS'!$A$4:$A$1048576,0),MATCH(B36,'PLATTS&OPIS'!$A$4:$BB$4,0)) -> 0 | AZ36: =OFFSET(INDEX('PLATTS&OPIS'!$A$4:$BB$1048576,MATCH('settlement day'!$B$3,'PLATTS&OPIS'!$A$4:$A$1048576,0),MATCH(B36,'PLATTS&OPIS'!$A$4:$BB$4,0)),-1,0) -> 0 | BA36: =(+AY36-AZ36) -> 0 | BC36: Florida | BD36: =+AY37-AY34 -> 0 | BF36: Variation | BG36: =BG34-BG35 -> 0 | BH36: =BH34-BH35 -> 0 | BI36: =BI34-BI35 -> 0 | BJ36: =BJ34-BJ35 -> 0 | BK36: =+BK34-BK35 -> 0 | BN36: Variation | BO36: =BO34-BO35 -> 0 | BP36: =BP34-BP35 -> 0 | BQ36: =BQ34-BQ35 -> 0 | BR36: =BR34-BR35 -> 0
B37: OPIS Florida | AY37: =INDEX('PLATTS&OPIS'!$A$4:$BB$1048576,MATCH('settlement day'!$B$3,'PLATTS&OPIS'!$A$4:$A$1048576,0),MATCH(B37,'PLATTS&OPIS'!$A$4:$BB$4,0)) -> 0 | AZ37: =OFFSET(INDEX('PLATTS&OPIS'!$A$4:$BB$1048576,MATCH('settlement day'!$B$3,'PLATTS&OPIS'!$A$4:$A$1048576,0),MATCH(B37,'PLATTS&OPIS'!$A$4:$BB$4,0)),-1,0) -> 0 | BA37: =(+AY37-AZ37) -> 0 | BC37: California | BD37: =+AY38-AY34 -> 0
B38: OPIS California | AY38: =INDEX('PLATTS&OPIS'!$A$4:$BB$1048576,MATCH('settlement day'!$B$3,'PLATTS&OPIS'!$A$4:$A$1048576,0),MATCH(B38,'PLATTS&OPIS'!$A$4:$BB$4,0)) -> 0 | AZ38: =OFFSET(INDEX('PLATTS&OPIS'!$A$4:$BB$1048576,MATCH('settlement day'!$B$3,'PLATTS&OPIS'!$A$4:$A$1048576,0),MATCH(B38,'PLATTS&OPIS'!$A$4:$BB$4,0)),-1,0) -> 0 | BA38: =(+AY38-AZ38) -> 0 | BC38: R11 | BD38: =+AY39-AY34 -> 0 | BF38: D5/D6 Opis | BG38: =+BI34-BG34 -> 0 | BN38: D5/D6 Platts | BO38: =+BQ34-BO34 -> 0
B39: OPIS Rule 11 | AY39: =INDEX('PLATTS&OPIS'!$A$4:$BB$1048576,MATCH('settlement day'!$B$3,'PLATTS&OPIS'!$A$4:$A$1048576,0),MATCH(B39,'PLATTS&OPIS'!$A$4:$BB$4,0)) -> 0 | AZ39: =OFFSET(INDEX('PLATTS&OPIS'!$A$4:$BB$1048576,MATCH('settlement day'!$B$3,'PLATTS&OPIS'!$A$4:$A$1048576,0),MATCH(B39,'PLATTS&OPIS'!$A$4:$BB$4,0)),-1,0) -> 0 | BA39: =(+AY39-AZ39) -> 0
B40: Platts CHICAGO (cpg) | AY40: =INDEX('PLATTS&OPIS'!$A$4:$BB$1048576,MATCH('settlement day'!$B$3,'PLATTS&OPIS'!$A$4:$A$1048576,0),MATCH(B40,'PLATTS&OPIS'!$A$4:$BB$4,0)) -> 0 | AZ40: =OFFSET(INDEX('PLATTS&OPIS'!$A$4:$BB$1048576,MATCH('settlement day'!$B$3,'PLATTS&OPIS'!$A$4:$A$1048576,0),MATCH(B40,'PLATTS&OPIS'!$A$4:$BB$4,0)),-1,0) -> 0 | BA40: =+AY40-AZ40 -> 0
B41: Platts T2 (eur/cbm) | AY41: =INDEX('PLATTS&OPIS'!$A$4:$BB$1048576,MATCH('settlement day'!$B$3,'PLATTS&OPIS'!$A$4:$A$1048576,0),MATCH(B41,'PLATTS&OPIS'!$A$4:$BB$4,0)) -> 0 | AZ41: =OFFSET(INDEX('PLATTS&OPIS'!$A$4:$BB$1048576,MATCH('settlement day'!$B$3,'PLATTS&OPIS'!$A$4:$A$1048576,0),MATCH(B41,'PLATTS&OPIS'!$A$4:$BB$4,0)),-1,0) -> 0 | BA41: =+AY41-AZ41 -> 0 | BC41: PNYH vs PCHI | BH41: ESALQ | BI41: R$/cbm | BJ41: R$/liter | BN41: CBios | BO41: CBio unit | BP41: per cbm HYD | BQ41: per cbm ANH | BR41: per vol CORN
B42: Platts FOB Brazil (usd/cbm) | AY42: =INDEX('PLATTS&OPIS'!$A$4:$BB$1048576,MATCH('settlement day'!$B$3,'PLATTS&OPIS'!$A$4:$A$1048576,0),MATCH(B42,'PLATTS&OPIS'!$A$4:$BB$4,0)) -> 0 | AZ42: =OFFSET(INDEX('PLATTS&OPIS'!$A$4:$BB$1048576,MATCH('settlement day'!$B$3,'PLATTS&OPIS'!$A$4:$A$1048576,0),MATCH(B42,'PLATTS&OPIS'!$A$4:$BB$4,0)),-1,0) -> 0 | BA42: =+AY42-AZ42 -> 0 | BD42: NYH | BE42: CHI | BF42: Δ cpg | BH42: Paulinia | BI42: =INDEX('ESALQ Paulinia'!A4:E1048576,MATCH('settlement day'!B3,'ESALQ Paulinia'!A4:A1048576,0),2) -> 2856.5 | BN42: R$ | BO42: =INDEX('PLATTS&OPIS'!$A$4:$BB$1048576,MATCH('settlement day'!$B$3,'PLATTS&OPIS'!$A$4:$A$1048576,0),MATCH(BK33,'PLATTS&OPIS'!$A$4:$BB$4,0)) -> 41.25 | BP42: =+BO42*BP44 -> 44.212219 | BQ42: =+BO42*BQ44 -> 50.121507 | BR42: =+BO42*BR44 -> 37.636861
B43: Platts FOB Grade B (usd/cbm) | AY43: =INDEX('PLATTS&OPIS'!$A$4:$BB$1048576,MATCH('settlement day'!$B$3,'PLATTS&OPIS'!$A$4:$A$1048576,0),MATCH(B43,'PLATTS&OPIS'!$A$4:$BB$4,0)) -> 0 | AZ43: =OFFSET(INDEX('PLATTS&OPIS'!$A$4:$BB$1048576,MATCH('settlement day'!$B$3,'PLATTS&OPIS'!$A$4:$A$1048576,0),MATCH(B43,'PLATTS&OPIS'!$A$4:$BB$4,0)),-1,0) -> 0 | BA43: =+AY43-AZ43 -> 0 | BC43: Last | BD43: =INDEX('PLATTS&OPIS'!$A$4:$BB$1048576,MATCH('settlement day'!$B$3,'PLATTS&OPIS'!$A$4:$A$1048576,0),4) -> 0 | BE43: =INDEX('PLATTS&OPIS'!$A$4:$BB$1048576,MATCH('settlement day'!$B$3,'PLATTS&OPIS'!$A$4:$A$1048576,0),2) -> 0 | BF43: =(+BD43-(BE43/100))*100 -> 0 | BH43: Ribeirao | BI43: =+BJ43*1000 -> 0 | BJ43: =INDEX('ESALQ Hydrous Ribeirao'!A5:J1048576,MATCH('settlement day'!B3,'ESALQ Hydrous Ribeirao'!A5:A1048576,1),2) -> 0 | BN43: U$ | BO43: =+BO42/AN30 -> 8.2786441 | BP43: =+BP42/AN30 -> 8.8731448 | BQ43: =+BQ42/AN30 -> 10.059106 | BR43: =+BR42/AN30 -> 7.5535074
B44: Platts Anhydrous (brl/cbm) | AY44: =INDEX('PLATTS&OPIS'!$A$4:$BB$1048576,MATCH('settlement day'!$B$3,'PLATTS&OPIS'!$A$4:$A$1048576,0),MATCH(B44,'PLATTS&OPIS'!$A$4:$BB$4,0)) -> 0 | AZ44: =OFFSET(INDEX('PLATTS&OPIS'!$A$4:$BB$1048576,MATCH('settlement day'!$B$3,'PLATTS&OPIS'!$A$4:$A$1048576,0),MATCH(B44,'PLATTS&OPIS'!$A$4:$BB$4,0)),-1,0) -> 0 | BA44: =+AY44-AZ44 -> 0 | BC44: D-1 | BD44: =OFFSET(INDEX('PLATTS&OPIS'!$A$4:$BB$1048576,MATCH('settlement day'!$B$3,'PLATTS&OPIS'!$A$4:$A$1048576,0),4),-1,0) -> 0 | BE44: =OFFSET(INDEX('PLATTS&OPIS'!$A$4:$BB$1048576,MATCH('settlement day'!$B$3,'PLATTS&OPIS'!$A$4:$A$1048576,0),2),-1,0) -> 0 | BF44: =(+BD44-(BE44/100))*100 -> 0 | BP44: =1000/933 -> 1.0718114 | BQ44: =1000/823 -> 1.2150668 | BR44: =1000/1096 -> 0.91240876
B45: Platts Hydrous (brl/cbm) | AY45: =INDEX('PLATTS&OPIS'!$A$4:$BB$1048576,MATCH('settlement day'!$B$3,'PLATTS&OPIS'!$A$4:$A$1048576,0),MATCH(B45,'PLATTS&OPIS'!$A$4:$BB$4,0)) -> 0 | AZ45: =OFFSET(INDEX('PLATTS&OPIS'!$A$4:$BB$1048576,MATCH('settlement day'!$B$3,'PLATTS&OPIS'!$A$4:$A$1048576,0),MATCH(B45,'PLATTS&OPIS'!$A$4:$BB$4,0)),-1,0) -> 0 | BA45: =+AY45-AZ45 -> 0 | BC45: Δ | BD45: =+BD43-BD44 -> 0 | BE45: =+BE43-BE44 -> 0 | BH45: ETBE Northwest Europe ($/mt) FOB ARA | BL45: =INDEX('PLATTS&OPIS'!$A$4:$BB$1048576,MATCH('settlement day'!$B$3,'PLATTS&OPIS'!$A$4:$A$1048576,0),MATCH(BH45,'PLATTS&OPIS'!$A$4:$BB$4,0)) -> 0 | BO45: plantas certificadas | BP45: 278 | BQ45: 184 | BR45: 4
B48: CHIP vs NYH | H48: =+H51-H9 -> 0 | I48: =+I51-I9 -> 0 | J48: =+J51-J9 -> 0 | K48: =+K51-K9 -> 0 | L48: =+L51-L9 -> 0 | M48: =+M51-M9 -> 0 | N48: =+N51-N9 -> 0 | O48: =+O51-O9 -> 0 | P48: =+P50-P8 -> 0.08506 | Q48: =+Q51-Q9 -> 0 | R48: =+R51-R9 -> 0 | S48: =+S51-S9 -> 0 | U48: =+U51-T9 -> 0 | W48: =+W51-U9 -> 0 | X48: =+X51-V9 -> 0 | Y48: =+Y51-W9 -> 0 | Z48: =+Z51-X9 -> 0 | AA48: =+AA51-Y9 -> 0 | AB48: =+AB51-AB9 -> 0 | AC48: =+AC51-AC9 -> 0 | AD48: =+AD51-AD9 -> 0 | AE48: =+AE51-AE9 -> 0 | AF48: =+AF51-AF9 -> 0 | AG48: =+AG51-AG9 -> 0 | AH48: =+AH51-AH9 -> 0 | AI48: =+AI51-AI9 -> 0 | ... AK48: =+AK51-AK9 -> 0 | AM48: =+AM51-AL9 -> 0 | AN48: =+AN51-AM9 -> 0 | AO48: =+AO51-AN9 -> 0 | AP48: =+AP51-AO9 -> 0 | AQ48: =+AQ51-AP9 -> 0 | AR48: =+AR51-AQ9 -> 0 | AS48: =+AS51-AR9 -> 0 | AY48: =+AY51-AS9 -> 0 | AZ48: =+AZ51-AV9 -> 0 | BA48: =+BA51-AW9 -> 0 | BB48: =+BB51-AX9 -> 0 | BC48: =+BC51-AY9 -> 0 | BD48: =+BD51-AZ9 -> 0 | BE48: =+BE51-BA9 -> 0 | BF48: =+BF51-BF9 -> 0 | BG48: =+BG51-BG9 -> 0 | BH48: =+BH51-BH9 -> 0.1 | BI48: =+BI51-BI9 -> 0.1 | BJ48: =+BJ51-BJ9 -> 0.105 | BK48: =+BK51-BK9 -> -1.5775 | BL48: =+BL51-BL9 -> -1.5825 | BM48: =+BM51-BM9 -> -1.6075 | ... BV48: =+BV51-BV9 -> -1.5825
B50: NYH (US$/gal) | M50: 3.8128 | N50: 3.6551 | O50: 2.3303 | P50: 2.2418 | R50: 2.7258 | S50: 2.8908 | U50: 2.9133 | W50: 2.5031 | X50: 2.5394 | Y50: 2.6264 | Z50: 2.2704 | AB50: =+AA51-AB51 -> 0 | AC50: =+AB51-AC51 -> 0 | AD50: =+AC51-AD51 -> 0 | AE50: =+AD51-AE51 -> 0 | AF50: =+AE51-AF51 -> 0 | AG50: =+AF51-AG51 -> 0 | AH50: =+AG51-AH51 -> 0 | AI50: =+AH51-AI51 -> 0 | ... AK50: =+AJ51-AK51 -> 0 | AM50: =+AK51-AM51 -> 0 | AN50: 1.5393 | AO50: =+AN51-AO51 -> 0 | AP50: =+AO51-AP51 -> 0 | AQ50: =+AP51-AQ51 -> 0 | AR50: =+AQ51-AR51 -> 0 | AS50: =+AR51-AS51 -> 0 | AY50: =+AX51-AY51 -> 0 | AZ50: =+AY51-AZ51 -> 0 | BA50: =+AZ51-BA51 -> 0 | BB50: =+BA51-BB51 -> 0 | BC50: =+BB51-BC51 -> 0 | BD50: =+BC51-BD51 -> 0 | BE50: =+BD51-BE51 -> 0 | BF50: =+BE51-BF51 -> 0 | ... BV50: =+BU51-BV51 -> 0
B51: Last settlement | C51: =+RBOB!C59 -> 0 | D51: =+RBOB!D59 -> 0 | E51: =+RBOB!E59 -> 0 | F51: =+RBOB!F94 -> 0 | G51: =+RBOB!G94 -> 0 | H51: =+NYH!I82 -> 0 | I51: =+NYH!J95 -> 0 | J51: =+NYH!K123 -> 0 | K51: =+NYH!L139 -> 0 | L51: =+NYH!M202 -> 0 | M51: =+NYH!N202 -> 0 | N51: =+NYH!O244 -> 0 | O51: =+NYH!P244 -> 0 | P51: =+NYH!Q269 -> 0 | Q51: =+NYH!R286 -> 0 | R51: =+NYH!S310 -> 0 | S51: =INDEX(NYH!$A$4:$BB$1048576,MATCH('settlement day'!$B$3,NYH!$A$4:$A$1048576,0),MATCH('settlement day'!S$3,NYH!$A$4:$BB$4,0)) -> 0 | U51: =INDEX(NYH!$A$4:$BB$1048576,MATCH('settlement day'!$B$3,NYH!$A$4:$A$1048576,0),MATCH('settlement day'!T$3,NYH!$A$4:$BB$4,0)) -> 0 | W51: =INDEX(NYH!$A$4:$BB$1048576,MATCH('settlement day'!$B$3,NYH!$A$4:$A$1048576,0),MATCH('settlement day'!U$3,NYH!$A$4:$BB$4,0)) -> 0 | X51: =INDEX(NYH!$A$4:$BB$1048576,MATCH('settlement day'!$B$3,NYH!$A$4:$A$1048576,0),MATCH('settlement day'!W$3,NYH!$A$4:$BB$4,0)) -> 0 | Y51: =INDEX(NYH!$A$4:$BB$1048576,MATCH('settlement day'!$B$3,NYH!$A$4:$A$1048576,0),MATCH('settlement day'!X$3,NYH!$A$4:$BB$4,0)) -> 0 | Z51: =INDEX(NYH!$A$4:$BB$1048576,MATCH('settlement day'!$B$3,NYH!$A$4:$A$1048576,0),MATCH('settlement day'!Y$3,NYH!$A$4:$BB$4,0)) -> 0 | AA51: =INDEX(NYH!$A$4:$BB$1048576,MATCH('settlement day'!$B$3,NYH!$A$4:$A$1048576,0),MATCH('settlement day'!Z$3,NYH!$A$4:$BB$4,0)) -> 0 | AB51: =INDEX(NYH!$A$4:$BB$1048576,MATCH('settlement day'!$B$3,NYH!$A$4:$A$1048576,0),MATCH('settlement day'!AB$3,NYH!$A$4:$BB$4,0)) -> 0 | AC51: =INDEX(NYH!$A$4:$BB$1048576,MATCH('settlement day'!$B$3,NYH!$A$4:$A$1048576,0),MATCH('settlement day'!AC$3,NYH!$A$4:$BB$4,0)) -> 0 | AD51: =INDEX(NYH!$A$4:$BB$1048576,MATCH('settlement day'!$B$3,NYH!$A$4:$A$1048576,0),MATCH('settlement day'!AD$3,NYH!$A$4:$BB$4,0)) -> 0 | AE51: =INDEX(NYH!$A$4:$BB$1048576,MATCH('settlement day'!$B$3,NYH!$A$4:$A$1048576,0),MATCH('settlement day'!AE$3,NYH!$A$4:$BB$4,0)) -> 0 | AF51: =INDEX(NYH!$A$4:$BB$1048576,MATCH('settlement day'!$B$3,NYH!$A$4:$A$1048576,0),MATCH('settlement day'!AF$3,NYH!$A$4:$BB$4,0)) -> 0 | AG51: =INDEX(NYH!$A$4:$BB$1048576,MATCH('settlement day'!$B$3,NYH!$A$4:$A$1048576,0),MATCH('settlement day'!AG$3,NYH!$A$4:$BB$4,0)) -> 0 | AH51: =INDEX(NYH!$A$4:$BB$1048576,MATCH('settlement day'!$B$3,NYH!$A$4:$A$1048576,0),MATCH('settlement day'!AH$3,NYH!$A$4:$BB$4,0)) -> 0 | AI51: =INDEX(NYH!$A$4:$BB$1048576,MATCH('settlement day'!$B$3,NYH!$A$4:$A$1048576,0),MATCH('settlement day'!AI$3,NYH!$A$4:$BB$4,0)) -> 0 | ... AK51: =INDEX(NYH!$A$4:$BB$1048576,MATCH('settlement day'!$B$3,NYH!$A$4:$A$1048576,0),MATCH('settlement day'!AK$3,NYH!$A$4:$BB$4,0)) -> 0 | AM51: =INDEX(NYH!$A$4:$BB$1048576,MATCH('settlement day'!$B$3,NYH!$A$4:$A$1048576,0),MATCH('settlement day'!AL$3,NYH!$A$4:$BB$4,0)) -> 0 | AN51: =INDEX(NYH!$A$4:$BB$1048576,MATCH('settlement day'!$B$3,NYH!$A$4:$A$1048576,0),MATCH('settlement day'!AM$3,NYH!$A$4:$BB$4,0)) -> 0 | AO51: =INDEX(NYH!$A$4:$BB$1048576,MATCH('settlement day'!$B$3,NYH!$A$4:$A$1048576,0),MATCH('settlement day'!AN$3,NYH!$A$4:$BB$4,0)) -> 0 | AP51: =INDEX(NYH!$A$4:$BB$1048576,MATCH('settlement day'!$B$3,NYH!$A$4:$A$1048576,0),MATCH('settlement day'!AO$3,NYH!$A$4:$BB$4,0)) -> 0 | AQ51: =INDEX(NYH!$A$4:$BB$1048576,MATCH('settlement day'!$B$3,NYH!$A$4:$A$1048576,0),MATCH('settlement day'!AP$3,NYH!$A$4:$BB$4,0)) -> 0 | AR51: =INDEX(NYH!$A$4:$BB$1048576,MATCH('settlement day'!$B$3,NYH!$A$4:$A$1048576,0),MATCH('settlement day'!AQ$3,NYH!$A$4:$BB$4,0)) -> 0 | AS51: =INDEX(NYH!$A$4:$BB$1048576,MATCH('settlement day'!$B$3,NYH!$A$4:$A$1048576,0),MATCH('settlement day'!AR$3,NYH!$A$4:$BB$4,0)) -> 0 | AY51: =INDEX(NYH!$A$4:$CC$1048576,MATCH('settlement day'!$B$3,NYH!$A$4:$A$1048576,0),MATCH('settlement day'!AY$3,NYH!$A$4:$CC$4,0)) -> 0 | AZ51: =INDEX(NYH!$A$4:$CC$1048576,MATCH('settlement day'!$B$3,NYH!$A$4:$A$1048576,0),MATCH('settlement day'!AZ$3,NYH!$A$4:$CC$4,0)) -> 0 | BA51: =INDEX(NYH!$A$4:$CC$1048576,MATCH('settlement day'!$B$3,NYH!$A$4:$A$1048576,0),MATCH('settlement day'!BA$3,NYH!$A$4:$CC$4,0)) -> 0 | BB51: =INDEX(NYH!$A$4:$CC$1048576,MATCH('settlement day'!$B$3,NYH!$A$4:$A$1048576,0),MATCH('settlement day'!BB$3,NYH!$A$4:$CC$4,0)) -> 0 | BC51: =INDEX(NYH!$A$4:$CC$1048576,MATCH('settlement day'!$B$3,NYH!$A$4:$A$1048576,0),MATCH('settlement day'!BC$3,NYH!$A$4:$CC$4,0)) -> 0 | BD51: =INDEX(NYH!$A$4:$CC$1048576,MATCH('settlement day'!$B$3,NYH!$A$4:$A$1048576,0),MATCH('settlement day'!BD$3,NYH!$A$4:$CC$4,0)) -> 0 | BE51: =INDEX(NYH!$A$4:$CC$1048576,MATCH('settlement day'!$B$3,NYH!$A$4:$A$1048576,0),MATCH('settlement day'!BE$3,NYH!$A$4:$CC$4,0)) -> 0 | BF51: =INDEX(NYH!$A$4:$CC$1048576,MATCH('settlement day'!$B$3,NYH!$A$4:$A$1048576,0),MATCH('settlement day'!BF$3,NYH!$A$4:$CC$4,0)) -> 0 | ... BV51: =INDEX(NYH!$A$4:$CC$1048576,MATCH('settlement day'!$B$3,NYH!$A$4:$A$1048576,0),MATCH('settlement day'!BV$3,NYH!$A$4:$CC$4,0)) -> 0
