Workbook

Sheet INDIA
A1: 44284 | B1: INDIA
B2: ST ROSE | C2: Freight | D2: =(+'Freight matrix'!G12)*A4 -> 51.285 | E2: usd/cbm
A3: 264.172 | B3: SANTOS | C3: Freight | D3: =(+'Freight matrix'!G23)*A4 -> 41.817 | E3: usd/cbm
A4: 0.789 | C4: Volume | D4: 20000 | E4: cbm
C6: Basis | D6: 0.105 | E6: cpg
B7: US | C7: APR | D7: MAY | E7: JUN | F7: JUL | G7: AUG | H7: SEP | I7: OCT | J7: NOV | K7: DEC | L7: JAN | M7: FEB | N7: MAR
B8: CHIP | C8: =+'settlement day'!F9 -> 0 | D8: =+'settlement day'!G9 -> 0 | E8: =+'settlement day'!H9 -> 0 | F8: =+'settlement day'!I9 -> 0 | G8: =+'settlement day'!J9 -> 0 | H8: =+'settlement day'!K9 -> 0 | I8: =+'settlement day'!L9 -> 0 | J8: =+'settlement day'!M9 -> 0 | K8: =+'settlement day'!N9 -> 0
B10: FOB IMTT | C10: =+(C8+$D$6)*$A$3 -> 27.73806 | D10: =+(D8+$D$6)*$A$3 -> 27.73806 | E10: =+(E8+$D$6)*$A$3 -> 27.73806 | F10: =+(F8+$D$6)*$A$3 -> 27.73806 | G10: =+(G8+$D$6)*$A$3 -> 27.73806 | H10: =+(H8+$D$6)*$A$3 -> 27.73806 | I10: =+(I8+$D$6)*$A$3 -> 27.73806 | J10: =+(J8+$D$6)*$A$3 -> 27.73806 | K10: =+(K8+$D$6)*$A$3 -> 27.73806
B11: CIF INDIA usd/cbm | C11: =+C10+$D$2 -> 79.02306 | D11: =+D10+$D$2 -> 79.02306 | E11: =+E10+$D$2 -> 79.02306 | F11: =+F10+$D$2 -> 79.02306 | G11: =+G10+$D$2 -> 79.02306 | H11: =+H10+$D$2 -> 79.02306 | I11: =+I10+$D$2 -> 79.02306 | J11: =+J10+$D$2 -> 79.02306 | K11: =+K10+$D$2 -> 79.02306
B13: CIF INDIA usd/mt | C13: =+C11/$A$4 -> 100.15597 | D13: =+D11/$A$4 -> 100.15597 | E13: =+E11/$A$4 -> 100.15597 | F13: =+F11/$A$4 -> 100.15597 | G13: =+G11/$A$4 -> 100.15597 | H13: =+H11/$A$4 -> 100.15597 | I13: =+I11/$A$4 -> 100.15597 | J13: =+J11/$A$4 -> 100.15597 | K13: =+K11/$A$4 -> 100.15597
A15: inland
A16: =+'mkt data'!G6+'mkt data'!G8 -> 90 | B16: BRAZIL | C16: APR | D16: MAY | E16: JUN | F16: JUL | G16: AUG | H16: SEP | I16: OCT | J16: NOV | K16: DEC | L16: JAN | M16: FEB | N16: MAR
A17: brl/cbm | B17: B3 | C17: =+'settlement day'!F13 -> 0 | D17: =+'settlement day'!G13 -> 0 | E17: =+'settlement day'!H13 -> 0 | F17: =+'settlement day'!I13 -> 0 | G17: =+'settlement day'!J13 -> 0 | H17: =+'settlement day'!K13 -> 0 | I17: =+'settlement day'!L13 -> 0 | J17: =+'settlement day'!M13 -> 0 | K17: =+'settlement day'!N13 -> 0
B18: BRL/USD | C18: =+D18 -> 0 | D18: =+'settlement day'!G30 -> 0 | E18: =+'settlement day'!H30 -> 0 | F18: =+'settlement day'!I30 -> 0 | G18: =+'settlement day'!J30 -> 0 | H18: =+'settlement day'!K30 -> 0 | I18: =+'settlement day'!L30 -> 0 | J18: =+'settlement day'!M30 -> 0 | K18: =+'settlement day'!N30 -> 0
B19: hydrous FOB BRZ | C19: =+(C17+$A$16)/C18 -> #DIV/0! | D19: =+(D17+$A$16)/D18 -> #DIV/0! | E19: =+(E17+$A$16)/E18 -> #DIV/0! | F19: =+(F17+$A$16)/F18 -> #DIV/0! | G19: =+(G17+$A$16)/G18 -> #DIV/0! | H19: =+(H17+$A$16)/H18 -> #DIV/0! | I19: =+(I17+$A$16)/I18 -> #DIV/0! | J19: =+(J17+$A$16)/J18 -> #DIV/0! | K19: =+(K17+$A$16)/K18 -> #DIV/0!
A20: 100 | B20: grade B FOB BRZ | C20: =+C19+($A$20/C18) -> #DIV/0! | D20: =+D19+($A$20/D18) -> #DIV/0! | E20: =+E19+($A$20/E18) -> #DIV/0! | F20: =+F19+($A$20/F18) -> #DIV/0! | G20: =+G19+($A$20/G18) -> #DIV/0! | H20: =+H19+($A$20/H18) -> #DIV/0! | I20: =+I19+($A$20/I18) -> #DIV/0! | J20: =+J19+($A$20/J18) -> #DIV/0! | K20: =+K19+($A$20/K18) -> #DIV/0!
A21: 1.12 | B21: anhydrous FOB BRZ | C21: =+C19*$A$21 -> #DIV/0! | D21: =+D19*$A$21 -> #DIV/0! | E21: =+E19*$A$21 -> #DIV/0! | F21: =+F19*$A$21 -> #DIV/0! | G21: =+G19*$A$21 -> #DIV/0! | H21: =+H19*$A$21 -> #DIV/0! | I21: =+I19*$A$21 -> #DIV/0! | J21: =+J19*$A$21 -> #DIV/0! | K21: =+K19*$A$21 -> #DIV/0!
B23: CIF INDIA usd/cbm | C23: =+C21+$D$3 -> #DIV/0! | D23: =+D21+$D$3 -> #DIV/0! | E23: =+E21+$D$3 -> #DIV/0! | F23: =+F21+$D$3 -> #DIV/0! | G23: =+G21+$D$3 -> #DIV/0! | H23: =+H21+$D$3 -> #DIV/0! | I23: =+I21+$D$3 -> #DIV/0! | J23: =+J21+$D$3 -> #DIV/0! | K23: =+K21+$D$3 -> #DIV/0!
B25: CIF INDIA usd/mt | C25: =+C23/$A$4 -> #DIV/0! | D25: =+D23/$A$4 -> #DIV/0! | E25: =+E23/$A$4 -> #DIV/0! | F25: =+F23/$A$4 -> #DIV/0! | G25: =+G23/$A$4 -> #DIV/0! | H25: =+H23/$A$4 -> #DIV/0! | I25: =+I23/$A$4 -> #DIV/0! | J25: =+J23/$A$4 -> #DIV/0! | K25: =+K23/$A$4 -> #DIV/0!
B28: usd/mt | C28: 100
B29: India indicative bid anhydrous | C29: =(((C8*$A$3)+$D$2)/$A$4)+$C$28 -> 165 | D29: =(((D8*$A$3)+$D$2)/$A$4)+$C$28 -> 165 | E29: =(((E8*$A$3)+$D$2)/$A$4)+$C$28 -> 165 | F29: =(((F8*$A$3)+$D$2)/$A$4)+$C$28 -> 165 | G29: =(((G8*$A$3)+$D$2)/$A$4)+$C$28 -> 165 | H29: =(((H8*$A$3)+$D$2)/$A$4)+$C$28 -> 165 | I29: =(((I8*$A$3)+$D$2)/$A$4)+$C$28 -> 165 | J29: =(((J8*$A$3)+$D$2)/$A$4)+$C$28 -> 165 | K29: =(((K8*$A$3)+$D$2)/$A$4)+$C$28 -> 165
B30: India indicative bid hydrous
C36: 0.789
C37: 264.172 | E37: june | I37: Raizen 22/4/21 -- FX 5.44
C38: chip cbm | D38: =+E38*C37 -> 0 | E38: =+E8 -> 0 | I38: 629 | J38: usd/cbm FOB
C39: chip pmt | D39: =+D38/C36 -> 0 | I39: =+I38/A4 -> 797.21166 | J39: usd/mt FOB
C40: bid premium pmt | D40: 100 | I40: =+I39+45 -> 842.21166 | J40: usd/mt CIF
C41: bid CIF WCI | D41: =+D39+D40 -> 100 | E41: pmt
D42: =+'Freight matrix'!G12 -> 65 | E42: pmt
D43: 9 | E43: pmt
D44: =+D41-D42-D43 -> 26 | E44: pmt fob
C46: anhydrous | D46: =+D44*0.789 -> 20.514 | E46: cbm fob | F46: =+D46/C37 -> 0.077653953
F47: =+F46-E38 -> 0.077653953
C48: hydrous | D48: =+D46/1.07 -> 19.171963 | E48: cbm fob
D50: =130/5.65 -> 23.00885

Sheet CHINA
A1: 44284 | B1: CHINA
B2: ST ROSE | C2: Freight | D2: =1500000/D4 -> 50 | E2: usd/cbm | F2: Yangtze River ports
A3: 264.172 | B3: SANTOS | C3: Freight | D3: =(+'Freight matrix'!J24)*A4 -> 43.395 | E3: usd/cbm
A4: 0.789 | C4: Volume | D4: 30000 | E4: cbm
C6: Basis | D6: 0.1 | E6: cpg
B7: US | C7: APR | D7: MAY | E7: JUN | F7: JUL | G7: AUG | H7: SEP | I7: OCT | J7: NOV | K7: DEC | L7: JAN | M7: FEB | N7: MAR
B8: CHIP | C8: =+'settlement day'!F9 -> 0 | D8: =+'settlement day'!G9 -> 0 | E8: =+'settlement day'!H9 -> 0 | F8: =+'settlement day'!I9 -> 0 | G8: =+'settlement day'!J9 -> 0 | H8: =+'settlement day'!K9 -> 0 | I8: =+'settlement day'!L9 -> 0 | J8: =+'settlement day'!M9 -> 0 | K8: =+'settlement day'!N9 -> 0
B10: FOB IMTT | C10: =+(C8+$D$6)*$A$3 -> 26.4172 | D10: =+(D8+$D$6)*$A$3 -> 26.4172 | E10: =+(E8+$D$6)*$A$3 -> 26.4172 | F10: =+(F8+$D$6)*$A$3 -> 26.4172 | G10: =+(G8+$D$6)*$A$3 -> 26.4172 | H10: =+(H8+$D$6)*$A$3 -> 26.4172 | I10: =+(I8+$D$6)*$A$3 -> 26.4172 | J10: =+(J8+$D$6)*$A$3 -> 26.4172 | K10: =+(K8+$D$6)*$A$3 -> 26.4172
B11: CIF China usd/cbm | C11: =+C10+$D$2 -> 76.4172 | D11: =+D10+$D$2 -> 76.4172 | E11: =+E10+$D$2 -> 76.4172 | F11: =+F10+$D$2 -> 76.4172 | G11: =+G10+$D$2 -> 76.4172 | H11: =+H10+$D$2 -> 76.4172 | I11: =+I10+$D$2 -> 76.4172 | J11: =+J10+$D$2 -> 76.4172 | K11: =+K10+$D$2 -> 76.4172
A12: 1.45 | B12: Import duty | C12: =+C11*$A$12 -> 110.80494 | D12: =+D11*$A$12 -> 110.80494 | E12: =+E11*$A$12 -> 110.80494 | F12: =+F11*$A$12 -> 110.80494 | G12: =+G11*$A$12 -> 110.80494 | H12: =+H11*$A$12 -> 110.80494 | I12: =+I11*$A$12 -> 110.80494 | J12: =+J11*$A$12 -> 110.80494 | K12: =+K11*$A$12 -> 110.80494
B14: CIF usd/mt | C14: =+C12/$A$4 -> 140.43719 | D14: =+D12/$A$4 -> 140.43719 | E14: =+E12/$A$4 -> 140.43719 | F14: =+F12/$A$4 -> 140.43719 | G14: =+G12/$A$4 -> 140.43719 | H14: =+H12/$A$4 -> 140.43719 | I14: =+I12/$A$4 -> 140.43719 | J14: =+J12/$A$4 -> 140.43719 | K14: =+K12/$A$4 -> 140.43719
A17: inland | B17: BRAZIL | C17: APR | D17: MAY | E17: JUN | F17: JUL | G17: AUG | H17: SEP | I17: OCT | J17: NOV | K17: DEC | L17: JAN | M17: FEB | N17: MAR
A18: =+'mkt data'!G6+'mkt data'!G8 -> 90 | B18: B3 | C18: =+'settlement day'!F13 -> 0 | D18: =+'settlement day'!G13 -> 0 | E18: =+'settlement day'!H13 -> 0 | F18: =+'settlement day'!I13 -> 0 | G18: =+'settlement day'!J13 -> 0 | H18: =+'settlement day'!K13 -> 0 | I18: =+'settlement day'!L13 -> 0 | J18: =+'settlement day'!M13 -> 0 | K18: =+'settlement day'!N13 -> 0
A19: brl/cbm | B19: BRL/USD | C19: =+D19 -> 0 | D19: =+'settlement day'!G30 -> 0 | E19: =+'settlement day'!H30 -> 0 | F19: =+'settlement day'!I30 -> 0 | G19: =+'settlement day'!J30 -> 0 | H19: =+'settlement day'!K30 -> 0 | I19: =+'settlement day'!L30 -> 0 | J19: =+'settlement day'!M30 -> 0 | K19: =+'settlement day'!N30 -> 0
B20: hydrous FOB BRZ | C20: =+(C18+$A$18)/C19 -> #DIV/0! | D20: =+(D18+$A$18)/D19 -> #DIV/0! | E20: =+(E18+$A$18)/E19 -> #DIV/0! | F20: =+(F18+$A$18)/F19 -> #DIV/0! | G20: =+(G18+$A$18)/G19 -> #DIV/0! | H20: =+(H18+$A$18)/H19 -> #DIV/0! | I20: =+(I18+$A$18)/I19 -> #DIV/0! | J20: =+(J18+$A$18)/J19 -> #DIV/0! | K20: =+(K18+$A$18)/K19 -> #DIV/0!
A21: 100 | B21: grade B FOB BRZ | C21: =+C20+($A$21/C19) -> #DIV/0! | D21: =+D20+($A$21/D19) -> #DIV/0! | E21: =+E20+($A$21/E19) -> #DIV/0! | F21: =+F20+($A$21/F19) -> #DIV/0! | G21: =+G20+($A$21/G19) -> #DIV/0! | H21: =+H20+($A$21/H19) -> #DIV/0! | I21: =+I20+($A$21/I19) -> #DIV/0! | J21: =+J20+($A$21/J19) -> #DIV/0! | K21: =+K20+($A$21/K19) -> #DIV/0!
A22: 1.12 | B22: anhydrous FOB BRZ | C22: =+C20*$A$22 -> #DIV/0! | D22: =+D20*$A$22 -> #DIV/0! | E22: =+E20*$A$22 -> #DIV/0! | F22: =+F20*$A$22 -> #DIV/0! | G22: =+G20*$A$22 -> #DIV/0! | H22: =+H20*$A$22 -> #DIV/0! | I22: =+I20*$A$22 -> #DIV/0! | J22: =+J20*$A$22 -> #DIV/0! | K22: =+K20*$A$22 -> #DIV/0!
B24: CIF China | C24: =+C22+$D$3 -> #DIV/0! | D24: =+D22+$D$3 -> #DIV/0! | E24: =+E22+$D$3 -> #DIV/0! | F24: =+F22+$D$3 -> #DIV/0! | G24: =+G22+$D$3 -> #DIV/0! | H24: =+H22+$D$3 -> #DIV/0! | I24: =+I22+$D$3 -> #DIV/0! | J24: =+J22+$D$3 -> #DIV/0! | K24: =+K22+$D$3 -> #DIV/0!
A25: 1.3 | B25: Import duty | C25: =+C24*$A$25 -> #DIV/0! | D25: =+D24*$A$25 -> #DIV/0! | E25: =+E24*$A$25 -> #DIV/0! | F25: =+F24*$A$25 -> #DIV/0! | G25: =+G24*$A$25 -> #DIV/0! | H25: =+H24*$A$25 -> #DIV/0! | I25: =+I24*$A$25 -> #DIV/0! | J25: =+J24*$A$25 -> #DIV/0! | K25: =+K24*$A$25 -> #DIV/0!
B27: CIF usd/mt | C27: =+C25/$A$4 -> #DIV/0! | D27: =+D25/$A$4 -> #DIV/0! | E27: =+E25/$A$4 -> #DIV/0! | F27: =+F25/$A$4 -> #DIV/0! | G27: =+G25/$A$4 -> #DIV/0! | H27: =+H25/$A$4 -> #DIV/0! | I27: =+I25/$A$4 -> #DIV/0! | J27: =+J25/$A$4 -> #DIV/0! | K27: =+K25/$A$4 -> #DIV/0!
B31: China domestic price

Sheet USA
C3: 264.172
B4: Arbitrage Brazil to California | H4: 3000
B5: Updated: | C5: 44286 | H5: =+H4/I5 -> #DIV/0! | I5: =+'settlement day'!H30 -> 0
B7: Volume | C7: 40000 | D7: m3 | E7: =(+C7*C3)/1000 -> 10566.88 | F7: mln gal | Q7: 2.4825
B8: FOB Santos | C8: 545 | D8: per m3 | E8: JUNE | F8: loading | I8: FREIGHT | Q8: 0.365
B9: FOB Santos | C9: =C8/264.172 -> 2.0630498 | D9: per gallon | I9: 05/02/2021: spi: $1.7-1.75 m as a guide | Q9: =+Q7+Q8 -> 2.8475
B10: Frt ($/mT) | C10: =E10/334 -> 0.16601777 | D10: per gallon | E10: =+I12 -> 55.449937 | F10: usd/mt | I10: 1750000 | J10: usd lps | K10: 400/400 | Q10: =+Q9*264.172 -> 752.22977
B11: CIF Cali | C11: =C9+C10 -> 2.2290676 | D11: per gallon | I11: =40000*0.789 -> 31560 | J11: mt | P11: FOB | Q11: =+Q10/1.1 -> 683.84525 | R11: eur/cbm
B12: CIF Cali ME importer of record | C12: =C11*1.025 -> 2.2847943 | D12: per gallon | E12: =+C12*C3 -> 603.57868 | F12: USD/cbm | I12: =+I10/I11 -> 55.449937 | J12: usd/mt
L13: =+I12*0.789 -> 43.75
B15: LCSF Baseline | C15: 79.9 | D15: CI value
B16: LCFS (Brazil) | C16: 58 | D16: CI value | I16: CIF SALE TO ME
B17: LCFS CI value | C17: =+'settlement day'!BJ34 -> 0 | D17: per gallon | I17: =+C9 -> 2.0630498 | J17: FOB Santos
B18: LCFS ( Brazilian producer) | C18: =(C15-C16)*C17 -> 0 | D18: per gallon | I18: 0.005 | J18: Costings
B19: D6 2021 | C19: =+'settlement day'!BG34 -> 0 | D19: per gallon | I19: =+C10 -> 0.16601777 | J19: Freight
B20: D5 2021 | C20: =+'settlement day'!BI34 -> 0 | D20: per gallon | I20: 0.01 | J20: Demurrage
B21: D5-D6 | C21: =C20-C19 -> 0 | D21: per gallon | I21: 0.01 | J21: MEG
B22: Total CI+RIN pick-up | C22: =(C21+C18)*E22 -> 0 | D22: per gallon | E22: 1 | I22: =SUM(I17:I21) -> 2.2540676 | J22: =+I22*C3 -> 595.46155 | K22: USD/cbm
B23: Total CI+RIN pick-up | C23: =C22*$C$3 -> 0 | D23: per m3
E24: OPIS spot | G24: Platts
B25: CIF Cali with Credit | C25: =C12-C22 -> 2.2847943 | E25: Argo | F25: =+'settlement day'!AY34 -> 0
B26: Cali delivered (CHIP + differential) | C26: =+F28+G27 -> 0.18 | E26: LA | F26: =+'settlement day'!AY38 -> 0 | H26: =+F25+G27 -> 0.18
F27: =+F26-F25 -> 0 | G27: 0.18
E28: CHIP | F28: =+'settlement day'!I9 -> 0 | G28: JULY | H28: arrival
B29: Bzl /Cali arb | C29: =C26-C25 -> -2.1047943 | D29: =+C29*C3 -> -556.02772 | F29: =+F28-C25 -> -2.2847943
B31: Duty Drawback (2.5%) | C31: =C11*0.025 -> 0.05572669 | D31: per gallon
B32: Duty Drawback (2.5%) | C32: =C31*264.172 -> 14.721431 | D32: per m3
B39: FLORIDA / USGC
B40: 0.12 | D40: usd/cbm
B41: LYB / Florida ind bid | D41: =(+'settlement day'!I9+B40)*C3 -> 31.70064 | F41: JULY arrival
B42: CIF USGC/USEC | C42: =+D41-D42 -> #REF! | D42: =+('FOB origin'!#REF!)+('Freight matrix'!H16*0.789) -> #REF! | E42: b3
C43: =+D41-D43 -> #REF! | D43: =+'FOB origin'!#REF!+('Freight matrix'!$H$16*0.789) -> #REF! | E43: phys

Sheet Freight matrix
B1: Last update | C1: April 21
B3: Freight rates in USD/MT
B4: ex USGC | C4: 5kt | E4: 10kt | G4: 20kt | I4: 30kt | K4: 40kt
B5: ARA | C5: 57 | D5: 60 | E5: 47 | F5: 55 | G5: 39 | H5: 42 | I5: 32 | J5: 35 | K5: 29 | L5: 32
B6: France | C6: 57 | D6: 60 | E6: 47 | F6: 55 | G6: 39 | H6: 42 | I6: 32 | J6: 35 | K6: 29 | L6: 32
B7: Baltics | C7: 57 | D7: 60 | E7: 47 | F7: 60 | G7: 39 | H7: 42 | I7: 32 | J7: 35 | K7: 29 | L7: 32
B8: North Brazil | C8: 65 | D8: 68 | E8: 55 | F8: 57 | G8: 40 | H8: 42 | I8: 37 | J8: 39 | K8: 30 | L8: 33
B9: Southeast Brazil | C9: - | D9: - | E9: - | F9: - | G9: 47 | H9: 49 | I9: 44 | J9: 46 | K9: 37 | L9: 40
B10: Colombia / Caribe | D10: 60 | F10: 50
B11: Far East | C11: 80 | D11: 83 | E11: 72 | F11: 75 | G11: 62 | H11: 65 | I11: 52 | J11: 55 | K11: 47 | L11: 50 | P11: 35
B12: WCI/AG | C12: 81 | D12: 85 | E12: 74 | F12: 78 | G12: 65 | H12: 70 | I12: 60 | J12: 65 | K12: 55 | L12: 60 | P12: =+P11*0.789 -> 27.615
B13: CHINA
B15: ex BRAZIL | C15: 5kt | E15: 10kt | G15: 20kt | I15: 30kt | K15: 40kt
B16: USG/USEC | C16: 50 | D16: 53 | E16: 43 | F16: 46 | G16: 32 | H16: 35 | I16: 26 | J16: 28 | K16: 22 | L16: 25
B17: USWC | C17: - | D17: - | E17: - | F17: - | G17: 70 | H17: 73 | I17: 53 | J17: 56 | K17: 39 | L17: 41
B18: ARA | C18: 65 | D18: 68 | E18: 50 | F18: 53 | G18: 40 | H18: 43 | I18: 32 | J18: 35 | K18: - | L18: -
B19: France | C19: 65 | D19: 68 | E19: 50 | F19: 53 | G19: 40 | H19: 43 | I19: 32 | J19: 35 | K19: - | L19: -
B20: Baltics | C20: 65 | D20: 68 | E20: 50 | F20: 53 | G20: 40 | H20: 43 | I20: 32 | J20: 35 | K20: - | L20: -
B21: Colombia / Caribe
B22: Far East | C22: 80 | D22: 83 | E22: 85 | F22: 90 | G22: 64 | H22: 68 | I22: 52 | J22: 55 | K22: 46 | L22: 49
B23: WCI/AG | C23: - | D23: - | E23: 70 | F23: 73 | G23: 53 | H23: 56 | I23: 55 | J23: 58 | K23: 48 | L23: 51
B24: CHINA | H24: 58 | J24: 55
B26: ex KARACHI | C26: 5kt | E26: 10kt | G26: 20kt | I26: 30kt | K26: 40kt
B27: ARA | C27: 85 | D27: 88 | E27: 73 | F27: 76 | G27: 65 | H27: 68 | I27: 55 | J27: 58 | K27: 45 | L27: 48
B28: FAR EAST | C28: 57 | D28: 60 | E28: 50 | F28: 53 | G28: 42 | H28: 45 | I28: 36 | J28: 39 | K28: 31 | L28: 33
B30: ex WCCAM/SAM | C30: 5kt | E30: 10kt | G30: 20kt | I30: 30kt | K30: 40kt
B31: North Brazil | C31: 71 | D31: 73 | E31: 60 | F31: 63 | G31: 49 | H31: 52 | I31: - | J31: - | K31: - | L31: -
B32: ARA | C32: 83 | D32: 86 | E32: 73 | F32: 76 | G32: 63 | H32: 66 | I32: 53 | J32: 56 | K32: 41 | L32: 45
B33: FAR EAST | C33: 85 | D33: 88 | E33: 75 | F33: 79 | G33: 67 | H33: 70 | I33: 59 | J33: 62 | K33: 50 | L33: 53

Sheet FOB origin
C1: FOB ORIGIN
B2: 264.172
B3: 0.789
B4: 0.1 | AH4: =+(AH9+$B$4)*$B$2 -> 26.4172 | AI4: =+(AI9+$B$4)*$B$2 -> 26.4172 | AJ4: =+(AJ9+$B$4)*$B$2 -> 26.4172 | AK4: =+(AK9+$B$4)*$B$2 -> 26.4172 | AL4: =+(AL9+$B$4)*$B$2 -> 26.4172 | AM4: =+(AM9+$B$4)*$B$2 -> 26.4172 | AN4: =+(AN9+$B$4)*$B$2 -> 26.4172 | AO4: =+(AO9+$B$4)*$B$2 -> 26.4172 | ... BF4: =+(BF9+$B$4)*$B$2 -> 466.92401
C6: FOB ORIGIN | D6: 44317 | E6: 44378 | F6: 44409 | G6: 44440 | H6: 44470 | I6: 44501 | J6: 44531 | K6: 44562 | L6: 44593 | M6: 44621 | N6: 44652 | O6: 44682 | P6: 44713 | Q6: 44743 | R6: 44774 | S6: 44805 | T6: 44835 | U6: 44866 | V6: 44896 | W6: 44927 | X6: 44958 | Y6: 44986 | Z6: 45017 | AA6: 45047 | AB6: 45078 | AC6: 45108 | AD6: 45139 | AE6: 45170 | AF6: 45200 | AG6: 45231 | AH6: 45261 | AI6: 45292 | AJ6: 45323 | AK6: 45352 | AL6: 45383 | AM6: 45413 | AN6: 45444 | AO6: 45474 | AP6: 45505 | AQ6: 45536 | AR6: 45566 | AS6: 45597 | AT6: 45627 | AU6: 45658 | AV6: 45689 | AW6: 45717 | AX6: 45748 | AY6: 45778 | AZ6: 45809 | BA6: 45839 | BB6: 45870 | BC6: 45901 | BD6: 45931 | BE6: 45962 | BF6: 45992 | BH6: Cbios | BI6: CBio unit | BJ6: per vol HYD | BK6: per vol ANH
C7: USGC | BH7: R$ | BI7: =+'settlement day'!BN42 -> 60.25 | BJ7: =+'settlement day'!BO42 -> 64.576635 | BK7: =+'settlement day'!BP42 -> 73.207776
C8: D-1 | D8: =+'settlement day'!G11 -> 0 | E8: =+'settlement day'!I11 -> 0 | F8: =+'settlement day'!J11 -> 0 | G8: =+'settlement day'!K11 -> 0 | H8: =+'settlement day'!L11 -> 0 | I8: =+'settlement day'!M11 -> 0 | J8: =+'settlement day'!N11 -> 0 | K8: =+'settlement day'!O11 -> 0 | L8: =+'settlement day'!P11 -> 0 | ... BF8: =+'settlement day'!BJ11 -> 0.0125 | BH8: U$ | BI8: =+'settlement day'!BN43 -> 12.091838 | BJ8: =+'settlement day'!BO43 -> 12.960169 | BK8: =+'settlement day'!BP43 -> 14.692391
C9: CHIP | D9: =+'settlement day'!G9 -> 0 | E9: =+'settlement day'!I9 -> 0 | F9: =+'settlement day'!J9 -> 0 | G9: =+'settlement day'!K9 -> 0 | H9: =+'settlement day'!L9 -> 0 | I9: =+'settlement day'!M9 -> 0 | J9: =+'settlement day'!N9 -> 0 | K9: =+'settlement day'!O9 -> 0 | L9: =+'settlement day'!P9 -> 0 | ... BF9: =+'settlement day'!BJ9 -> 1.6675 | BJ9: =+BK8-BJ8 -> 1.7322219
B11: 0.1 | C11: FOB US IMTT - D12 | D11: =+(D9+$B$11)*$B$2 -> 26.4172 | E11: =+(E9+$B$11)*$B$2 -> 26.4172 | F11: =+(F9+$B$11)*$B$2 -> 26.4172 | G11: =+(G9+$B$11)*$B$2 -> 26.4172 | H11: =+(H9+$B$11)*$B$2 -> 26.4172 | I11: =+(I9+$B$11)*$B$2 -> 26.4172 | J11: =+(J9+$B$11)*$B$2 -> 26.4172 | K11: =+(K9+$B$11)*$B$2 -> 26.4172 | ... BF11: =+(BF9+$B$11)*$B$2 -> 466.92401
B12: =+'mkt data'!G14 -> 0.22 | C12: FOB US IMTT - U3 | D12: =+(D9+$B$12)*$B$2 -> 58.11784 | E12: =+(E9+$B$12)*$B$2 -> 58.11784 | F12: =+(F9+$B$12)*$B$2 -> 58.11784 | G12: =+(G9+$B$12)*$B$2 -> 58.11784 | H12: =+(H9+$B$12)*$B$2 -> 58.11784 | I12: =+(I9+$B$12)*$B$2 -> 58.11784 | J12: =+(J9+$B$12)*$B$2 -> 58.11784 | K12: =+(K9+$B$12)*$B$2 -> 58.11784 | ... BF12: =+(BF9+$B$12)*$B$2 -> 498.62465
C14: BRAZIL CS
B15: inland | C15: D-1 | D15: =+'settlement day'!G15 -> 0 | E15: =+'settlement day'!I15 -> 0 | F15: =+'settlement day'!J15 -> 0 | G15: =+'settlement day'!K15 -> 0 | H15: =+'settlement day'!L15 -> 0 | I15: =+'settlement day'!M15 -> 0 | J15: =+'settlement day'!N15 -> 0 | K15: =+'settlement day'!O15 -> 0 | L15: =+'settlement day'!P15 -> 0 | ... BF15: =+'settlement day'!BJ15 -> 0
B16: =+'mkt data'!G23 -> 90 | C16: B3 ETH Brazil | D16: =+'settlement day'!G13 -> 0 | E16: =+'settlement day'!I13 -> 0 | F16: =+'settlement day'!J13 -> 0 | G16: =+'settlement day'!K13 -> 0 | H16: =+'settlement day'!L13 -> 0 | I16: =+'settlement day'!M13 -> 0 | J16: =+'settlement day'!N13 -> 0 | K16: =+'settlement day'!O13 -> 0 | L16: =+'settlement day'!P13 -> 0 | ... BF16: =+'settlement day'!BJ13 -> 2825
B17: brl/cbm | C17: BRL/USD | D17: =+'settlement day'!G30 -> 0 | E17: =+'settlement day'!I30 -> 0 | F17: =+'settlement day'!J30 -> 0 | G17: =+'settlement day'!K30 -> 0 | H17: =+'settlement day'!L30 -> 0 | I17: =+'settlement day'!M30 -> 0 | J17: =+'settlement day'!N30 -> 0 | K17: =+'settlement day'!O30 -> 0 | L17: =+'settlement day'!P30 -> 0 | ... BF17: =+'settlement day'!BJ30 -> 5.9417706 | BH17: ADD CBIO VALUE , factor for HYDROUS and ANHYDROUS
BJ18: HYD | BK18: ANH
B20: =+(B31+B32)-B16 -> 460 | C20: Hydrous FOB BRZ | D20: =+(D16+$B$16)/D17 -> #DIV/0! | E20: =+(E16+$B$16)/E17 -> #DIV/0! | F20: =+(F16+$B$16)/F17 -> #DIV/0! | G20: =+(G16+$B$16)/G17 -> #DIV/0! | H20: =+(H16+$B$16)/H17 -> #DIV/0! | I20: =+(I16+$B$16)/I17 -> #DIV/0! | J20: =+(J16+$B$16)/J17 -> #DIV/0! | K20: =+(K16+$B$16)/K17 -> #DIV/0! | L20: =+((L16+$B$16)/L17)+BJ8 -> #DIV/0! | M20: =+((M16+$B$16)/M17)+$BJ$8 -> #DIV/0! | N20: =+((N16+$B$16)/N17)+$BJ$8 -> #DIV/0! | O20: =+((O16+$B$16)/O17)+$BJ$8 -> #DIV/0! | P20: =+((P16+$B$16)/P17)+$BJ$8 -> #DIV/0! | Q20: =+((Q16+$B$16)/Q17)+$BJ$8 -> #DIV/0! | R20: =+((R16+$B$16)/R17)+$BJ$8 -> #DIV/0! | S20: =+((S16+$B$16)/S17)+$BJ$8 -> #DIV/0! | T20: =+((T16+$B$16)/T17)+$BJ$8 -> #DIV/0! | ... BF20: =+((BF16+$B$16)/BF17)+$BJ$8 -> 503.55467 | BI20: cbio $/cbm | BJ20: 23.533119 | BK20: 24.609798
B21: =+'mkt data'!H2 -> 1.11 | C21: Grade B FOB BRZ | D21: =+D20+($B$20/D17) -> #DIV/0! | E21: =+E20+($B$20/E17) -> #DIV/0! | F21: =+F20+($B$20/F17) -> #DIV/0! | G21: =+G20+($B$20/G17) -> #DIV/0! | H21: =+H20+($B$20/H17) -> #DIV/0! | I21: =+I20+($B$20/I17) -> #DIV/0! | J21: =+J20+($B$20/J17) -> #DIV/0! | K21: =+K20+($B$20/K17) -> #DIV/0! | ... BF21: =+BF20+($B$20/BF17) -> 580.97267
B22: =+EU!BB3 -> 0 | C22: Anhydrous FOB BRZ | D22: =+D20*$B$21 -> #DIV/0! | E22: =+E20*$B$21 -> #DIV/0! | F22: =+F20*$B$21 -> #DIV/0! | G22: =+G20*$B$21 -> #DIV/0! | H22: =+H20*$B$21+$B$22 -> #DIV/0! | I22: =+I20*$B$21+$B$22 -> #DIV/0! | J22: =+J20*$B$21+$B$22 -> #DIV/0! | K22: =+K20*$B$21+$B$22 -> #DIV/0! | L22: =+L20*$B$21+$B$22+$BK$8 -> #DIV/0! | M22: =+M20*$B$21+$B$22+$BK$8 -> #DIV/0! | N22: =+N20*$B$21+$B$22+$BK$8 -> #DIV/0! | O22: =+O20*$B$21+$B$22+$BK$8 -> #DIV/0! | P22: =+P20*$B$21+$B$22+$BK$8 -> #DIV/0! | Q22: =+Q20*$B$21+$B$22+$BK$8 -> #DIV/0! | R22: =+R20*$B$21+$B$22+$BK$8 -> #DIV/0! | S22: =+S20*$B$21+$B$22+$BK$8 -> #DIV/0! | ... W22: =+W20*$B$21+$B$22+$BK$8 -> #DIV/0! | X22: =+(X20-$BJ$8)*$B$21+$B$22+$BK$8 -> #DIV/0! | Y22: =+(Y20-$BJ$8)*$B$21+$B$22+$BK$8 -> #DIV/0! | Z22: =+(Z20-$BJ$8)*$B$21+$B$22+$BK$8 -> #DIV/0! | AA22: =+(AA20-$BJ$8)*$B$21+$B$22+$BK$8 -> #DIV/0! | AB22: =+(AB20-$BJ$8)*$B$21+$B$22+$BK$8 -> #DIV/0! | AC22: =+(AC20-$BJ$8)*$B$21+$B$22+$BK$8 -> #DIV/0! | AD22: =+(AD20-$BJ$8)*$B$21+$B$22+$BK$8 -> #DIV/0! | AE22: =+(AE20-$BJ$8)*$B$21+$B$22+$BK$8 -> #DIV/0! | ... BF22: =+(BF20-$BJ$8)*$B$21+$B$22+$BK$8 -> 559.25229
C23: hyd CHIP basis net back cpg | AI23: =+((AI20/264.172)-AI9)*100 -> 11.784497 | AJ23: =+((AJ20/264.172)-AJ9)*100 -> 11.743359 | AK23: =+((AK20/264.172)-AK9)*100 -> 11.725703 | AL23: =+((AL20/264.172)-AL9)*100 -> 11.494122 | AM23: =+((AM20/264.172)-AM9)*100 -> 11.406381 | AN23: =+((AN20/264.172)-AN9)*100 -> 11.035299 | AO23: =+((AO20/264.172)-AO9)*100 -> 10.923571 | AP23: =+((AP20/264.172)-AP9)*100 -> 10.929849 | ... BF23: =+((BF20/264.172)-BF9)*100 -> 23.866216
B24: 1 | C24: Anhydrous FOB- flat hyd | D24: =+D22*$B$21 -> #DIV/0! | E24: =+E22*$B$21 -> #DIV/0! | F24: =+F22*$B$21 -> #DIV/0! | G24: =+G22*$B$21 -> #DIV/0! | H24: =+H22*$B$21+$B$22 -> #DIV/0! | I24: =+I22*$B$21+$B$22 -> #DIV/0! | J24: =+J22*$B$21+$B$22 -> #DIV/0! | K24: =+K22*$B$21+$B$22 -> #DIV/0! | L24: =+L22*$B$21+$B$22+$BK$8 -> #DIV/0! | M24: =+M22*$B$21+$B$22+$BK$8 -> #DIV/0! | N24: =+N22*$B$21+$B$22+$BK$8 -> #DIV/0! | O24: =+O22*$B$21+$B$22+$BK$8 -> #DIV/0! | P24: =+P22*$B$21+$B$22+$BK$8 -> #DIV/0! | Q24: =+Q22*$B$21+$B$22+$BK$8 -> #DIV/0! | R24: =+R22*$B$21+$B$22+$BK$8 -> #DIV/0! | S24: =+S22*$B$21+$B$22+$BK$8 -> #DIV/0! | ... W24: =+W22*$B$21+$B$22+$BK$8 -> #DIV/0! | X24: =+(X22-$BJ$8)*$B$21+$B$22+$BK$8 -> #DIV/0! | Y24: =+(Y22-$BJ$8)*$B$21+$B$22+$BK$8 -> #DIV/0! | Z24: =+(Z22-$BJ$8)*$B$21+$B$22+$BK$8 -> #DIV/0! | AA24: =+(AA22-$BJ$8)*$B$21+$B$22+$BK$8 -> #DIV/0! | AB24: =+(AB22-$BJ$8)*$B$21+$B$22+$BK$8 -> #DIV/0! | AC24: =+(AC22-$BJ$8)*$B$21+$B$22+$BK$8 -> #DIV/0! | AD24: =+(AD22-$BJ$8)*$B$21+$B$22+$BK$8 -> #DIV/0! | AE24: =+(AE22-$BJ$8)*$B$21+$B$22+$BK$8 -> #DIV/0! | ... AK24: =+(AK22-$BJ$8)*$B$21+$B$22+$BK$8 -> 38.812491 | AL24: =+(AL20-$BJ$8)*$B$24+$B$22+$BK$8 -> 32.096475 | AM24: =+(AM20-$BJ$8)*$B$24+$B$22+$BK$8 -> 31.864686 | AN24: =+(AN20-$BJ$8)*$B$24+$B$22+$BK$8 -> 30.884392 | AO24: =+(AO20-$BJ$8)*$B$24+$B$22+$BK$8 -> 30.589238 | AP24: =+(AP20-$BJ$8)*$B$24+$B$22+$BK$8 -> 30.605822 | AQ24: =+(AQ20-$BJ$8)*$B$24+$B$22+$BK$8 -> 31.213731 | AR24: =+(AR20-$BJ$8)*$B$24+$B$22+$BK$8 -> 30.191728 | AS24: =+(AS20-$BJ$8)*$B$24+$B$22+$BK$8 -> 29.561297 | ... BF24: =+(BF20-$BJ$8)*$B$24+$B$22+$BK$8 -> 505.28689
C26: diff anhydrous/hydrous | AM26: =+AM22-AM20 -> 3.6211744 | AN26: =+AN22-AN20 -> 3.513342 | AO26: =+AO22-AO20 -> 3.4808751 | AP26: =+AP22-AP20 -> 3.4826993 | AQ26: =+AQ22-AQ20 -> 3.5495693 | AR26: =+AR22-AR20 -> 3.4371489 | AS26: =+AS22-AS20 -> 3.3678015 | AT26: =+AT22-AT20 -> 3.3311365 | ... AW26: =+AW22-AW20 -> 3.4564799 | AZ26: =AZ22-AZ12 -> 34.77279 | BA26: =BA22-BA12 -> 27.394462 | BB26: =BB22-BB12 -> 26.576511 | BC26: =BC22-BC12 -> 31.793557
BI27: ANH EU | BJ27: =750+BK20 -> 774.6098 | BK27: =+BJ27/264.172 -> 2.9322176
K28: 44562 | L28: 44593 | M28: 44621 | N28: 44652 | O28: 44682 | P28: 44713 | Q28: 44743 | R28: 44774 | S28: 44805 | T28: 44835 | U28: 44866 | V28: 44896 | W28: 44927 | X28: 44958 | Y28: 44986 | Z28: 45017 | AA28: 45047 | AB28: 45078 | AC28: 45108 | AD28: 45139 | AE28: 45170 | AF28: 45200 | AG28: 45231 | AH28: 45261 | AI28: 45292 | AJ28: 45323 | AK28: 45352 | AL28: 45383 | AM28: 45413 | AN28: 45444 | AO28: 45474 | AP28: 45505 | AQ28: 45536 | AR28: 45566 | AS28: 45597 | AT28: 45627 | AU28: 45658 | AV28: 45689 | AW28: 45717 | AX28: 45748 | AY28: 45778 | AZ28: 45809 | BA28: 45839 | BB28: 45870 | BC28: 45901 | BD28: 45931 | BE28: 45962 | BF28: 45992
C29: Grade B ind offer
C30: B3 | K30: =+K16 -> 0 | L30: =+L16 -> 0 | M30: =+M16 -> 0 | N30: =+N16 -> 0 | O30: =+O16 -> 0 | P30: =+P16 -> 0 | Q30: =+Q16 -> 0 | R30: =+R16 -> 0 | ... BF30: =+BF16 -> 2825
B31: 300 | C31: Fobbing | K31: =+$B$31 -> 300 | L31: =+$B$31 -> 300 | M31: =+$B$31 -> 300 | N31: =+$B$31 -> 300 | O31: =+$B$31 -> 300 | P31: =+$B$31 -> 300 | Q31: =+$B$31 -> 300 | R31: =+$B$31 -> 300 | ... BF31: =+$B$31 -> 300
B32: 250 | C32: Premium | K32: =+$B$32 -> 250 | L32: =+$B$32 -> 250 | M32: =+$B$32 -> 250 | N32: =+$B$32 -> 250 | O32: =+$B$32 -> 250 | P32: =+$B$32 -> 250 | Q32: =+$B$32 -> 250 | R32: =+$B$32 -> 250 | ... BF32: =+$B$32 -> 250
B33: =+BJ7 -> 64.576635 | C33: Cbios | L33: =+$B$33 -> 64.576635 | M33: =+$B$33 -> 64.576635 | N33: =+$B$33 -> 64.576635 | O33: =+$B$33 -> 64.576635 | P33: =+$B$33 -> 64.576635 | Q33: =+$B$33 -> 64.576635 | R33: =+$B$33 -> 64.576635 | S33: =+$B$33 -> 64.576635 | ... BF33: =+$B$33 -> 64.576635
C34: FOB Sts R$/cbm | K34: =SUM(K30:K32) -> 550 | L34: =SUM(L30:L33) -> 614.57663 | M34: =SUM(M30:M33) -> 614.57663 | N34: =SUM(N30:N33) -> 614.57663 | O34: =SUM(O30:O33) -> 614.57663 | P34: =SUM(P30:P33) -> 614.57663 | Q34: =SUM(Q30:Q33) -> 614.57663 | R34: =SUM(R30:R33) -> 614.57663 | S34: =SUM(S30:S33) -> 614.57663 | ... BF34: =SUM(BF30:BF33) -> 3439.5766
C36: FOB Sts usd/cbm | K36: =+K34/K17 -> #DIV/0! | L36: =+L34/L17 -> #DIV/0! | M36: =+M34/M17 -> #DIV/0! | N36: =+N34/N17 -> #DIV/0! | O36: =+O34/O17 -> #DIV/0! | P36: =+P34/P17 -> #DIV/0! | Q36: =+Q34/Q17 -> #DIV/0! | R36: =+R34/R17 -> #DIV/0! | ... BF36: =+BF34/BF17 -> 578.88075 | BH36: =AVERAGE(Q36:S36) -> #DIV/0! | BI36: =+BH36/264.172 -> #DIV/0!
C37: FOB Sts usd/gal | K37: =+K36/$B$2 -> #DIV/0! | L37: =+L36/$B$2 -> #DIV/0! | M37: =+M36/$B$2 -> #DIV/0! | N37: =+N36/$B$2 -> #DIV/0! | O37: =+O36/$B$2 -> #DIV/0! | P37: =+P36/$B$2 -> #DIV/0! | Q37: =+Q36/$B$2 -> #DIV/0! | R37: =+R36/$B$2 -> #DIV/0! | ... BF37: =+BF36/$B$2 -> 2.1913024
C38: CHIP | K38: =+K9 -> 0 | L38: =+L9 -> 0 | M38: =+M9 -> 0 | N38: =+N9 -> 0 | O38: =+O9 -> 0 | P38: =+P9 -> 0 | Q38: =+Q9 -> 0 | R38: =+R9 -> 0 | ... BF38: =+BF9 -> 1.6675
C39: grade b basis usg | K39: =+K37-K38 -> #DIV/0! | L39: =+L37-L38 -> #DIV/0! | M39: =+M37-M38 -> #DIV/0! | N39: =+N37-N38 -> #DIV/0! | O39: =+O37-O38 -> #DIV/0! | P39: =+P37-P38 -> #DIV/0! | Q39: =+Q37-Q38 -> #DIV/0! | R39: =+R37-R38 -> #DIV/0! | ... BF39: =+BF37-BF38 -> 0.52380244
B41: =+'mkt data'!G18 -> 0.3 | C41: Grade B USA
C42: CHIP | K42: =+K9 -> 0 | L42: =+L9 -> 0 | M42: =+M9 -> 0 | N42: =+N9 -> 0 | O42: =+O9 -> 0 | P42: =+P9 -> 0 | Q42: =+Q9 -> 0 | R42: =+R9 -> 0 | ... BF42: =+BF9 -> 1.6675
C43: FOB USG usd/gal | K43: =+K42+$B$41 -> 0.3 | L43: =+L42+$B$41 -> 0.3 | M43: =+M42+$B$41 -> 0.3 | N43: =+N42+$B$41 -> 0.3 | O43: =+O42+$B$41 -> 0.3 | P43: =+P42+$B$41 -> 0.3 | Q43: =+Q42+$B$41 -> 0.3 | R43: =+R42+$B$41 -> 0.3 | ... BF43: =+BF42+$B$41 -> 1.9675
C44: FOB USG usd/cbm | K44: =+K43*$B$2 -> 79.2516 | L44: =+L43*$B$2 -> 79.2516 | M44: =+M43*$B$2 -> 79.2516 | N44: =+N43*$B$2 -> 79.2516 | O44: =+O43*$B$2 -> 79.2516 | P44: =+P43*$B$2 -> 79.2516 | Q44: =+Q43*$B$2 -> 79.2516 | R44: =+R43*$B$2 -> 79.2516 | ... BF44: =+BF43*$B$2 -> 519.75841
A47: pmt | B47: $/cbm | C47: Anhydrous CIF USGC | L47: 44593 | M47: 44621 | N47: 44652 | O47: 44682 | P47: 44713 | Q47: 44743 | R47: 44774 | S47: 44805 | T47: 44835 | U47: 44866 | V47: 44896 | AB47: pmt | AC47: $/cbm | AD47: 10kcbm = USD 45-48 pmt
A48: 48 | B48: =+A48*$B$3 -> 37.872 | C48: 10kcbm | L48: =+$L$22+B48 -> #DIV/0! | M48: =+$M$22+B48 -> #DIV/0! | N48: =+$N$22+$B$48 -> #DIV/0! | O48: =+$O$22+$B$48 -> #DIV/0! | P48: =+$P$22+$B$48 -> #DIV/0! | Q48: =+$Q$22+$B$48 -> #DIV/0! | R48: =+$R$22+$B$48 -> #DIV/0! | S48: =+$S$22+$B$48 -> #DIV/0! | T48: =+$T$22+$B$48 -> #DIV/0! | U48: =+$U$22+$B$48 -> #DIV/0! | V48: =+$V$22+$B$48 -> #DIV/0! | AB48: 48 | AC48: =+AB48*$B$3 -> 37.872 | AD48: 20kcbm = USD 33-35 pmt
A49: 35 | B49: =+A49*$B$3 -> 27.615 | C49: 20kcbm | L49: =+$L$22+B49 -> #DIV/0! | M49: =+$M$22+B49 -> #DIV/0! | N49: =+$N$22+$B$49 -> #DIV/0! | O49: =+$O$22+$B$49 -> #DIV/0! | P49: =+$P$22+$B$49 -> #DIV/0! | Q49: =+$Q$22+$B$49 -> #DIV/0! | R49: =+$R$22+$B$49 -> #DIV/0! | S49: =+$S$22+$B$49 -> #DIV/0! | T49: =+$T$22+$B$49 -> #DIV/0! | U49: =+$U$22+$B$49 -> #DIV/0! | V49: =+$V$22+$B$49 -> #DIV/0! | AB49: 35 | AC49: =+AB49*$B$3 -> 27.615 | AD49: 40kcbm = USD 25-27 pmt (right now looking like low 30s pmt) *MR market fluctuates more
A50: 27 | B50: =+A50*$B$3 -> 21.303 | C50: 40kcbm | L50: =+$L$22+B50 -> #DIV/0! | M50: =+$M$22+B50 -> #DIV/0! | N50: =+$N$22+$B$50 -> #DIV/0! | O50: =+$O$22+$B$50 -> #DIV/0! | P50: =+$P$22+$B$50 -> #DIV/0! | Q50: =+$Q$22+$B$50 -> #DIV/0! | R50: =+$R$22+$B$50 -> #DIV/0! | S50: =+$S$22+$B$50 -> #DIV/0! | T50: =+$T$22+$B$50 -> #DIV/0! | U50: =+$U$22+$B$50 -> #DIV/0! | V50: =+$V$22+$B$50 -> #DIV/0! | AB50: 27 | AC50: =+AB50*$B$3 -> 21.303

Sheet EU
B1: 264.172
B2: 0.789 | BA2: Cbios | BB2: =+'FOB origin'!BK8 -> 14.692391 | BC2: usd/cbm
C3: usd/cbm | AV3: FREIGHT | AX3: pmt | BA3: Export + BonSucro premium | BB3: 0 | BC3: usd/cbm
B4: USA | C4: =+AX4*B2 -> 35.505 | AV4: ST ROSE | AX4: 45 | BA4: Premiun EN Grade USA | BB4: =+'mkt data'!G14 -> 0.22 | BC4: usd/gal
B5: BRZ | C5: =+AX5*B2 -> 43.395 | AV5: SANTOS | AX5: 55 | BA5: T2 CIF discount | BB5: 0 | BC5: eur/cbm
C6: 20000 | AX6: cbm | BA6: EU import duty (den) | BB6: 102 | BC6: eur/cbm
BA7: EU import duty (und) | BB7: 192 | BC7: eur/cbm
C10: CHIP | D10: =+'settlement day'!I9 -> 0 | E10: =+'settlement day'!J9 -> 0 | F10: =+'settlement day'!K9 -> 0 | G10: =+'settlement day'!L9 -> 0 | H10: =+'settlement day'!M9 -> 0 | I10: =+'settlement day'!N9 -> 0 | J10: =+'settlement day'!O9 -> 0 | K10: =+'settlement day'!P9 -> 0 | ... BE10: =+'settlement day'!BJ9 -> 1.6675
D11: JUL | E11: AUG | F11: SEP | G11: OCT | H11: NOV | I11: DEC | J11: JAN | K11: FEB | L11: MAR | M11: APR | N11: MAY | O11: JUN | P11: JUL | Q11: AUG | R11: SEP | S11: OCT | T11: NOV | U11: DEC | V11: JAN | W11: FEB | X11: MAR | Y11: APR | Z11: MAY | AA11: JUN | AB11: JUL | AC11: AUG | AD11: SEP | AE11: OCT | AF11: NOV | AG11: DEC | AH11: JAN | AI11: FEB | AJ11: MAR | AK11: APR | AL11: MAY | AM11: JUN | AN11: JUL | AO11: AUG | AP11: SEP | AQ11: OCT | AR11: NOV | AS11: DEC | AT11: JAN | AU11: FEB | AV11: MAR | AW11: APR | AX11: MAY | AY11: JUN | AZ11: JUL | BA11: AUG | BB11: SEP | BC11: OCT | BD11: NOV | BE11: DEC
C12: T2 eur/cbm | D12: =+'settlement day'!I5 -> 0 | E12: =+'settlement day'!J5 -> 0 | F12: =+'settlement day'!K5 -> 0 | G12: =+'settlement day'!L5 -> 0 | H12: =+'settlement day'!M5 -> 0 | I12: =+'settlement day'!N5 -> 0 | J12: =+'settlement day'!O5 -> 0 | K12: =+'settlement day'!P5 -> 0 | ... BE12: =+'settlement day'!BJ5 -> 607.333
C13: T1 eur/cbm - ind bid | D13: =+D12-$BB$6-$BB$5 -> -102 | E13: =+E12-$BB$6-$BB$5 -> -102 | F13: =+F12-$BB$6-$BB$5 -> -102 | G13: =+G12-$BB$6-$BB$5 -> -102 | H13: =+H12-$BB$6-$BB$5 -> -102 | I13: =+I12-$BB$6-$BB$5 -> -102 | J13: =+J12-$BB$6-$BB$5 -> -102 | K13: =+K12-$BB$6-$BB$5 -> -102 | ... BE13: =+BE12-$BB$6-$BB$5 -> 505.333
C14: eur/usd | D14: =+'settlement day'!I29 -> 0 | E14: =+F14 -> 0 | F14: =+'settlement day'!K29 -> 0 | G14: =+I14 -> 0 | H14: =+I14 -> 0 | I14: =+'settlement day'!O29 -> 0 | J14: =+I14 -> 0 | K14: =+L14 -> 0 | L14: =+'settlement day'!Q29 -> 0 | M14: =+'settlement day'!R29 -> 0 | N14: =+'settlement day'!S29 -> 0 | O14: =+'settlement day'!T29 -> 0 | P14: =+'settlement day'!U29 -> 0 | Q14: =+R14 -> 0 | R14: =+'settlement day'!W29 -> 0 | S14: =+'settlement day'!W29 -> 0 | T14: =+'settlement day'!W29 -> 0 | U14: =+'settlement day'!Z29 -> 0 | V14: =+'settlement day'!AA29 -> 0 | W14: =+'settlement day'!AB29 -> 0 | X14: =+'settlement day'!AC29 -> 0 | Y14: =+'settlement day'!AD29 -> 0 | Z14: =+'settlement day'!AE29 -> 0 | AA14: =+'settlement day'!AF29 -> 0 | AB14: =+'settlement day'!AG29 -> 0 | ... BE14: =+'settlement day'!BJ29 -> 1.13805
C15: T1 usd/cbm - ind bid | D15: =+D14*D13 -> 0 | E15: =+D14*E13 -> 0 | F15: =+F14*F13 -> 0 | G15: =+F14*G13 -> 0 | H15: =+F14*H13 -> 0 | I15: =+I14*I13 -> 0 | J15: =+J14*J13 -> 0 | K15: =+K14*K13 -> 0 | L15: =+L14*L13 -> 0 | M15: =+M14*M13 -> 0 | N15: =+N14*N13 -> 0 | O15: =+O14*O13 -> 0 | P15: =+P14*P13 -> 0 | ... BE15: =+BE14*BE13 -> 575.09422
C18: CIF ARA - shipment from origin
C19: eur/usd | D19: =+'settlement day'!I34 -> 0 | E19: =+F19 -> 0 | F19: =+'settlement day'!K34 -> 0 | G19: =+I19 -> 0 | H19: =+I19 -> 0 | I19: =+'settlement day'!O34 -> 0 | J19: =+I19 -> 0 | K19: =+L19 -> 0 | L19: =+'settlement day'!Q34 -> 0 | M19: =+'settlement day'!R34 -> 0 | N19: =+'settlement day'!S34 -> 0 | O19: =+'settlement day'!T34 -> 0 | P19: =+'settlement day'!U34 -> 0 | Q19: =+R19 -> 0 | R19: =+'settlement day'!W34 -> 0 | S19: =+'settlement day'!W34 -> 0 | T19: =+T14 -> 0 | U19: =+U14 -> 0 | V19: =+V14 -> 0 | W19: =+W14 -> 0 | X19: =+X14 -> 0 | Y19: =+Y14 -> 0 | Z19: =+Z14 -> 0 | AA19: =+AA14 -> 0 | ... BE19: =+BE14 -> 1.13805
D20: JUL | E20: AUG | F20: SEP | G20: OCT | H20: NOV | I20: DEC | J20: JAN | K20: FEB | L20: MAR | M20: APR | N20: MAY | O20: JUN | P20: JUL | Q20: AUG | R20: SEP | S20: OCT | T20: NOV | U20: DEC | V20: JAN | W20: FEB | X20: MAR | Y20: APR | Z20: MAY | AA20: JUN | AB20: JUL | AC20: AUG | AD20: SEP | AE20: OCT | AF20: NOV | AG20: DEC | AH20: JAN'24 | AI20: FEB'24 | AJ20: MAR'24 | AK20: APR'24 | AL20: 45413 | AM20: 45444 | AN20: 45474 | AO20: 45505 | AP20: 45536 | AQ20: 45566 | AR20: 45597 | AS20: 45627 | AT20: 45658 | AU20: 45689 | AV20: 45717 | AW20: 45748 | AX20: 45778 | AY20: 45809 | AZ20: 45839 | BA20: 45870 | BB20: 45901 | BC20: 45931 | BD20: 45962 | BE20: 45992
C21: T2 eur/cbm flat | D21: =+D12-$BB$5 -> 0 | E21: =+E12-$BB$5 -> 0 | F21: =+F12-$BB$5 -> 0 | G21: =+G12-$BB$5 -> 0 | H21: =+H12-$BB$5 -> 0 | I21: =+I12-$BB$5 -> 0 | J21: =+J12-$BB$5-$BD$5 -> 0 | K21: =+K12-$BB$5-$BD$5 -> 0 | L21: =+L12-$BB$5-$BD$5 -> 0 | M21: =+M12-$BB$5-$BD$5 -> 0 | N21: =+N12-$BB$5-$BD$5 -> 0 | O21: =+O12-$BB$5-$BD$5 -> 0 | P21: =+P12-$BB$5-$BD$5 -> 0 | Q21: =+Q12-$BB$5-$BD$5 -> 0 | ... BE21: =+BE12-$BB$5-$BD$5 -> 607.333
C22: D-1 | H22: =+'settlement day'!M7 -> 0 | I22: =+'settlement day'!N7 -> 0 | J22: =+'settlement day'!O7 -> 0 | K22: =+'settlement day'!P7 -> 0 | L22: =+'settlement day'!Q7 -> 0 | M22: =+'settlement day'!R7 -> 0 | N22: =+'settlement day'!S7 -> 0 | O22: =+'settlement day'!T7 -> 0 | ... BE22: =+'settlement day'!BJ7 -> 6.666
C23: BRZ Origin
C24: Anhydrous BS FOB usd/cbm | D24: =+'FOB origin'!E22+$BB$3 -> #DIV/0! | E24: =+'FOB origin'!F22+$BB$3 -> #DIV/0! | F24: =+'FOB origin'!G22+$BB$3 -> #DIV/0! | G24: =+'FOB origin'!H22+$BB$3 -> #DIV/0! | H24: =+'FOB origin'!I22+$BB$3 -> #DIV/0! | I24: =+'FOB origin'!J22+$BB$3 -> #DIV/0! | J24: =+'FOB origin'!K22+$BB$3 -> #DIV/0! | K24: =+'FOB origin'!L22+$BB$3 -> #DIV/0! | ... BE24: =+'FOB origin'!BF22+$BB$3 -> 559.25229
C25: CIF ARA - T1 usd/cbm | D25: =+D24+$C$5 -> #DIV/0! | E25: =+E24+$C$5 -> #DIV/0! | F25: =+F24+$C$5 -> #DIV/0! | G25: =+G24+$C$5 -> #DIV/0! | H25: =+H24+$C$5 -> #DIV/0! | I25: =+I24+$C$5 -> #DIV/0! | J25: =+J24+$C$5 -> #DIV/0! | K25: =+K24+$C$5 -> #DIV/0! | ... BE25: =+BE24+$C$5 -> 602.64729
C26: CIF ARA eur/cbm T2 DEN. | D26: =+(D25/D14)+$BB$6 -> #DIV/0! | E26: =+(E25/E14)+$BB$6 -> #DIV/0! | F26: =+(F25/F14)+$BB$6 -> #DIV/0! | G26: =+(G25/G14)+$BB$6 -> #DIV/0! | H26: =+(H25/H14)+$BB$6 -> #DIV/0! | I26: =+(I25/I14)+$BB$6 -> #DIV/0! | J26: =+(J25/J14)+$BB$6 -> #DIV/0! | K26: =+(K25/K14)+$BB$6 -> #DIV/0! | ... BE26: =+(BE25/BE14)+$BB$6 -> 631.54377
C27: BRZ DEN Arb M0 vs T2 M+1 | T27: =+U21-T26 -> #DIV/0! | U27: =+V21-U26 -> #DIV/0! | V27: =+W21-V26 -> #DIV/0! | W27: =+X21-W26 -> #DIV/0! | X27: =+Y21-X26 -> #DIV/0! | Y27: =+Z21-Y26 -> #DIV/0! | Z27: =+AA21-Z26 -> #DIV/0! | AA27: =+AB21-AA26 -> #DIV/0! | ... BD27: =+BE21-BD26 -> -24.612029 | BE27: =+BE21-BE26 -> -24.210769
C28: **CIF ARA eur/cbm T2 DEN. | D28: =+(D26/D15)+$BB$6 -> #DIV/0! | E28: =+(E26/E15)+$BB$6 -> #DIV/0! | F28: =+(F26/F15)+$BB$6 -> #DIV/0! | G28: =+(G26/G15)+$BB$6 -> #DIV/0! | H28: =+(H26/H15)+$BB$6 -> #DIV/0! | I28: =+(I26/I15)+$BB$6 -> #DIV/0! | J28: =+(J26/J15)+$BB$6 -> #DIV/0! | K28: =+(K26/K15)+$BB$6 -> #DIV/0! | ... AJ28: =+(AJ26/AJ15)+$BB$6 -> 100.42002 | AK28: =((('FOB origin'!AL24+EU!$C$5)/AK14)+$BB$6) -> 172.43429 | AL28: =((('FOB origin'!AM24+EU!$C$5)/AL14)+$BB$6) -> 171.35098 | AM28: =((('FOB origin'!AN24+EU!$C$5)/AM14)+$BB$6) -> 171.38757 | AN28: =((('FOB origin'!AO24+EU!$C$5)/AN14)+$BB$6) -> 170.32678 | AO28: =((('FOB origin'!AP24+EU!$C$5)/AO14)+$BB$6) -> 169.0601 | AP28: =((('FOB origin'!AQ24+EU!$C$5)/AP14)+$BB$6) -> 168.63874 | AQ28: =((('FOB origin'!AR24+EU!$C$5)/AQ14)+$BB$6) -> 169.62243 | AR28: =((('FOB origin'!AS24+EU!$C$5)/AR14)+$BB$6) -> 171.07432 | ... BE28: =((('FOB origin'!BF24+EU!$C$5)/BE14)+$BB$6) -> 584.12459
C29: **BRZ DEN Arb M0 vs T2 M+1 | AK29: =+AL21-AK28 -> -172.43429 | AL29: =+AM21-AL28 -> -171.35098 | AM29: =+AN21-AM28 -> -171.38757 | AN29: =+AO21-AN28 -> -170.32678 | AO29: =+AP21-AO28 -> -169.0601 | AP29: =+AQ21-AP28 -> -168.63874 | AQ29: =+AR21-AQ28 -> -169.62243 | AR29: =+AS21-AR28 -> -171.07432 | ... AU29: =+AV21-AU28 -> -172.57607 | AV29: =+AV21-AV28 -> -170.20385 | AW29: =+AW21-AW28 -> -167.05574 | AX29: =+AX21-AX28 -> 0.13971451 | AY29: =+AY21-AY28 -> 21.626608 | AZ29: =+AZ21-AZ28 -> 35.58271 | BA29: =+BA21-BA28 -> 46.219526 | BB29: =+BB21-BB28 -> 42.466977 | BC29: =+BC21-BC28 -> 33.871656 | ... BE29: =+BE21-BE28 -> 23.208409
C30: US Origin
C31: FOB IMTT usd/cbm (M0) | D31: =+(D10+$BB$4)*$B$1 -> 58.11784 | E31: =+(E10+$BB$4)*$B$1 -> 58.11784 | F31: =+(F10+$BB$4)*$B$1 -> 58.11784 | G31: =+(G10+$BB$4)*$B$1 -> 58.11784 | H31: =+(H10+$BB$4)*$B$1 -> 58.11784 | I31: =+(I10+$BB$4)*$B$1 -> 58.11784 | J31: =+(J10+$BB$4)*$B$1 -> 58.11784 | K31: =+(K10+$BB$4)*$B$1 -> 58.11784 | ... BE31: =+(BE10+$BB$4)*$B$1 -> 498.62465
C32: CIF ARA - T1 usd/cbm | D32: =+D31+$C$4 -> 93.62284 | E32: =+E31+$C$4 -> 93.62284 | F32: =+F31+$C$4 -> 93.62284 | G32: =+G31+$C$4 -> 93.62284 | H32: =+H31+$C$4 -> 93.62284 | I32: =+I31+$C$4 -> 93.62284 | J32: =+J31+$C$4 -> 93.62284 | K32: =+K31+$C$4 -> 93.62284 | ... BE32: =+BE31+$C$4 -> 534.12965
C33: CIF ARA eur/cbm T2 DEN. | D33: =+(D32/D14)+$BB$6 -> #DIV/0! | E33: =+(E32/E14)+$BB$6 -> #DIV/0! | F33: =+(F32/F14)+$BB$6 -> #DIV/0! | G33: =+(G32/G14)+$BB$6 -> #DIV/0! | H33: =+(H32/H14)+$BB$6 -> #DIV/0! | I33: =+(I32/I14)+$BB$6 -> #DIV/0! | J33: =+(J32/J14)+$BB$6 -> #DIV/0! | K33: =+(K32/K14)+$BB$6 -> #DIV/0! | ... BE33: =+(BE32/BE14)+$BB$6 -> 571.3376
C34: USA DEN Arb M0 vs T2 M+1 | T34: =+U26-T33 -> #DIV/0! | U34: =+V21-U33 -> #DIV/0! | V34: =+W21-V33 -> #DIV/0! | W34: =+X21-W33 -> #DIV/0! | X34: =+Y21-X33 -> #DIV/0! | Y34: =+Z21-Y33 -> #DIV/0! | Z34: =+AA21-Z33 -> #DIV/0! | AA34: =+AB21-AA33 -> #DIV/0! | AB34: =+AC21-AB33 -> #DIV/0! | ... BD34: =+BE21-BD33 -> 30.192233 | BE34: =+BE21-BE33 -> 35.995405
B36: 1.25 | AV36: =AV32*$B$36 -> 117.02855 | AW36: =AW32*$B$36 -> 117.02855 | AX36: =AX32*$B$36 -> 688.3005 | AY36: =AY32*$B$36 -> 700.68356 | AZ36: =AZ32*$B$36 -> 705.63679 | BA36: =BA32*$B$36 -> 704.81125 | BB36: =BB32*$B$36 -> 699.85802 | BC36: =BC32*$B$36 -> 687.47496 | ... BE36: =BE32*$B$36 -> 667.66206
C37: USD vs BRZ | AV37: =AV36-AV25 -> 41.541828 | AW37: =AW36-AW25 -> 41.291606 | AX37: =AX36-AX25 -> 71.821192 | AY37: =AY36-AY25 -> 97.473923 | AZ37: =AZ36-AZ25 -> 105.8429 | BA37: =BA36-BA25 -> 106.49574 | BB37: =BB36-BB25 -> 100.28805 | BC37: =BC36-BC25 -> 82.717123 | ... BE37: =BE36-BE25 -> 65.014777
AV38: =AV37/264.172 -> 0.15725296 | AW38: =AW37/264.172 -> 0.15630576 | AX38: =AX37/264.172 -> 0.27187284 | AY38: =AY37/264.172 -> 0.36897901 | AZ38: =AZ37/264.172 -> 0.40065902 | BA38: =BA37/264.172 -> 0.40313031 | BB38: =BB37/264.172 -> 0.37963163 | BC38: =BC37/264.172 -> 0.31311843 | ... BE38: =BE37/264.172 -> 0.24610775
C39: ** Anhydrous flat Hydrous
C40: Brazil premium over USA | AI40: =AI26-AI33 -> -14.304524 | AJ40: =AJ26-AJ33 -> -14.372261 | AK40: =AK26-AK33 -> -15.130543 | AL40: =AL26-AL33 -> -15.180797 | AM40: =AM26-AM33 -> -16.405724 | AN40: =AN26-AN33 -> -16.521933 | AO40: =AO26-AO33 -> -16.195325 | AP40: =AP26-AP33 -> -15.359737 | ... BE40: =BE26-BE33 -> 60.206174
C43: T2 M+1 eur/cbm disc | K43: =+L10 -> 0 | L43: =+M10 -> 0 | M43: =+N10 -> 0 | N43: =+O10 -> 0 | O43: =+P10 -> 0 | P43: =+Q10 -> 0 | Q43: =+R21+$C$44 -> -130 | R43: =+S21+$C$44 -> -130 | S43: =+T21+$C$44 -> -130 | T43: =+U21+$C$44 -> -130 | U43: =+V21+$C$44 -> -130 | V43: =+W21+$C$44 -> -130 | W43: =+X21+$C$44 -> -130 | X43: =+Y21+$C$44 -> -130 | ... BE43: =+BF21+$C$44 -> -130
C44: -130
C45: ARB UISA/EU Denatured | K45: =+K43-K42 -> 0 | L45: =+L43-L42 -> 0 | M45: =+M43-M42 -> 0 | N45: =+N43-N42 -> 0 | O45: =+O43-O42 -> 0 | P45: =+P43-P42 -> 0 | Q45: =+Q43-Q33 -> #DIV/0! | R45: =+R43-R33 -> #DIV/0! | S45: =+S43-S33 -> #DIV/0! | T45: =+T43-T33 -> #DIV/0! | U45: =+U43-U33 -> #DIV/0! | V45: =+V43-V33 -> #DIV/0! | W45: =+W43-W33 -> #DIV/0! | X45: =+X43-X33 -> #DIV/0! | ... BE45: =+BE43-BE33 -> -701.3376
C48: ARB BRZ/EU, Bon Sucro | K48: FEB | L48: MAR | M48: APR | N48: MAY | O48: JUN | P48: JUL | Q48: AUG | R48: SEP | S48: OCT | T48: NOV | U48: DEC | V48: JAN | W48: FEB | X48: MAR | Y48: APR | Z48: MAY | AA48: JUN | AB48: JUL | AC48: AUG | AD48: SEP | AE48: OCT | AF48: NOV | AG48: DEC | AH48: JAN'24 | AI48: FEB'24 | AJ48: MAR'24 | AK48: APR'24 | AL48: 45413 | AM48: 45444 | AN48: 45474 | AO48: 45505 | AP48: 45536 | AQ48: 45566 | AR48: 45597 | AS48: 45627 | AT48: 45658 | AU48: 45689 | AV48: 45717 | AW48: 45748 | AX48: 45778 | AY48: 45809 | AZ48: 45839 | BA48: 45870 | BB48: 45901 | BC48: 45931 | BD48: 45962 | BE48: 45992
C49: FOB Brazil, usd/cbm | K49: =+K24 -> #DIV/0! | L49: =+L24 -> #DIV/0! | M49: =+M24 -> #DIV/0! | N49: =+N24 -> #DIV/0! | O49: =+O24 -> #DIV/0! | P49: =+P24 -> #DIV/0! | Q49: =+Q24 -> #DIV/0! | R49: =+R24 -> #DIV/0! | ... BE49: =+BE24 -> 559.25229
C51: CIF ARA "T2" UND eur/cbm | K51: =+((K49+$C$5)/K14)+$BB$7 -> #DIV/0! | L51: =+((L49+$C$5)/L14)+$BB$7 -> #DIV/0! | M51: =+((M49+$C$5)/M14)+$BB$7 -> #DIV/0! | N51: =+((N49+$C$5)/N14)+$BB$7 -> #DIV/0! | O51: =+((O49+$C$5)/O14)+$BB$7 -> #DIV/0! | P51: =+((P49+$C$5)/P14)+$BB$7 -> #DIV/0! | Q51: =+((Q49+$C$5)/Q14)+$BB$7 -> #DIV/0! | R51: =+((R49+$C$5)/R14)+$BB$7 -> #DIV/0! | ... BE51: =+((BE49+$C$5)/BE14)+$BB$7 -> 721.54377
C52: T2 M+1 eur/cbm flat | K52: =+L21 -> 0 | L52: =+M21 -> 0 | M52: =+N21 -> 0 | N52: =+O21 -> 0 | O52: =+P21 -> 0 | P52: =+Q21 -> 0 | Q52: =+R21 -> 0 | R52: =+S21 -> 0 | ... BD52: =+BE21 -> 607.333 | BE52: =+BE21 -> 607.333
C54: ARB BRZ/EU Undenatured | K54: =+K52-K51 -> #DIV/0! | L54: =+L52-L51 -> #DIV/0! | M54: =+M52-M51 -> #DIV/0! | N54: =+N52-N51 -> #DIV/0! | O54: =+O52-O51 -> #DIV/0! | P54: =+P52-P51 -> #DIV/0! | Q54: =+Q52-Q51 -> #DIV/0! | R54: =+R52-R51 -> #DIV/0! | ... BE54: =+BE52-BE51 -> -114.21077
C57: T2 M+1 eur/cbm disc | K57: =+L25 -> #DIV/0! | L57: =+M25 -> #DIV/0! | M57: =+N25 -> #DIV/0! | N57: =+O25 -> #DIV/0! | O57: =+P25 -> #DIV/0! | P57: =+Q25 -> #DIV/0! | Q57: =+R21+$C$58 -> -130 | R57: =+S21+$C$58 -> -130 | S57: =+T21+$C$58 -> -130 | T57: =+U21+$C$58 -> -130 | U57: =+V21+$C$58 -> -130 | V57: =+W21+$C$58 -> -130 | W57: =+X21+$C$58 -> -130 | X57: =+Y21+$C$58 -> -130 | ... BE57: =+BF21+$C$58 -> -130
C58: =+C44 -> -130
C59: ARB BRZ/EU Undenatured | K59: =+K57-K56 -> #DIV/0! | L59: =+L57-L56 -> #DIV/0! | M59: =+M57-M56 -> #DIV/0! | N59: =+N57-N56 -> #DIV/0! | O59: =+O57-O56 -> #DIV/0! | P59: =+P57-P56 -> #DIV/0! | Q59: =+Q57-Q51 -> #DIV/0! | R59: =+R57-R51 -> #DIV/0! | S59: =+S57-S51 -> #DIV/0! | T59: =+T57-T51 -> #DIV/0! | U59: =+U57-U51 -> #DIV/0! | V59: =+V57-V51 -> #DIV/0! | W59: =+W57-W51 -> #DIV/0! | X59: =+X57-X51 -> #DIV/0! | ... BE59: =+BE57-BE51 -> -851.54377
C61: T2 M+1 eur/cbm disc | K61: =+L32 -> 93.62284 | L61: =+M32 -> 93.62284 | M61: =+N32 -> 93.62284 | N61: =+O32 -> 93.62284 | O61: =+P32 -> 93.62284 | P61: =+Q32 -> 93.62284 | Q61: =+R21+$C$58 -> -130 | R61: =+S21+$C$58 -> -130 | S61: =+T21+$C$58 -> -130 | T61: =+U21+$C$58 -> -130 | U61: =+V21+$C$58 -> -130 | V61: =+W21+$C$58 -> -130 | W61: =+X21+$C$58 -> -130 | X61: =+Y21+$C$58 -> -130 | ... BE61: =+BF21+$C$58 -> -130
C62: =+C44 -> -130
C63: ARB BRZ/EU Denatured | K63: =+K61-K60 -> 93.62284 | L63: =+L61-L60 -> 93.62284 | M63: =+M61-M60 -> 93.62284 | N63: =+N61-N60 -> 93.62284 | O63: =+O61-O60 -> 93.62284 | P63: =+P61-P60 -> 93.62284 | Q63: =+Q61-(Q51-$BB$7+$BB$6) -> #DIV/0! | R63: =+R61-(R51-$BB$7+$BB$6) -> #DIV/0! | S63: =+S61-(S51-$BB$7+$BB$6) -> #DIV/0! | T63: =+T61-(T51-$BB$7+$BB$6) -> #DIV/0! | U63: =+U61-(U51-$BB$7+$BB$6) -> #DIV/0! | V63: =+V61-(V51-$BB$7+$BB$6) -> #DIV/0! | W63: =+W61-(W51-$BB$7+$BB$6) -> #DIV/0! | X63: =+X61-(X51-$BB$7+$BB$6) -> #DIV/0! | ... BE63: =+BE61-(BE51-$BB$7+$BB$6) -> -761.54377
N69: eur/usd | Q69: =+J14 -> 0 | T69: =+Q69 -> 0 | U69: eur/usd | AI69: =+M14 -> 0 | AJ69: eur/usd
C70: Paraguay | Q70: Brasil
C71: =+E21 -> 0 | H71: AUG | I71: T2 | K71: eur/cbm | M71: JUL | N71: T2 | Q71: =+R21 -> 0 | R71: eur/cbm | T71: 710 | AI71: 820 | AJ71: 1H MAR | AK71: >>> ind offer from Green/Brazil
C72: -150 | Q72: -102 | T72: =+-Q75 -> 47.34 | U72: freight | AI72: =+-Q75 -> 47.34 | AJ72: freight
C73: =+C71+C72 -> -150 | Q73: =+Q71+Q72 -> -102 | T73: =+T71+T72 -> 757.34 | U73: CIF T1 | AI73: =+AI71+AI72 -> 867.34 | AJ73: CIF T1
C74: =+C73*D14 -> 0 | I74: T1 CIF | K74: usd/cbm | N74: T1 CIF | Q74: =+Q73*Q69 -> 0 | R74: usd/cbm
C75: =-(70*0.789) -> -55.23 | M75: 60pmt | N75: freight | Q75: =-(60*0.789) -> -47.34 | T75: =+T73/Q69 -> #DIV/0! | U75: CIF T2 | AI75: =+AI73/AI69 -> #DIV/0! | AJ75: CIF T2
C76: =+C74+C75 -> -55.23 | H76: JUL | I76: FOB ARG | K76: usd/cbm | M76: JUN | N76: FOB STS | Q76: =+Q74+Q75 -> -47.34 | R76: usd/cbm | T76: 102 | AI76: 102
C77: =-(0.05*264.172) -> -13.2086 | Q77: =-(0.03*264.172) -> -7.92516 | T77: =+T75+T76 -> #DIV/0! | U77: AUG arrival | AI77: =+AI75+AI76 -> #DIV/0! | AJ77: 2H MAR arrival - CIF T2
C78: =+C76+C77 -> -68.4386 | I78: MEG ind bid | N78: MEG ind bid | Q78: =+Q76+Q77 -> -55.26516 | R78: usd/cbm | T78: =+R21 -> 0 | U78: SEP T2
T79: -35 | AI79: =+M21 -> 0 | AJ79: APR T2
T80: =+T78+T79 -> -35 | AI80: =+AI79-AI77 -> #DIV/0! | AJ80: spread T1/T2 CIF vs T2
N81: 15000 | Q81: =+N81*-Q77 -> 118877.4 | T81: =+T80-T77 -> #DIV/0!
AL85: Sucden
AK86: JUNE load | AL86: 2.3825 | AM86: =+'settlement day'!T9 -> 0 | AN86: settle 28/3
AK87: FOB basis | AL87: 0.365
AK88: cost | AL88: 0.01
AK89: demurrage | AL89: 0.01
AJ90: =SUM(AL87:AL90) -> 0.405 | AK90: margin | AL90: 0.02
AK91: freight | AL91: =+AP91/264.172 -> 0.19883447 | AO91: 65 | AP91: =+AO91*0.8081 -> 52.5265
AK92: CIF Rdam | AL92: =SUM(AL86:AL91) -> 2.9863345 | AM92: usd/gal
AL93: =+AL92*264.172 -> 788.90595 | AM93: usd/cbm
AO94: =+AL95-AL93 -> 1.09405 | AP94: =+AO94/264.172 -> 0.0041414306
AK95: offer CIF | AL95: 790 | AM95: usd/cbm
AK96: =+O14 -> 0 | AL96: =+AL95/AK96 -> #DIV/0! | AM96: eur/cbm
AK97: 0.06 | AL97: 192 | AM97: eur/cbm
AL98: =+AL96+AL97 -> #DIV/0! | AM98: eur/cbm
AK100: ref price PAK FOB | AL100: 900 | AM100: usd/ton
AK101: PAK FOB | AL101: =+AL100*0.8081 -> 727.29 | AM101: usd/cbm
AK102: freight | AL102: =+AN102*0.8081 -> 64.648 | AM102: usd/cbm | AN102: 80
AK103: CIF ARA | AL103: =+AL101+AL102 -> 791.938 | AM103: usd/cbm
AL104: =+AL103/AK96 -> #DIV/0! | AM104: eur/cbm
AK107: replacement vs PAK | AL107: =+AL104-AL98 -> #DIV/0!

Sheet BRAZIL domestic
D2: BRAZILIAN DOMESTIC MARKET
I3: Date | J3: =+'settlement day'!B3 -> 45797
E4: Anhydrous premium over Hydrous | F4: =100%-(+E12/I12) -> 0.12560891 | I4: FX | J4: ='settlement day'!BA30 -> 5.7416
C6: EXPORTS | K6: IMPORTS
E7: BRL/cbm | F7: USD/cbm | H7: CS | I7: BRL/cbm | J7: USD/cbm | L7: NE | M7: BRL/cbm | N7: USD/cbm | O7: =470/0.867 -> 542.09919 | P7: 470 s/ICMS | Q7: 190 | R7: RS | S7: BRL/cbm | T7: USD/cbm
D8: HYDROUS | E8: =+'settlement day'!AY45 -> 3320 | H8: ANHYDROUS | I8: =+'settlement day'!AY44 -> 3320 | L8: ANHYDROUS | M8: =+'PLATTS&OPIS'!I256 -> 3900 | Q8: https://covid19.apple.com/mobility | R8: ANHYDROUS | S8: =+I8+Q7 -> 3510
D9: (-) INSS 2,85% | E9: =+E8*2.85% -> 94.62 | I9: =+I8*2.85% -> 94.62 | M9: 0 | O9: (-) INSS 2,85% | S9: 0
D10: (-) ICMS 12% | E10: =+E8*12% -> 398.4 | I10: 122 | O10: (-) ICMS XX%
B11: 130.9 | D11: (-) PIS/COFINS | E11: 130.9 | I11: 20 | L11: 131 | M11: 0 | O11: (-) PIS/COFINS | S11: 149
E12: =+E8-(E9+E10+E11) -> 2696.08 | I12: =+I8-(I9+I10+I11) -> 3083.38 | J12: =+I12/E12 -> 1.143653 | M12: =+M8-(M9+M10+M11) -> 3900 | S12: =+S8-(S9+S10+S11) -> 3361
C13: 1 | D13: (+) CBIOS | E13: =+'settlement day'!BK34*'BRAZIL domestic'!C13 -> 60.75 | G13: 1.2 | I13: =+'settlement day'!BK34*'BRAZIL domestic'!G13 -> 72.9
D15: (+) Inland freight to port | E15: =+'mkt data'!G5 -> 300 | I15: =+E15 -> 300 | M15: 50 | O15: (+) Inland freight to hub | S15: 0
D16: (+) Terminal port | E16: =+'mkt data'!H8 -> 100 | I16: =+E16 -> 100 | M16: 0 | S16: 0
D18: (=) TOTAL | E18: =+E12+E13+E15+E16 -> 3156.83 | F18: =+E18/$J$4 -> 549.81712 | I18: =+I12+I13+I15+I16 -> 3556.28 | J18: =+I18/$J$4 -> 619.38832 | M18: =+M12+M15+M16 -> 3950 | N18: =+M18/$J$4 -> 687.96154 | S18: =+S12+S15+S16 -> 3361 | T18: =+S18/$J$4 -> 585.3769
D20: (+) Port costs | E20: 10 | F20: =+E20/J4 -> 1.7416748 | J20: =+F20 -> 1.7416748 | M20: 70 | N20: =+M20/$J$4 -> 12.191724 | O20: (+) Port costs | S20: 65 | T20: =+S20/$J$4 -> 11.320886
D21: (+) Inspection | E21: 5 | F21: =+E21/J4 -> 0.8708374 | J21: =+F21 -> 0.8708374 | M21: 15 | N21: =+M21/$J$4 -> 2.6125122 | O21: (+) Inspection | S21: 36 | T21: =+S21/$J$4 -> 6.2700293
D22: (+) EXPORT premium B grade | E22: =+'mkt data'!G4 -> 150 | F22: =+E22/J4 -> 26.125122 | J22: 0 | M22: 25 | N22: =+M22/$J$4 -> 4.354187 | O22: (+) Inland freight to hub | S22: 65 | T22: =+S22/$J$4 -> 11.320886
K23: 44593 | M23: =+N23*J4 -> 5.7416 | N23: 1 | O23: (+) other costs | S23: 10 | T23: =+S23/J4 -> 1.7416748
E24: FOB Santos | F24: =+F18+F20+F21+F22 -> 578.55476 | I24: FOB Santos | J24: =+J18+J20+J21+J22 -> 622.00084 | K24: 765 | M24: =+N24*J4 -> 516.09807 | N24: =+K24*K25 -> 89.8875 | O24: (+) PIS/COFINS on CFR | R24: =(+'settlement day'!M9+0.33+0.03)*264.172 -> 95.10192 | S24: =+T24*J4 -> 64.159369 | T24: =+R24*R25 -> 11.174476
K25: 0.1175 | M25: 100 | N25: =+M25/$J$4 -> 17.416748 | O25: (+) margin | R25: 0.1175 | S25: 100 | T25: =+S25/$J$4 -> 17.416748
M26: =SUM(M20:M25) -> 731.83967
N27: =+N18-(N20+N21+N22+N23+N24+N25) -> 560.49887 | O27: Suape Value with TRQ | T27: =+T18-(T20+T21+T22+T23+T24+T25) -> 526.1322
N28: =+N18-(N20+N21+N22+N23+N24+N25)-N29 -> 560.49887 | O28: Suape Value w/o TRQ | T28: =+T18-(T20+T21+T22+T23+T24+T25)-T29 -> 507.11181
K29: 0 | M29: =+N29*J4 -> 0 | N29: =+K29*K24 -> 0 | O29: Import duty | Q29: 0.2 | S29: =+T29*J4 -> 109.20744 | T29: =+Q29*R24 -> 19.020384
C32: BRAZILIAN DOMESTIC MARKET -- basis B3
E34: Frete | F34: 65 | G34: R$/cbm | H34: 65 | I34: 75 frete 14/6/21
E35: PIS/COFINS | F35: 130.9 | G35: R$/cbm
D36: 30 | E36: ICMS | F36: 0.133 | G36: 0.867
E37: anh/hydrous | F37: 0.14 | G37: 1.14
U39: 264.172
D40: 44621 | E40: 44652 | F40: 44682 | G40: 44713 | H40: 44743 | I40: 44774 | J40: 44805 | K40: 44835 | L40: 44866 | M40: 44896 | N40: 44927 | O40: 44958 | P40: 44986 | S40: 750
C41: B3 | D41: =+'settlement day'!Q13 -> 0 | E41: =+'settlement day'!R13 -> 0 | F41: =+'settlement day'!S13 -> 0 | G41: =+'settlement day'!T13 -> 0 | H41: =+'settlement day'!U13 -> 0 | I41: =+'settlement day'!V13 -> 0 | J41: =+'settlement day'!W13 -> 0 | K41: =+'settlement day'!X13 -> 0 | ... P41: =+'settlement day'!AC13 -> 0 | S41: =+S40/U39 -> 2.8390594
C42: ESALQ P | D42: =+'settlement day'!BI42 -> 2802
D43: =+D41-D42 -> -2802
C45: Ex plant | D45: =+(D41-$F$34+$F$35)/$G$36 -> 76.009227 | E45: =+(E41-$F$34+$F$35)/$G$36 -> 76.009227 | F45: =+(F41-$F$34+$F$35)/$G$36 -> 76.009227 | G45: =+(G41-$F$34+$F$35)/$G$36 -> 76.009227 | H45: =+(H41-$F$34+$F$35)/$G$36 -> 76.009227 | I45: =+(I41-$F$34+$F$35)/$G$36 -> 76.009227 | J45: =+(J41-$F$34+$F$35)/$G$36 -> 76.009227 | K45: =+(K41-$F$34+$F$35)/$G$36 -> 76.009227 | ... P45: =+(P41-$F$34+$F$35)/$G$36 -> 76.009227
C46: net tax | D46: =D41-$F$34 -> -65
C47: Anhydrous ex mill equivalent | D47: =((D41-$F$34)*$G$37)+$F$35 -> 56.8 | E47: =((E41-$F$34)*$G$37)+$F$35 -> 56.8 | F47: =((F41-$F$34)*$G$37)+$F$35 -> 56.8 | G47: =((G41-$F$34)*$G$37)+$F$35 -> 56.8 | H47: =((H41-$F$34)*$G$37)+$F$35 -> 56.8 | I47: =((I41-$F$34)*$G$37)+$F$35 -> 56.8 | J47: =((J41-$F$34)*$G$37)+$F$35 -> 56.8 | K47: =((K41-$F$34)*$G$37)+$F$35 -> 56.8 | ... P47: =((P41-$F$34)*$G$37)+$F$35 -> 56.8
C49: ESALQ RB | D49: =+'settlement day'!$BI$43 -> 0
D50: =+D46-D49 -> -65
D52: =+((D49+$F$35)/$G$36)+H34 -> 215.98039

Sheet ARB BRZ 2022
A1: 0.789 | E1: =+'settlement day'!M30 -> 0
A2: 264.172 | C2: FX | D2: =+'settlement day'!M30 -> 0 | E2: =+'settlement day'!N30 -> 0 | F2: =+'settlement day'!O30 -> 0 | G2: =+'settlement day'!P30 -> 0 | H2: =+'settlement day'!Q30 -> 0 | I2: =+'settlement day'!R30 -> 0 | J2: =+'settlement day'!S30 -> 0 | K2: =+'settlement day'!T30 -> 0 | ... T2: =+'settlement day'!AC30 -> 0
D3: 44501 | E3: 44531 | F3: 44562 | G3: 44593 | H3: 44621 | I3: 44652 | J3: 44682 | K3: 44713 | L3: 44743 | M3: 44774 | N3: 44805 | O3: 44835 | P3: 44866 | Q3: 44896 | R3: 44927 | S3: 44958 | T3: 44986
C4: CHIP | D4: =+'settlement day'!M9 -> 0 | E4: =+'settlement day'!N9 -> 0 | F4: =+'settlement day'!O9 -> 0 | G4: =+'settlement day'!P9 -> 0 | H4: =+'settlement day'!Q9 -> 0 | I4: =+'settlement day'!R9 -> 0 | J4: =+'settlement day'!S9 -> 0 | K4: =+'settlement day'!T9 -> 0 | ... T4: =+'settlement day'!AC9 -> 0
B5: 0.13 | C5: FOB (usd/gal) | D5: =+D4+$B$5 -> 0.13 | E5: =+E4+$B$5 -> 0.13 | F5: =+F4+$B$5 -> 0.13 | G5: =+G4+$B$5 -> 0.13 | H5: =+H4+$B$5 -> 0.13 | I5: =+I4+$B$5 -> 0.13 | J5: =+J4+$B$5 -> 0.13 | K5: =+K4+$B$5 -> 0.13 | ... T5: =+T4+$B$5 -> 0.13
C6: FOB usd/cbm | D6: =+D5*$A$2 -> 34.34236 | E6: =+E5*$A$2 -> 34.34236 | F6: =+F5*$A$2 -> 34.34236 | G6: =+G5*$A$2 -> 34.34236 | H6: =+H5*$A$2 -> 34.34236 | I6: =+I5*$A$2 -> 34.34236 | J6: =+J5*$A$2 -> 34.34236 | K6: =+K5*$A$2 -> 34.34236 | ... T6: =+T5*$A$2 -> 34.34236
B8: 0.02 | C8: cost (usd/cbm) | D8: =+$B$8*$A$2 -> 5.28344 | E8: =+D8 -> 5.28344 | F8: =+E8 -> 5.28344 | G8: =+F8 -> 5.28344 | H8: =+G8 -> 5.28344 | I8: =+H8 -> 5.28344 | J8: =+I8 -> 5.28344 | K8: =+J8 -> 5.28344 | L8: =+K8 -> 5.28344 | ... T8: =+S8 -> 5.28344
A9: 20kcbm | B9: 85 | C9: freight usd/cbm | D9: =+$B$9*$A$1 -> 67.065 | E9: =+D9 -> 67.065 | F9: =+E9 -> 67.065 | G9: =+F9 -> 67.065 | H9: =+G9 -> 67.065 | I9: =+H9 -> 67.065 | J9: =+I9 -> 67.065 | K9: =+J9 -> 67.065 | L9: =+K9 -> 67.065 | ... T9: =+S9 -> 67.065
C10: CIF usd/cbm | D10: =SUM(D6:D9) -> 106.6908 | E10: =SUM(E6:E9) -> 106.6908 | F10: =SUM(F6:F9) -> 106.6908 | G10: =SUM(G6:G9) -> 106.6908 | H10: =SUM(H6:H9) -> 106.6908 | I10: =SUM(I6:I9) -> 106.6908 | J10: =SUM(J6:J9) -> 106.6908 | K10: =SUM(K6:K9) -> 106.6908 | ... T10: =SUM(T6:T9) -> 106.6908
C11: CIF brl/cbm | E11: =+E10*E2 -> 0 | F11: =+F10*F2 -> 0 | G11: =+G10*G2 -> 0 | H11: =+H10*H2 -> 0 | I11: =+I10*I2 -> 0 | J11: =+J10*J2 -> 0 | K11: =+K10*K2 -> 0 | L11: =+L10*L2 -> 0 | ... T11: =+T10*T2 -> 0
B13: 0 | C13: Import duly | D13: =+D10*$B$13 -> 0 | E13: =+E11*$B$13 -> 0 | F13: =+F11*$B$13 -> 0 | G13: =+G11*$B$13 -> 0 | H13: =+H11*$B$13 -> 0 | I13: =+I11*$B$13 -> 0 | J13: =+J11*$B$13 -> 0 | K13: =+K11*$B$13 -> 0 | L13: =+L11*$B$13 -> 0 | ... T13: =+T11*$B$13 -> 0
A14: antes 11.75% | B14: 0 | C14: PIS/COFINS | D14: =+D10*$B$14 -> 0 | E14: =+E11*$B$14 -> 0 | F14: =+F11*$B$14 -> 0 | G14: =+G11*$B$14 -> 0 | H14: =+H11*$B$14 -> 0 | I14: =+I11*$B$14 -> 0 | J14: =+J11*$B$14 -> 0 | K14: =+K11*$B$14 -> 0 | L14: =+L11*$B$14 -> 0 | ... T14: =+T11*$B$14 -> 0
C15: ICMS | D15: 0 | E15: 0 | F15: 0 | G15: 0 | H15: 0 | I15: 0 | J15: 0 | K15: 0 | L15: 0 | M15: 0 | N15: 0 | O15: 0 | P15: 0 | Q15: 0 | R15: 1 | S15: 2 | T15: 3
B16: 0.08 | C16: AFRMM | D16: 0 | E16: 0 | F16: 0 | G16: 0 | H16: =+H9*$B$16 -> 5.3652 | I16: =+I9*$B$16 -> 5.3652 | J16: =+J9*$B$16 -> 5.3652 | K16: =+K9*$B$16 -> 5.3652 | L16: =+L9*$B$16 -> 5.3652 | M16: =+M9*$B$16 -> 5.3652 | N16: =+N9*$B$16 -> 5.3652 | O16: =+O9*$B$16 -> 5.3652 | ... T16: =+T9*$B$16 -> 5.3652
C17: Cargo Cleared usd/cbm | D17: =SUM(D10:D16) -> 106.6908 | E17: =SUM(E11:E16) -> 0 | F17: =SUM(F11:F16) -> 0 | G17: =SUM(G11:G16) -> 0 | H17: =SUM(H11:H16) -> 5.3652 | I17: =SUM(I11:I16) -> 5.3652 | J17: =SUM(J11:J16) -> 5.3652 | K17: =SUM(K11:K16) -> 5.3652 | L17: =SUM(L11:L16) -> 5.3652 | ... T17: =SUM(T11:T16) -> 8.3652
C19: Terminal cost (brl/cbm) | D19: 80 | E19: 80 | F19: 80 | G19: 80 | H19: 80 | I19: 80 | J19: 80 | K19: 80 | L19: 80 | M19: 80 | N19: 80 | O19: 80 | P19: 80 | Q19: 80 | R19: 80 | S19: 80 | T19: 80
C20: Inspection (brl/cbm) | D20: 15 | E20: 15 | F20: 15 | G20: 15 | H20: 15 | I20: 15 | J20: 15 | K20: 15 | L20: 15 | M20: 15 | N20: 15 | O20: 15 | P20: 15 | Q20: 15 | R20: 15 | S20: 15 | T20: 15
C21: Inland freight (brl/cbm) | D21: 25 | E21: 25 | F21: 25 | G21: 25 | H21: 25 | I21: 25 | J21: 25 | K21: 25 | L21: 25 | M21: 25 | N21: 25 | O21: 25 | P21: 25 | Q21: 25 | R21: 25 | S21: 25 | T21: 25
C22: Other costs (brl/cbm)
C23: Margin (brl/cbm)
C25: EX Tank disport (brl/cbm) | D25: =SUM(D19:D24) -> 120 | E25: =SUM(E17:E24) -> 120 | F25: =SUM(F17:F24) -> 120 | G25: =SUM(G17:G24) -> 120 | H25: =SUM(H17:H24) -> 125.3652 | I25: =SUM(I17:I24) -> 125.3652 | J25: =SUM(J17:J24) -> 125.3652 | K25: =SUM(K17:K24) -> 125.3652 | L25: =SUM(L17:L24) -> 125.3652 | ... T25: =SUM(T17:T24) -> 128.3652
C26: EX Tank disport (usd/cbm) | E26: =+E25/E2 -> #DIV/0! | F26: =+F25/F2 -> #DIV/0! | G26: =+G25/G2 -> #DIV/0! | H26: =+H25/H2 -> #DIV/0! | I26: =+I25/I2 -> #DIV/0! | J26: =+J25/J2 -> #DIV/0! | K26: =+K25/K2 -> #DIV/0! | L26: =+L25/L2 -> #DIV/0! | ... T26: =+T25/T2 -> #DIV/0!
C28: NE BRZ (brl/cbm) | D28: =+'PLATTS&OPIS'!I156 -> 4470 | E28: =+'PLATTS&OPIS'!I171 -> 4480 | G28: =+'PLATTS&OPIS'!I236 -> 3565 | H28: =+'PLATTS&OPIS'!I266 -> 4150 | I28: =+'PLATTS&OPIS'!I285 -> 4195 | J28: =+'PLATTS&OPIS'!I305 -> 4445 | K28: =+'PLATTS&OPIS'!I330 -> 4045 | L28: =+'PLATTS&OPIS'!I350 -> 4095 | M28: =+'PLATTS&OPIS'!I370 -> 3495 | N28: =+'PLATTS&OPIS'!I400 -> 3160 | O28: =+'PLATTS&OPIS'!I415 -> 3245 | P28: =+'PLATTS&OPIS'!I579 -> 3595 | Q28: =+P28 -> 3595 | R28: =+Q28 -> 3595 | S28: =+R28 -> 3595 | T28: =+S28 -> 3595
C29: 0% import tax | D29: 44501 | E29: 44531 | F29: 44562 | G29: 44593 | H29: 44621 | I29: 44652 | J29: 44682 | K29: 44713 | L29: 44743 | M29: 44774 | N29: 44805 | O29: 44835 | P29: 44866 | Q29: 44896 | R29: 44927 | S29: 44958 | T29: 44986
C30: ARB (brl/cbm) | D30: =+D28-D25 -> 4350 | E30: =+E28-E25 -> 4360 | F30: =+F28-F25 -> -120 | G30: =+G28-G25 -> 3445 | H30: =+H28-H25 -> 4024.6348 | I30: =+I28-I25 -> 4069.6348 | J30: =+J28-J25 -> 4319.6348 | K30: =+K28-K25 -> 3919.6348 | ... T30: =+T28-T25 -> 3466.6348
C31: ARB (usd/cbm) | D31: =+D30/$E$1 -> #DIV/0! | E31: =+E30/E2 -> #DIV/0! | F31: =+F30/F2 -> #DIV/0! | G31: =+G30/G2 -> #DIV/0! | H31: =+H30/H2 -> #DIV/0! | I31: =+I30/I2 -> #DIV/0! | J31: =+J30/J2 -> #DIV/0! | K31: =+K30/K2 -> #DIV/0! | L31: =+L30/L2 -> #DIV/0! | ... T31: =+T30/T2 -> #DIV/0!
C32: ARB (usd/gal) | H32: =+H31/264.172 -> #DIV/0! | I32: =+I31/264.172 -> #DIV/0! | J32: =+J31/264.172 -> #DIV/0! | K32: =+K31/264.172 -> #DIV/0! | L32: =+L31/264.172 -> #DIV/0! | M32: =+M31/264.172 -> #DIV/0! | N32: =+N31/264.172 -> #DIV/0! | O32: =+O31/264.172 -> #DIV/0! | ... T32: =+T31/264.172 -> #DIV/0!
C34: load mth+1 | D34: 44531 | E34: 44562 | F34: 44593 | G34: 44621 | I34: 44652 | J34: 44682 | K34: 44713 | L34: 44743 | M34: 44774 | N34: 44805 | O34: 44835 | P34: 44866 | Q34: 44896 | R34: 44927 | S34: 44958 | T34: 44986
C35: B3 hyd | D35: =+'settlement day'!N13 -> 0 | E35: =+'settlement day'!O13 -> 0 | F35: =+'settlement day'!P13 -> 0 | G35: =+'settlement day'!Q13 -> 0 | I35: =+'settlement day'!R13 -> 0 | J35: =+'settlement day'!S13 -> 0 | K35: =+'settlement day'!T13 -> 0 | L35: =+'settlement day'!U13 -> 0 | M35: =+'settlement day'!V13 -> 0 | N35: =+'settlement day'!W13 -> 0 | O35: =+'settlement day'!X13 -> 0 | P35: =+'settlement day'!Y13 -> 0 | ... T35: =+'settlement day'!AC13 -> 0
C36: B3 hyd ex plant | D36: =+(D35-'mkt data'!$G$23+'mkt data'!$G$24)/'mkt data'!$H$25 -> -99.524494 | E36: =+(E35-'mkt data'!$G$23+'mkt data'!$G$24)/'mkt data'!$H$25 -> -99.524494 | F36: =+(F35-'mkt data'!$G$23+'mkt data'!$G$24)/'mkt data'!$H$25 -> -99.524494 | G36: =+(G35-'mkt data'!$G$23+'mkt data'!$G$24)/'mkt data'!$H$25 -> -99.524494 | I36: =+(I35-'mkt data'!$G$23+'mkt data'!$G$24)/'mkt data'!$H$25 -> -99.524494 | J36: =+(J35-'mkt data'!$G$23+'mkt data'!$G$24)/'mkt data'!$H$25 -> -99.524494 | K36: =+(K35-'mkt data'!$G$23+'mkt data'!$G$24)/'mkt data'!$H$25 -> -99.524494 | L36: =+(L35-'mkt data'!$G$23+'mkt data'!$G$24)/'mkt data'!$H$25 -> -99.524494 | M36: =+(M35-'mkt data'!$G$23+'mkt data'!$G$24)/'mkt data'!$H$25 -> -99.524494 | N36: =+(N35-'mkt data'!$G$23+'mkt data'!$G$24)/'mkt data'!$H$25 -> -99.524494 | O36: =+(O35-'mkt data'!$G$23+'mkt data'!$G$24)/'mkt data'!$H$25 -> -99.524494 | P36: =+(P35-'mkt data'!$G$23+'mkt data'!$G$24)/'mkt data'!$H$25 -> -99.524494 | ... T36: =+(T35-'mkt data'!$G$23+'mkt data'!$G$24)/'mkt data'!$H$25 -> -99.524494
B38: =+'mkt data'!G26 -> 0.12 | C38: B3 anydrous ex plant | D38: =+((D35-'mkt data'!$G$23)*'mkt data'!$H$26)+('mkt data'!$G$24) -> -100.8 | E38: =+((E35-'mkt data'!$G$23)*'mkt data'!$H$26)+('mkt data'!$G$24) -> -100.8 | F38: =+((F35-'mkt data'!$G$23)*'mkt data'!$H$26)+('mkt data'!$G$24) -> -100.8 | G38: =+((G35-'mkt data'!$G$23)*'mkt data'!$H$26)+('mkt data'!$G$24) -> -100.8 | I38: =+((I35-'mkt data'!$G$23)*'mkt data'!$H$26)+('mkt data'!$G$24) -> -100.8 | J38: =+((J35-'mkt data'!$G$23)*'mkt data'!$H$26)+('mkt data'!$G$24) -> -100.8 | K38: =+((K35-'mkt data'!$G$23)*'mkt data'!$H$26)+('mkt data'!$G$24) -> -100.8 | L38: =+((L35-'mkt data'!$G$23)*'mkt data'!$H$26)+('mkt data'!$G$24) -> -100.8 | M38: =+((M35-'mkt data'!$G$23)*'mkt data'!$H$26)+('mkt data'!$G$24) -> -100.8 | N38: =+((N35-'mkt data'!$G$23)*'mkt data'!$H$26)+('mkt data'!$G$24) -> -100.8 | O38: =+((O35-'mkt data'!$G$23)*'mkt data'!$H$26)+('mkt data'!$G$24) -> -100.8 | P38: =+((P35-'mkt data'!$G$23)*'mkt data'!$H$26)+('mkt data'!$G$24) -> -100.8 | ... T38: =+((T35-'mkt data'!$G$23)*'mkt data'!$H$26)+('mkt data'!$G$24) -> -100.8
B40: =470/0.867 -> 542.09919 | C40: B3 CS to NE (brl/cbm) | D40: =+D38+$B$40 -> 441.29919 | E40: =+E38+$B$40 -> 441.29919 | F40: =+F38+$B$40 -> 441.29919 | G40: =+G38+$B$40 -> 441.29919 | I40: =+I38+$B$40 -> 441.29919 | J40: =+J38+$B$40 -> 441.29919 | K40: =+K38+$B$40 -> 441.29919 | L40: =+L38+$B$40 -> 441.29919 | M40: =+M38+$B$40 -> 441.29919 | N40: =+N38+$B$40 -> 441.29919 | O40: =+O38+$B$40 -> 441.29919 | P40: =+P38+$B$40 -> 441.29919 | ... T40: =+T38+$B$40 -> 441.29919
D41: 44531 | E41: 44562 | F41: 44593 | G41: 44621 | I41: 44652 | J41: 44682 | K41: 44713 | L41: 44743 | M41: 44774 | N41: 44805 | O41: 44835 | P41: 44866 | Q41: 44896 | R41: 44927 | S41: 44958 | T41: 44986
C42: ARB (brl/cbm) | D42: =+D40-D25 -> 321.29919 | E42: =+E40-E25 -> 321.29919 | F42: =+F40-F25 -> 321.29919 | G42: =+G40-G25 -> 321.29919 | I42: =+I40-I25 -> 315.93399 | J42: =+J40-J25 -> 315.93399 | K42: =+K40-K25 -> 315.93399 | L42: =+L40-L25 -> 315.93399 | M42: =+M40-M25 -> 315.93399 | N42: =+N40-N25 -> 315.93399 | O42: =+O40-O25 -> 315.93399 | P42: =+P40-P25 -> 315.93399 | ... T42: =+T40-T25 -> 312.93399
C43: ARB (usd/cbm) | D43: =+D42/$E$1 -> #DIV/0! | E43: =+E42/E2 -> #DIV/0! | F43: =+F42/F2 -> #DIV/0! | G43: =+G42/G2 -> #DIV/0! | I43: =+I42/H2 -> #DIV/0! | J43: =+J42/I2 -> #DIV/0! | K43: =+K42/J2 -> #DIV/0! | L43: =+L42/L2 -> #DIV/0! | M43: =+M42/M2 -> #DIV/0! | N43: =+N42/N2 -> #DIV/0! | O43: =+O42/O2 -> #DIV/0! | P43: =+P42/P2 -> #DIV/0! | Q43: =+Q42/Q2 -> #DIV/0! | R43: =+R42/R2 -> #DIV/0! | S43: =+S42/S2 -> #DIV/0! | T43: =+T42/T2 -> #DIV/0!
C44: ARB (usd/gal) | I44: =+I43/264.172 -> #DIV/0! | J44: =+J43/264.172 -> #DIV/0! | K44: =+K43/264.172 -> #DIV/0! | L44: =+L43/264.172 -> #DIV/0! | M44: =+M43/264.172 -> #DIV/0! | N44: =+N43/264.172 -> #DIV/0! | O44: =+O43/264.172 -> #DIV/0! | P44: =+P43/264.172 -> #DIV/0! | ... T44: =+T43/264.172 -> #DIV/0!

Sheet ARB BRZ 2024_25
A1: 0.789 | E1: =+'settlement day'!M30 -> 0
A2: 264.172 | C2: BRL/USD | D2: =+'settlement day'!M30 -> 0 | E2: =+'settlement day'!N30 -> 0 | F2: =+'settlement day'!O30 -> 0 | G2: =+'settlement day'!P30 -> 0 | H2: =+'settlement day'!Q30 -> 0 | I2: =+'settlement day'!R30 -> 0 | J2: =+'settlement day'!S30 -> 0 | K2: =+'settlement day'!T30 -> 0 | ... BA2: =+'settlement day'!BJ30 -> 5.9417706
D3: 44501 | E3: 44531 | F3: 44562 | G3: 44593 | H3: 44621 | I3: 44652 | J3: 44682 | K3: 44713 | L3: 44743 | M3: 44774 | N3: 44805 | O3: 44835 | P3: 44866 | Q3: 44896 | R3: 44927 | S3: 44958 | T3: 44986 | U3: 45017 | V3: 45047 | W3: 45078 | X3: 45108 | Y3: 45139 | Z3: 45170 | AA3: 45200 | AB3: 45231 | AC3: 45261 | AD3: 45292 | AE3: 45323 | AF3: 45352 | AG3: 45383 | AH3: 45413 | AI3: 45444 | AJ3: 45474 | AK3: 45505 | AL3: 45536 | AM3: 45566 | AN3: 45597 | AO3: 45627 | AP3: 45658 | AQ3: 45689 | AR3: 45717 | AS3: 45748 | AT3: 45778 | AU3: 45809 | AV3: 45839 | AW3: 45870 | AX3: 45901 | AY3: 45931 | AZ3: 45962 | BA3: 45992
C4: CHIP | D4: =+'settlement day'!M9 -> 0 | E4: =+'settlement day'!N9 -> 0 | F4: =+'settlement day'!O9 -> 0 | G4: =+'settlement day'!P9 -> 0 | H4: =+'settlement day'!Q9 -> 0 | I4: =+'settlement day'!R9 -> 0 | J4: =+'settlement day'!S9 -> 0 | K4: =+'settlement day'!T9 -> 0 | ... U4: =+'settlement day'!AD9 -> 0 | V4: =+'settlement day'!AE8 -> 2.43773 | W4: =+'settlement day'!AF8 -> 2.50714 | X4: =+'settlement day'!AG8 -> 2.44342 | Y4: =+'settlement day'!AH8 -> 2.1663 | Z4: =+'settlement day'!AI9 -> 0 | AA4: =+'settlement day'!AJ9 -> 0 | AB4: =+'settlement day'!AK9 -> 0 | AC4: =+'settlement day'!AL9 -> 0 | AD4: =+'settlement day'!AM9 -> 0 | AE4: =+'settlement day'!AN9 -> 0 | AF4: =+'settlement day'!AO9 -> 0 | AG4: =+'settlement day'!AP9 -> 0 | ... BA4: =+'settlement day'!BJ9 -> 1.6675
B5: ='mkt data'!G16 -> 0.12 | C5: FOB (usd/gal) | D5: =+D4+$B$5 -> 0.12 | E5: =+E4+$B$5 -> 0.12 | F5: =+F4+$B$5 -> 0.12 | G5: =+G4+$B$5 -> 0.12 | H5: =+H4+$B$5 -> 0.12 | I5: =+I4+$B$5 -> 0.12 | J5: =+J4+$B$5 -> 0.12 | K5: =+K4+$B$5 -> 0.12 | ... BA5: =+BA4+$B$5 -> 1.7875
C6: FOB usd/cbm | D6: =+D5*$A$2 -> 31.70064 | E6: =+E5*$A$2 -> 31.70064 | F6: =+F5*$A$2 -> 31.70064 | G6: =+G5*$A$2 -> 31.70064 | H6: =+H5*$A$2 -> 31.70064 | I6: =+I5*$A$2 -> 31.70064 | J6: =+J5*$A$2 -> 31.70064 | K6: =+K5*$A$2 -> 31.70064 | ... BA6: =+BA5*$A$2 -> 472.20745
B8: 0.02 | C8: cost (usd/cbm) | D8: =+$B$8*$A$2 -> 5.28344 | E8: =+D8 -> 5.28344 | F8: =+E8 -> 5.28344 | G8: =+F8 -> 5.28344 | H8: =+G8 -> 5.28344 | I8: =+H8 -> 5.28344 | J8: =+I8 -> 5.28344 | K8: =+J8 -> 5.28344 | L8: =+K8 -> 5.28344 | ... BA8: =+AZ8 -> 5.28344
A9: 20kcbm | B9: =75*0.789 -> 59.175 | C9: freight usd/cbm | D9: =+$B$9*$A$1 -> 46.689075 | E9: =+$B$9*$A$1 -> 46.689075 | F9: =+$B$9*$A$1 -> 46.689075 | G9: =+$B$9*$A$1 -> 46.689075 | H9: =+$B$9*$A$1 -> 46.689075 | I9: =+$B$9*$A$1 -> 46.689075 | J9: =+$B$9*$A$1 -> 46.689075 | K9: =+$B$9*$A$1 -> 46.689075 | ... AG9: =+$B$9*$A$1 -> 46.689075 | AH9: =+B9 -> 59.175 | AI9: =+$B$9 -> 59.175 | AJ9: =+$B$9 -> 59.175 | AK9: =+$B$9 -> 59.175 | AL9: =+$B$9 -> 59.175 | AM9: =+$B$9 -> 59.175 | AN9: =+$B$9 -> 59.175 | AO9: =+$B$9 -> 59.175 | AP9: =+$B$9 -> 59.175 | ... BA9: =+$B$9 -> 59.175
C10: CIF usd/cbm | D10: =SUM(D6:D9) -> 83.673155 | E10: =SUM(E6:E9) -> 83.673155 | F10: =SUM(F6:F9) -> 83.673155 | G10: =SUM(G6:G9) -> 83.673155 | H10: =SUM(H6:H9) -> 83.673155 | I10: =SUM(I6:I9) -> 83.673155 | J10: =SUM(J6:J9) -> 83.673155 | K10: =SUM(K6:K9) -> 83.673155 | ... BA10: =SUM(BA6:BA9) -> 536.66589
C11: CIF brl/cbm | E11: =+E10*E2 -> 0 | F11: =+F10*F2 -> 0 | G11: =+G10*G2 -> 0 | H11: =+H10*H2 -> 0 | I11: =+I10*I2 -> 0 | J11: =+J10*J2 -> 0 | K11: =+K10*K2 -> 0 | L11: =+L10*L2 -> 0 | ... BA11: =+BA10*BA2 -> 3188.7456
B13: 0.18 | C13: Import duly | D13: =+D10*$B$13 -> 15.061168 | E13: =+E11*$B$13 -> 0 | F13: =+F11*$B$13 -> 0 | G13: =+G11*$B$13 -> 0 | H13: =+H11*$B$13 -> 0 | I13: =+I11*$B$13 -> 0 | J13: =+J11*$B$13 -> 0 | K13: =+K11*$B$13 -> 0 | L13: =+L11*$B$13 -> 0 | ... BA13: =+BA11*$B$13 -> 573.97421
A14: antes 11.75% | B14: 0.1175 | C14: PIS/COFINS | D14: =+D10*$B$14 -> 9.8315957 | E14: =+E11*$B$14 -> 0 | F14: =+F11*$B$14 -> 0 | G14: =+G11*$B$14 -> 0 | H14: =+H11*$B$14 -> 0 | I14: =+I11*$B$14 -> 0 | J14: =+J11*$B$14 -> 0 | K14: =+K11*$B$14 -> 0 | L14: =+L11*$B$14 -> 0 | ... R14: =+R11*$B$14 -> 0 | S14: 20 | T14: 20 | U14: 20 | V14: 20 | W14: 20 | X14: 20 | Y14: 20 | Z14: 20 | AA14: 20 | AB14: 20 | AC14: 20 | AD14: 20 | AE14: 20 | AF14: =AF11*$B$14 -> 49.11472 | AG14: =AG11*$B$14 -> 50.841148 | AH14: =AH11*$B$14 -> 59.216444 | AI14: =AI11*$B$14 -> 62.801519 | AJ14: =AJ11*$B$14 -> 63.967544 | AK14: =AK11*$B$14 -> 63.900882 | AL14: =AL11*$B$14 -> 61.549624 | AM14: =AM11*$B$14 -> 65.608114 | ... BA14: =BA11*$B$14 -> 374.67761
C15: ICMS | D15: 0 | E15: 0 | F15: 0 | G15: 0 | H15: 0 | I15: 0 | J15: 0 | K15: 0 | L15: 0 | M15: 0 | N15: 0 | O15: 0 | P15: 0 | Q15: 0 | R15: 1 | S15: 0 | T15: 0 | U15: 0 | V15: 0 | W15: 0 | X15: 0 | Y15: 0 | Z15: 0 | AA15: 0 | AB15: 0 | AC15: 0 | AD15: 0 | AE15: 0 | AF15: 0 | AG15: 0 | AH15: 0 | AI15: 0 | AJ15: 0 | AK15: 0 | AL15: 0 | AM15: 0 | AN15: 0 | AO15: 0 | AP15: 0 | AQ15: 0 | AR15: 0 | AS15: 0 | AT15: 0 | AU15: 0 | AV15: 0 | AW15: 0 | AX15: 0 | AY15: 0 | AZ15: 0 | BA15: 0
B16: 0.08 | C16: AFRMM | D16: 0 | E16: 0 | F16: 0 | G16: 0 | H16: =+H9*$B$16 -> 3.735126 | I16: =+I9*$B$16 -> 3.735126 | J16: =+J9*$B$16 -> 3.735126 | K16: =+K9*$B$16 -> 3.735126 | L16: =+L9*$B$16 -> 3.735126 | M16: =+M9*$B$16 -> 3.735126 | N16: =+N9*$B$16 -> 3.735126 | O16: =+O9*$B$16 -> 3.735126 | ... BA16: =+BA9*$B$16 -> 4.734
C17: Cargo Cleared usd/cbm | D17: =SUM(D10:D16) -> 108.56592 | E17: =SUM(E11:E16) -> 0 | F17: =SUM(F11:F16) -> 0 | G17: =SUM(G11:G16) -> 0 | H17: =SUM(H11:H16) -> 3.735126 | I17: =SUM(I11:I16) -> 3.735126 | J17: =SUM(J11:J16) -> 3.735126 | K17: =SUM(K11:K16) -> 3.735126 | L17: =SUM(L11:L16) -> 3.735126 | ... BA17: =SUM(BA11:BA16) -> 4142.1315
C19: Terminal cost (brl/cbm) | D19: 80 | E19: 80 | F19: 80 | G19: 80 | H19: 80 | I19: 80 | J19: 80 | K19: 80 | L19: 80 | M19: 80 | N19: 80 | O19: 80 | P19: 80 | Q19: 80 | R19: 80 | S19: 80 | T19: 80 | U19: 80 | V19: 80 | W19: 80 | X19: 80 | Y19: 80 | Z19: 80 | AA19: 80 | AB19: 80 | AC19: 80 | AD19: 80 | AE19: 80 | AF19: 80 | AG19: 80 | AH19: 80 | AI19: 80 | AJ19: 80 | AK19: 80 | AL19: 80 | AM19: 80 | AN19: 80 | AO19: 80 | AP19: 80 | AQ19: 80 | AR19: 80 | AS19: 80 | AT19: 80 | AU19: 80 | AV19: 80 | AW19: 80 | AX19: 80 | AY19: 80 | AZ19: 80 | BA19: 80
C20: Inspection (brl/cbm) | D20: 15 | E20: 15 | F20: 15 | G20: 15 | H20: 15 | I20: 15 | J20: 15 | K20: 15 | L20: 15 | M20: 15 | N20: 15 | O20: 15 | P20: 15 | Q20: 15 | R20: 15 | S20: 15 | T20: 15 | U20: 15 | V20: 15 | W20: 15 | X20: 15 | Y20: 15 | Z20: 15 | AA20: 15 | AB20: 15 | AC20: 15 | AD20: 15 | AE20: 15 | AF20: 15 | AG20: 15 | AH20: 15 | AI20: 15 | AJ20: 15 | AK20: 15 | AL20: 15 | AM20: 15 | AN20: 15 | AO20: 15 | AP20: 15 | AQ20: 15 | AR20: 15 | AS20: 15 | AT20: 15 | AU20: 15 | AV20: 15 | AW20: 15 | AX20: 15 | AY20: 15 | AZ20: 15 | BA20: 15
C21: Inland freight (brl/cbm) | D21: 25 | E21: 25 | F21: 25 | G21: 25 | H21: 25 | I21: 25 | J21: 25 | K21: 25 | L21: 25 | M21: 25 | N21: 25 | O21: 25 | P21: 25 | Q21: 25 | R21: 25 | S21: 25 | T21: 25 | U21: 25 | V21: 25 | W21: 25 | X21: 25 | Y21: 25 | Z21: 25 | AA21: 25 | AB21: 25 | AC21: 25 | AD21: 25 | AE21: 25 | AF21: 25 | AG21: 25 | AH21: 25 | AI21: 25 | AJ21: 25 | AK21: 25 | AL21: 25 | AM21: 25 | AN21: 25 | AO21: 25 | AP21: 25 | AQ21: 25 | AR21: 25 | AS21: 25 | AT21: 25 | AU21: 25 | AV21: 25 | AW21: 25 | AX21: 25 | AY21: 25 | AZ21: 25 | BA21: 25
C22: Other costs (brl/cbm)
C23: Margin (brl/cbm)
C25: EX Tank disport (brl/cbm) | D25: =SUM(D19:D24) -> 120 | E25: =SUM(E17:E24) -> 120 | F25: =SUM(F17:F24) -> 120 | G25: =SUM(G17:G24) -> 120 | H25: =SUM(H17:H24) -> 123.73513 | I25: =SUM(I17:I24) -> 123.73513 | J25: =SUM(J17:J24) -> 123.73513 | K25: =SUM(K17:K24) -> 123.73513 | L25: =SUM(L17:L24) -> 123.73513 | ... BA25: =SUM(BA17:BA24) -> 4262.1315
C26: EX Tank disport (usd/cbm) | E26: =+E25/E2 -> #DIV/0! | F26: =+F25/F2 -> #DIV/0! | G26: =+G25/G2 -> #DIV/0! | H26: =+H25/H2 -> #DIV/0! | I26: =+I25/I2 -> #DIV/0! | J26: =+J25/J2 -> #DIV/0! | K26: =+K25/K2 -> #DIV/0! | L26: =+L25/L2 -> #DIV/0! | ... BA26: =+BA25/BA2 -> 717.31672
C28: NE BRZ (brl/cbm) | D28: =+'PLATTS&OPIS'!I156 -> 4470 | E28: =+'PLATTS&OPIS'!I171 -> 4480 | G28: =+'PLATTS&OPIS'!I236 -> 3565 | H28: =+'PLATTS&OPIS'!I266 -> 4150 | I28: =+'PLATTS&OPIS'!I285 -> 4195 | J28: =+'PLATTS&OPIS'!I305 -> 4445 | K28: =+'PLATTS&OPIS'!I330 -> 4045 | L28: =+'PLATTS&OPIS'!I350 -> 4095 | M28: =+'PLATTS&OPIS'!I350 -> 4095 | N28: =+M28 -> 4095 | O28: =+N28 -> 4095 | P28: =+O28 -> 4095 | Q28: =+P28 -> 4095 | R28: =+'PLATTS&OPIS'!I485 -> 3450 | S28: =+'PLATTS&OPIS'!I505 -> 3580 | T28: =+'PLATTS&OPIS'!I520 -> 3575 | U28: =+'PLATTS&OPIS'!I544 -> 3945 | V28: =+'PLATTS&OPIS'!I559 -> 3445 | W28: =+'PLATTS&OPIS'!I589 -> 3650 | X28: =+'PLATTS&OPIS'!I609 -> 3140 | Y28: =+'PLATTS&OPIS'!I634 -> 3265 | Z28: =+'PLATTS&OPIS'!I654 -> 3295 | AA28: =+'PLATTS&OPIS'!I676 -> 2895 | AB28: =+'PLATTS&OPIS'!I697 -> 2815 | AC28: =+'PLATTS&OPIS'!I713 -> 2800 | AD28: =+'PLATTS&OPIS'!I740 -> 3065 | AE28: =+'PLATTS&OPIS'!I761 -> 3245 | AF28: =+'PLATTS&OPIS'!I781 -> 3205 | AG28: =+'PLATTS&OPIS'!I803 -> 3175 | AH28: =+'PLATTS&OPIS'!I827 -> 3200 | AI28: =+'PLATTS&OPIS'!I846 -> 3225 | AJ28: =+'PLATTS&OPIS'!I869 -> 3640 | AK28: =+'PLATTS&OPIS'!I892 -> 3495 | AL28: =+'PLATTS&OPIS'!I912 -> 3150 | AM28: =+'PLATTS&OPIS'!I936 -> 3030 | AN28: =+'PLATTS&OPIS'!I956 -> 3100 | AO28: =+'PLATTS&OPIS'!I968 -> 3370 | AP28: =+'PLATTS&OPIS'!I1000 -> 3655 | AQ28: =+'PLATTS&OPIS'!I1019 -> 3545 | AR28: =+'PLATTS&OPIS'!I1040 -> 3395 | AS28: =+'PLATTS&OPIS'!I1063 -> 3560 | AT28: =+'PLATTS&OPIS'!I1074 -> 3675 | AU28: =+AT28 -> 3675 | AV28: =+AU28 -> 3675 | AW28: =+AV28 -> 3675 | AX28: =+AW28 -> 3675 | AY28: =+AX28 -> 3675 | AZ28: =+AY28 -> 3675 | BA28: =+AZ28 -> 3675
D29: 44501 | E29: 44531 | F29: 44562 | G29: 44593 | H29: 44621 | I29: 44652 | J29: 44682 | K29: 44713 | L29: 44743 | M29: 44774 | N29: 44805 | O29: 44835 | P29: 44866 | Q29: 44896 | R29: 44927 | S29: 44958 | T29: 44986 | U29: 45017 | V29: 45047 | W29: 45078 | X29: 45108 | Y29: 45139 | Z29: 45170 | AA29: 45200 | AB29: 45231 | AC29: 45261 | AD29: 45292 | AE29: 45323 | AF29: 45352 | AG29: 45383 | AH29: 45413 | AI29: 45444 | AJ29: 45474 | AK29: 45505 | AL29: 45536 | AM29: 45566 | AN29: 45597 | AO29: 45627 | AP29: 45658 | AQ29: 45689 | AR29: 45717 | AS29: 45748 | AT29: 45778 | AU29: 45809 | AV29: 45839 | AW29: 45870 | AX29: 45901 | AY29: 45931 | AZ29: 45962 | BA29: 45992
C30: ARB (brl/cbm) | D30: =+D28-D25 -> 4350 | E30: =+E28-E25 -> 4360 | F30: =+F28-F25 -> -120 | G30: =+G28-G25 -> 3445 | H30: =+H28-H25 -> 4026.2649 | I30: =+I28-I25 -> 4071.2649 | J30: =+J28-J25 -> 4321.2649 | K30: =+K28-K25 -> 3921.2649 | ... BA30: =+BA28-BA25 -> -587.13146
C31: ARB (usd/cbm) | D31: =+D30/$E$1 -> #DIV/0! | E31: =+E30/E2 -> #DIV/0! | F31: =+F30/F2 -> #DIV/0! | G31: =+G30/G2 -> #DIV/0! | H31: =+H30/H2 -> #DIV/0! | I31: =+I30/I2 -> #DIV/0! | J31: =+J30/J2 -> #DIV/0! | K31: =+K30/K2 -> #DIV/0! | L31: =+L30/L2 -> #DIV/0! | ... BA31: =+BA30/BA2 -> -98.814224
C32: ARB (usd/gal) | H32: =+H31/264.172 -> #DIV/0! | I32: =+I31/264.172 -> #DIV/0! | J32: =+J31/264.172 -> #DIV/0! | K32: =+K31/264.172 -> #DIV/0! | L32: =+L31/264.172 -> #DIV/0! | M32: =+M31/264.172 -> #DIV/0! | N32: =+N31/264.172 -> #DIV/0! | O32: =+O31/264.172 -> #DIV/0! | ... BA32: =+BA31/264.172 -> -0.3740526
C35: USA / NNE Brazil arbitrage
A36: NE incl mkt structure | C36: NE BRZ (brl/cbm) | D36: =+'PLATTS&OPIS'!I162 -> 0 | E36: =+'PLATTS&OPIS'!I177 -> 0 | G36: =+'PLATTS&OPIS'!I242 -> 0 | H36: =+'PLATTS&OPIS'!I272 -> 0 | I36: =+'PLATTS&OPIS'!I291 -> 0 | J36: =+'PLATTS&OPIS'!I311 -> 0 | K36: =+'PLATTS&OPIS'!I336 -> 0 | L36: =+'PLATTS&OPIS'!I356 -> 0 | M36: =+'PLATTS&OPIS'!I356 -> 0 | N36: =+M36 -> 0 | O36: =+N36 -> 0 | P36: =+O36 -> 0 | Q36: =+P36 -> 0 | R36: =+'PLATTS&OPIS'!I491 -> 0 | S36: =+'PLATTS&OPIS'!I511 -> 0 | T36: =+T28+T45 -> 6401 | U36: =+U28+U45 -> 7026 | V36: =+V28+V45 -> 3445 | W36: =+W28+W45 -> 3650 | X36: =+X28+X45 -> 3140 | Y36: =+Y28+Y45 -> 3265 | Z36: =+Z28+Z45 -> 3295 | AA36: =+Z36+AA45 -> 3295 | AB36: =+AB28+AB45 -> 2815 | AC36: =+AB36+AC45 -> 2815 | AD36: =+AC36+AD45 -> 2815 | AE36: =+AD36+AE45 -> 2815 | AF36: =AF28+AF45 -> 3205 | AG36: =+AG28+AG45 -> 3175 | AH36: =+AH28+AH45 -> 3200 | AI36: =+AI28+AI45 -> 3225 | AJ36: =+AJ28+AJ45 -> 3640 | AK36: =+AK28+AK45 -> 3495 | AL36: =+AL28+AL45 -> 3150 | AM36: =+AM28+AM45 -> 3030 | AN36: =+AN28+AN45 -> 3100 | ... AQ36: =+AQ28+AQ45 -> 3545 | AR36: =+AR28 -> 3395 | AS36: =+AS28+AS45 -> 3560 | AT36: =+AT28+AT45 -> 3675 | AU36: =+AT36+AU45 -> 3624.5 | AV36: =+AU36+AV45 -> 3624.5 | AW36: =+AV36+AW45 -> 3637 | AX36: =+AW36+AX45 -> 3664 | AY36: =+AX36+AY45 -> 3713 | AZ36: =+AY36+AZ45 -> 3725.5 | BA36: =+AZ36+BA45 -> 3742
C37: BRL/USD | D37: =+'settlement day'!M66 -> 0 | E37: =+'settlement day'!N66 -> 0 | F37: =+'settlement day'!O66 -> 0 | G37: =+'settlement day'!P66 -> 0 | H37: =+'settlement day'!Q66 -> 0 | I37: =+'settlement day'!R66 -> 0 | J37: =+'settlement day'!S66 -> 0 | K37: =+'settlement day'!T66 -> 0 | ... U37: =+'settlement day'!AD66 -> 0 | V37: =V2 -> 0 | W37: =W2 -> 0 | X37: =X2 -> 0 | Y37: =Y2 -> 0 | Z37: =Z2 -> 0 | AA37: =AA2 -> 0 | AB37: =AB2 -> 0 | AC37: =AC2 -> 4.8412998 | ... BA37: =BA2 -> 5.9417706
D38: 44501 | E38: 44531 | F38: 44562 | G38: 44593 | H38: 44621 | I38: 44652 | J38: 44682 | K38: 44713 | L38: 44743 | M38: 44774 | N38: 44805 | O38: 44835 | P38: 44866 | Q38: 44896 | R38: 44927 | S38: 44958 | T38: 44986 | U38: 45017 | V38: 45047 | W38: 45078 | X38: 45108 | Y38: 45139 | Z38: 45170 | AA38: 45200 | AB38: 45231 | AC38: 45261 | AD38: 45292 | AE38: 45323 | AF38: 45352 | AG38: 45383 | AH38: 45413 | AI38: 45444 | AJ38: 45474 | AK38: 45505 | AL38: 45536 | AM38: 45566 | AN38: 45597 | AO38: 45627 | AP38: 45658 | AQ38: 45689 | AR38: 45717 | AS38: 45748 | AT38: 45778 | AU38: 45809 | AV38: 45839 | AW38: 45870 | AX38: 45901 | AY38: 45931 | AZ38: 45962 | BA38: 45992
C39: ARB (brl/cbm) | D39: =+D36-D31 -> #DIV/0! | E39: =+E36-E31 -> #DIV/0! | F39: =+F36-F31 -> #DIV/0! | G39: =+G36-G31 -> #DIV/0! | H39: =+H36-H31 -> #DIV/0! | I39: =+I36-I31 -> #DIV/0! | J39: =+J36-J31 -> #DIV/0! | K39: =+K36-K31 -> #DIV/0! | ... S39: =+S36-S31 -> #DIV/0! | T39: =+T36-T25 -> 6257.2649 | U39: =+U36-U25 -> 6882.2649 | V39: =+V36-V25 -> 3301.2649 | W39: =+W36-W25 -> 3506.2649 | X39: =+X36-X25 -> 2996.2649 | Y39: =+Y36-Y25 -> 3121.2649 | Z39: =+Z36-Z25 -> 3151.2649 | AA39: =+AA36-AA25 -> 3151.2649 | ... BA39: =+BA36-BA25 -> -520.13146
C40: ARB (usd/cbm) | D40: =+D39/$E$1 -> #DIV/0! | E40: =+E39/E8 -> #DIV/0! | F40: =+F39/F8 -> #DIV/0! | G40: =+G39/G8 -> #DIV/0! | H40: =+H39/H8 -> #DIV/0! | I40: =+I39/I8 -> #DIV/0! | J40: =+J39/J8 -> #DIV/0! | K40: =+K39/K8 -> #DIV/0! | L40: =+L39/L8 -> #DIV/0! | ... S40: =+S39/S8 -> #DIV/0! | T40: =+T39/T2 -> #DIV/0! | U40: =+U39/U2 -> #DIV/0! | V40: =+V39/V2 -> #DIV/0! | W40: =+W39/W2 -> #DIV/0! | X40: =+X39/X2 -> #DIV/0! | Y40: =+Y39/Y2 -> #DIV/0! | Z40: =+Z39/Z2 -> #DIV/0! | AA40: =+AA39/AA2 -> #DIV/0! | ... BA40: =+BA39/BA2 -> -87.538124
C41: ARB (usd/gal) - 18% import duty | H41: =+H40/264.172 -> #DIV/0! | I41: =+I40/264.172 -> #DIV/0! | J41: =+J40/264.172 -> #DIV/0! | K41: =+K40/264.172 -> #DIV/0! | L41: =+L40/264.172 -> #DIV/0! | M41: =+M40/264.172 -> #DIV/0! | N41: =+N40/264.172 -> #DIV/0! | O41: =+O40/264.172 -> #DIV/0! | ... BA41: =+BA40/264.172 -> -0.33136791
C42: ARB (usd/gal) - 0% import duty | T42: ='ARB BRZ 2023 (no tax)'!T38 -> #DIV/0! | U42: ='ARB BRZ 2023 (no tax)'!U38 -> #DIV/0! | V42: ='ARB BRZ 2023 (no tax)'!V38 -> #DIV/0! | W42: ='ARB BRZ 2023 (no tax)'!W38 -> #DIV/0! | X42: ='ARB BRZ 2023 (no tax)'!X38 -> #DIV/0! | Y42: ='ARB BRZ 2023 (no tax)'!Y38 -> #DIV/0! | Z42: ='ARB BRZ 2023 (no tax)'!Z38 -> #DIV/0! | AA42: ='ARB BRZ 2023 (no tax)'!AA38 -> #DIV/0! | ... BA42: ='ARB BRZ 2023 (no tax)'!BA38 -> 0.084969999
AL43: =AL42*264.172 -> 524.62288 | AM43: =AM42*264.172 -> 406.26086 | AN43: =AN42*264.172 -> 397.46815 | AO43: =AO42*264.172 -> 430.05242 | AP43: =AP42*264.172 -> 511.51667 | AQ43: =AQ42*264.172 -> 490.77054 | AR43: =AR42*264.172 -> 475.50673 | AS43: =AS42*264.172 -> 512.85112 | ... BA43: =BA42*264.172 -> 22.446695
T45: ='settlement day'!AC12 -> 2826 | U45: ='settlement day'!AD12 -> 3081 | V45: 0 | W45: 0 | X45: 0 | Z45: 0 | AR45: 0 | AU45: =AU47-AT47 -> -50.5 | AV45: =AV47-AU47 -> 0 | AW45: =AW47-AV47 -> 12.5 | AX45: =AX47-AW47 -> 27 | AY45: =AY47-AX47 -> 49 | AZ45: =AZ47-AY47 -> 12.5 | BA45: =BA47-AZ47 -> 16.5
C46: load mth+1 | D46: 44531 | E46: 44562 | F46: 44593 | G46: 44621 | I46: 44652 | J46: 44682 | K46: 44713 | L46: 44743 | M46: 44774 | N46: 44805 | O46: 44835 | P46: 44866 | Q46: 44896 | R46: 44927 | S46: 44958 | T46: 44986 | U46: 45017 | V46: 45047 | W46: 45078 | X46: 45108 | Y46: 45139 | Z46: 45170 | AA46: 45200 | AB46: 45231 | AC46: 45261 | AD46: 45292 | AE46: 45323 | AF46: 45352 | AG46: 45383 | AH46: 45413 | AI46: 45444 | AJ46: 45474 | AK46: 45505 | AL46: 45536 | AM46: 45566 | AN46: 45597 | AO46: 45627 | AP46: 45658 | AQ46: 45689 | AR46: 45717 | AS46: 45748 | AT46: 45778 | AU46: 45809 | AV46: 45839 | AW46: 45870 | AX46: 45901 | AY46: 45931 | AZ46: 45962 | BA46: 45992
C47: B3 hyd | D47: =+'settlement day'!N13 -> 0 | E47: =+'settlement day'!O13 -> 0 | F47: =+'settlement day'!P13 -> 0 | G47: =+'settlement day'!Q13 -> 0 | I47: =+'settlement day'!R13 -> 0 | J47: =+'settlement day'!S13 -> 0 | K47: =+'settlement day'!T13 -> 0 | L47: =+'settlement day'!U13 -> 0 | M47: =+'settlement day'!V13 -> 0 | N47: =+'settlement day'!W13 -> 0 | O47: =+'settlement day'!X13 -> 0 | P47: =+'settlement day'!Y13 -> 0 | ... BA47: =+'settlement day'!BJ13 -> 2825
C48: B3 hyd ex plant | D48: =+(D47-'mkt data'!$G$23+'mkt data'!$G$24)/'mkt data'!$H$25 -> -99.524494 | E48: =+(E47-'mkt data'!$G$23+'mkt data'!$G$24)/'mkt data'!$H$25 -> -99.524494 | F48: =+(F47-'mkt data'!$G$23+'mkt data'!$G$24)/'mkt data'!$H$25 -> -99.524494 | G48: =+(G47-'mkt data'!$G$23+'mkt data'!$G$24)/'mkt data'!$H$25 -> -99.524494 | I48: =+(I47-'mkt data'!$G$23+'mkt data'!$G$24)/'mkt data'!$H$25 -> -99.524494 | J48: =+(J47-'mkt data'!$G$23+'mkt data'!$G$24)/'mkt data'!$H$25 -> -99.524494 | K48: =+(K47-'mkt data'!$G$23+'mkt data'!$G$24)/'mkt data'!$H$25 -> -99.524494 | L48: =+(L47-'mkt data'!$G$23+'mkt data'!$G$24)/'mkt data'!$H$25 -> -99.524494 | M48: =+(M47-'mkt data'!$G$23+'mkt data'!$G$24)/'mkt data'!$H$25 -> -99.524494 | N48: =+(N47-'mkt data'!$G$23+'mkt data'!$G$24)/'mkt data'!$H$25 -> -99.524494 | O48: =+(O47-'mkt data'!$G$23+'mkt data'!$G$24)/'mkt data'!$H$25 -> -99.524494 | P48: =+(P47-'mkt data'!$G$23+'mkt data'!$G$24)/'mkt data'!$H$25 -> -99.524494 | ... BA48: =+(BA47-'mkt data'!$G$23+'mkt data'!$G$24)/'mkt data'!$H$25 -> 3024.4388
B50: =+'mkt data'!G26 -> 0.12 | C50: B3 anydrous ex plant | D50: =+((D47-'mkt data'!$G$23)*'mkt data'!$H$26)+('mkt data'!$G$24) -> -100.8 | E50: =+((E47-'mkt data'!$G$23)*'mkt data'!$H$26)+('mkt data'!$G$24) -> -100.8 | F50: =+((F47-'mkt data'!$G$23)*'mkt data'!$H$26)+('mkt data'!$G$24) -> -100.8 | G50: =+((G47-'mkt data'!$G$23)*'mkt data'!$H$26)+('mkt data'!$G$24) -> -100.8 | I50: =+((I47-'mkt data'!$G$23)*'mkt data'!$H$26)+('mkt data'!$G$24) -> -100.8 | J50: =+((J47-'mkt data'!$G$23)*'mkt data'!$H$26)+('mkt data'!$G$24) -> -100.8 | K50: =+((K47-'mkt data'!$G$23)*'mkt data'!$H$26)+('mkt data'!$G$24) -> -100.8 | L50: =+((L47-'mkt data'!$G$23)*'mkt data'!$H$26)+('mkt data'!$G$24) -> -100.8 | M50: =+((M47-'mkt data'!$G$23)*'mkt data'!$H$26)+('mkt data'!$G$24) -> -100.8 | N50: =+((N47-'mkt data'!$G$23)*'mkt data'!$H$26)+('mkt data'!$G$24) -> -100.8 | O50: =+((O47-'mkt data'!$G$23)*'mkt data'!$H$26)+('mkt data'!$G$24) -> -100.8 | P50: =+((P47-'mkt data'!$G$23)*'mkt data'!$H$26)+('mkt data'!$G$24) -> -100.8 | ... BA50: =+((BA47-'mkt data'!$G$23)*'mkt data'!$H$26)+('mkt data'!$G$24) -> 3063.2
B52: =470/0.867 -> 542.09919 | C52: B3 CS to NE (brl/cbm) | D52: =+D50+$B$52 -> 441.29919 | E52: =+E50+$B$52 -> 441.29919 | F52: =+F50+$B$52 -> 441.29919 | G52: =+G50+$B$52 -> 441.29919 | I52: =+I50+$B$52 -> 441.29919 | J52: =+J50+$B$52 -> 441.29919 | K52: =+K50+$B$52 -> 441.29919 | L52: =+L50+$B$52 -> 441.29919 | M52: =+M50+$B$52 -> 441.29919 | N52: =+N50+$B$52 -> 441.29919 | O52: =+O50+$B$52 -> 441.29919 | P52: =+P50+$B$52 -> 441.29919 | ... BA52: =+BA50+$B$52 -> 3605.2992
D53: 44531 | E53: 44562 | F53: 44593 | G53: 44621 | I53: 44652 | J53: 44682 | K53: 44713 | L53: 44743 | M53: 44774 | N53: 44805 | O53: 44835 | P53: 44866 | Q53: 44896 | R53: 44927 | S53: 44958 | T53: 44986 | U53: 45017 | V53: 45047 | W53: 45078 | X53: 45108 | Y53: 45139 | Z53: 45170 | AA53: 45200 | AB53: 45231 | AC53: 45261 | AD53: 45292 | AE53: 45323 | AF53: 45352 | AG53: 45383 | AH53: 45413 | AI53: 45444 | AJ53: 45474 | AK53: 45505 | AL53: 45536 | AM53: 45566 | AN53: 45597 | AO53: 45627 | AP53: 45658 | AQ53: 45689 | AR53: 45717 | AS53: 45748 | AT53: 45778 | AU53: 45809 | AV53: 45839 | AW53: 45870 | AX53: 45901 | AY53: 45931 | AZ53: 45962 | BA53: 45992
C54: ARB (brl/cbm) | D54: =+D52-D25 -> 321.29919 | E54: =+E52-E25 -> 321.29919 | F54: =+F52-F25 -> 321.29919 | G54: =+G52-G25 -> 321.29919 | I54: =+I52-I25 -> 317.56407 | J54: =+J52-J25 -> 317.56407 | K54: =+K52-K25 -> 317.56407 | L54: =+L52-L25 -> 317.56407 | M54: =+M52-M25 -> 317.56407 | N54: =+N52-N25 -> 317.56407 | O54: =+O52-O25 -> 317.56407 | P54: =+P52-P25 -> 317.56407 | ... BA54: =+BA52-BA25 -> -656.83227
C55: ARB (usd/cbm) | D55: =+D54/$E$1 -> #DIV/0! | E55: =+E54/E2 -> #DIV/0! | F55: =+F54/F2 -> #DIV/0! | G55: =+G54/G2 -> #DIV/0! | I55: =+I54/H2 -> #DIV/0! | J55: =+J54/I2 -> #DIV/0! | K55: =+K54/J2 -> #DIV/0! | L55: =+L54/L2 -> #DIV/0! | M55: =+M54/M2 -> #DIV/0! | N55: =+N54/N2 -> #DIV/0! | O55: =+O54/O2 -> #DIV/0! | P55: =+P54/P2 -> #DIV/0! | Q55: =+Q54/Q2 -> #DIV/0! | R55: =+R54/R2 -> #DIV/0! | S55: =+S54/S2 -> #DIV/0! | ... BA55: =+BA54/BA2 -> -110.54487
C56: ARB (usd/gal) | I56: =+I55/264.172 -> #DIV/0! | J56: =+J55/264.172 -> #DIV/0! | K56: =+K55/264.172 -> #DIV/0! | L56: =+L55/264.172 -> #DIV/0! | M56: =+M55/264.172 -> #DIV/0! | N56: =+N55/264.172 -> #DIV/0! | O56: =+O55/264.172 -> #DIV/0! | P56: =+P55/264.172 -> #DIV/0! | ... BA56: =+BA55/264.172 -> -0.41845794

Sheet ARB BRZ 2023 (no tax)
A1: 0.789 | E1: =+'settlement day'!M30 -> 0
A2: 264.172 | C2: FX | D2: =+'settlement day'!M30 -> 0 | E2: =+'settlement day'!N30 -> 0 | F2: =+'settlement day'!O30 -> 0 | G2: =+'settlement day'!P30 -> 0 | H2: =+'settlement day'!Q30 -> 0 | I2: =+'settlement day'!R30 -> 0 | J2: =+'settlement day'!S30 -> 0 | K2: =+'settlement day'!T30 -> 0 | ... BA2: =+'settlement day'!BJ30 -> 5.9417706
D3: 44501 | E3: 44531 | F3: 44562 | G3: 44593 | H3: 44621 | I3: 44652 | J3: 44682 | K3: 44713 | L3: 44743 | M3: 44774 | N3: 44805 | O3: 44835 | P3: 44866 | Q3: 44896 | R3: 44927 | S3: 44958 | T3: 44986 | U3: 45017 | V3: 45047 | W3: 45078 | X3: 45108 | Y3: 45139 | Z3: 45170 | AA3: 45200 | AB3: 45231 | AC3: 45261 | AD3: 45292 | AE3: 45323 | AF3: 45352 | AG3: 45383 | AH3: 45413 | AI3: 45444 | AJ3: 45474 | AK3: 45505 | AL3: 45536 | AM3: 45566 | AN3: 45597 | AO3: 45627 | AP3: 45658 | AQ3: 45689 | AR3: 45717 | AS3: 45748 | AT3: 45778 | AU3: 45809 | AV3: 45839 | AW3: 45870 | AX3: 45901 | AY3: 45931 | AZ3: 45962 | BA3: 45992
C4: CHIP | D4: =+'settlement day'!M9 -> 0 | E4: =+'settlement day'!N9 -> 0 | F4: =+'settlement day'!O9 -> 0 | G4: =+'settlement day'!P9 -> 0 | H4: =+'settlement day'!Q9 -> 0 | I4: =+'settlement day'!R9 -> 0 | J4: =+'settlement day'!S9 -> 0 | K4: =+'settlement day'!T9 -> 0 | ... BA4: =+'settlement day'!BJ9 -> 1.6675
B5: ='ARB BRZ 2024_25'!B5 -> 0.12 | C5: FOB (usd/gal) | D5: =+D4+$B$5 -> 0.12 | E5: =+E4+$B$5 -> 0.12 | F5: =+F4+$B$5 -> 0.12 | G5: =+G4+$B$5 -> 0.12 | H5: =+H4+$B$5 -> 0.12 | I5: =+I4+$B$5 -> 0.12 | J5: =+J4+$B$5 -> 0.12 | K5: =+K4+$B$5 -> 0.12 | ... BA5: =+BA4+$B$5 -> 1.7875
C6: FOB usd/cbm | D6: =+D5*$A$2 -> 31.70064 | E6: =+E5*$A$2 -> 31.70064 | F6: =+F5*$A$2 -> 31.70064 | G6: =+G5*$A$2 -> 31.70064 | H6: =+H5*$A$2 -> 31.70064 | I6: =+I5*$A$2 -> 31.70064 | J6: =+J5*$A$2 -> 31.70064 | K6: =+K5*$A$2 -> 31.70064 | ... BA6: =+BA5*$A$2 -> 472.20745
B8: 0.02 | C8: cost (usd/cbm) | D8: =+$B$8*$A$2 -> 5.28344 | E8: =+D8 -> 5.28344 | F8: =+E8 -> 5.28344 | G8: =+F8 -> 5.28344 | H8: =+G8 -> 5.28344 | I8: =+H8 -> 5.28344 | J8: =+I8 -> 5.28344 | K8: =+J8 -> 5.28344 | L8: =+K8 -> 5.28344 | ... BA8: =+AZ8 -> 5.28344
A9: 20kcbm | B9: =60*0.789 -> 47.34 | C9: freight usd/cbm | D9: =+$B$9*$A$1 -> 37.35126 | E9: =+D9 -> 37.35126 | F9: =+E9 -> 37.35126 | G9: =+F9 -> 37.35126 | H9: =+G9 -> 37.35126 | I9: =+H9 -> 37.35126 | J9: =+I9 -> 37.35126 | K9: =+J9 -> 37.35126 | L9: =+K9 -> 37.35126 | ... AG9: =+AF9 -> 37.35126 | AH9: =+B9 -> 47.34 | AI9: =+AH9 -> 47.34 | AJ9: =+AI9 -> 47.34 | AK9: =+AJ9 -> 47.34 | AL9: =+AK9 -> 47.34 | AM9: =+AL9 -> 47.34 | AN9: =+AM9 -> 47.34 | AO9: =+AN9 -> 47.34 | AP9: =+AO9 -> 47.34 | ... BA9: =+AZ9 -> 47.34
C10: CIF usd/cbm | D10: =SUM(D6:D9) -> 74.33534 | E10: =SUM(E6:E9) -> 74.33534 | F10: =SUM(F6:F9) -> 74.33534 | G10: =SUM(G6:G9) -> 74.33534 | H10: =SUM(H6:H9) -> 74.33534 | I10: =SUM(I6:I9) -> 74.33534 | J10: =SUM(J6:J9) -> 74.33534 | K10: =SUM(K6:K9) -> 74.33534 | ... BA10: =SUM(BA6:BA9) -> 524.83089
C11: CIF brl/cbm | E11: =+E10*E2 -> 0 | F11: =+F10*F2 -> 0 | G11: =+G10*G2 -> 0 | H11: =+H10*H2 -> 0 | I11: =+I10*I2 -> 0 | J11: =+J10*J2 -> 0 | K11: =+K10*K2 -> 0 | L11: =+L10*L2 -> 0 | ... BA11: =+BA10*BA2 -> 3118.4248
A12: da cfr value
B13: 0 | C13: Import duly | D13: =+D10*$B$13 -> 0 | E13: =+E11*$B$13 -> 0 | F13: =+F11*$B$13 -> 0 | G13: =+G11*$B$13 -> 0 | H13: =+H11*$B$13 -> 0 | I13: =+I11*$B$13 -> 0 | J13: =+J11*$B$13 -> 0 | K13: =+K11*$B$13 -> 0 | L13: =+L11*$B$13 -> 0 | ... BA13: =+BA11*$B$13 -> 0
A14: antes 11.75% | B14: 0.1175 | C14: PIS/COFINS | D14: =+D10*$B$14 -> 8.7344024 | E14: =+E11*$B$14 -> 0 | F14: =+F11*$B$14 -> 0 | G14: =+G11*$B$14 -> 0 | H14: =+H11*$B$14 -> 0 | I14: =+I11*$B$14 -> 0 | J14: =+J11*$B$14 -> 0 | K14: =+K11*$B$14 -> 0 | L14: =+L11*$B$14 -> 0 | ... R14: =+R11*$B$14 -> 0 | S14: 20 | T14: 20 | U14: 20 | V14: 20 | W14: 20 | X14: 20 | Y14: 20 | Z14: 20 | AA14: 20 | AB14: 20 | AC14: 20 | AD14: 20 | AE14: 20 | AF14: =AF11*$B$14 -> 43.633581 | AG14: =AG11*$B$14 -> 45.167342 | AH14: =AH11*$B$14 -> 51.928244 | AI14: =AI11*$B$14 -> 55.072078 | AJ14: =AJ11*$B$14 -> 56.094592 | AK14: =AK11*$B$14 -> 56.036134 | AL14: =AL11*$B$14 -> 53.974263 | AM14: =AM11*$B$14 -> 57.533245 | ... BA14: =BA11*$B$14 -> 366.41491
C15: ICMS | D15: 0 | E15: 0 | F15: 0 | G15: 0 | H15: 0 | I15: 0 | J15: 0 | K15: 0 | L15: 0 | M15: 0 | N15: 0 | O15: 0 | P15: 0 | Q15: 0 | R15: 1 | S15: 0 | T15: 0 | U15: 0 | V15: 0 | W15: 0 | X15: 0 | Y15: 0 | Z15: 0 | AA15: 0 | AB15: 0 | AC15: 0 | AD15: 0 | AE15: 0 | AF15: 0 | AG15: 0 | AH15: 0 | AI15: 0 | AJ15: 0 | AK15: 0 | AL15: 0 | AM15: 0 | AN15: 0 | AO15: 0 | AP15: 0 | AQ15: 0 | AR15: 0 | AS15: 0 | AT15: 0 | AU15: 0 | AV15: 0 | AW15: 0 | AX15: 0 | AY15: 0 | AZ15: 0 | BA15: 0
B16: 0.08 | C16: AFRMM | D16: 0 | E16: 0 | F16: 0 | G16: 0 | H16: =+H9*$B$16 -> 2.9881008 | I16: =+I9*$B$16 -> 2.9881008 | J16: =+J9*$B$16 -> 2.9881008 | K16: =+K9*$B$16 -> 2.9881008 | L16: =+L9*$B$16 -> 2.9881008 | M16: =+M9*$B$16 -> 2.9881008 | N16: =+N9*$B$16 -> 2.9881008 | O16: =+O9*$B$16 -> 2.9881008 | ... BA16: =+BA9*$B$16 -> 3.7872
C17: Cargo Cleared usd/cbm | D17: =SUM(D10:D16) -> 83.069742 | E17: =SUM(E11:E16) -> 0 | F17: =SUM(F11:F16) -> 0 | G17: =SUM(G11:G16) -> 0 | H17: =SUM(H11:H16) -> 2.9881008 | I17: =SUM(I11:I16) -> 2.9881008 | J17: =SUM(J11:J16) -> 2.9881008 | K17: =SUM(K11:K16) -> 2.9881008 | L17: =SUM(L11:L16) -> 2.9881008 | ... BA17: =SUM(BA11:BA16) -> 3488.6269
C19: Terminal cost (brl/cbm) | D19: 80 | E19: 80 | F19: 80 | G19: 80 | H19: 80 | I19: 80 | J19: 80 | K19: 80 | L19: 80 | M19: 80 | N19: 80 | O19: 80 | P19: 80 | Q19: 80 | R19: 80 | S19: 80 | T19: 80 | U19: 80 | V19: 80 | W19: 80 | X19: 80 | Y19: 80 | Z19: 80 | AA19: 80 | AB19: 80 | AC19: 80 | AD19: 80 | AE19: 80 | AF19: 80 | AG19: 80 | AH19: 80 | AI19: 80 | AJ19: 80 | AK19: 80 | AL19: 80 | AM19: 80 | AN19: 80 | AO19: 80 | AP19: 80 | AQ19: 80 | AR19: 80 | AS19: 80 | AT19: 80 | AU19: 80 | AV19: 80 | AW19: 80 | AX19: 80 | AY19: 80 | AZ19: 80 | BA19: 80
C20: Inspection (brl/cbm) | D20: 15 | E20: 15 | F20: 15 | G20: 15 | H20: 15 | I20: 15 | J20: 15 | K20: 15 | L20: 15 | M20: 15 | N20: 15 | O20: 15 | P20: 15 | Q20: 15 | R20: 15 | S20: 15 | T20: 15 | U20: 15 | V20: 15 | W20: 15 | X20: 15 | Y20: 15 | Z20: 15 | AA20: 15 | AB20: 15 | AC20: 15 | AD20: 15 | AE20: 15 | AF20: 15 | AG20: 15 | AH20: 15 | AI20: 15 | AJ20: 15 | AK20: 15 | AL20: 15 | AM20: 15 | AN20: 15 | AO20: 15 | AP20: 15 | AQ20: 15 | AR20: 15 | AS20: 15 | AT20: 15 | AU20: 15 | AV20: 15 | AW20: 15 | AX20: 15 | AY20: 15 | AZ20: 15 | BA20: 15
C21: Inland freight (brl/cbm) | D21: 25 | E21: 25 | F21: 25 | G21: 25 | H21: 25 | I21: 25 | J21: 25 | K21: 25 | L21: 25 | M21: 25 | N21: 25 | O21: 25 | P21: 25 | Q21: 25 | R21: 25 | S21: 25 | T21: 25 | U21: 25 | V21: 25 | W21: 25 | X21: 25 | Y21: 25 | Z21: 25 | AA21: 25 | AB21: 25 | AC21: 25 | AD21: 25 | AE21: 25 | AF21: 25 | AG21: 25 | AH21: 25 | AI21: 25 | AJ21: 25 | AK21: 25 | AL21: 25 | AM21: 25 | AN21: 25 | AO21: 25 | AP21: 25 | AQ21: 25 | AR21: 25 | AS21: 25 | AT21: 25 | AU21: 25 | AV21: 25 | AW21: 25 | AX21: 25 | AY21: 25 | AZ21: 25 | BA21: 25
C22: Other costs (brl/cbm)
C23: Margin (brl/cbm)
C25: EX Tank disport (brl/cbm) | D25: =SUM(D19:D24) -> 120 | E25: =SUM(E17:E24) -> 120 | F25: =SUM(F17:F24) -> 120 | G25: =SUM(G17:G24) -> 120 | H25: =SUM(H17:H24) -> 122.9881 | I25: =SUM(I17:I24) -> 122.9881 | J25: =SUM(J17:J24) -> 122.9881 | K25: =SUM(K17:K24) -> 122.9881 | L25: =SUM(L17:L24) -> 122.9881 | ... BA25: =SUM(BA17:BA24) -> 3608.6269
C26: EX Tank disport (usd/cbm) | E26: =+E25/E2 -> #DIV/0! | F26: =+F25/F2 -> #DIV/0! | G26: =+G25/G2 -> #DIV/0! | H26: =+H25/H2 -> #DIV/0! | I26: =+I25/I2 -> #DIV/0! | J26: =+J25/J2 -> #DIV/0! | K26: =+K25/K2 -> #DIV/0! | L26: =+L25/L2 -> #DIV/0! | ... BA26: =+BA25/BA2 -> 607.33191
C28: NE BRZ (brl/cbm) | D28: =+'PLATTS&OPIS'!I156 -> 4470 | E28: =+'PLATTS&OPIS'!I171 -> 4480 | G28: =+'PLATTS&OPIS'!I236 -> 3565 | H28: =+'PLATTS&OPIS'!I266 -> 4150 | I28: =+'PLATTS&OPIS'!I285 -> 4195 | J28: =+'PLATTS&OPIS'!I305 -> 4445 | K28: =+'PLATTS&OPIS'!I330 -> 4045 | L28: =+'PLATTS&OPIS'!I350 -> 4095 | M28: =+'PLATTS&OPIS'!I350 -> 4095 | N28: =+M28 -> 4095 | O28: =+N28 -> 4095 | P28: =+O28 -> 4095 | Q28: =+P28 -> 4095 | R28: =+'PLATTS&OPIS'!I485 -> 3450 | S28: =+'PLATTS&OPIS'!I505 -> 3580 | T28: =+'PLATTS&OPIS'!I554 -> 3895 | U28: =+T28 -> 3895 | V28: =+U28 -> 3895 | W28: =+'PLATTS&OPIS'!I584 -> 3600 | X28: =+'PLATTS&OPIS'!I609 -> 3140 | Y28: =+'PLATTS&OPIS'!I641 -> 3300 | Z28: =+'PLATTS&OPIS'!I654 -> 3295 | AA28: =+'PLATTS&OPIS'!I677 -> 2895 | AB28: =+'PLATTS&OPIS'!I699 -> 2720 | AC28: =+'PLATTS&OPIS'!I713 -> 2800 | AD28: =+'PLATTS&OPIS'!I740 -> 3065 | AE28: =+'PLATTS&OPIS'!I761 -> 3245 | AF28: =+'PLATTS&OPIS'!I781 -> 3205 | AG28: =+'PLATTS&OPIS'!I804 -> 3175 | AH28: =+'PLATTS&OPIS'!I827 -> 3200 | AI28: =+'PLATTS&OPIS'!I846 -> 3225 | AJ28: =+'PLATTS&OPIS'!I869 -> 3640 | AK28: =+'PLATTS&OPIS'!I892 -> 3495 | AL28: =+'PLATTS&OPIS'!I912 -> 3150 | AM28: =+'PLATTS&OPIS'!I936 -> 3030 | AN28: =+'PLATTS&OPIS'!I956 -> 3100 | AO28: =+'PLATTS&OPIS'!I968 -> 3370 | AP28: =+'PLATTS&OPIS'!I1000 -> 3655 | AQ28: =+'PLATTS&OPIS'!I1019 -> 3545 | AR28: =+'PLATTS&OPIS'!I1040 -> 3395 | AS28: =+'PLATTS&OPIS'!I1063 -> 3560 | AT28: =+'PLATTS&OPIS'!I1074 -> 3675 | AU28: =+AT28 -> 3675 | AV28: =+AU28 -> 3675 | AW28: =+AV28 -> 3675 | AX28: =+AW28 -> 3675 | AY28: =+AX28 -> 3675 | AZ28: =+AY28 -> 3675 | BA28: =+AZ28 -> 3675
C29: 0% import tax | D29: 44501 | E29: 44531 | F29: 44562 | G29: 44593 | H29: 44621 | I29: 44652 | J29: 44682 | K29: 44713 | L29: 44743 | M29: 44774 | N29: 44805 | O29: 44835 | P29: 44866 | Q29: 44896 | R29: 44927 | S29: 44958 | T29: 44986 | U29: 45017 | V29: 45047 | W29: 45078 | X29: 45108 | Y29: 45139 | Z29: 45170 | AA29: 45200 | AB29: 45231 | AC29: 45261 | AD29: 45292 | AE29: 45323 | AF29: 45352 | AG29: 45383 | AH29: 45413 | AI29: 45444 | AJ29: 45474 | AK29: 45505 | AL29: 45536 | AM29: 45566 | AN29: 45597 | AO29: 45627 | AP29: 45658 | AQ29: 45689 | AR29: 45717 | AS29: 45748 | AT29: 45778 | AU29: 45809 | AV29: 45839 | AW29: 45870 | AX29: 45901 | AY29: 45931 | AZ29: 45962 | BA29: 45992
C30: ARB (brl/cbm) | D30: =+D28-D25 -> 4350 | E30: =+E28-E25 -> 4360 | F30: =+F28-F25 -> -120 | G30: =+G28-G25 -> 3445 | H30: =+H28-H25 -> 4027.0119 | I30: =+I28-I25 -> 4072.0119 | J30: =+J28-J25 -> 4322.0119 | K30: =+K28-K25 -> 3922.0119 | ... BA30: =+BA28-BA25 -> 66.373111
C31: ARB (usd/cbm) | D31: =+D30/$E$1 -> #DIV/0! | E31: =+E30/E2 -> #DIV/0! | F31: =+F30/F2 -> #DIV/0! | G31: =+G30/G2 -> #DIV/0! | H31: =+H30/H2 -> #DIV/0! | I31: =+I30/I2 -> #DIV/0! | J31: =+J30/J2 -> #DIV/0! | K31: =+K30/K2 -> #DIV/0! | L31: =+L30/L2 -> #DIV/0! | ... BA31: =+BA30/BA2 -> 11.170595
C32: ARB (usd/gal) | H32: =+H31/264.172 -> #DIV/0! | I32: =+I31/264.172 -> #DIV/0! | J32: =+J31/264.172 -> #DIV/0! | K32: =+K31/264.172 -> #DIV/0! | L32: =+L31/264.172 -> #DIV/0! | M32: =+M31/264.172 -> #DIV/0! | N32: =+N31/264.172 -> #DIV/0! | O32: =+O31/264.172 -> #DIV/0! | ... BA32: =+BA31/264.172 -> 0.042285309
A34: NE incl mkt structure | C34: NE BRZ (brl/cbm) | D34: =+'PLATTS&OPIS'!I162 -> 0 | E34: =+'PLATTS&OPIS'!I177 -> 0 | G34: =+'PLATTS&OPIS'!I242 -> 0 | H34: =+'PLATTS&OPIS'!I272 -> 0 | I34: =+'PLATTS&OPIS'!I291 -> 0 | J34: =+'PLATTS&OPIS'!I311 -> 0 | K34: =+'PLATTS&OPIS'!I336 -> 0 | L34: =+'PLATTS&OPIS'!I356 -> 0 | M34: =+'PLATTS&OPIS'!I356 -> 0 | N34: =+M34 -> 0 | O34: =+N34 -> 0 | P34: =+O34 -> 0 | Q34: =+P34 -> 0 | R34: =+'PLATTS&OPIS'!I491 -> 0 | S34: =+'PLATTS&OPIS'!I511 -> 0 | T34: =+T28+T40 -> 6721 | U34: =+U28+U40 -> 6976 | V34: =+V28+V40 -> 6546.5 | W34: =+W28+W40 -> 3600 | X34: =+X28+X40 -> 5375.5 | Y34: =+Y28+Y40 -> 3300 | Z34: =+Y34+Z40 -> 3300 | AA34: =+Z34+AA40 -> 3300 | AB34: =+AB28+AB40 -> 2720 | AC34: =+AB34+AC40 -> 2720 | AD34: =+AC34+AD40 -> 2720 | AE34: =+AD34+AE40 -> 2720 | AF34: =+AF28+AF40 -> 3205 | AG34: =+AG28+AG40 -> 3175 | AH34: =+AH28+AH40 -> 3200 | AI34: =+AI28+AI40 -> 3225 | AJ34: =+AJ28+AJ40 -> 3640 | AK34: =+AK28+AK40 -> 3495 | AL34: =+AK34+AL40 -> 3495 | AM34: =+AM28+AM40 -> 3030 | AN34: =+AN28+AN40 -> 3100 | AO34: =+AO28+AO40 -> 3370 | AP34: =+AP28+AP40 -> 3655 | AQ34: =+AQ28+AQ40 -> 3545 | AR34: =+AR28+AR40 -> 3395 | AS34: =+AS28+AS40 -> 3560 | AT34: =+AT28+AT40 -> 3675 | AU34: =+AT34+AU40 -> 3624.5 | AV34: =+AU34+AV40 -> 3624.5 | AW34: =+AV34+AW40 -> 3637 | AX34: =+AW34+AX40 -> 3664 | AY34: =+AX34+AY40 -> 3713 | AZ34: =+AY34+AZ40 -> 3725.5 | BA34: =+AZ34+BA40 -> 3742
C35: 0% import tax | D35: 44501 | E35: 44531 | F35: 44562 | G35: 44593 | H35: 44621 | I35: 44652 | J35: 44682 | K35: 44713 | L35: 44743 | M35: 44774 | N35: 44805 | O35: 44835 | P35: 44866 | Q35: 44896 | R35: 44927 | S35: 44958 | T35: 44986 | U35: 45017 | V35: 45047 | W35: 45078 | X35: 45108 | Y35: 45139 | Z35: 45170 | AA35: 45200 | AB35: 45231 | AC35: 45261 | AD35: 45292 | AE35: 45323 | AF35: 45352 | AG35: 45383 | AH35: 45413 | AI35: 45444 | AJ35: 45474 | AK35: 45505 | AL35: 45536 | AM35: 45566 | AN35: 45597 | AO35: 45627 | AP35: 45658 | AQ35: 45689 | AR35: 45717 | AS35: 45748 | AT35: 45778 | AU35: 45809 | AV35: 45839 | AW35: 45870 | AX35: 45901 | AY35: 45931 | AZ35: 45962 | BA35: 45992
C36: ARB (brl/cbm) | D36: =+D34-D31 -> #DIV/0! | E36: =+E34-E31 -> #DIV/0! | F36: =+F34-F31 -> #DIV/0! | G36: =+G34-G31 -> #DIV/0! | H36: =+H34-H31 -> #DIV/0! | I36: =+I34-I31 -> #DIV/0! | J36: =+J34-J31 -> #DIV/0! | K36: =+K34-K31 -> #DIV/0! | ... S36: =+S34-S31 -> #DIV/0! | T36: =+T34-T25 -> 6578.0119 | U36: =+U34-U25 -> 6833.0119 | V36: =+V34-V25 -> 6403.5119 | W36: =+W34-W25 -> 3457.0119 | X36: =+X34-X25 -> 5232.5119 | Y36: =+Y34-Y25 -> 3157.0119 | Z36: =+Z34-Z25 -> 3157.0119 | AA36: =+AA34-AA25 -> 3157.0119 | ... BA36: =+BA34-BA25 -> 133.37311
C37: ARB (usd/cbm) | D37: =+D36/$E$1 -> #DIV/0! | E37: =+E36/E8 -> #DIV/0! | F37: =+F36/F8 -> #DIV/0! | G37: =+G36/G8 -> #DIV/0! | H37: =+H36/H8 -> #DIV/0! | I37: =+I36/I8 -> #DIV/0! | J37: =+J36/J8 -> #DIV/0! | K37: =+K36/K8 -> #DIV/0! | L37: =+L36/L8 -> #DIV/0! | ... S37: =+S36/S8 -> #DIV/0! | T37: =+T36/T2 -> #DIV/0! | U37: =+U36/U2 -> #DIV/0! | V37: =+V36/V2 -> #DIV/0! | W37: =+W36/W2 -> #DIV/0! | X37: =+X36/X2 -> #DIV/0! | Y37: =+Y36/Y2 -> #DIV/0! | Z37: =+Z36/Z2 -> #DIV/0! | AA37: =+AA36/AA2 -> #DIV/0! | ... BA37: =+BA36/BA2 -> 22.446695
C38: ARB (usd/gal) | H38: =+H37/264.172 -> #DIV/0! | I38: =+I37/264.172 -> #DIV/0! | J38: =+J37/264.172 -> #DIV/0! | K38: =+K37/264.172 -> #DIV/0! | L38: =+L37/264.172 -> #DIV/0! | M38: =+M37/264.172 -> #DIV/0! | N38: =+N37/264.172 -> #DIV/0! | O38: =+O37/264.172 -> #DIV/0! | ... BA38: =+BA37/264.172 -> 0.084969999
T40: ='settlement day'!AC12 -> 2826 | U40: ='settlement day'!AD12 -> 3081 | V40: ='settlement day'!AE12 -> 2651.5 | W40: 0 | X40: ='settlement day'!AG12 -> 2235.5 | Z40: 0 | AU40: =AU42-AT42 -> -50.5 | AV40: =AV42-AU42 -> 0 | AW40: =AW42-AV42 -> 12.5 | AX40: =AX42-AW42 -> 27 | AY40: =AY42-AX42 -> 49 | AZ40: =AZ42-AY42 -> 12.5 | BA40: =BA42-AZ42 -> 16.5
C41: load mth+1 | D41: 44531 | E41: 44562 | F41: 44593 | G41: 44621 | I41: 44652 | J41: 44682 | K41: 44713 | L41: 44743 | M41: 44774 | N41: 44805 | O41: 44835 | P41: 44866 | Q41: 44896 | R41: 44927 | S41: 44958 | T41: 44986 | U41: 45017 | V41: 45047 | W41: 45078 | X41: 45108 | Y41: 45139 | Z41: 45170 | AA41: 45200 | AB41: 45231 | AC41: 45261 | AD41: 45292 | AE41: 45323 | AF41: 45352 | AG41: 45383 | AH41: 45413 | AI41: 45444 | AJ41: 45474 | AK41: 45505 | AL41: 45536 | AM41: 45566 | AN41: 45597 | AO41: 45627 | AP41: 45658 | AQ41: 45689 | AR41: 45717 | AS41: 45748 | AT41: 45778 | AU41: 45809 | AV41: 45839 | AW41: 45870 | AX41: 45901 | AY41: 45931 | AZ41: 45962 | BA41: 45992
C42: B3 hyd | D42: =+'settlement day'!N13 -> 0 | E42: =+'settlement day'!O13 -> 0 | F42: =+'settlement day'!P13 -> 0 | G42: =+'settlement day'!Q13 -> 0 | I42: =+'settlement day'!R13 -> 0 | J42: =+'settlement day'!S13 -> 0 | K42: =+'settlement day'!T13 -> 0 | L42: =+'settlement day'!U13 -> 0 | M42: =+'settlement day'!V13 -> 0 | N42: =+'settlement day'!W13 -> 0 | O42: =+'settlement day'!X13 -> 0 | P42: =+'settlement day'!Y13 -> 0 | ... BA42: =+'settlement day'!BJ13 -> 2825
C43: B3 hyd ex plant | D43: =+(D42-'mkt data'!$G$23+'mkt data'!$G$24)/'mkt data'!$H$25 -> -99.524494 | E43: =+(E42-'mkt data'!$G$23+'mkt data'!$G$24)/'mkt data'!$H$25 -> -99.524494 | F43: =+(F42-'mkt data'!$G$23+'mkt data'!$G$24)/'mkt data'!$H$25 -> -99.524494 | G43: =+(G42-'mkt data'!$G$23+'mkt data'!$G$24)/'mkt data'!$H$25 -> -99.524494 | I43: =+(I42-'mkt data'!$G$23+'mkt data'!$G$24)/'mkt data'!$H$25 -> -99.524494 | J43: =+(J42-'mkt data'!$G$23+'mkt data'!$G$24)/'mkt data'!$H$25 -> -99.524494 | K43: =+(K42-'mkt data'!$G$23+'mkt data'!$G$24)/'mkt data'!$H$25 -> -99.524494 | L43: =+(L42-'mkt data'!$G$23+'mkt data'!$G$24)/'mkt data'!$H$25 -> -99.524494 | M43: =+(M42-'mkt data'!$G$23+'mkt data'!$G$24)/'mkt data'!$H$25 -> -99.524494 | N43: =+(N42-'mkt data'!$G$23+'mkt data'!$G$24)/'mkt data'!$H$25 -> -99.524494 | O43: =+(O42-'mkt data'!$G$23+'mkt data'!$G$24)/'mkt data'!$H$25 -> -99.524494 | P43: =+(P42-'mkt data'!$G$23+'mkt data'!$G$24)/'mkt data'!$H$25 -> -99.524494 | ... BA43: =+(BA42-'mkt data'!$G$23+'mkt data'!$G$24)/'mkt data'!$H$25 -> 3024.4388
B45: =+'mkt data'!G26 -> 0.12 | C45: B3 anydrous ex plant | D45: =+((D42-'mkt data'!$G$23)*'mkt data'!$H$26)+('mkt data'!$G$24) -> -100.8 | E45: =+((E42-'mkt data'!$G$23)*'mkt data'!$H$26)+('mkt data'!$G$24) -> -100.8 | F45: =+((F42-'mkt data'!$G$23)*'mkt data'!$H$26)+('mkt data'!$G$24) -> -100.8 | G45: =+((G42-'mkt data'!$G$23)*'mkt data'!$H$26)+('mkt data'!$G$24) -> -100.8 | I45: =+((I42-'mkt data'!$G$23)*'mkt data'!$H$26)+('mkt data'!$G$24) -> -100.8 | J45: =+((J42-'mkt data'!$G$23)*'mkt data'!$H$26)+('mkt data'!$G$24) -> -100.8 | K45: =+((K42-'mkt data'!$G$23)*'mkt data'!$H$26)+('mkt data'!$G$24) -> -100.8 | L45: =+((L42-'mkt data'!$G$23)*'mkt data'!$H$26)+('mkt data'!$G$24) -> -100.8 | M45: =+((M42-'mkt data'!$G$23)*'mkt data'!$H$26)+('mkt data'!$G$24) -> -100.8 | N45: =+((N42-'mkt data'!$G$23)*'mkt data'!$H$26)+('mkt data'!$G$24) -> -100.8 | O45: =+((O42-'mkt data'!$G$23)*'mkt data'!$H$26)+('mkt data'!$G$24) -> -100.8 | P45: =+((P42-'mkt data'!$G$23)*'mkt data'!$H$26)+('mkt data'!$G$24) -> -100.8 | ... BA45: =+((BA42-'mkt data'!$G$23)*'mkt data'!$H$26)+('mkt data'!$G$24) -> 3063.2
B47: =470/0.867 -> 542.09919 | C47: B3 CS to NE (brl/cbm) | D47: =+D45+$B$47 -> 441.29919 | E47: =+E45+$B$47 -> 441.29919 | F47: =+F45+$B$47 -> 441.29919 | G47: =+G45+$B$47 -> 441.29919 | I47: =+I45+$B$47 -> 441.29919 | J47: =+J45+$B$47 -> 441.29919 | K47: =+K45+$B$47 -> 441.29919 | L47: =+L45+$B$47 -> 441.29919 | M47: =+M45+$B$47 -> 441.29919 | N47: =+N45+$B$47 -> 441.29919 | O47: =+O45+$B$47 -> 441.29919 | P47: =+P45+$B$47 -> 441.29919 | ... BA47: =+BA45+$B$47 -> 3605.2992
D48: 44531 | E48: 44562 | F48: 44593 | G48: 44621 | I48: 44652 | J48: 44682 | K48: 44713 | L48: 44743 | M48: 44774 | N48: 44805 | O48: 44835 | P48: 44866 | Q48: 44896 | R48: 44927 | S48: 44958 | T48: 44986 | U48: 45017 | V48: 45047 | W48: 45078 | X48: 45108 | Y48: 45139 | Z48: 45170 | AA48: 45200 | AB48: 45231 | AC48: 45261 | AD48: 45292 | AE48: 45323 | AF48: 45352 | AG48: 45383 | AH48: 45413 | AI48: 45444 | AJ48: 45474 | AK48: 45505 | AL48: 45536 | AM48: 45566 | AN48: 45597 | AO48: 45627 | AP48: 45658 | AQ48: 45689 | AR48: 45717 | AS48: 45748 | AT48: 45778 | AU48: 45809 | AV48: 45839 | AW48: 45870 | AX48: 45901 | AY48: 45931 | AZ48: 45962 | BA48: 45992
C49: ARB (brl/cbm) | D49: =+D47-D25 -> 321.29919 | E49: =+E47-E25 -> 321.29919 | F49: =+F47-F25 -> 321.29919 | G49: =+G47-G25 -> 321.29919 | I49: =+I47-I25 -> 318.31109 | J49: =+J47-J25 -> 318.31109 | K49: =+K47-K25 -> 318.31109 | L49: =+L47-L25 -> 318.31109 | M49: =+M47-M25 -> 318.31109 | N49: =+N47-N25 -> 318.31109 | O49: =+O47-O25 -> 318.31109 | P49: =+P47-P25 -> 318.31109 | ... BA49: =+BA47-BA25 -> -3.3276959
C50: ARB (usd/cbm) | D50: =+D49/$E$1 -> #DIV/0! | E50: =+E49/E2 -> #DIV/0! | F50: =+F49/F2 -> #DIV/0! | G50: =+G49/G2 -> #DIV/0! | I50: =+I49/H2 -> #DIV/0! | J50: =+J49/I2 -> #DIV/0! | K50: =+K49/J2 -> #DIV/0! | L50: =+L49/L2 -> #DIV/0! | M50: =+M49/M2 -> #DIV/0! | N50: =+N49/N2 -> #DIV/0! | O50: =+O49/O2 -> #DIV/0! | P50: =+P49/P2 -> #DIV/0! | Q50: =+Q49/Q2 -> #DIV/0! | R50: =+R49/R2 -> #DIV/0! | S50: =+S49/S2 -> #DIV/0! | ... BA50: =+BA49/BA2 -> -0.56005122
C51: ARB (usd/gal) | I51: =+I50/264.172 -> #DIV/0! | J51: =+J50/264.172 -> #DIV/0! | K51: =+K50/264.172 -> #DIV/0! | L51: =+L50/264.172 -> #DIV/0! | M51: =+M50/264.172 -> #DIV/0! | N51: =+N50/264.172 -> #DIV/0! | O51: =+O50/264.172 -> #DIV/0! | P51: =+P50/264.172 -> #DIV/0! | ... BA51: =+BA50/264.172 -> -0.0021200249

Sheet mkt data
E2: BRAZIL | F2: A/H spread | G2: 0.11 | H2: 1.11 | K2: EU T1 bid (eur/cbm) | L2: -150
F3: Anhydrous CARB/ISCC premium (usd/cbm) | G3: 35 | K3: EU T2 bid (eur/cbm) | L3: 0
F4: Grade B qlt premium (brl/cbm) | G4: 150 | H4: 150 | K4: EU import duty (eur/cbm) | L4: 102
F5: Freight RB-Santos (brl/cbm) | G5: 300 | K5: EU extra import duty for US (eur/cbm) | L5: 0
F6: Freight RB-Paulinia (brl/cbm) | G6: 90
F7: Freight Paulinia-Santos (brl/cbm) | G7: 80
F8: Storage load port (brl/cbm) | G8: 0 | H8: 100 | K8: CS BRZ import cost (brl/cbm) | L8: =+L9+20 -> 130
F9: PIS COFINS | G9: 130.9 | K9: NE BRZ import cost (brl/cbm) | L9: 110
F10: ICMS SP | G10: 0.12 | H10: =+(100-12)/100 -> 0.88 | K10: Extra PIS/COFINS on imports BRZ (%) | L10: 0.1175
F11: INSS | G11: 0.0285
F12: Port Costs + Inspection BRZ (brl/cbm) | G12: 15 | H12: =10+5 -> 15
F14: USA basis U3 cert (cpg) | G14: 0.22 | K14: Conversion factor gallons to cbm | L14: 264.172
F15: USA basis ASTM (cpg) | G15: 0.08 | K15: Conversion usd/mt to usd/cbm (anhydrous) | L15: 0.789
F16: USA basis U5 (cpg) | G16: 0.12 | K16: Conversion usd/mt to usd/cbm (hydrous) | L16: 0.805
F17: USA basis PNS (cpg) | G17: 0.11
F18: USA basis GRADE B (cpg) | G18: 0.3
F22: B3
F23: Frete | G23: 90 | H23: R$/cbm
F24: PIS/COFINS | G24: 0 | H24: R$/cbm | I24: 130.9 | J24: >> PEC 15-16, no Pis/COFINS?
F25: ICMS | G25: 0.0957 | H25: 0.9043
F26: anh/hydrous | G26: 0.12 | H26: 1.12

Sheet settlement day
AM1: =+AM8*264.172/AM29 -> 387.34338
B2: Last settlement date:
B3: 45797 | C3: 44197 | D3: 44228 | E3: 44256 | F3: 44287 | G3: 44317 | H3: 44348 | I3: 44378 | J3: 44409 | K3: 44440 | L3: 44470 | M3: 44501 | N3: 44531 | O3: 44562 | P3: 44593 | Q3: 44621 | R3: 44652 | S3: 44682 | T3: 44713 | U3: 44743 | V3: 44774 | W3: 44805 | X3: 44835 | Y3: 44866 | Z3: 44896 | AA3: 44927 | AB3: 44958 | AC3: 44986 | AD3: 45017 | AE3: 45047 | AF3: 45078 | AG3: 45108 | AH3: 45139 | AI3: 45170 | AJ3: 45200 | AK3: 45231 | AL3: 45261 | AM3: 45292 | AN3: 45323 | AO3: 45352 | AP3: 45383 | AQ3: 45413 | AR3: 45444 | AS3: 45474 | AT3: 45505 | AU3: 45536 | AV3: 45566 | AW3: 45597 | AX3: 45627 | AY3: 45658 | AZ3: 45689 | BA3: 45717 | BB3: 45748 | BC3: 45778 | BD3: 45809 | BE3: 45839 | BF3: 45870 | BG3: 45901 | BH3: 45931 | BI3: 45962 | BJ3: 45992 | BK3: Q4 24 | BL3: Q1 25 | BM3: Q2 25 | BN3: Q3 25 | BO3: Q4 25
B4: EU T2 CME (Eur/cbm) | F4: =+(AVERAGE('[1]PLATTt & OPIt'!C6:C26)) -> #REF! | G4: =+(AVERAGE('PLATTS&OPIS'!C28:C46)) -> 635.15789 | H4: =+(AVERAGE('PLATTS&OPIS'!C48:C69)) -> 656.59091 | I4: 656.591 | J4: 660.56 | K4: 792.716 | L4: 987.179 | M4: 1276.807 | N4: 1060.917 | O4: 938.775 | P4: 946.188 | Q4: 1143.152 | R4: 1189.013 | S4: 1138.583 | T4: 1273.825 | U4: 1199.5 | V4: 1039.591 | W4: 997.405 | X4: 862.19 | Y4: 785.955 | Z4: 722.163 | AA4: 751.75 | AB4: 835.488 | AC4: 899.63 | AD4: 866.806 | AE4: 756.563 | AF4: 775.773 | AG4: 736.012 | AH4: 726.841 | AI4: 785.869 | AJ4: 813.386 | AK4: 685.023 | AL4: 601.987 | AM4: 605.795 | AN4: 633.667 | AO4: 676.85 | AP4: 685.095 | AQ4: 691.964 | AR4: 745.688 | AS4: 715.793 | AT4: 669.56 | AU4: 629.988 | AV4: 652.424 | AW4: 670.012 | AX4: 662.988 | AY4: 671.466 | AZ4: 688.088 | BA4: 671.56 | BB4: 645.275 | BD4: =+BC5-BD5 -> -8.667 | BE4: =+BD5-BE5 -> -10.333 | BF4: =+BE5-BF5 -> -8.334 | BG4: =+BF5-BG5 -> 3.667 | BH4: =+BG5-BH5 -> 5.333 | BI4: =+BH5-BI5 -> 6.334 | BJ4: =+BI5-BJ5 -> 6 | BL4: =+BK5-BL5 -> 0 | BM4: =+BL5-BM5 -> -403.77767 | BN4: =+BM5-BN5 -> -220.889 | BO4: =+BN5-BO5 -> 11.222333
B5: Settlement | C5: =+'T2'!C27 -> 0 | D5: =+'T2'!D27 -> 0 | E5: =+'T2'!E27 -> 0 | F5: =+'T2'!F70 -> 0 | G5: =+'T2'!G91 -> 0 | H5: =+'T2'!H139 -> 0 | I5: =+'T2'!I139 -> 0 | J5: =+'T2'!J139 -> 0 | K5: =+'T2'!K160 -> 0 | L5: =+'T2'!L202 -> 0 | M5: =+'T2'!M202 -> 0 | N5: =+'T2'!N244 -> 0 | O5: =+'T2'!O244 -> 0 | P5: =+'T2'!P270 -> 0 | Q5: =+'T2'!Q286 -> 0 | R5: =+'T2'!R310 -> 0 | S5: =INDEX('T2'!$A$4:$BB$1048576,MATCH('settlement day'!$B$3,'T2'!$A$4:$A$1048576,0),MATCH('settlement day'!S$3,'T2'!$A$4:$BB$4,0)) -> 0 | T5: =INDEX('T2'!$A$4:$BB$1048576,MATCH('settlement day'!$B$3,'T2'!$A$4:$A$1048576,0),MATCH('settlement day'!T$3,'T2'!$A$4:$BB$4,0)) -> 0 | U5: =INDEX('T2'!$A$4:$BB$1048576,MATCH('settlement day'!$B$3,'T2'!$A$4:$A$1048576,0),MATCH('settlement day'!U$3,'T2'!$A$4:$BB$4,0)) -> 0 | V5: =INDEX('T2'!$A$4:$BB$1048576,MATCH('settlement day'!$B$3,'T2'!$A$4:$A$1048576,0),MATCH('settlement day'!V$3,'T2'!$A$4:$BB$4,0)) -> 0 | W5: =INDEX('T2'!$A$4:$BB$1048576,MATCH('settlement day'!$B$3,'T2'!$A$4:$A$1048576,0),MATCH('settlement day'!W$3,'T2'!$A$4:$BB$4,0)) -> 0 | X5: =INDEX('T2'!$A$4:$BB$1048576,MATCH('settlement day'!$B$3,'T2'!$A$4:$A$1048576,0),MATCH('settlement day'!X$3,'T2'!$A$4:$BB$4,0)) -> 0 | Y5: =INDEX('T2'!$A$4:$BB$1048576,MATCH('settlement day'!$B$3,'T2'!$A$4:$A$1048576,0),MATCH('settlement day'!Y$3,'T2'!$A$4:$BB$4,0)) -> 0 | Z5: =INDEX('T2'!$A$4:$BB$1048576,MATCH('settlement day'!$B$3,'T2'!$A$4:$A$1048576,0),MATCH('settlement day'!Z$3,'T2'!$A$4:$BB$4,0)) -> 0 | ... BB5: =INDEX('T2'!$A$4:$BB$1048576,MATCH('settlement day'!$B$3,'T2'!$A$4:$A$1048576,0),MATCH('settlement day'!BB$3,'T2'!$A$4:$BB$4,0)) -> 0 | BC5: =INDEX('T2'!$A$4:$CC$1048576,MATCH('settlement day'!$B$3,'T2'!$A$4:$A$1048576,0),MATCH('settlement day'!BC$3,'T2'!$A$4:$CC$4,0)) -> 601.333 | BD5: =INDEX('T2'!$A$4:$CC$1048576,MATCH('settlement day'!$B$3,'T2'!$A$4:$A$1048576,0),MATCH('settlement day'!BD$3,'T2'!$A$4:$CC$4,0)) -> 610 | BE5: =INDEX('T2'!$A$4:$CC$1048576,MATCH('settlement day'!$B$3,'T2'!$A$4:$A$1048576,0),MATCH('settlement day'!BE$3,'T2'!$A$4:$CC$4,0)) -> 620.333 | BF5: =INDEX('T2'!$A$4:$CC$1048576,MATCH('settlement day'!$B$3,'T2'!$A$4:$A$1048576,0),MATCH('settlement day'!BF$3,'T2'!$A$4:$CC$4,0)) -> 628.667 | BG5: =INDEX('T2'!$A$4:$CC$1048576,MATCH('settlement day'!$B$3,'T2'!$A$4:$A$1048576,0),MATCH('settlement day'!BG$3,'T2'!$A$4:$CC$4,0)) -> 625 | BH5: =INDEX('T2'!$A$4:$CC$1048576,MATCH('settlement day'!$B$3,'T2'!$A$4:$A$1048576,0),MATCH('settlement day'!BH$3,'T2'!$A$4:$CC$4,0)) -> 619.667 | BI5: =INDEX('T2'!$A$4:$CC$1048576,MATCH('settlement day'!$B$3,'T2'!$A$4:$A$1048576,0),MATCH('settlement day'!BI$3,'T2'!$A$4:$CC$4,0)) -> 613.333 | BJ5: =INDEX('T2'!$A$4:$CC$1048576,MATCH('settlement day'!$B$3,'T2'!$A$4:$A$1048576,0),MATCH('settlement day'!BJ$3,'T2'!$A$4:$CC$4,0)) -> 607.333 | BK5: =SUM(AV5:AX5)/3 -> 0 | BL5: =SUM(AY5:BA5)/3 -> 0 | BM5: =SUM(BB5:BD5)/3 -> 403.77767 | BN5: =SUM(BE5:BG5)/3 -> 624.66667 | BO5: =SUM(BH5:BJ5)/3 -> 613.44433
B6: D-1 | C6: =+'T2'!C26 -> 0 | D6: =+'T2'!D26 -> 0 | E6: =+'T2'!E26 -> 0 | F6: =+'T2'!F69 -> 0 | G6: =+'T2'!G90 -> 0 | H6: =+'T2'!H138 -> 0 | I6: =+'T2'!I138 -> 0 | J6: =+'T2'!J138 -> 0 | K6: =+'T2'!K159 -> 0 | L6: =+'T2'!L201 -> 0 | M6: =+'T2'!M201 -> 0 | N6: =+'T2'!N243 -> 0 | O6: =+'T2'!O243 -> 0 | P6: =+'T2'!P269 -> 0 | Q6: =+'T2'!Q285 -> 0 | R6: =+'T2'!R309 -> 0 | S6: =OFFSET(INDEX('T2'!$A$4:$BB$1048576,MATCH('settlement day'!$B$3,'T2'!$A$4:$A$1048576,0),MATCH('settlement day'!S$3,'T2'!$A$4:$BB$4,0)),-1,0) -> 0 | T6: =OFFSET(INDEX('T2'!$A$4:$BB$1048576,MATCH('settlement day'!$B$3,'T2'!$A$4:$A$1048576,0),MATCH('settlement day'!T$3,'T2'!$A$4:$BB$4,0)),-1,0) -> 0 | U6: =OFFSET(INDEX('T2'!$A$4:$BB$1048576,MATCH('settlement day'!$B$3,'T2'!$A$4:$A$1048576,0),MATCH('settlement day'!U$3,'T2'!$A$4:$BB$4,0)),-1,0) -> 0 | V6: =OFFSET(INDEX('T2'!$A$4:$BB$1048576,MATCH('settlement day'!$B$3,'T2'!$A$4:$A$1048576,0),MATCH('settlement day'!V$3,'T2'!$A$4:$BB$4,0)),-1,0) -> 0 | W6: =OFFSET(INDEX('T2'!$A$4:$BB$1048576,MATCH('settlement day'!$B$3,'T2'!$A$4:$A$1048576,0),MATCH('settlement day'!W$3,'T2'!$A$4:$BB$4,0)),-1,0) -> 0 | X6: =OFFSET(INDEX('T2'!$A$4:$BB$1048576,MATCH('settlement day'!$B$3,'T2'!$A$4:$A$1048576,0),MATCH('settlement day'!X$3,'T2'!$A$4:$BB$4,0)),-1,0) -> 0 | Y6: =OFFSET(INDEX('T2'!$A$4:$BB$1048576,MATCH('settlement day'!$B$3,'T2'!$A$4:$A$1048576,0),MATCH('settlement day'!Y$3,'T2'!$A$4:$BB$4,0)),-1,0) -> 0 | Z6: =OFFSET(INDEX('T2'!$A$4:$BB$1048576,MATCH('settlement day'!$B$3,'T2'!$A$4:$A$1048576,0),MATCH('settlement day'!Z$3,'T2'!$A$4:$BB$4,0)),-1,0) -> 0 | ... BB6: =OFFSET(INDEX('T2'!$A$4:$BB$1048576,MATCH('settlement day'!$B$3,'T2'!$A$4:$A$1048576,0),MATCH('settlement day'!BB$3,'T2'!$A$4:$BB$4,0)),-1,0) -> 0 | BC6: =OFFSET(INDEX('T2'!$A$4:$CC$1048576,MATCH('settlement day'!$B$3,'T2'!$A$4:$A$1048576,0),MATCH('settlement day'!BC$3,'T2'!$A$4:$CC$4,0)),-1,0) -> 598.333 | BD6: =OFFSET(INDEX('T2'!$A$4:$CC$1048576,MATCH('settlement day'!$B$3,'T2'!$A$4:$A$1048576,0),MATCH('settlement day'!BD$3,'T2'!$A$4:$CC$4,0)),-1,0) -> 604 | BE6: =OFFSET(INDEX('T2'!$A$4:$CC$1048576,MATCH('settlement day'!$B$3,'T2'!$A$4:$A$1048576,0),MATCH('settlement day'!BE$3,'T2'!$A$4:$CC$4,0)),-1,0) -> 614.667 | BF6: =OFFSET(INDEX('T2'!$A$4:$CC$1048576,MATCH('settlement day'!$B$3,'T2'!$A$4:$A$1048576,0),MATCH('settlement day'!BF$3,'T2'!$A$4:$CC$4,0)),-1,0) -> 624.667 | BG6: =OFFSET(INDEX('T2'!$A$4:$CC$1048576,MATCH('settlement day'!$B$3,'T2'!$A$4:$A$1048576,0),MATCH('settlement day'!BG$3,'T2'!$A$4:$CC$4,0)),-1,0) -> 620.667 | BH6: =OFFSET(INDEX('T2'!$A$4:$CC$1048576,MATCH('settlement day'!$B$3,'T2'!$A$4:$A$1048576,0),MATCH('settlement day'!BH$3,'T2'!$A$4:$CC$4,0)),-1,0) -> 613.333 | BI6: =OFFSET(INDEX('T2'!$A$4:$CC$1048576,MATCH('settlement day'!$B$3,'T2'!$A$4:$A$1048576,0),MATCH('settlement day'!BI$3,'T2'!$A$4:$CC$4,0)),-1,0) -> 606.333 | BJ6: =OFFSET(INDEX('T2'!$A$4:$CC$1048576,MATCH('settlement day'!$B$3,'T2'!$A$4:$A$1048576,0),MATCH('settlement day'!BJ$3,'T2'!$A$4:$CC$4,0)),-1,0) -> 600.667 | BK6: =SUM(AV6:AX6)/3 -> 0 | BL6: =SUM(AY6:BA6)/3 -> 0 | BM6: =SUM(BB6:BD6)/3 -> 400.77767 | BN6: =SUM(BE6:BG6)/3 -> 620.00033 | BO6: =SUM(BH6:BJ6)/3 -> 606.77767
B7: Variation | C7: =C5-C6 -> 0 | D7: =D5-D6 -> 0 | E7: =E5-E6 -> 0 | F7: =F5-F6 -> 0 | G7: =G5-G6 -> 0 | H7: =H5-H6 -> 0 | I7: =I5-I6 -> 0 | J7: =J5-J6 -> 0 | ... BO7: =BO5-BO6 -> 6.6666667
B8: US CU CME (US$/gal) | F8: =AVERAGE('PLATTS&OPIS'!B6:B26)/100 -> 2.1193095 | G8: =AVERAGE('PLATTS&OPIS'!B28:B46)/100 -> 2.551 | H8: =AVERAGE('PLATTS&OPIS'!B48:B69)/100 -> 2.3812045 | I8: 2.23 | J8: 2.24732 | K8: 2.41169 | L8: 2.60193 | M8: 3.4042 | N8: 2.973 | O8: 2.15903 | P8: 2.15674 | Q8: 2.46807 | R8: 2.63575 | S8: 2.75574 | T8: 2.78986 | U8: 2.51938 | V8: 2.54667 | W8: 2.44292 | X8: 2.46457 | Y8: 2.57873 | Z8: 2.20306 | AA8: 2.19058 | AB8: 2.17318 | AC8: 2.24302 | AD8: 2.42224 | AE8: 2.43773 | AF8: 2.50714 | AG8: 2.44342 | AH8: 2.1663 | AI8: 2.35293 | AJ8: 2.27059 | AK8: 1.86235 | AL8: 1.66878 | AM8: 1.58898 | AN8: 1.50218 | AO8: 1.5776 | AP8: 1.65439 | AQ8: 1.78299 | AR8: 1.92958 | AS8: 1.90324 | AT8: 1.826 | AU8: 1.69903 | AV8: 1.56505 | AW8: 1.62655 | AX8: 1.62131 | AY8: 1.68214 | AZ8: 1.75087 | BA8: 1.7022 | BB8: 1.77026 | BD8: =+BC9-BD9 -> -0.0375 | BE8: =+BD9-BE9 -> -0.015 | BF8: =+BE9-BF9 -> 0.0025 | BG8: =+BF9-BG9 -> 0.015 | BH8: =+BG9-BH9 -> 0.0375 | BI8: =+BH9-BI9 -> 0.035 | BJ8: =+BI9-BJ9 -> 0.025 | BL8: =+BK9-BL9 -> 0 | BM8: =+BL9-BM9 -> -1.1658333 | BN8: =+BM9-BN9 -> -0.61 | BO8: =+BN9-BO9 -> 0.08 | BR8: Apr | BS8: May | BT8: Jun
B9: Last settlement | C9: =+CU!D27 -> 0 | D9: =+CU!E27 -> 0 | E9: =+CU!F27 -> 0 | F9: =+CU!G70 -> 0 | G9: =+CU!H91 -> 0 | H9: =+CU!I139 -> 0 | I9: =+CU!J139 -> 0 | J9: =+CU!K139 -> 0 | K9: =+CU!L160 -> 0 | L9: =+CU!M202 -> 0 | M9: =+CU!N202 -> 0 | N9: =+CU!O244 -> 0 | O9: =+CU!P244 -> 0 | P9: =+CU!Q269 -> 0 | Q9: =+CU!R286 -> 0 | R9: =+CU!S310 -> 0 | S9: =INDEX(CU!$A$4:$BB$1048576,MATCH('settlement day'!$B$3,CU!$A$4:$A$1048576,0),MATCH('settlement day'!S$3,CU!$A$4:$BB$4,0)) -> 0 | T9: =INDEX(CU!$A$4:$BB$1048576,MATCH('settlement day'!$B$3,CU!$A$4:$A$1048576,0),MATCH('settlement day'!T$3,CU!$A$4:$BB$4,0)) -> 0 | U9: =INDEX(CU!$A$4:$BB$1048576,MATCH('settlement day'!$B$3,CU!$A$4:$A$1048576,0),MATCH('settlement day'!U$3,CU!$A$4:$BB$4,0)) -> 0 | V9: =INDEX(CU!$A$4:$BB$1048576,MATCH('settlement day'!$B$3,CU!$A$4:$A$1048576,0),MATCH('settlement day'!V$3,CU!$A$4:$BB$4,0)) -> 0 | W9: =INDEX(CU!$A$4:$BB$1048576,MATCH('settlement day'!$B$3,CU!$A$4:$A$1048576,0),MATCH('settlement day'!W$3,CU!$A$4:$BB$4,0)) -> 0 | X9: =INDEX(CU!$A$4:$BB$1048576,MATCH('settlement day'!$B$3,CU!$A$4:$A$1048576,0),MATCH('settlement day'!X$3,CU!$A$4:$BB$4,0)) -> 0 | Y9: =INDEX(CU!$A$4:$BB$1048576,MATCH('settlement day'!$B$3,CU!$A$4:$A$1048576,0),MATCH('settlement day'!Y$3,CU!$A$4:$BB$4,0)) -> 0 | Z9: =INDEX(CU!$A$4:$BB$1048576,MATCH('settlement day'!$B$3,CU!$A$4:$A$1048576,0),MATCH('settlement day'!Z$3,CU!$A$4:$BB$4,0)) -> 0 | ... BA9: =INDEX(CU!$A$4:$BB$1048576,MATCH('settlement day'!$B$3,CU!$A$4:$A$1048576,0),MATCH('settlement day'!BA$3,CU!$A$4:$BB$4,0)) -> 0 | BB9: =INDEX(CU!$A$4:$CC$1048576,MATCH('settlement day'!$B$3,CU!$A$4:$A$1048576,0),MATCH('settlement day'!BB$3,CU!$A$4:$CC$4,0)) -> 0 | BC9: =INDEX(CU!$A$4:$CC$1048576,MATCH('settlement day'!$B$3,CU!$A$4:$A$1048576,0),MATCH('settlement day'!BC$3,CU!$A$4:$CC$4,0)) -> 1.73 | BD9: =INDEX(CU!$A$4:$CC$1048576,MATCH('settlement day'!$B$3,CU!$A$4:$A$1048576,0),MATCH('settlement day'!BD$3,CU!$A$4:$CC$4,0)) -> 1.7675 | BE9: =INDEX(CU!$A$4:$CC$1048576,MATCH('settlement day'!$B$3,CU!$A$4:$A$1048576,0),MATCH('settlement day'!BE$3,CU!$A$4:$CC$4,0)) -> 1.7825 | BF9: =INDEX(CU!$A$4:$CC$1048576,MATCH('settlement day'!$B$3,CU!$A$4:$A$1048576,0),MATCH('settlement day'!BF$3,CU!$A$4:$CC$4,0)) -> 1.78 | BG9: =INDEX(CU!$A$4:$CC$1048576,MATCH('settlement day'!$B$3,CU!$A$4:$A$1048576,0),MATCH('settlement day'!BG$3,CU!$A$4:$CC$4,0)) -> 1.765 | BH9: =INDEX(CU!$A$4:$CC$1048576,MATCH('settlement day'!$B$3,CU!$A$4:$A$1048576,0),MATCH('settlement day'!BH$3,CU!$A$4:$CC$4,0)) -> 1.7275 | BI9: =INDEX(CU!$A$4:$CC$1048576,MATCH('settlement day'!$B$3,CU!$A$4:$A$1048576,0),MATCH('settlement day'!BI$3,CU!$A$4:$CC$4,0)) -> 1.6925 | BJ9: =INDEX(CU!$A$4:$CC$1048576,MATCH('settlement day'!$B$3,CU!$A$4:$A$1048576,0),MATCH('settlement day'!BJ$3,CU!$A$4:$CC$4,0)) -> 1.6675 | BK9: =SUM(AV9:AX9)/3 -> 0 | BL9: =SUM(AY9:BA9)/3 -> 0 | BM9: =SUM(BB9:BD9)/3 -> 1.1658333 | BN9: =SUM(BE9:BG9)/3 -> 1.7758333 | BO9: =SUM(BH9:BJ9)/3 -> 1.6958333 | BR9: 1.7675 | BS9: 1.785 | BT9: 1.7875 | BU9: CHIP
B10: day before D-1 | C10: =+CU!D26 -> 0 | D10: =+CU!E26 -> 0 | E10: =+CU!F26 -> 0 | F10: =+CU!G69 -> 0 | G10: =+CU!H90 -> 0 | H10: =+CU!I138 -> 0 | I10: =+CU!J138 -> 0 | J10: =+CU!K138 -> 0 | K10: =+CU!L159 -> 0 | L10: =+CU!M201 -> 0 | M10: =+CU!N201 -> 0 | N10: =+CU!O243 -> 0 | O10: =+CU!P243 -> 0 | P10: =+CU!Q267 -> 0 | Q10: =+CU!R285 -> 0 | R10: =+CU!S309 -> 0 | S10: =OFFSET(INDEX(CU!$A$4:$BB$1048576,MATCH('settlement day'!$B$3,CU!$A$4:$A$1048576,0),MATCH('settlement day'!S$3,CU!$A$4:$BB$4,0)),-1,0) -> 0 | T10: =OFFSET(INDEX(CU!$A$4:$BB$1048576,MATCH('settlement day'!$B$3,CU!$A$4:$A$1048576,0),MATCH('settlement day'!T$3,CU!$A$4:$BB$4,0)),-1,0) -> 0 | U10: =OFFSET(INDEX(CU!$A$4:$BB$1048576,MATCH('settlement day'!$B$3,CU!$A$4:$A$1048576,0),MATCH('settlement day'!U$3,CU!$A$4:$BB$4,0)),-1,0) -> 0 | V10: =OFFSET(INDEX(CU!$A$4:$BB$1048576,MATCH('settlement day'!$B$3,CU!$A$4:$A$1048576,0),MATCH('settlement day'!V$3,CU!$A$4:$BB$4,0)),-1,0) -> 0 | W10: =OFFSET(INDEX(CU!$A$4:$BB$1048576,MATCH('settlement day'!$B$3,CU!$A$4:$A$1048576,0),MATCH('settlement day'!W$3,CU!$A$4:$BB$4,0)),-1,0) -> 0 | X10: =OFFSET(INDEX(CU!$A$4:$BB$1048576,MATCH('settlement day'!$B$3,CU!$A$4:$A$1048576,0),MATCH('settlement day'!X$3,CU!$A$4:$BB$4,0)),-1,0) -> 0 | Y10: =OFFSET(INDEX(CU!$A$4:$BB$1048576,MATCH('settlement day'!$B$3,CU!$A$4:$A$1048576,0),MATCH('settlement day'!Y$3,CU!$A$4:$BB$4,0)),-1,0) -> 0 | Z10: =OFFSET(INDEX(CU!$A$4:$BB$1048576,MATCH('settlement day'!$B$3,CU!$A$4:$A$1048576,0),MATCH('settlement day'!Z$3,CU!$A$4:$BB$4,0)),-1,0) -> 0 | ... BA10: =OFFSET(INDEX(CU!$A$4:$BB$1048576,MATCH('settlement day'!$B$3,CU!$A$4:$A$1048576,0),MATCH('settlement day'!BA$3,CU!$A$4:$BB$4,0)),-1,0) -> 0 | BB10: =OFFSET(INDEX(CU!$A$4:$CC$1048576,MATCH('settlement day'!$B$3,CU!$A$4:$A$1048576,0),MATCH('settlement day'!BB$3,CU!$A$4:$CC$4,0)),-1,0) -> 0 | BC10: =OFFSET(INDEX(CU!$A$4:$CC$1048576,MATCH('settlement day'!$B$3,CU!$A$4:$A$1048576,0),MATCH('settlement day'!BC$3,CU!$A$4:$CC$4,0)),-1,0) -> 1.7275 | BD10: =OFFSET(INDEX(CU!$A$4:$CC$1048576,MATCH('settlement day'!$B$3,CU!$A$4:$A$1048576,0),MATCH('settlement day'!BD$3,CU!$A$4:$CC$4,0)),-1,0) -> 1.7425 | BE10: =OFFSET(INDEX(CU!$A$4:$CC$1048576,MATCH('settlement day'!$B$3,CU!$A$4:$A$1048576,0),MATCH('settlement day'!BE$3,CU!$A$4:$CC$4,0)),-1,0) -> 1.7575 | BF10: =OFFSET(INDEX(CU!$A$4:$CC$1048576,MATCH('settlement day'!$B$3,CU!$A$4:$A$1048576,0),MATCH('settlement day'!BF$3,CU!$A$4:$CC$4,0)),-1,0) -> 1.7575 | BG10: =OFFSET(INDEX(CU!$A$4:$CC$1048576,MATCH('settlement day'!$B$3,CU!$A$4:$A$1048576,0),MATCH('settlement day'!BG$3,CU!$A$4:$CC$4,0)),-1,0) -> 1.745 | BH10: =OFFSET(INDEX(CU!$A$4:$CC$1048576,MATCH('settlement day'!$B$3,CU!$A$4:$A$1048576,0),MATCH('settlement day'!BH$3,CU!$A$4:$CC$4,0)),-1,0) -> 1.7125 | BI10: =OFFSET(INDEX(CU!$A$4:$CC$1048576,MATCH('settlement day'!$B$3,CU!$A$4:$A$1048576,0),MATCH('settlement day'!BI$3,CU!$A$4:$CC$4,0)),-1,0) -> 1.68 | BJ10: =OFFSET(INDEX(CU!$A$4:$CC$1048576,MATCH('settlement day'!$B$3,CU!$A$4:$A$1048576,0),MATCH('settlement day'!BJ$3,CU!$A$4:$CC$4,0)),-1,0) -> 1.655 | BK10: =SUM(AV10:AX10)/3 -> 0 | BL10: =SUM(AY10:BA10)/3 -> 0 | BM10: =SUM(BB10:BD10)/3 -> 1.1566667 | BN10: =SUM(BE10:BG10)/3 -> 1.7533333 | BO10: =SUM(BH10:BJ10)/3 -> 1.6825 | BR10: 0.25 | BS10: 0.25 | BT10: 0.25 | BU10: basis
B11: Variation | C11: =C9-C10 -> 0 | D11: =D9-D10 -> 0 | E11: =E9-E10 -> 0 | F11: =F9-F10 -> 0 | G11: =G9-G10 -> 0 | H11: =H9-H10 -> 0 | I11: =I9-I10 -> 0 | J11: =J9-J10 -> 0 | ... BJ11: =BJ9-BJ10 -> 0.0125 | BK11: =+BK9-BK10 -> 0 | BL11: =+BL9-BL10 -> 0 | BM11: =+BM9-BM10 -> 0.0091666667 | BN11: =+BN9-BN10 -> 0.0225 | BO11: =+BO9-BO10 -> 0.013333333 | BR11: 0.15 | BS11: 0.15 | BT11: 0.15 | BU11: freight US-EU
B12: B3 ETH (R$/cbm) | F12: =AVERAGE('B3 ETH'!H22:H26) -> 2726.8 | G12: =AVERAGE('[2]ESALr Paulinia'!B2808:B2812) -> #REF! | H12: =+'ESALQ Paulinia'!E2834 -> 2873.9 | I12: 3023 | J12: 3273 | K12: 3365.5 | L12: 3897.5 | M12: 3587.5 | N12: 3403 | O12: 3179 | P12: 2936 | Q12: 3478.5 | R12: 3594.5 | S12: 3244 | T12: 3080 | U12: 3035 | V12: 2478 | W12: 2580.5 | X12: 2795 | Y12: 2895 | Z12: 2971.5 | AA12: 2852 | AB12: 2819.5 | AC12: 2826 | AD12: 3081 | AE12: 2651.5 | AF12: 2613 | AG12: 2235.5 | AH12: 2303 | AI12: 2276 | AJ12: 2317.5 | AK12: 2177 | AL12: 2004 | AM12: 2247.5 | AN12: 2235 | AO12: 2380 | AP12: 2427.5 | AQ12: 2406.5 | AR12: 2564 | AS12: 2692.5 | AT12: 2677 | AU12: 2600.5 | AV12: 2705.5 | AW12: 2726.5 | AX12: 2745.5 | AY12: 2986 | AZ12: 2945 | BA12: 2834 | BB12: 2807 | BD12: =+BC13-BD13 -> 50.5 | BE12: =+BD13-BE13 -> 0 | BF12: =+BE13-BF13 -> -12.5 | BG12: =+BF13-BG13 -> -27 | BH12: =+BG13-BH13 -> -49 | BI12: =+BH13-BI13 -> -12.5 | BJ12: =+BI13-BJ13 -> -16.5 | BL12: =+BK13-BL13 -> 0 | BM12: =+BL13-BM13 -> -1821.8333 | BN12: =+BM13-BN13 -> -903 | BO12: =+BN13-BO13 -> -85 | BR12: =BR9+BR10+BR11 -> 2.1675 | BS12: =BS9+BS10+BS11 -> 2.185 | BT12: =BT9+BT10+BT11 -> 2.1875 | BU12: usd/gal
B13: Last settlement | C13: =+'B3 ETH'!E27 -> 0 | D13: =+'B3 ETH'!F27 -> 0 | E13: =+'B3 ETH'!G27 -> 0 | F13: =+'B3 ETH'!H70 -> 0 | G13: =+'B3 ETH'!I91 -> 0 | H13: =+'B3 ETH'!J139 -> 0 | I13: =+'B3 ETH'!K139 -> 0 | J13: =+'B3 ETH'!L139 -> 0 | K13: =+'B3 ETH'!M160 -> 0 | L13: =+'B3 ETH'!N202 -> 0 | M13: =+'B3 ETH'!O202 -> 0 | N13: =+'B3 ETH'!P244 -> 0 | O13: =+'B3 ETH'!Q244 -> 0 | P13: =+'B3 ETH'!R268 -> 0 | Q13: =+'B3 ETH'!S286 -> 0 | R13: =+'B3 ETH'!T310 -> 0 | S13: =INDEX('B3 ETH'!$A$4:$BB$1048576,MATCH('settlement day'!$B$3,'B3 ETH'!$A$4:$A$1048576,0),MATCH('settlement day'!S$3,'B3 ETH'!$A$4:$BB$4,0)) -> 0 | T13: =INDEX('B3 ETH'!$A$4:$BB$1048576,MATCH('settlement day'!$B$3,'B3 ETH'!$A$4:$A$1048576,0),MATCH('settlement day'!T$3,'B3 ETH'!$A$4:$BB$4,0)) -> 0 | U13: =INDEX('B3 ETH'!$A$4:$BB$1048576,MATCH('settlement day'!$B$3,'B3 ETH'!$A$4:$A$1048576,0),MATCH('settlement day'!U$3,'B3 ETH'!$A$4:$BB$4,0)) -> 0 | V13: =INDEX('B3 ETH'!$A$4:$BB$1048576,MATCH('settlement day'!$B$3,'B3 ETH'!$A$4:$A$1048576,0),MATCH('settlement day'!V$3,'B3 ETH'!$A$4:$BB$4,0)) -> 0 | W13: =INDEX('B3 ETH'!$A$4:$BB$1048576,MATCH('settlement day'!$B$3,'B3 ETH'!$A$4:$A$1048576,0),MATCH('settlement day'!W$3,'B3 ETH'!$A$4:$BB$4,0)) -> 0 | X13: =INDEX('B3 ETH'!$A$4:$BB$1048576,MATCH('settlement day'!$B$3,'B3 ETH'!$A$4:$A$1048576,0),MATCH('settlement day'!X$3,'B3 ETH'!$A$4:$BB$4,0)) -> 0 | Y13: =INDEX('B3 ETH'!$A$4:$BB$1048576,MATCH('settlement day'!$B$3,'B3 ETH'!$A$4:$A$1048576,0),MATCH('settlement day'!Y$3,'B3 ETH'!$A$4:$BB$4,0)) -> 0 | Z13: =INDEX('B3 ETH'!$A$4:$BB$1048576,MATCH('settlement day'!$B$3,'B3 ETH'!$A$4:$A$1048576,0),MATCH('settlement day'!Z$3,'B3 ETH'!$A$4:$BB$4,0)) -> 0 | ... AZ13: =INDEX('B3 ETH'!$A$4:$BB$1048576,MATCH('settlement day'!$B$3,'B3 ETH'!$A$4:$A$1048576,0),MATCH('settlement day'!AZ$3,'B3 ETH'!$A$4:$BB$4,0)) -> 0 | BA13: =INDEX('B3 ETH'!$A$4:$CC$1048576,MATCH('settlement day'!$B$3,'B3 ETH'!$A$4:$A$1048576,0),MATCH('settlement day'!BA$3,'B3 ETH'!$A$4:$CC$4,0)) -> 0 | BB13: =INDEX('B3 ETH'!$A$4:$CC$1048576,MATCH('settlement day'!$B$3,'B3 ETH'!$A$4:$A$1048576,0),MATCH('settlement day'!BB$3,'B3 ETH'!$A$4:$CC$4,0)) -> 0 | BC13: =INDEX('B3 ETH'!$A$4:$CC$1048576,MATCH('settlement day'!$B$3,'B3 ETH'!$A$4:$A$1048576,0),MATCH('settlement day'!BC$3,'B3 ETH'!$A$4:$CC$4,0)) -> 2758 | BD13: =INDEX('B3 ETH'!$A$4:$CC$1048576,MATCH('settlement day'!$B$3,'B3 ETH'!$A$4:$A$1048576,0),MATCH('settlement day'!BD$3,'B3 ETH'!$A$4:$CC$4,0)) -> 2707.5 | BE13: =INDEX('B3 ETH'!$A$4:$CC$1048576,MATCH('settlement day'!$B$3,'B3 ETH'!$A$4:$A$1048576,0),MATCH('settlement day'!BE$3,'B3 ETH'!$A$4:$CC$4,0)) -> 2707.5 | BF13: =INDEX('B3 ETH'!$A$4:$CC$1048576,MATCH('settlement day'!$B$3,'B3 ETH'!$A$4:$A$1048576,0),MATCH('settlement day'!BF$3,'B3 ETH'!$A$4:$CC$4,0)) -> 2720 | BG13: =INDEX('B3 ETH'!$A$4:$CC$1048576,MATCH('settlement day'!$B$3,'B3 ETH'!$A$4:$A$1048576,0),MATCH('settlement day'!BG$3,'B3 ETH'!$A$4:$CC$4,0)) -> 2747 | BH13: =INDEX('B3 ETH'!$A$4:$CC$1048576,MATCH('settlement day'!$B$3,'B3 ETH'!$A$4:$A$1048576,0),MATCH('settlement day'!BH$3,'B3 ETH'!$A$4:$CC$4,0)) -> 2796 | ... BJ13: =INDEX('B3 ETH'!$A$4:$CC$1048576,MATCH('settlement day'!$B$3,'B3 ETH'!$A$4:$A$1048576,0),MATCH('settlement day'!BJ$3,'B3 ETH'!$A$4:$CC$4,0)) -> 2825 | BK13: =SUM(AV13:AX13)/3 -> 0 | BL13: =SUM(AY13:BA13)/3 -> 0 | BM13: =SUM(BB13:BD13)/3 -> 1821.8333 | BN13: =SUM(BE13:BG13)/3 -> 2724.8333 | BO13: =SUM(BH13:BJ13)/3 -> 2809.8333 | BR13: =BR12*264.172 -> 572.59281 | BS13: =BS12*264.172 -> 577.21582 | BT13: =BT12*264.172 -> 577.87625 | BU13: usd/cbm
B14: day before D-1 | C14: =+'B3 ETH'!E26 -> 0 | D14: =+'B3 ETH'!F26 -> 0 | E14: =+'B3 ETH'!G26 -> 0 | F14: =+'B3 ETH'!H69 -> 0 | G14: =+'B3 ETH'!I90 -> 0 | H14: =+'B3 ETH'!J138 -> 0 | I14: =+'B3 ETH'!K138 -> 0 | J14: =+'B3 ETH'!L138 -> 0 | K14: =+'B3 ETH'!M159 -> 0 | L14: =+'B3 ETH'!N201 -> 0 | M14: =+'B3 ETH'!O201 -> 0 | N14: =+'B3 ETH'!P243 -> 0 | O14: =+'B3 ETH'!Q243 -> 0 | P14: =+'B3 ETH'!R267 -> 0 | Q14: =+'B3 ETH'!S285 -> 0 | R14: =+'B3 ETH'!T309 -> 0 | S14: =OFFSET(INDEX('B3 ETH'!$A$4:$BB$1048576,MATCH('settlement day'!$B$3,'B3 ETH'!$A$4:$A$1048576,0),MATCH('settlement day'!S$3,'B3 ETH'!$A$4:$BB$4,0)),-1,0) -> 0 | T14: =OFFSET(INDEX('B3 ETH'!$A$4:$BB$1048576,MATCH('settlement day'!$B$3,'B3 ETH'!$A$4:$A$1048576,0),MATCH('settlement day'!T$3,'B3 ETH'!$A$4:$BB$4,0)),-1,0) -> 0 | U14: =OFFSET(INDEX('B3 ETH'!$A$4:$BB$1048576,MATCH('settlement day'!$B$3,'B3 ETH'!$A$4:$A$1048576,0),MATCH('settlement day'!U$3,'B3 ETH'!$A$4:$BB$4,0)),-1,0) -> 0 | V14: =OFFSET(INDEX('B3 ETH'!$A$4:$BB$1048576,MATCH('settlement day'!$B$3,'B3 ETH'!$A$4:$A$1048576,0),MATCH('settlement day'!V$3,'B3 ETH'!$A$4:$BB$4,0)),-1,0) -> 0 | W14: =OFFSET(INDEX('B3 ETH'!$A$4:$BB$1048576,MATCH('settlement day'!$B$3,'B3 ETH'!$A$4:$A$1048576,0),MATCH('settlement day'!W$3,'B3 ETH'!$A$4:$BB$4,0)),-1,0) -> 0 | X14: =OFFSET(INDEX('B3 ETH'!$A$4:$BB$1048576,MATCH('settlement day'!$B$3,'B3 ETH'!$A$4:$A$1048576,0),MATCH('settlement day'!X$3,'B3 ETH'!$A$4:$BB$4,0)),-1,0) -> 0 | Y14: =OFFSET(INDEX('B3 ETH'!$A$4:$BB$1048576,MATCH('settlement day'!$B$3,'B3 ETH'!$A$4:$A$1048576,0),MATCH('settlement day'!Y$3,'B3 ETH'!$A$4:$BB$4,0)),-1,0) -> 0 | Z14: =OFFSET(INDEX('B3 ETH'!$A$4:$BB$1048576,MATCH('settlement day'!$B$3,'B3 ETH'!$A$4:$A$1048576,0),MATCH('settlement day'!Z$3,'B3 ETH'!$A$4:$BB$4,0)),-1,0) -> 0 | ... AZ14: =OFFSET(INDEX('B3 ETH'!$A$4:$BB$1048576,MATCH('settlement day'!$B$3,'B3 ETH'!$A$4:$A$1048576,0),MATCH('settlement day'!AZ$3,'B3 ETH'!$A$4:$BB$4,0)),-1,0) -> 0 | BA14: =OFFSET(INDEX('B3 ETH'!$A$4:$CC$1048576,MATCH('settlement day'!$B$3,'B3 ETH'!$A$4:$A$1048576,0),MATCH('settlement day'!BA$3,'B3 ETH'!$A$4:$CC$4,0)),-1,0) -> 0 | BB14: =OFFSET(INDEX('B3 ETH'!$A$4:$CC$1048576,MATCH('settlement day'!$B$3,'B3 ETH'!$A$4:$A$1048576,0),MATCH('settlement day'!BB$3,'B3 ETH'!$A$4:$CC$4,0)),-1,0) -> 0 | BC14: =OFFSET(INDEX('B3 ETH'!$A$4:$CC$1048576,MATCH('settlement day'!$B$3,'B3 ETH'!$A$4:$A$1048576,0),MATCH('settlement day'!BC$3,'B3 ETH'!$A$4:$CC$4,0)),-1,0) -> 2757.5 | BD14: =OFFSET(INDEX('B3 ETH'!$A$4:$CC$1048576,MATCH('settlement day'!$B$3,'B3 ETH'!$A$4:$A$1048576,0),MATCH('settlement day'!BD$3,'B3 ETH'!$A$4:$CC$4,0)),-1,0) -> 2696 | BE14: =OFFSET(INDEX('B3 ETH'!$A$4:$CC$1048576,MATCH('settlement day'!$B$3,'B3 ETH'!$A$4:$A$1048576,0),MATCH('settlement day'!BE$3,'B3 ETH'!$A$4:$CC$4,0)),-1,0) -> 2696 | BF14: =OFFSET(INDEX('B3 ETH'!$A$4:$CC$1048576,MATCH('settlement day'!$B$3,'B3 ETH'!$A$4:$A$1048576,0),MATCH('settlement day'!BF$3,'B3 ETH'!$A$4:$CC$4,0)),-1,0) -> 2720 | BG14: =OFFSET(INDEX('B3 ETH'!$A$4:$CC$1048576,MATCH('settlement day'!$B$3,'B3 ETH'!$A$4:$A$1048576,0),MATCH('settlement day'!BG$3,'B3 ETH'!$A$4:$CC$4,0)),-1,0) -> 2747 | BH14: =OFFSET(INDEX('B3 ETH'!$A$4:$CC$1048576,MATCH('settlement day'!$B$3,'B3 ETH'!$A$4:$A$1048576,0),MATCH('settlement day'!BH$3,'B3 ETH'!$A$4:$CC$4,0)),-1,0) -> 2796 | ... BJ14: =OFFSET(INDEX('B3 ETH'!$A$4:$CC$1048576,MATCH('settlement day'!$B$3,'B3 ETH'!$A$4:$A$1048576,0),MATCH('settlement day'!BJ$3,'B3 ETH'!$A$4:$CC$4,0)),-1,0) -> 2825 | BK14: =SUM(AV14:AX14)/3 -> 0 | BL14: =SUM(AY14:BA14)/3 -> 0 | BM14: =SUM(BB14:BD14)/3 -> 1817.8333 | BN14: =SUM(BE14:BG14)/3 -> 2721 | BO14: =SUM(BH14:BJ14)/3 -> 2809.8333
B15: Variation | C15: =C13-C14 -> 0 | D15: =D13-D14 -> 0 | E15: =E13-E14 -> 0 | F15: =F13-F14 -> 0 | G15: =G13-G14 -> 0 | H15: =H13-H14 -> 0 | I15: =I13-I14 -> 0 | J15: =J13-J14 -> 0 | ... BJ15: =BJ13-BJ14 -> 0 | BK15: =+BK13-BK14 -> 0 | BL15: =+BL13-BL14 -> 0 | BM15: =+BM13-BM14 -> 4 | BN15: =+BN13-BN14 -> 3.8333333 | BO15: =+BO13-BO14 -> 0 | BR15: 1.0251 | BS15: 1.02705 | BT15: 1.02705 | BU15: FX
B16: RBOB (US$/gal) | N16: 1.9801 | O16: 2.2285 | P16: 2.5543 | Q16: 2.797 | R16: 3.1896 | S16: 3.4721 | T16: 4.0804 | U16: 3.6498 | V16: 3.4881 | W16: 2.6059 | X16: 2.4726 | Y16: 2.8107 | Z16: 2.4185 | AA16: 2.4595 | AB16: 2.5435 | AC16: 2.4343 | AD16: 2.7005 | AE16: 2.578 | AF16: 2.5599 | AG16: 2.634 | AH16: 2.929 | AI16: 2.7664 | AJ16: 2.4399 | AK16: 2.2227 | AL16: 2.1998 | AM16: 2.1026 | AN16: 2.1833 | AO16: 2.3043 | AP16: 2.7611 | AQ16: 2.7108 | AR16: 2.426 | AS16: 2.5291 | AT16: 2.482 | AU16: 2.2117 | AV16: 1.9621 | AW16: 2.0035 | AX16: 1.9437 | AY16: 2.0015 | AZ16: 2.0365 | BA16: 1.9703 | BB16: 2.2831 | BC16: 2.037 | BE16: =+BD17-BE17 -> 0.0473 | BF16: =+BE17-BF17 -> 0.0359 | BG16: =+BF17-BG17 -> 0.0405 | BH16: =+BG17-BH17 -> 0.1538 | BI16: =+BH17-BI17 -> 0.0502 | BJ16: =+BI17-BJ17 -> 0.0336 | BL16: =+BK17-BL17 -> 0 | BM16: =+BL17-BM17 -> -0.71736667 | BN16: =+BM17-BN17 -> -1.35 | BO16: =+BN17-BO17 -> 0.23743333
B17: Last settlement | C17: =+RBOB!C26 -> 0 | D17: =+RBOB!D26 -> 0 | E17: =+RBOB!E26 -> 0 | F17: =+RBOB!F70 -> 0 | G17: =+RBOB!G91 -> 0 | H17: =+RBOB!H139 -> 0 | I17: =+RBOB!I139 -> 0 | J17: =+RBOB!J139 -> 0 | K17: =+RBOB!K160 -> 0 | L17: =+RBOB!L202 -> 0 | M17: =+RBOB!M202 -> 0 | N17: =+RBOB!N244 -> 0 | O17: =+RBOB!O244 -> 0 | P17: =+RBOB!P268 -> 0 | Q17: =+RBOB!Q286 -> 0 | R17: =+RBOB!R310 -> 0 | S17: =INDEX(RBOB!$A$4:$BB$1048576,MATCH('settlement day'!$B$3,RBOB!$A$4:$A$1048576,0),MATCH('settlement day'!S$3,RBOB!$A$4:$BB$4,0)) -> 0 | T17: =INDEX(RBOB!$A$4:$BB$1048576,MATCH('settlement day'!$B$3,RBOB!$A$4:$A$1048576,0),MATCH('settlement day'!T$3,RBOB!$A$4:$BB$4,0)) -> 0 | U17: =INDEX(RBOB!$A$4:$BB$1048576,MATCH('settlement day'!$B$3,RBOB!$A$4:$A$1048576,0),MATCH('settlement day'!U$3,RBOB!$A$4:$BB$4,0)) -> 0 | V17: =INDEX(RBOB!$A$4:$BB$1048576,MATCH('settlement day'!$B$3,RBOB!$A$4:$A$1048576,0),MATCH('settlement day'!V$3,RBOB!$A$4:$BB$4,0)) -> 0 | W17: =INDEX(RBOB!$A$4:$BB$1048576,MATCH('settlement day'!$B$3,RBOB!$A$4:$A$1048576,0),MATCH('settlement day'!W$3,RBOB!$A$4:$BB$4,0)) -> 0 | X17: =INDEX(RBOB!$A$4:$BB$1048576,MATCH('settlement day'!$B$3,RBOB!$A$4:$A$1048576,0),MATCH('settlement day'!X$3,RBOB!$A$4:$BB$4,0)) -> 0 | Y17: =INDEX(RBOB!$A$4:$BB$1048576,MATCH('settlement day'!$B$3,RBOB!$A$4:$A$1048576,0),MATCH('settlement day'!Y$3,RBOB!$A$4:$BB$4,0)) -> 0 | Z17: =INDEX(RBOB!$A$4:$BB$1048576,MATCH('settlement day'!$B$3,RBOB!$A$4:$A$1048576,0),MATCH('settlement day'!Z$3,RBOB!$A$4:$BB$4,0)) -> 0 | ... BB17: =INDEX(RBOB!$A$4:$BB$1048576,MATCH('settlement day'!$B$3,RBOB!$A$4:$A$1048576,0),MATCH('settlement day'!BB$3,RBOB!$A$4:$BB$4,0)) -> 0 | BC17: =INDEX(RBOB!$A$4:$CC$1048576,MATCH('settlement day'!$B$3,RBOB!$A$4:$A$1048576,0),MATCH('settlement day'!BC$3,RBOB!$A$4:$CC$4,0)) -> 0 | BD17: =INDEX(RBOB!$A$4:$CC$1048576,MATCH('settlement day'!$B$3,RBOB!$A$4:$A$1048576,0),MATCH('settlement day'!BD$3,RBOB!$A$4:$CC$4,0)) -> 2.1521 | BE17: =INDEX(RBOB!$A$4:$CC$1048576,MATCH('settlement day'!$B$3,RBOB!$A$4:$A$1048576,0),MATCH('settlement day'!BE$3,RBOB!$A$4:$CC$4,0)) -> 2.1048 | BF17: =INDEX(RBOB!$A$4:$CC$1048576,MATCH('settlement day'!$B$3,RBOB!$A$4:$A$1048576,0),MATCH('settlement day'!BF$3,RBOB!$A$4:$CC$4,0)) -> 2.0689 | BG17: =INDEX(RBOB!$A$4:$CC$1048576,MATCH('settlement day'!$B$3,RBOB!$A$4:$A$1048576,0),MATCH('settlement day'!BG$3,RBOB!$A$4:$CC$4,0)) -> 2.0284 | BH17: =INDEX(RBOB!$A$4:$CC$1048576,MATCH('settlement day'!$B$3,RBOB!$A$4:$A$1048576,0),MATCH('settlement day'!BH$3,RBOB!$A$4:$CC$4,0)) -> 1.8746 | BI17: =INDEX(RBOB!$A$4:$CC$1048576,MATCH('settlement day'!$B$3,RBOB!$A$4:$A$1048576,0),MATCH('settlement day'!BI$3,RBOB!$A$4:$CC$4,0)) -> 1.8244 | BJ17: =INDEX(RBOB!$A$4:$CC$1048576,MATCH('settlement day'!$B$3,RBOB!$A$4:$A$1048576,0),MATCH('settlement day'!BJ$3,RBOB!$A$4:$CC$4,0)) -> 1.7908 | BK17: =SUM(AV17:AX17)/3 -> 0 | BL17: =SUM(AY17:BA17)/3 -> 0 | BM17: =SUM(BB17:BD17)/3 -> 0.71736667 | BN17: =SUM(BE17:BG17)/3 -> 2.0673667 | BO17: =SUM(BH17:BJ17)/3 -> 1.8299333 | BR17: =BR13/BR15 -> 558.57264 | BS17: =BS13/BS15 -> 562.01336 | BT17: =BT13/BT15 -> 562.65639 | BU17: eur/cbm
B18: day before D-1 | C18: =+RBOB!C25 -> 0 | D18: =+RBOB!D25 -> 0 | E18: =+RBOB!E25 -> 0 | F18: =+RBOB!F69 -> 0 | G18: =+RBOB!G90 -> 0 | H18: =+RBOB!H138 -> 0 | I18: =+RBOB!I138 -> 0 | J18: =+RBOB!J138 -> 0 | K18: =+RBOB!K159 -> 0 | L18: =+RBOB!L201 -> 0 | M18: =+RBOB!M201 -> 0 | N18: =+RBOB!N243 -> 0 | O18: =+RBOB!O243 -> 0 | P18: =+RBOB!P267 -> 0 | Q18: =+RBOB!Q285 -> 0 | R18: =+RBOB!R309 -> 0 | S18: =OFFSET(INDEX(RBOB!$A$4:$BB$1048576,MATCH('settlement day'!$B$3,RBOB!$A$4:$A$1048576,0),MATCH('settlement day'!S$3,RBOB!$A$4:$BB$4,0)),-1,0) -> 0 | T18: =OFFSET(INDEX(RBOB!$A$4:$BB$1048576,MATCH('settlement day'!$B$3,RBOB!$A$4:$A$1048576,0),MATCH('settlement day'!T$3,RBOB!$A$4:$BB$4,0)),-1,0) -> 0 | U18: =OFFSET(INDEX(RBOB!$A$4:$BB$1048576,MATCH('settlement day'!$B$3,RBOB!$A$4:$A$1048576,0),MATCH('settlement day'!U$3,RBOB!$A$4:$BB$4,0)),-1,0) -> 0 | V18: =OFFSET(INDEX(RBOB!$A$4:$BB$1048576,MATCH('settlement day'!$B$3,RBOB!$A$4:$A$1048576,0),MATCH('settlement day'!V$3,RBOB!$A$4:$BB$4,0)),-1,0) -> 0 | W18: =OFFSET(INDEX(RBOB!$A$4:$BB$1048576,MATCH('settlement day'!$B$3,RBOB!$A$4:$A$1048576,0),MATCH('settlement day'!W$3,RBOB!$A$4:$BB$4,0)),-1,0) -> 0 | X18: =OFFSET(INDEX(RBOB!$A$4:$BB$1048576,MATCH('settlement day'!$B$3,RBOB!$A$4:$A$1048576,0),MATCH('settlement day'!X$3,RBOB!$A$4:$BB$4,0)),-1,0) -> 0 | Y18: =OFFSET(INDEX(RBOB!$A$4:$BB$1048576,MATCH('settlement day'!$B$3,RBOB!$A$4:$A$1048576,0),MATCH('settlement day'!Y$3,RBOB!$A$4:$BB$4,0)),-1,0) -> 0 | Z18: =OFFSET(INDEX(RBOB!$A$4:$BB$1048576,MATCH('settlement day'!$B$3,RBOB!$A$4:$A$1048576,0),MATCH('settlement day'!Z$3,RBOB!$A$4:$BB$4,0)),-1,0) -> 0 | ... BB18: =OFFSET(INDEX(RBOB!$A$4:$BB$1048576,MATCH('settlement day'!$B$3,RBOB!$A$4:$A$1048576,0),MATCH('settlement day'!BB$3,RBOB!$A$4:$BB$4,0)),-1,0) -> 0 | BC18: =OFFSET(INDEX(RBOB!$A$4:$CC$1048576,MATCH('settlement day'!$B$3,RBOB!$A$4:$A$1048576,0),MATCH('settlement day'!BC$3,RBOB!$A$4:$CC$4,0)),-1,0) -> 0 | BD18: =OFFSET(INDEX(RBOB!$A$4:$CC$1048576,MATCH('settlement day'!$B$3,RBOB!$A$4:$A$1048576,0),MATCH('settlement day'!BD$3,RBOB!$A$4:$CC$4,0)),-1,0) -> 2.1388 | BE18: =OFFSET(INDEX(RBOB!$A$4:$CC$1048576,MATCH('settlement day'!$B$3,RBOB!$A$4:$A$1048576,0),MATCH('settlement day'!BE$3,RBOB!$A$4:$CC$4,0)),-1,0) -> 2.0941 | BF18: =OFFSET(INDEX(RBOB!$A$4:$CC$1048576,MATCH('settlement day'!$B$3,RBOB!$A$4:$A$1048576,0),MATCH('settlement day'!BF$3,RBOB!$A$4:$CC$4,0)),-1,0) -> 2.0587 | BG18: =OFFSET(INDEX(RBOB!$A$4:$CC$1048576,MATCH('settlement day'!$B$3,RBOB!$A$4:$A$1048576,0),MATCH('settlement day'!BG$3,RBOB!$A$4:$CC$4,0)),-1,0) -> 2.0196 | BH18: =OFFSET(INDEX(RBOB!$A$4:$CC$1048576,MATCH('settlement day'!$B$3,RBOB!$A$4:$A$1048576,0),MATCH('settlement day'!BH$3,RBOB!$A$4:$CC$4,0)),-1,0) -> 1.8664 | BI18: =OFFSET(INDEX(RBOB!$A$4:$CC$1048576,MATCH('settlement day'!$B$3,RBOB!$A$4:$A$1048576,0),MATCH('settlement day'!BI$3,RBOB!$A$4:$CC$4,0)),-1,0) -> 1.8151 | BJ18: =OFFSET(INDEX(RBOB!$A$4:$CC$1048576,MATCH('settlement day'!$B$3,RBOB!$A$4:$A$1048576,0),MATCH('settlement day'!BJ$3,RBOB!$A$4:$CC$4,0)),-1,0) -> 1.78 | BK18: =SUM(AV18:AX18)/3 -> 0 | BL18: =SUM(AY18:BA18)/3 -> 0 | BM18: =SUM(BB18:BD18)/3 -> 0.71293333 | BN18: =SUM(BE18:BG18)/3 -> 2.0574667 | BO18: =SUM(BH18:BJ18)/3 -> 1.8205 | BR18: 687.333 | BS18: 686.667 | BT18: 684.667 | BU18: T2
B19: Variation | C19: =C17-C18 -> 0 | D19: =D17-D18 -> 0 | E19: =E17-E18 -> 0 | F19: =F17-F18 -> 0 | G19: =G17-G18 -> 0 | H19: =H17-H18 -> 0 | I19: =I17-I18 -> 0 | J19: =J17-J18 -> 0 | ... BO19: =BO17-BO18 -> 0.0094333333
B20: US CORN Fut. (US$/bu) | AC20: =+Z21-AC21 -> 0 | AE20: =+AC21-AE21 -> 0 | AG20: =+AE21-AG21 -> 0 | AI20: =+AG21-AI21 -> 0 | AL20: =+AI21-AL21 -> 0 | AO20: =+AL21-AO21 -> 0 | AQ20: =+AO21-AQ21 -> 0 | AS20: =+AQ21-AS21 -> 0 | AU20: =+AS21-AU21 -> 0 | AX20: =+AU21-AX21 -> 0 | BA20: =+AX21-BA21 -> 0 | BC20: =+AZ21-BC21 -> 0 | BE20: =+BB21-BE21 -> -4.544 | BG20: =+BD21-BG21 -> -4.352 | BJ20: =+BG21-BJ21 -> -0.132 | BR20: =BR17-BR18 -> -128.76036 | BS20: =BS17-BS18 -> -124.65364 | BT20: =BT17-BT18 -> -122.01061 | BU20: T1 basis
B21: Last settlement | E21: =+CORN!C26 -> 0 | G21: =+CORN!D83 -> 0 | I21: =+CORN!E83 -> 0 | J21: =+K21-I21 -> 0 | K21: =+CORN!F125 -> 0 | L21: =+N21-K21 -> 0 | M21: =+N21-I21 -> 0 | N21: =+CORN!G192 -> 0 | Q21: =+CORN!H270 -> 0 | S21: =IFERROR(INDEX(CORN!$A$4:$BB$1048576,MATCH('settlement day'!$B$3,CORN!$A$4:$A$1048576,0),MATCH('settlement day'!S$3,CORN!$A$4:$BB$4,0)),"") -> 0 | T21: =IFERROR(INDEX(CORN!$A$4:$BB$1048576,MATCH('settlement day'!$B$3,CORN!$A$4:$A$1048576,0),MATCH('settlement day'!T$3,CORN!$A$4:$BB$4,0)),"") | U21: =IFERROR(INDEX(CORN!$A$4:$BB$1048576,MATCH('settlement day'!$B$3,CORN!$A$4:$A$1048576,0),MATCH('settlement day'!U$3,CORN!$A$4:$BB$4,0)),"") -> 0 | V21: =IFERROR(INDEX(CORN!$A$4:$BB$1048576,MATCH('settlement day'!$B$3,CORN!$A$4:$A$1048576,0),MATCH('settlement day'!V$3,CORN!$A$4:$BB$4,0)),"") | W21: =IFERROR(INDEX(CORN!$A$4:$BB$1048576,MATCH('settlement day'!$B$3,CORN!$A$4:$A$1048576,0),MATCH('settlement day'!W$3,CORN!$A$4:$BB$4,0)),"") -> 0 | X21: =IFERROR(INDEX(CORN!$A$4:$BB$1048576,MATCH('settlement day'!$B$3,CORN!$A$4:$A$1048576,0),MATCH('settlement day'!X$3,CORN!$A$4:$BB$4,0)),"") | Y21: =IFERROR(INDEX(CORN!$A$4:$BB$1048576,MATCH('settlement day'!$B$3,CORN!$A$4:$A$1048576,0),MATCH('settlement day'!Y$3,CORN!$A$4:$BB$4,0)),"") | Z21: =IFERROR(INDEX(CORN!$A$4:$BB$1048576,MATCH('settlement day'!$B$3,CORN!$A$4:$A$1048576,0),MATCH('settlement day'!Z$3,CORN!$A$4:$BB$4,0)),"") -> 0 | ... AE21: =IFERROR(INDEX(CORN!$A$4:$BB$1048576,MATCH('settlement day'!$B$3,CORN!$A$4:$A$1048576,0),MATCH('settlement day'!AE$3,CORN!$A$4:$BB$4,0)),"") -> 0 | AG21: =IFERROR(INDEX(CORN!$A$4:$BB$1048576,MATCH('settlement day'!$B$3,CORN!$A$4:$A$1048576,0),MATCH('settlement day'!AG$3,CORN!$A$4:$BB$4,0)),"") -> 0 | AI21: =IFERROR(INDEX(CORN!$A$4:$BB$1048576,MATCH('settlement day'!$B$3,CORN!$A$4:$A$1048576,0),MATCH('settlement day'!AI$3,CORN!$A$4:$BB$4,0)),"") -> 0 | AL21: =IFERROR(INDEX(CORN!$A$4:$BB$1048576,MATCH('settlement day'!$B$3,CORN!$A$4:$A$1048576,0),MATCH('settlement day'!AL$3,CORN!$A$4:$BB$4,0)),"") -> 0 | AO21: =IFERROR(INDEX(CORN!$A$4:$BB$1048576,MATCH('settlement day'!$B$3,CORN!$A$4:$A$1048576,0),MATCH('settlement day'!AO$3,CORN!$A$4:$BB$4,0)),"") -> 0 | AQ21: =IFERROR(INDEX(CORN!$A$4:$BB$1048576,MATCH('settlement day'!$B$3,CORN!$A$4:$A$1048576,0),MATCH('settlement day'!AQ$3,CORN!$A$4:$BB$4,0)),"") -> 0 | AS21: =IFERROR(INDEX(CORN!$A$4:$BB$1048576,MATCH('settlement day'!$B$3,CORN!$A$4:$A$1048576,0),MATCH('settlement day'!AS$3,CORN!$A$4:$BB$4,0)),"") -> 0 | AU21: =IFERROR(INDEX(CORN!$A$4:$BB$1048576,MATCH('settlement day'!$B$3,CORN!$A$4:$A$1048576,0),MATCH('settlement day'!AU$3,CORN!$A$4:$BB$4,0)),"") -> 0 | AX21: =IFERROR(INDEX(CORN!$A$4:$BB$1048576,MATCH('settlement day'!$B$3,CORN!$A$4:$A$1048576,0),MATCH('settlement day'!AX$3,CORN!$A$4:$BB$4,0)),"") -> 0 | BA21: =IFERROR(INDEX(CORN!$A$4:$BB$1048576,MATCH('settlement day'!$B$3,CORN!$A$4:$A$1048576,0),MATCH('settlement day'!BA$3,CORN!$A$4:$BB$4,0)),"") -> 0 | BC21: =IFERROR(INDEX(CORN!$A$4:$CC$1048576,MATCH('settlement day'!$B$3,CORN!$A$4:$A$1048576,0),MATCH('settlement day'!BC$3,CORN!$A$4:$CC$4,0)),"") -> 0 | BE21: =IFERROR(INDEX(CORN!$A$4:$CC$1048576,MATCH('settlement day'!$B$3,CORN!$A$4:$A$1048576,0),MATCH('settlement day'!BE$3,CORN!$A$4:$CC$4,0)),"") -> 4.544 | BG21: =IFERROR(INDEX(CORN!$A$4:$CC$1048576,MATCH('settlement day'!$B$3,CORN!$A$4:$A$1048576,0),MATCH('settlement day'!BG$3,CORN!$A$4:$CC$4,0)),"") -> 4.352 | BJ21: =IFERROR(INDEX(CORN!$A$4:$CC$1048576,MATCH('settlement day'!$B$3,CORN!$A$4:$A$1048576,0),MATCH('settlement day'!BJ$3,CORN!$A$4:$CC$4,0)),"") -> 4.484
B22: day before D-1 | E22: =+CORN!C25 -> 0 | G22: =+CORN!D82 -> 0 | I22: =+CORN!E82 -> 0 | K22: =+CORN!F124 -> 0 | N22: =+CORN!G191 -> 0 | Q22: =+CORN!H269 -> 0 | S22: =IFERROR(OFFSET(INDEX(CORN!$A$4:$BB$1048576,MATCH('settlement day'!$B$3,CORN!$A$4:$A$1048576,0),MATCH('settlement day'!S$3,CORN!$A$4:$BB$4,0)),-1,0),"") -> 0 | T22: =IFERROR(OFFSET(INDEX(CORN!$A$4:$BB$1048576,MATCH('settlement day'!$B$3,CORN!$A$4:$A$1048576,0),MATCH('settlement day'!T$3,CORN!$A$4:$BB$4,0)),-1,0),"") | U22: =IFERROR(OFFSET(INDEX(CORN!$A$4:$BB$1048576,MATCH('settlement day'!$B$3,CORN!$A$4:$A$1048576,0),MATCH('settlement day'!U$3,CORN!$A$4:$BB$4,0)),-1,0),"") -> 0 | V22: =IFERROR(OFFSET(INDEX(CORN!$A$4:$BB$1048576,MATCH('settlement day'!$B$3,CORN!$A$4:$A$1048576,0),MATCH('settlement day'!V$3,CORN!$A$4:$BB$4,0)),-1,0),"") | W22: =IFERROR(OFFSET(INDEX(CORN!$A$4:$BB$1048576,MATCH('settlement day'!$B$3,CORN!$A$4:$A$1048576,0),MATCH('settlement day'!W$3,CORN!$A$4:$BB$4,0)),-1,0),"") -> 0 | X22: =IFERROR(OFFSET(INDEX(CORN!$A$4:$BB$1048576,MATCH('settlement day'!$B$3,CORN!$A$4:$A$1048576,0),MATCH('settlement day'!X$3,CORN!$A$4:$BB$4,0)),-1,0),"") | Y22: =IFERROR(OFFSET(INDEX(CORN!$A$4:$BB$1048576,MATCH('settlement day'!$B$3,CORN!$A$4:$A$1048576,0),MATCH('settlement day'!Y$3,CORN!$A$4:$BB$4,0)),-1,0),"") | Z22: =IFERROR(OFFSET(INDEX(CORN!$A$4:$BB$1048576,MATCH('settlement day'!$B$3,CORN!$A$4:$A$1048576,0),MATCH('settlement day'!Z$3,CORN!$A$4:$BB$4,0)),-1,0),"") -> 0 | ... AE22: =IFERROR(OFFSET(INDEX(CORN!$A$4:$BB$1048576,MATCH('settlement day'!$B$3,CORN!$A$4:$A$1048576,0),MATCH('settlement day'!AE$3,CORN!$A$4:$BB$4,0)),-1,0),"") -> 0 | AG22: =IFERROR(OFFSET(INDEX(CORN!$A$4:$BB$1048576,MATCH('settlement day'!$B$3,CORN!$A$4:$A$1048576,0),MATCH('settlement day'!AG$3,CORN!$A$4:$BB$4,0)),-1,0),"") -> 0 | AI22: =IFERROR(OFFSET(INDEX(CORN!$A$4:$BB$1048576,MATCH('settlement day'!$B$3,CORN!$A$4:$A$1048576,0),MATCH('settlement day'!AI$3,CORN!$A$4:$BB$4,0)),-1,0),"") -> 0 | AL22: =IFERROR(OFFSET(INDEX(CORN!$A$4:$BB$1048576,MATCH('settlement day'!$B$3,CORN!$A$4:$A$1048576,0),MATCH('settlement day'!AL$3,CORN!$A$4:$BB$4,0)),-1,0),"") -> 0 | AO22: =IFERROR(OFFSET(INDEX(CORN!$A$4:$BB$1048576,MATCH('settlement day'!$B$3,CORN!$A$4:$A$1048576,0),MATCH('settlement day'!AO$3,CORN!$A$4:$BB$4,0)),-1,0),"") -> 0 | AQ22: =IFERROR(OFFSET(INDEX(CORN!$A$4:$BB$1048576,MATCH('settlement day'!$B$3,CORN!$A$4:$A$1048576,0),MATCH('settlement day'!AQ$3,CORN!$A$4:$BB$4,0)),-1,0),"") -> 0 | AS22: =IFERROR(OFFSET(INDEX(CORN!$A$4:$BB$1048576,MATCH('settlement day'!$B$3,CORN!$A$4:$A$1048576,0),MATCH('settlement day'!AS$3,CORN!$A$4:$BB$4,0)),-1,0),"") -> 0 | AU22: =IFERROR(OFFSET(INDEX(CORN!$A$4:$BB$1048576,MATCH('settlement day'!$B$3,CORN!$A$4:$A$1048576,0),MATCH('settlement day'!AU$3,CORN!$A$4:$BB$4,0)),-1,0),"") -> 0 | AX22: =IFERROR(OFFSET(INDEX(CORN!$A$4:$BB$1048576,MATCH('settlement day'!$B$3,CORN!$A$4:$A$1048576,0),MATCH('settlement day'!AX$3,CORN!$A$4:$BB$4,0)),-1,0),"") -> 0 | BA22: =IFERROR(OFFSET(INDEX(CORN!$A$4:$BB$1048576,MATCH('settlement day'!$B$3,CORN!$A$4:$A$1048576,0),MATCH('settlement day'!BA$3,CORN!$A$4:$BB$4,0)),-1,0),"") -> 0 | BC22: =IFERROR(OFFSET(INDEX(CORN!$A$4:$CC$1048576,MATCH('settlement day'!$B$3,CORN!$A$4:$A$1048576,0),MATCH('settlement day'!BC$3,CORN!$A$4:$CC$4,0)),-1,0),"") -> 0 | BE22: =IFERROR(OFFSET(INDEX(CORN!$A$4:$CC$1048576,MATCH('settlement day'!$B$3,CORN!$A$4:$A$1048576,0),MATCH('settlement day'!BE$3,CORN!$A$4:$CC$4,0)),-1,0),"") -> 4.474 | BG22: =IFERROR(OFFSET(INDEX(CORN!$A$4:$CC$1048576,MATCH('settlement day'!$B$3,CORN!$A$4:$A$1048576,0),MATCH('settlement day'!BG$3,CORN!$A$4:$CC$4,0)),-1,0),"") -> 4.282 | BJ22: =IFERROR(OFFSET(INDEX(CORN!$A$4:$CC$1048576,MATCH('settlement day'!$B$3,CORN!$A$4:$A$1048576,0),MATCH('settlement day'!BJ$3,CORN!$A$4:$CC$4,0)),-1,0),"") -> 4.416
B23: Variation | E23: =E21-E22 -> 0 | G23: =G21-G22 -> 0 | I23: =I21-I22 -> 0 | K23: =K21-K22 -> 0 | N23: =N21-N22 -> 0 | Q23: =Q21-Q22 -> 0 | S23: =S21-S22 -> 0 | U23: =U21-U22 -> 0 | W23: =W21-W22 -> 0 | Z23: =Z21-Z22 -> 0 | AC23: =AC21-AC22 -> 0 | AE23: =AE21-AE22 -> 0 | AG23: =AG21-AG22 -> 0 | AI23: =AI21-AI22 -> 0 | AL23: =AL21-AL22 -> 0 | AO23: =AO21-AO22 -> 0 | AQ23: =AQ21-AQ22 -> 0 | AS23: =AS21-AS22 -> 0 | AU23: =AU21-AU22 -> 0 | AX23: =AX21-AX22 -> 0 | BA23: =BA21-BA22 -> 0 | BC23: =BC21-BC22 -> 0 | BE23: =BE21-BE22 -> 0.07 | BG23: =BG21-BG22 -> 0.07 | BJ23: =BJ21-BJ22 -> 0.068
B24: Sugar #11 (US$/pound)
B25: Last settlement | E25: =+'Sugar 11'!B26 -> 0 | G25: =+'Sugar 11'!C83 -> 0 | I25: =+'Sugar 11'!D83 -> 0 | L25: =+'Sugar 11'!E137 -> 0 | Q25: =+'Sugar 11'!F282 -> 0 | S25: =IFERROR(INDEX('Sugar 11'!$A$4:$BB$1048576,MATCH('settlement day'!$B$3,'Sugar 11'!$A$4:$A$1048576,0),MATCH('settlement day'!S$3,'Sugar 11'!$A$4:$BB$4,0)),"") -> 0 | T25: =IFERROR(INDEX('Sugar 11'!$A$4:$BB$1048576,MATCH('settlement day'!$B$3,'Sugar 11'!$A$4:$A$1048576,0),MATCH('settlement day'!T$3,'Sugar 11'!$A$4:$BB$4,0)),"") | U25: 0 | V25: =IFERROR(INDEX('Sugar 11'!$A$4:$BB$1048576,MATCH('settlement day'!$B$3,'Sugar 11'!$A$4:$A$1048576,0),MATCH('settlement day'!V$3,'Sugar 11'!$A$4:$BB$4,0)),"") | W25: =IFERROR(INDEX('Sugar 11'!$A$4:$BB$1048576,MATCH('settlement day'!$B$3,'Sugar 11'!$A$4:$A$1048576,0),MATCH('settlement day'!W$3,'Sugar 11'!$A$4:$BB$4,0)),"") | X25: =IFERROR(INDEX('Sugar 11'!$A$4:$BB$1048576,MATCH('settlement day'!$B$3,'Sugar 11'!$A$4:$A$1048576,0),MATCH('settlement day'!X$3,'Sugar 11'!$A$4:$BB$4,0)),"") -> 0 | Y25: =IFERROR(INDEX('Sugar 11'!$A$4:$BB$1048576,MATCH('settlement day'!$B$3,'Sugar 11'!$A$4:$A$1048576,0),MATCH('settlement day'!Y$3,'Sugar 11'!$A$4:$BB$4,0)),"") | Z25: =IFERROR(INDEX('Sugar 11'!$A$4:$BB$1048576,MATCH('settlement day'!$B$3,'Sugar 11'!$A$4:$A$1048576,0),MATCH('settlement day'!Z$3,'Sugar 11'!$A$4:$BB$4,0)),"") | AA25: =IFERROR(INDEX('Sugar 11'!$A$4:$BB$1048576,MATCH('settlement day'!$B$3,'Sugar 11'!$A$4:$A$1048576,0),MATCH('settlement day'!AA$3,'Sugar 11'!$A$4:$BB$4,0)),"") | AB25: =IFERROR(INDEX('Sugar 11'!$A$4:$BB$1048576,MATCH('settlement day'!$B$3,'Sugar 11'!$A$4:$A$1048576,0),MATCH('settlement day'!AB$3,'Sugar 11'!$A$4:$BB$4,0)),"") | AC25: =IFERROR(INDEX('Sugar 11'!$A$4:$BB$1048576,MATCH('settlement day'!$B$3,'Sugar 11'!$A$4:$A$1048576,0),MATCH('settlement day'!AC$3,'Sugar 11'!$A$4:$BB$4,0)),"") -> 0 | ... AM25: =IFERROR(INDEX('Sugar 11'!$A$4:$BB$1048576,MATCH('settlement day'!$B$3,'Sugar 11'!$A$4:$A$1048576,0),MATCH('settlement day'!AM$3,'Sugar 11'!$A$4:$BB$4,0)),"") | AO25: =IFERROR(INDEX('Sugar 11'!$A$4:$BB$1048576,MATCH('settlement day'!$B$3,'Sugar 11'!$A$4:$A$1048576,0),MATCH('settlement day'!AO$3,'Sugar 11'!$A$4:$BB$4,0)),"") -> 0 | AQ25: =IFERROR(INDEX('Sugar 11'!$A$4:$BB$1048576,MATCH('settlement day'!$B$3,'Sugar 11'!$A$4:$A$1048576,0),MATCH('settlement day'!AQ$3,'Sugar 11'!$A$4:$BB$4,0)),"") -> 0 | AS25: =IFERROR(INDEX('Sugar 11'!$A$4:$BB$1048576,MATCH('settlement day'!$B$3,'Sugar 11'!$A$4:$A$1048576,0),MATCH('settlement day'!AS$3,'Sugar 11'!$A$4:$BB$4,0)),"") -> 0 | AV25: =IFERROR(INDEX('Sugar 11'!$A$4:$CC$1048576,MATCH('settlement day'!$B$3,'Sugar 11'!$A$4:$A$1048576,0),MATCH('settlement day'!AV$3,'Sugar 11'!$A$4:$CC$4,0)),"") -> 0 | AX25: 20 | BA25: =IFERROR(INDEX('Sugar 11'!$A$4:$CC$1048576,MATCH('settlement day'!$B$3,'Sugar 11'!$A$4:$A$1048576,0),MATCH('settlement day'!BA$3,'Sugar 11'!$A$4:$CC$4,0)),"") -> 0 | BC25: =IFERROR(INDEX('Sugar 11'!$A$4:$CC$1048576,MATCH('settlement day'!$B$3,'Sugar 11'!$A$4:$A$1048576,0),MATCH('settlement day'!BC$3,'Sugar 11'!$A$4:$CC$4,0)),"") -> 0 | BE25: =IFERROR(INDEX('Sugar 11'!$A$4:$CC$1048576,MATCH('settlement day'!$B$3,'Sugar 11'!$A$4:$A$1048576,0),MATCH('settlement day'!BE$3,'Sugar 11'!$A$4:$CC$4,0)),"") -> 0.1734 | BH25: =IFERROR(INDEX('Sugar 11'!$A$4:$CC$1048576,MATCH('settlement day'!$B$3,'Sugar 11'!$A$4:$A$1048576,0),MATCH('settlement day'!BH$3,'Sugar 11'!$A$4:$CC$4,0)),"") -> 0.1753
B26: day before D-1 | E26: =+'Sugar 11'!B25 -> 0 | G26: =+'Sugar 11'!C82 -> 0 | I26: =+'Sugar 11'!D82 -> 0 | L26: =+'Sugar 11'!E136 -> 0 | Q26: =+'Sugar 11'!F271 -> 0 | S26: =IFERROR(INDEX('Sugar 11'!$A$4:$BB$1048576,MATCH('settlement day'!$B$3,'Sugar 11'!$A$4:$A$1048576,0),MATCH('settlement day'!S$3,'Sugar 11'!$A$4:$BB$4,0)),"") -> 0 | T26: =IFERROR(INDEX('Sugar 11'!$A$4:$BB$1048576,MATCH('settlement day'!$B$3,'Sugar 11'!$A$4:$A$1048576,0),MATCH('settlement day'!T$3,'Sugar 11'!$A$4:$BB$4,0)),"") | U26: 0 | V26: =IFERROR(INDEX('Sugar 11'!$A$4:$BB$1048576,MATCH('settlement day'!$B$3,'Sugar 11'!$A$4:$A$1048576,0),MATCH('settlement day'!V$3,'Sugar 11'!$A$4:$BB$4,0)),"") | W26: =IFERROR(INDEX('Sugar 11'!$A$4:$BB$1048576,MATCH('settlement day'!$B$3,'Sugar 11'!$A$4:$A$1048576,0),MATCH('settlement day'!W$3,'Sugar 11'!$A$4:$BB$4,0)),"") | X26: =IFERROR(OFFSET(INDEX('Sugar 11'!$A$4:$BB$1048576,MATCH('settlement day'!$B$3,'Sugar 11'!$A$4:$A$1048576,0),MATCH('settlement day'!X$3,'Sugar 11'!$A$4:$BB$4,0)),-1,0),"") -> 0 | Y26: =IFERROR(OFFSET(INDEX('Sugar 11'!$A$4:$BB$1048576,MATCH('settlement day'!$B$3,'Sugar 11'!$A$4:$A$1048576,0),MATCH('settlement day'!Y$3,'Sugar 11'!$A$4:$BB$4,0)),-1,0),"") | Z26: =IFERROR(OFFSET(INDEX('Sugar 11'!$A$4:$BB$1048576,MATCH('settlement day'!$B$3,'Sugar 11'!$A$4:$A$1048576,0),MATCH('settlement day'!Z$3,'Sugar 11'!$A$4:$BB$4,0)),-1,0),"") | AA26: =IFERROR(OFFSET(INDEX('Sugar 11'!$A$4:$BB$1048576,MATCH('settlement day'!$B$3,'Sugar 11'!$A$4:$A$1048576,0),MATCH('settlement day'!AA$3,'Sugar 11'!$A$4:$BB$4,0)),-1,0),"") | AB26: =IFERROR(OFFSET(INDEX('Sugar 11'!$A$4:$BB$1048576,MATCH('settlement day'!$B$3,'Sugar 11'!$A$4:$A$1048576,0),MATCH('settlement day'!AB$3,'Sugar 11'!$A$4:$BB$4,0)),-1,0),"") | AC26: =IFERROR(OFFSET(INDEX('Sugar 11'!$A$4:$BB$1048576,MATCH('settlement day'!$B$3,'Sugar 11'!$A$4:$A$1048576,0),MATCH('settlement day'!AC$3,'Sugar 11'!$A$4:$BB$4,0)),-1,0),"") -> 0 | AD26: =IFERROR(OFFSET(INDEX('Sugar 11'!$A$4:$BB$1048576,MATCH('settlement day'!$B$3,'Sugar 11'!$A$4:$A$1048576,0),MATCH('settlement day'!AD$3,'Sugar 11'!$A$4:$BB$4,0)),-1,0),"") | AE26: =IFERROR(OFFSET(INDEX('Sugar 11'!$A$4:$BB$1048576,MATCH('settlement day'!$B$3,'Sugar 11'!$A$4:$A$1048576,0),MATCH('settlement day'!AE$3,'Sugar 11'!$A$4:$BB$4,0)),-1,0),"") -> 0 | ... AM26: =IFERROR(OFFSET(INDEX('Sugar 11'!$A$4:$BB$1048576,MATCH('settlement day'!$B$3,'Sugar 11'!$A$4:$A$1048576,0),MATCH('settlement day'!AM$3,'Sugar 11'!$A$4:$BB$4,0)),-1,0),"") | AO26: =IFERROR(OFFSET(INDEX('Sugar 11'!$A$4:$BB$1048576,MATCH('settlement day'!$B$3,'Sugar 11'!$A$4:$A$1048576,0),MATCH('settlement day'!AO$3,'Sugar 11'!$A$4:$BB$4,0)),-1,0),"") -> 0 | AQ26: =IFERROR(OFFSET(INDEX('Sugar 11'!$A$4:$BB$1048576,MATCH('settlement day'!$B$3,'Sugar 11'!$A$4:$A$1048576,0),MATCH('settlement day'!AQ$3,'Sugar 11'!$A$4:$BB$4,0)),-1,0),"") -> 0 | AS26: =IFERROR(OFFSET(INDEX('Sugar 11'!$A$4:$BB$1048576,MATCH('settlement day'!$B$3,'Sugar 11'!$A$4:$A$1048576,0),MATCH('settlement day'!AS$3,'Sugar 11'!$A$4:$BB$4,0)),-1,0),"") -> 0 | AV26: =IFERROR(OFFSET(INDEX('Sugar 11'!$A$4:$CC$1048576,MATCH('settlement day'!$B$3,'Sugar 11'!$A$4:$A$1048576,0),MATCH('settlement day'!AV$3,'Sugar 11'!$A$4:$CC$4,0)),-1,0),"") -> 0 | BA26: =IFERROR(OFFSET(INDEX('Sugar 11'!$A$4:$CC$1048576,MATCH('settlement day'!$B$3,'Sugar 11'!$A$4:$A$1048576,0),MATCH('settlement day'!BA$3,'Sugar 11'!$A$4:$CC$4,0)),-1,0),"") -> 0 | BC26: =IFERROR(OFFSET(INDEX('Sugar 11'!$A$4:$CC$1048576,MATCH('settlement day'!$B$3,'Sugar 11'!$A$4:$A$1048576,0),MATCH('settlement day'!BC$3,'Sugar 11'!$A$4:$CC$4,0)),-1,0),"") -> 0 | BE26: =IFERROR(OFFSET(INDEX('Sugar 11'!$A$4:$CC$1048576,MATCH('settlement day'!$B$3,'Sugar 11'!$A$4:$A$1048576,0),MATCH('settlement day'!BE$3,'Sugar 11'!$A$4:$CC$4,0)),-1,0),"") -> 0.1745 | BH26: =IFERROR(OFFSET(INDEX('Sugar 11'!$A$4:$CC$1048576,MATCH('settlement day'!$B$3,'Sugar 11'!$A$4:$A$1048576,0),MATCH('settlement day'!BH$3,'Sugar 11'!$A$4:$CC$4,0)),-1,0),"") -> 0.1765
B27: Variation | E27: =E25-E26 -> 0 | G27: =G25-G26 -> 0 | I27: =I25-I26 -> 0 | L27: =L25-L26 -> 0 | Q27: =Q25-Q26 -> 0 | S27: =S25-S26 -> 0 | U27: =U25-U26 -> 0 | X27: =X25-X26 -> 0 | AC27: =AC25-AC26 -> 0 | AE27: =AE25-AE26 -> 0 | AG27: =AG25-AG26 -> 0 | AJ27: =AJ25-AJ26 -> 0 | AO27: =AO25-AO26 -> 0 | AQ27: =AQ25-AQ26 -> 0 | AS27: =AS25-AS26 -> 0 | AV27: =AV25-AV26 -> 0 | BA27: =BA25-BA26 -> 0 | BC27: =BC25-BC26 -> 0 | BE27: =BE25-BE26 -> -0.0011 | BH27: =BH25-BH26 -> -0.0012
B28: FX
B29: USD/EUR | F29: =+'EUR USD'!B30 -> 0 | G29: =+'EUR USD'!C48 -> 0 | H29: =+'EUR USD'!D713 -> 0 | I29: =+'EUR USD'!E93 -> 0 | J29: =+'EUR USD'!F116 -> 0 | K29: =+'EUR USD'!G140 -> 0 | L29: =+'EUR USD'!H166 -> 0 | N29: =+'EUR USD'!J193 -> 0 | O29: =+'EUR USD'!K230 -> 0 | P29: =+'EUR USD'!L242 -> 0 | Q29: =+R29 -> 0 | R29: =+S29 -> 0 | S29: =IFERROR(INDEX('EUR USD'!$A$4:$BV$1048576,MATCH('settlement day'!$B$3,'EUR USD'!$A$4:$A$1048576,0),MATCH('settlement day'!S$3,'EUR USD'!$A$4:$BV$4,0)),"") -> 0 | T29: =IFERROR(INDEX('EUR USD'!$A$4:$BV$1048576,MATCH('settlement day'!$B$3,'EUR USD'!$A$4:$A$1048576,0),MATCH('settlement day'!T$3,'EUR USD'!$A$4:$BV$4,0)),"") -> 0 | U29: =+V29 -> 0 | V29: =+W29 -> 0 | W29: =+X29 -> 0 | X29: =+Y29 -> 0 | Y29: =+Z29 -> 0 | Z29: =AA29 -> 0 | AA29: =INDEX('EUR USD'!$A$4:$BV$1048576,MATCH('settlement day'!$B$3,'EUR USD'!$A$4:$A$1048576,0),MATCH('settlement day'!AA$3,'EUR USD'!$A$4:$BV$4,0)) -> 0 | AB29: =INDEX('EUR USD'!$A$4:$BV$1048576,MATCH('settlement day'!$B$3,'EUR USD'!$A$4:$A$1048576,0),MATCH('settlement day'!AB$3,'EUR USD'!$A$4:$BV$4,0)) -> 0 | AC29: =INDEX('EUR USD'!$A$4:$BV$1048576,MATCH('settlement day'!$B$3,'EUR USD'!$A$4:$A$1048576,0),MATCH('settlement day'!AC$3,'EUR USD'!$A$4:$BV$4,0)) -> 0 | AD29: =INDEX('EUR USD'!$A$4:$BV$1048576,MATCH('settlement day'!$B$3,'EUR USD'!$A$4:$A$1048576,0),MATCH('settlement day'!AD$3,'EUR USD'!$A$4:$BV$4,0)) -> 0 | AE29: =INDEX('EUR USD'!$A$4:$BV$1048576,MATCH('settlement day'!$B$3,'EUR USD'!$A$4:$A$1048576,0),MATCH('settlement day'!AE$3,'EUR USD'!$A$4:$BV$4,0)) -> 0 | AF29: =INDEX('EUR USD'!$A$4:$BV$1048576,MATCH('settlement day'!$B$3,'EUR USD'!$A$4:$A$1048576,0),MATCH('settlement day'!AF$3,'EUR USD'!$A$4:$BV$4,0)) -> 0 | AG29: =INDEX('EUR USD'!$A$4:$BV$1048576,MATCH('settlement day'!$B$3,'EUR USD'!$A$4:$A$1048576,0),MATCH('settlement day'!AG$3,'EUR USD'!$A$4:$BV$4,0)) -> 0 | AH29: =INDEX('EUR USD'!$A$4:$BV$1048576,MATCH('settlement day'!$B$3,'EUR USD'!$A$4:$A$1048576,0),MATCH('settlement day'!AH$3,'EUR USD'!$A$4:$BV$4,0)) -> 0 | ... AU29: =INDEX('EUR USD'!$A$4:$BV$1048576,MATCH('settlement day'!$B$3,'EUR USD'!$A$4:$A$1048576,0),MATCH('settlement day'!AU$3,'EUR USD'!$A$4:$BV$4,0)) -> 1.1196 | AV29: =INDEX('EUR USD'!$A$4:$CJ$1048576,MATCH('settlement day'!$B$3,'EUR USD'!$A$4:$A$1048576,0),MATCH('settlement day'!AV$3,'EUR USD'!$A$4:$CJ$4,0)) -> 1.0882 | AW29: =INDEX('EUR USD'!$A$4:$CJ$1048576,MATCH('settlement day'!$B$3,'EUR USD'!$A$4:$A$1048576,0),MATCH('settlement day'!AW$3,'EUR USD'!$A$4:$CJ$4,0)) -> 1.0562 | AX29: =INDEX('EUR USD'!$A$4:$CJ$1048576,MATCH('settlement day'!$B$3,'EUR USD'!$A$4:$A$1048576,0),MATCH('settlement day'!AX$3,'EUR USD'!$A$4:$CJ$4,0)) -> 1.0389 | AY29: =INDEX('EUR USD'!$A$4:$CJ$1048576,MATCH('settlement day'!$B$3,'EUR USD'!$A$4:$A$1048576,0),MATCH('settlement day'!AY$3,'EUR USD'!$A$4:$CJ$4,0)) -> 1.0393 | AZ29: =INDEX('EUR USD'!$A$4:$CJ$1048576,MATCH('settlement day'!$B$3,'EUR USD'!$A$4:$A$1048576,0),MATCH('settlement day'!AZ$3,'EUR USD'!$A$4:$CJ$4,0)) -> 1.0411 | BA29: =INDEX('EUR USD'!$A$4:$CJ$1048576,MATCH('settlement day'!$B$3,'EUR USD'!$A$4:$A$1048576,0),MATCH('settlement day'!BA$3,'EUR USD'!$A$4:$CJ$4,0)) -> 1.0815 | BB29: =INDEX('EUR USD'!$A$4:$CJ$1048576,MATCH('settlement day'!$B$3,'EUR USD'!$A$4:$A$1048576,0),MATCH('settlement day'!BB$3,'EUR USD'!$A$4:$CJ$4,0)) -> 1.1373 | BC29: =INDEX('EUR USD'!$A$4:$CJ$1048576,MATCH('settlement day'!$B$3,'EUR USD'!$A$4:$A$1048576,0),MATCH('settlement day'!BC$3,'EUR USD'!$A$4:$CJ$4,0)) -> 1.1241 | ... BG29: =INDEX('EUR USD'!$A$4:$CJ$1048576,MATCH('settlement day'!$B$3,'EUR USD'!$A$4:$A$1048576,0),MATCH('settlement day'!BG$3,'EUR USD'!$A$4:$CJ$4,0)) -> 1.13605 | BH29: =BJ29 -> 1.13805 | BI29: =BJ29 -> 1.13805 | BJ29: =INDEX('EUR USD'!$A$4:$CJ$1048576,MATCH('settlement day'!$B$3,'EUR USD'!$A$4:$A$1048576,0),MATCH('settlement day'!BJ$3,'EUR USD'!$A$4:$CJ$4,0)) -> 1.13805
B30: BRL/USD | C30: =+'BRL USD'!C8 -> 0 | D30: =+'BRL USD'!D7 -> 0 | E30: =+'BRL USD'!E7 -> 0 | F30: 0 | G30: 0 | H30: 0 | I30: 0 | J30: =+K30 -> 0 | K30: =+L30 -> 0 | M30: =+N30 -> 0 | N30: =+O30 -> 0 | O30: =+P30 -> 0 | P30: =+Q30 -> 0 | Q30: =+R30 -> 0 | R30: =+S30 -> 0 | S30: =+T30 -> 0 | T30: =+U30 -> 0 | ... Y30: =+Z30 -> 0 | Z30: =AA30 -> 0 | AA30: =AB30 -> 0 | AB30: =AC30 -> 0 | AC30: =AD30 -> 0 | AD30: =INDEX('BRL USD'!$A$4:$BB$1048576,MATCH('settlement day'!$B$3,'BRL USD'!$A$4:$A$1048576,0),MATCH('settlement day'!AD$3,'BRL USD'!$A$4:$BB$4,0)) -> 0 | AE30: =INDEX('BRL USD'!$A$4:$BB$1048576,MATCH('settlement day'!$B$3,'BRL USD'!$A$4:$A$1048576,0),MATCH('settlement day'!AE$3,'BRL USD'!$A$4:$BB$4,0)) -> 0 | AF30: =INDEX('BRL USD'!$A$4:$BB$1048576,MATCH('settlement day'!$B$3,'BRL USD'!$A$4:$A$1048576,0),MATCH('settlement day'!AF$3,'BRL USD'!$A$4:$BB$4,0)) -> 0 | AG30: =INDEX('BRL USD'!$A$4:$BB$1048576,MATCH('settlement day'!$B$3,'BRL USD'!$A$4:$A$1048576,0),MATCH('settlement day'!AG$3,'BRL USD'!$A$4:$BB$4,0)) -> 0 | AH30: =INDEX('BRL USD'!$A$4:$BB$1048576,MATCH('settlement day'!$B$3,'BRL USD'!$A$4:$A$1048576,0),MATCH('settlement day'!AH$3,'BRL USD'!$A$4:$BB$4,0)) -> 0 | AI30: =INDEX('BRL USD'!$A$4:$BB$1048576,MATCH('settlement day'!$B$3,'BRL USD'!$A$4:$A$1048576,0),MATCH('settlement day'!AI$3,'BRL USD'!$A$4:$BB$4,0)) -> 0 | AJ30: =INDEX('BRL USD'!$A$4:$BB$1048576,MATCH('settlement day'!$B$3,'BRL USD'!$A$4:$A$1048576,0),MATCH('settlement day'!AJ$3,'BRL USD'!$A$4:$BB$4,0)) -> 0 | AK30: =INDEX('BRL USD'!$A$4:$BB$1048576,MATCH('settlement day'!$B$3,'BRL USD'!$A$4:$A$1048576,0),MATCH('settlement day'!AK$3,'BRL USD'!$A$4:$BB$4,0)) -> 0 | ... BA30: =INDEX('BRL USD'!$A$4:$BB$1048576,MATCH('settlement day'!$B$3,'BRL USD'!$A$4:$A$1048576,0),MATCH('settlement day'!BA$3,'BRL USD'!$A$4:$BB$4,0)) -> 5.7416 | BB30: =INDEX('BRL USD'!$A$4:$CC$1048576,MATCH('settlement day'!$B$3,'BRL USD'!$A$4:$A$1048576,0),MATCH('settlement day'!BB$3,'BRL USD'!$A$4:$CC$4,0)) -> 5.6602 | BC30: =INDEX('BRL USD'!$A$4:$CC$1048576,MATCH('settlement day'!$B$3,'BRL USD'!$A$4:$A$1048576,0),MATCH('settlement day'!BC$3,'BRL USD'!$A$4:$CC$4,0)) -> 5.6614 | BD30: =INDEX('BRL USD'!$A$4:$CC$1048576,MATCH('settlement day'!$B$3,'BRL USD'!$A$4:$A$1048576,0),MATCH('settlement day'!BD$3,'BRL USD'!$A$4:$CC$4,0)) -> 5.6963828 | BE30: =INDEX('BRL USD'!$A$4:$CC$1048576,MATCH('settlement day'!$B$3,'BRL USD'!$A$4:$A$1048576,0),MATCH('settlement day'!BE$3,'BRL USD'!$A$4:$CC$4,0)) -> 5.7323015 | BF30: =INDEX('BRL USD'!$A$4:$CC$1048576,MATCH('settlement day'!$B$3,'BRL USD'!$A$4:$A$1048576,0),MATCH('settlement day'!BF$3,'BRL USD'!$A$4:$CC$4,0)) -> 5.7736721 | BG30: =INDEX('BRL USD'!$A$4:$CC$1048576,MATCH('settlement day'!$B$3,'BRL USD'!$A$4:$A$1048576,0),MATCH('settlement day'!BG$3,'BRL USD'!$A$4:$CC$4,0)) -> 5.8156441 | BH30: =INDEX('BRL USD'!$A$4:$CC$1048576,MATCH('settlement day'!$B$3,'BRL USD'!$A$4:$A$1048576,0),MATCH('settlement day'!BH$3,'BRL USD'!$A$4:$CC$4,0)) -> 5.8599473 | BI30: =INDEX('BRL USD'!$A$4:$CC$1048576,MATCH('settlement day'!$B$3,'BRL USD'!$A$4:$A$1048576,0),MATCH('settlement day'!BI$3,'BRL USD'!$A$4:$CC$4,0)) -> 5.9031877 | BJ30: =INDEX('BRL USD'!$A$4:$CC$1048576,MATCH('settlement day'!$B$3,'BRL USD'!$A$4:$A$1048576,0),MATCH('settlement day'!BJ$3,'BRL USD'!$A$4:$CC$4,0)) -> 5.9417706
B33: SPOT PHYS | AY33: Last | AZ33: D-1 | BA33: Variation | BC33: Phys Spread CHICAGO | BF33: RIN Opis | BG33: D6 | BH33: D4 | BI33: D5 | BJ33: CARB ($/CI) | BK33: Cbio (R$/Cb) | BM33: RIN Platts | BN33: D6-P | BO33: D4-P | BP33: D5-P | BQ33: CARB ($/ton)
B34: OPIS Chicago | AY34: =INDEX('PLATTS&OPIS'!$A$4:$BB$1048576,MATCH('settlement day'!$B$3,'PLATTS&OPIS'!$A$4:$A$1048576,0),MATCH(B34,'PLATTS&OPIS'!$A$4:$BB$4,0)) -> 0 | AZ34: =OFFSET(INDEX('PLATTS&OPIS'!$A$4:$BB$1048576,MATCH('settlement day'!$B$3,'PLATTS&OPIS'!$A$4:$A$1048576,0),MATCH(B34,'PLATTS&OPIS'!$A$4:$BB$4,0)),-1,0) -> 0 | BA34: =(+AY34-AZ34) -> 0 | BC34: New York | BD34: =+AY35-AY34 -> 0 | BF34: D-1 | BG34: =INDEX('PLATTS&OPIS'!$A$4:$BB$1048576,MATCH('settlement day'!$B$3,'PLATTS&OPIS'!$A$4:$A$1048576,0),MATCH(BG33,'PLATTS&OPIS'!$A$4:$BB$4,0)) -> 0 | BH34: =INDEX('PLATTS&OPIS'!$A$4:$BB$1048576,MATCH('settlement day'!$B$3,'PLATTS&OPIS'!$A$4:$A$1048576,0),MATCH(BH33,'PLATTS&OPIS'!$A$4:$BB$4,0)) -> 0 | BI34: =INDEX('PLATTS&OPIS'!$A$4:$BB$1048576,MATCH('settlement day'!$B$3,'PLATTS&OPIS'!$A$4:$A$1048576,0),MATCH(BI33,'PLATTS&OPIS'!$A$4:$BB$4,0)) -> 0 | BJ34: =INDEX('PLATTS&OPIS'!$A$4:$BB$1048576,MATCH('settlement day'!$B$3,'PLATTS&OPIS'!$A$4:$A$1048576,0),MATCH(BJ33,'PLATTS&OPIS'!$A$4:$BB$4,0)) -> 0 | BK34: =OFFSET(INDEX('PLATTS&OPIS'!$A$4:$BB$1048576,MATCH('settlement day'!$B$3,'PLATTS&OPIS'!$A$4:$A$1048576,0),MATCH(BK33,'PLATTS&OPIS'!$A$4:$BB$4,0)),-1,0) -> 60.75 | BM34: Last | BN34: =INDEX('PLATTS&OPIS'!$A$4:$BB$1048576,MATCH('settlement day'!$B$3,'PLATTS&OPIS'!$A$4:$A$1048576,0),MATCH(BN33,'PLATTS&OPIS'!$A$4:$BB$4,0)) -> 104.5 | BO34: =INDEX('PLATTS&OPIS'!$A$4:$BB$1048576,MATCH('settlement day'!$B$3,'PLATTS&OPIS'!$A$4:$A$1048576,0),MATCH(BO33,'PLATTS&OPIS'!$A$4:$BB$4,0)) -> 110 | BP34: =INDEX('PLATTS&OPIS'!$A$4:$BB$1048576,MATCH('settlement day'!$B$3,'PLATTS&OPIS'!$A$4:$A$1048576,0),MATCH(BP33,'PLATTS&OPIS'!$A$4:$BB$4,0)) -> 109.25 | BQ34: =INDEX('PLATTS&OPIS'!$A$4:$BB$1048576,MATCH('settlement day'!$B$3,'PLATTS&OPIS'!$A$4:$A$1048576,0),MATCH(BQ33,'PLATTS&OPIS'!$A$4:$BB$4,0)) -> 55.5
B35: OPIS New York | AY35: =INDEX('PLATTS&OPIS'!$A$4:$BB$1048576,MATCH('settlement day'!$B$3,'PLATTS&OPIS'!$A$4:$A$1048576,0),MATCH(B35,'PLATTS&OPIS'!$A$4:$BB$4,0)) -> 0 | AZ35: =OFFSET(INDEX('PLATTS&OPIS'!$A$4:$BB$1048576,MATCH('settlement day'!$B$3,'PLATTS&OPIS'!$A$4:$A$1048576,0),MATCH(B35,'PLATTS&OPIS'!$A$4:$BB$4,0)),-1,0) -> 0 | BA35: =(+AY35-AZ35) -> 0 | BC35: Gulf Coast | BD35: =+AY36-AY34 -> 0 | BF35: D-2 | BG35: =OFFSET(INDEX('PLATTS&OPIS'!$A$4:$BB$1048576,MATCH('settlement day'!$B$3,'PLATTS&OPIS'!$A$4:$A$1048576,0),MATCH(BG33,'PLATTS&OPIS'!$A$4:$BB$4,0)),-1,0) -> 0 | BH35: =OFFSET(INDEX('PLATTS&OPIS'!$A$4:$BB$1048576,MATCH('settlement day'!$B$3,'PLATTS&OPIS'!$A$4:$A$1048576,0),MATCH(BH33,'PLATTS&OPIS'!$A$4:$BB$4,0)),-1,0) -> 0 | BI35: =OFFSET(INDEX('PLATTS&OPIS'!$A$4:$BB$1048576,MATCH('settlement day'!$B$3,'PLATTS&OPIS'!$A$4:$A$1048576,0),MATCH(BI33,'PLATTS&OPIS'!$A$4:$BB$4,0)),-1,0) -> 0 | BJ35: =OFFSET(INDEX('PLATTS&OPIS'!$A$4:$BB$1048576,MATCH('settlement day'!$B$3,'PLATTS&OPIS'!$A$4:$A$1048576,0),MATCH(BJ33,'PLATTS&OPIS'!$A$4:$BB$4,0)),-1,0) -> 0 | BK35: =OFFSET(INDEX('PLATTS&OPIS'!$A$4:$BB$1048576,MATCH('settlement day'!$B$3,'PLATTS&OPIS'!$A$4:$A$1048576,0),MATCH(BK33,'PLATTS&OPIS'!$A$4:$BB$4,0)),-2,0) -> 60.75 | BM35: D-1 | BN35: =OFFSET(INDEX('PLATTS&OPIS'!$A$4:$BB$1048576,MATCH('settlement day'!$B$3,'PLATTS&OPIS'!$A$4:$A$1048576,0),MATCH(BN33,'PLATTS&OPIS'!$A$4:$BB$4,0)),-1,0) -> 103.25 | BO35: =OFFSET(INDEX('PLATTS&OPIS'!$A$4:$BB$1048576,MATCH('settlement day'!$B$3,'PLATTS&OPIS'!$A$4:$A$1048576,0),MATCH(BO33,'PLATTS&OPIS'!$A$4:$BB$4,0)),-1,0) -> 109.25 | BP35: =OFFSET(INDEX('PLATTS&OPIS'!$A$4:$BB$1048576,MATCH('settlement day'!$B$3,'PLATTS&OPIS'!$A$4:$A$1048576,0),MATCH(BP33,'PLATTS&OPIS'!$A$4:$BB$4,0)),-1,0) -> 108.5 | BQ35: =OFFSET(INDEX('PLATTS&OPIS'!$A$4:$BB$1048576,MATCH('settlement day'!$B$3,'PLATTS&OPIS'!$A$4:$A$1048576,0),MATCH(BQ33,'PLATTS&OPIS'!$A$4:$BB$4,0)),-1,0) -> 56.5
B36: OPIS Gulf Coast | AY36: =INDEX('PLATTS&OPIS'!$A$4:$BB$1048576,MATCH('settlement day'!$B$3,'PLATTS&OPIS'!$A$4:$A$1048576,0),MATCH(B36,'PLATTS&OPIS'!$A$4:$BB$4,0)) -> 0 | AZ36: =OFFSET(INDEX('PLATTS&OPIS'!$A$4:$BB$1048576,MATCH('settlement day'!$B$3,'PLATTS&OPIS'!$A$4:$A$1048576,0),MATCH(B36,'PLATTS&OPIS'!$A$4:$BB$4,0)),-1,0) -> 0 | BA36: =(+AY36-AZ36) -> 0 | BC36: Florida | BD36: =+AY37-AY34 -> 0 | BF36: Variation | BG36: =BG34-BG35 -> 0 | BH36: =BH34-BH35 -> 0 | BI36: =BI34-BI35 -> 0 | BJ36: =BJ34-BJ35 -> 0 | BK36: =+BK34-BK35 -> 0 | BM36: Variation | BN36: =BN34-BN35 -> 1.25 | BO36: =BO34-BO35 -> 0.75 | BP36: =BP34-BP35 -> 0.75 | BQ36: =BQ34-BQ35 -> -1
B37: OPIS Florida | AY37: =INDEX('PLATTS&OPIS'!$A$4:$BB$1048576,MATCH('settlement day'!$B$3,'PLATTS&OPIS'!$A$4:$A$1048576,0),MATCH(B37,'PLATTS&OPIS'!$A$4:$BB$4,0)) -> 0 | AZ37: =OFFSET(INDEX('PLATTS&OPIS'!$A$4:$BB$1048576,MATCH('settlement day'!$B$3,'PLATTS&OPIS'!$A$4:$A$1048576,0),MATCH(B37,'PLATTS&OPIS'!$A$4:$BB$4,0)),-1,0) -> 0 | BA37: =(+AY37-AZ37) -> 0 | BC37: California | BD37: =+AY38-AY34 -> 0
B38: OPIS California | AY38: =INDEX('PLATTS&OPIS'!$A$4:$BB$1048576,MATCH('settlement day'!$B$3,'PLATTS&OPIS'!$A$4:$A$1048576,0),MATCH(B38,'PLATTS&OPIS'!$A$4:$BB$4,0)) -> 0 | AZ38: =OFFSET(INDEX('PLATTS&OPIS'!$A$4:$BB$1048576,MATCH('settlement day'!$B$3,'PLATTS&OPIS'!$A$4:$A$1048576,0),MATCH(B38,'PLATTS&OPIS'!$A$4:$BB$4,0)),-1,0) -> 0 | BA38: =(+AY38-AZ38) -> 0 | BC38: R11 | BD38: =+AY39-AY34 -> 0 | BF38: D5/D6 Opis | BG38: =+BI34-BG34 -> 0 | BM38: D5/D6 Platts | BN38: =+BP34-BN34 -> 4.75
B39: OPIS Rule 11 | AY39: =INDEX('PLATTS&OPIS'!$A$4:$BB$1048576,MATCH('settlement day'!$B$3,'PLATTS&OPIS'!$A$4:$A$1048576,0),MATCH(B39,'PLATTS&OPIS'!$A$4:$BB$4,0)) -> 0 | AZ39: =OFFSET(INDEX('PLATTS&OPIS'!$A$4:$BB$1048576,MATCH('settlement day'!$B$3,'PLATTS&OPIS'!$A$4:$A$1048576,0),MATCH(B39,'PLATTS&OPIS'!$A$4:$BB$4,0)),-1,0) -> 0 | BA39: =(+AY39-AZ39) -> 0
B40: Platts CHICAGO (cpg) | AY40: =INDEX('PLATTS&OPIS'!$A$4:$BB$1048576,MATCH('settlement day'!$B$3,'PLATTS&OPIS'!$A$4:$A$1048576,0),MATCH(B40,'PLATTS&OPIS'!$A$4:$BB$4,0)) -> 174.8 | AZ40: =OFFSET(INDEX('PLATTS&OPIS'!$A$4:$BB$1048576,MATCH('settlement day'!$B$3,'PLATTS&OPIS'!$A$4:$A$1048576,0),MATCH(B40,'PLATTS&OPIS'!$A$4:$BB$4,0)),-1,0) -> 171.5 | BA40: =+AY40-AZ40 -> 3.3
B41: Platts T2 (eur/cbm) | AY41: =INDEX('PLATTS&OPIS'!$A$4:$BB$1048576,MATCH('settlement day'!$B$3,'PLATTS&OPIS'!$A$4:$A$1048576,0),MATCH(B41,'PLATTS&OPIS'!$A$4:$BB$4,0)) -> 611.75 | AZ41: =OFFSET(INDEX('PLATTS&OPIS'!$A$4:$BB$1048576,MATCH('settlement day'!$B$3,'PLATTS&OPIS'!$A$4:$A$1048576,0),MATCH(B41,'PLATTS&OPIS'!$A$4:$BB$4,0)),-1,0) -> 599.75 | BA41: =+AY41-AZ41 -> 12 | BC41: PNYH vs PCHI | BH41: ESALQ | BI41: R$/cbm | BJ41: R$/liter | BM41: CBios | BN41: CBio unit | BO41: per cbm HYD | BP41: per cbm ANH | BQ41: per vol CORN
B42: Platts FOB Brazil (usd/cbm) | AY42: =INDEX('PLATTS&OPIS'!$A$4:$BB$1048576,MATCH('settlement day'!$B$3,'PLATTS&OPIS'!$A$4:$A$1048576,0),MATCH(B42,'PLATTS&OPIS'!$A$4:$BB$4,0)) -> 587 | AZ42: =OFFSET(INDEX('PLATTS&OPIS'!$A$4:$BB$1048576,MATCH('settlement day'!$B$3,'PLATTS&OPIS'!$A$4:$A$1048576,0),MATCH(B42,'PLATTS&OPIS'!$A$4:$BB$4,0)),-1,0) -> 586 | BA42: =+AY42-AZ42 -> 1 | BD42: NYH | BE42: CHI | BF42: Δ cpg | BH42: Paulinia | BI42: =INDEX('ESALQ Paulinia'!A4:E1048576,MATCH('settlement day'!B3,'ESALQ Paulinia'!A4:A1048576,0),2) -> 2802 | BM42: R$ | BN42: =INDEX('PLATTS&OPIS'!$A$4:$BB$1048576,MATCH('settlement day'!$B$3,'PLATTS&OPIS'!$A$4:$A$1048576,0),MATCH(BK33,'PLATTS&OPIS'!$A$4:$BB$4,0)) -> 60.25 | BO42: =+BN42*BO44 -> 64.576635 | BP42: =+BN42*BP44 -> 73.207776 | BQ42: =+BN42*BQ44 -> 54.972628
B43: Platts FOB Grade B (usd/cbm) | AY43: =INDEX('PLATTS&OPIS'!$A$4:$BB$1048576,MATCH('settlement day'!$B$3,'PLATTS&OPIS'!$A$4:$A$1048576,0),MATCH(B43,'PLATTS&OPIS'!$A$4:$BB$4,0)) -> 598 | AZ43: =OFFSET(INDEX('PLATTS&OPIS'!$A$4:$BB$1048576,MATCH('settlement day'!$B$3,'PLATTS&OPIS'!$A$4:$A$1048576,0),MATCH(B43,'PLATTS&OPIS'!$A$4:$BB$4,0)),-1,0) -> 594 | BA43: =+AY43-AZ43 -> 4 | BC43: Last | BD43: =INDEX('PLATTS&OPIS'!$A$4:$BB$1048576,MATCH('settlement day'!$B$3,'PLATTS&OPIS'!$A$4:$A$1048576,0),4) -> 186.5 | BE43: =INDEX('PLATTS&OPIS'!$A$4:$BB$1048576,MATCH('settlement day'!$B$3,'PLATTS&OPIS'!$A$4:$A$1048576,0),2) -> 174.8 | BF43: =(+BD43-(BE43/100))*100 -> 18475.2 | BH43: Ribeirao | BI43: =+BJ43*1000 -> 0 | BJ43: =INDEX('ESALQ Hydrous Ribeirao'!A5:J1048576,MATCH('settlement day'!B3,'ESALQ Hydrous Ribeirao'!A5:A1048576,1),2) -> 0 | BM43: U$ | BN43: =+BN42/AN30 -> 12.091838 | BO43: =+BO42/AN30 -> 12.960169 | BP43: =+BP42/AN30 -> 14.692391 | BQ43: =+BQ42/AN30 -> 11.032699
B44: Platts Anhydrous (brl/cbm) | AY44: =INDEX('PLATTS&OPIS'!$A$4:$BB$1048576,MATCH('settlement day'!$B$3,'PLATTS&OPIS'!$A$4:$A$1048576,0),MATCH(B44,'PLATTS&OPIS'!$A$4:$BB$4,0)) -> 3320 | AZ44: =OFFSET(INDEX('PLATTS&OPIS'!$A$4:$BB$1048576,MATCH('settlement day'!$B$3,'PLATTS&OPIS'!$A$4:$A$1048576,0),MATCH(B44,'PLATTS&OPIS'!$A$4:$BB$4,0)),-1,0) -> 3300 | BA44: =+AY44-AZ44 -> 20 | BC44: D-1 | BD44: =OFFSET(INDEX('PLATTS&OPIS'!$A$4:$BB$1048576,MATCH('settlement day'!$B$3,'PLATTS&OPIS'!$A$4:$A$1048576,0),4),-1,0) -> 184 | BE44: =OFFSET(INDEX('PLATTS&OPIS'!$A$4:$BB$1048576,MATCH('settlement day'!$B$3,'PLATTS&OPIS'!$A$4:$A$1048576,0),2),-1,0) -> 171.5 | BF44: =(+BD44-(BE44/100))*100 -> 18228.5 | BO44: =1000/933 -> 1.0718114 | BP44: =1000/823 -> 1.2150668 | BQ44: =1000/1096 -> 0.91240876
B45: Platts Hydrous (brl/cbm) | AY45: =INDEX('PLATTS&OPIS'!$A$4:$BB$1048576,MATCH('settlement day'!$B$3,'PLATTS&OPIS'!$A$4:$A$1048576,0),MATCH(B45,'PLATTS&OPIS'!$A$4:$BB$4,0)) -> 3320 | AZ45: =OFFSET(INDEX('PLATTS&OPIS'!$A$4:$BB$1048576,MATCH('settlement day'!$B$3,'PLATTS&OPIS'!$A$4:$A$1048576,0),MATCH(B45,'PLATTS&OPIS'!$A$4:$BB$4,0)),-1,0) -> 3280 | BA45: =+AY45-AZ45 -> 40 | BC45: Δ | BD45: =+BD43-BD44 -> 2.5 | BE45: =+BE43-BE44 -> 3.3 | BH45: ETBE Northwest Europe ($/mt) FOB ARA | BL45: =INDEX('PLATTS&OPIS'!$A$4:$BB$1048576,MATCH('settlement day'!$B$3,'PLATTS&OPIS'!$A$4:$A$1048576,0),MATCH(BH45,'PLATTS&OPIS'!$A$4:$BB$4,0)) -> 1000.5 | BN45: plantas certificadas | BO45: 278 | BP45: 184 | BQ45: 4
B48: CHIP vs NYH | H48: =+H51-H9 -> 0 | I48: =+I51-I9 -> 0 | J48: =+J51-J9 -> 0 | K48: =+K51-K9 -> 0 | L48: =+L51-L9 -> 0 | M48: =+M51-M9 -> 0 | N48: =+N51-N9 -> 0 | O48: =+O51-O9 -> 0 | P48: =+P50-P8 -> 0.08506 | Q48: =+Q51-Q9 -> 0 | R48: =+R51-R9 -> 0 | S48: =+S51-S9 -> 0 | U48: =+U51-T9 -> 0 | W48: =+W51-U9 -> 0 | X48: =+X51-V9 -> 0 | Y48: =+Y51-W9 -> 0 | Z48: =+Z51-X9 -> 0 | AA48: =+AA51-Y9 -> 0 | AB48: =+AB51-AB9 -> 0 | AC48: =+AC51-AC9 -> 0 | AD48: =+AD51-AD9 -> 0 | AE48: =+AE51-AE9 -> 0 | AF48: =+AF51-AF9 -> 0 | AG48: =+AG51-AG9 -> 0 | AH48: =+AH51-AH9 -> 0 | AI48: =+AI51-AI9 -> 0 | ... AK48: =+AK51-AK9 -> 0 | AM48: =+AM51-AL9 -> 0 | AN48: =+AN51-AM9 -> 0 | AO48: =+AO51-AN9 -> 0 | AP48: =+AP51-AO9 -> 0 | AQ48: =+AQ51-AP9 -> 0 | AR48: =+AR51-AQ9 -> 0 | AS48: =+AS51-AR9 -> 0 | AY48: =+AY51-AS9 -> 0 | AZ48: =+AZ51-AV9 -> 0 | BA48: =+BA51-AW9 -> 0 | BB48: =+BB51-AX9 -> 0 | BC48: =+BC51-AY9 -> 0 | BD48: =+BD51-AZ9 -> 0 | BE48: =+BE51-BA9 -> 0 | BF48: =+BF51-BB9 -> 0 | BG48: =+BG51-BC9 -> 0.1125 | ... BO48: =+BO51-BK9 -> #N/A
B50: NYH (US$/gal) | M50: 3.8128 | N50: 3.6551 | O50: 2.3303 | P50: 2.2418 | R50: 2.7258 | S50: 2.8908 | U50: 2.9133 | W50: 2.5031 | X50: 2.5394 | Y50: 2.6264 | Z50: 2.2704 | AB50: =+AA51-AB51 -> 0 | AC50: =+AB51-AC51 -> 0 | AD50: =+AC51-AD51 -> 0 | AE50: =+AD51-AE51 -> 0 | AF50: =+AE51-AF51 -> 0 | AG50: =+AF51-AG51 -> 0 | AH50: =+AG51-AH51 -> 0 | AI50: =+AH51-AI51 -> 0 | ... AK50: =+AJ51-AK51 -> 0 | AM50: =+AK51-AM51 -> 0 | AN50: 1.5393 | AO50: =+AN51-AO51 -> 0 | AP50: =+AO51-AP51 -> 0 | AQ50: =+AP51-AQ51 -> 0 | AR50: =+AQ51-AR51 -> 0 | AS50: =+AR51-AS51 -> 0 | AY50: =+AS51-AY51 -> 0 | AZ50: =+AY51-AZ51 -> 0 | BA50: =+AZ51-BA51 -> 0 | BB50: =+BA51-BB51 -> 0 | BC50: =+BB51-BC51 -> 0 | BD50: =+BC51-BD51 -> 0 | BE50: =+BD51-BE51 -> 0 | BF50: =+BE51-BF51 -> 0 | BG50: =+BF51-BG51 -> -1.8425 | ... BO50: =+BN51-BO51 -> #N/A
B51: Last settlement | C51: =+RBOB!C59 -> 0 | D51: =+RBOB!D59 -> 0 | E51: =+RBOB!E59 -> 0 | F51: =+RBOB!F94 -> 0 | G51: =+RBOB!G94 -> 0 | H51: =+NYH!I82 -> 0 | I51: =+NYH!J95 -> 0 | J51: =+NYH!K123 -> 0 | K51: =+NYH!L139 -> 0 | L51: =+NYH!M202 -> 0 | M51: =+NYH!N202 -> 0 | N51: =+NYH!O244 -> 0 | O51: =+NYH!P244 -> 0 | P51: =+NYH!Q269 -> 0 | Q51: =+NYH!R286 -> 0 | R51: =+NYH!S310 -> 0 | S51: =INDEX(NYH!$A$4:$BB$1048576,MATCH('settlement day'!$B$3,NYH!$A$4:$A$1048576,0),MATCH('settlement day'!S$3,NYH!$A$4:$BB$4,0)) -> 0 | U51: =INDEX(NYH!$A$4:$BB$1048576,MATCH('settlement day'!$B$3,NYH!$A$4:$A$1048576,0),MATCH('settlement day'!T$3,NYH!$A$4:$BB$4,0)) -> 0 | W51: =INDEX(NYH!$A$4:$BB$1048576,MATCH('settlement day'!$B$3,NYH!$A$4:$A$1048576,0),MATCH('settlement day'!U$3,NYH!$A$4:$BB$4,0)) -> 0 | X51: =INDEX(NYH!$A$4:$BB$1048576,MATCH('settlement day'!$B$3,NYH!$A$4:$A$1048576,0),MATCH('settlement day'!W$3,NYH!$A$4:$BB$4,0)) -> 0 | Y51: =INDEX(NYH!$A$4:$BB$1048576,MATCH('settlement day'!$B$3,NYH!$A$4:$A$1048576,0),MATCH('settlement day'!X$3,NYH!$A$4:$BB$4,0)) -> 0 | Z51: =INDEX(NYH!$A$4:$BB$1048576,MATCH('settlement day'!$B$3,NYH!$A$4:$A$1048576,0),MATCH('settlement day'!Y$3,NYH!$A$4:$BB$4,0)) -> 0 | AA51: =INDEX(NYH!$A$4:$BB$1048576,MATCH('settlement day'!$B$3,NYH!$A$4:$A$1048576,0),MATCH('settlement day'!Z$3,NYH!$A$4:$BB$4,0)) -> 0 | AB51: =INDEX(NYH!$A$4:$BB$1048576,MATCH('settlement day'!$B$3,NYH!$A$4:$A$1048576,0),MATCH('settlement day'!AB$3,NYH!$A$4:$BB$4,0)) -> 0 | AC51: =INDEX(NYH!$A$4:$BB$1048576,MATCH('settlement day'!$B$3,NYH!$A$4:$A$1048576,0),MATCH('settlement day'!AC$3,NYH!$A$4:$BB$4,0)) -> 0 | AD51: =INDEX(NYH!$A$4:$BB$1048576,MATCH('settlement day'!$B$3,NYH!$A$4:$A$1048576,0),MATCH('settlement day'!AD$3,NYH!$A$4:$BB$4,0)) -> 0 | AE51: =INDEX(NYH!$A$4:$BB$1048576,MATCH('settlement day'!$B$3,NYH!$A$4:$A$1048576,0),MATCH('settlement day'!AE$3,NYH!$A$4:$BB$4,0)) -> 0 | AF51: =INDEX(NYH!$A$4:$BB$1048576,MATCH('settlement day'!$B$3,NYH!$A$4:$A$1048576,0),MATCH('settlement day'!AF$3,NYH!$A$4:$BB$4,0)) -> 0 | AG51: =INDEX(NYH!$A$4:$BB$1048576,MATCH('settlement day'!$B$3,NYH!$A$4:$A$1048576,0),MATCH('settlement day'!AG$3,NYH!$A$4:$BB$4,0)) -> 0 | AH51: =INDEX(NYH!$A$4:$BB$1048576,MATCH('settlement day'!$B$3,NYH!$A$4:$A$1048576,0),MATCH('settlement day'!AH$3,NYH!$A$4:$BB$4,0)) -> 0 | AI51: =INDEX(NYH!$A$4:$BB$1048576,MATCH('settlement day'!$B$3,NYH!$A$4:$A$1048576,0),MATCH('settlement day'!AI$3,NYH!$A$4:$BB$4,0)) -> 0 | ... AK51: =INDEX(NYH!$A$4:$BB$1048576,MATCH('settlement day'!$B$3,NYH!$A$4:$A$1048576,0),MATCH('settlement day'!AK$3,NYH!$A$4:$BB$4,0)) -> 0 | AM51: =INDEX(NYH!$A$4:$BB$1048576,MATCH('settlement day'!$B$3,NYH!$A$4:$A$1048576,0),MATCH('settlement day'!AL$3,NYH!$A$4:$BB$4,0)) -> 0 | AN51: =INDEX(NYH!$A$4:$BB$1048576,MATCH('settlement day'!$B$3,NYH!$A$4:$A$1048576,0),MATCH('settlement day'!AM$3,NYH!$A$4:$BB$4,0)) -> 0 | AO51: =INDEX(NYH!$A$4:$BB$1048576,MATCH('settlement day'!$B$3,NYH!$A$4:$A$1048576,0),MATCH('settlement day'!AN$3,NYH!$A$4:$BB$4,0)) -> 0 | AP51: =INDEX(NYH!$A$4:$BB$1048576,MATCH('settlement day'!$B$3,NYH!$A$4:$A$1048576,0),MATCH('settlement day'!AO$3,NYH!$A$4:$BB$4,0)) -> 0 | AQ51: =INDEX(NYH!$A$4:$BB$1048576,MATCH('settlement day'!$B$3,NYH!$A$4:$A$1048576,0),MATCH('settlement day'!AP$3,NYH!$A$4:$BB$4,0)) -> 0 | AR51: =INDEX(NYH!$A$4:$BB$1048576,MATCH('settlement day'!$B$3,NYH!$A$4:$A$1048576,0),MATCH('settlement day'!AQ$3,NYH!$A$4:$BB$4,0)) -> 0 | AS51: =INDEX(NYH!$A$4:$BB$1048576,MATCH('settlement day'!$B$3,NYH!$A$4:$A$1048576,0),MATCH('settlement day'!AR$3,NYH!$A$4:$BB$4,0)) -> 0 | AY51: =INDEX(NYH!$A$4:$BB$1048576,MATCH('settlement day'!$B$3,NYH!$A$4:$A$1048576,0),MATCH('settlement day'!AS$3,NYH!$A$4:$BB$4,0)) -> 0 | AZ51: =INDEX(NYH!$A$4:$CC$1048576,MATCH('settlement day'!$B$3,NYH!$A$4:$A$1048576,0),MATCH('settlement day'!AV$3,NYH!$A$4:$CC$4,0)) -> 0 | BA51: =INDEX(NYH!$A$4:$CC$1048576,MATCH('settlement day'!$B$3,NYH!$A$4:$A$1048576,0),MATCH('settlement day'!AW$3,NYH!$A$4:$CC$4,0)) -> 0 | BB51: =INDEX(NYH!$A$4:$CC$1048576,MATCH('settlement day'!$B$3,NYH!$A$4:$A$1048576,0),MATCH('settlement day'!AX$3,NYH!$A$4:$CC$4,0)) -> 0 | BC51: =INDEX(NYH!$A$4:$CC$1048576,MATCH('settlement day'!$B$3,NYH!$A$4:$A$1048576,0),MATCH('settlement day'!AY$3,NYH!$A$4:$CC$4,0)) -> 0 | BD51: =INDEX(NYH!$A$4:$CC$1048576,MATCH('settlement day'!$B$3,NYH!$A$4:$A$1048576,0),MATCH('settlement day'!AZ$3,NYH!$A$4:$CC$4,0)) -> 0 | BE51: =INDEX(NYH!$A$4:$CC$1048576,MATCH('settlement day'!$B$3,NYH!$A$4:$A$1048576,0),MATCH('settlement day'!BA$3,NYH!$A$4:$CC$4,0)) -> 0 | BF51: =INDEX(NYH!$A$4:$CC$1048576,MATCH('settlement day'!$B$3,NYH!$A$4:$A$1048576,0),MATCH('settlement day'!BB$3,NYH!$A$4:$CC$4,0)) -> 0 | BG51: =INDEX(NYH!$A$4:$CC$1048576,MATCH('settlement day'!$B$3,NYH!$A$4:$A$1048576,0),MATCH('settlement day'!BC$3,NYH!$A$4:$CC$4,0)) -> 1.8425 | ... BO51: =INDEX(NYH!$A$4:$CC$1048576,MATCH('settlement day'!$B$3,NYH!$A$4:$A$1048576,0),MATCH('settlement day'!BK$3,NYH!$A$4:$CC$4,0)) -> #N/A
B52: day before D-1 | C52: =+RBOB!C58 -> 0 | D52: =+RBOB!D58 -> 0 | E52: =+RBOB!E58 -> 0 | F52: =+RBOB!F93 -> 0 | G52: =+RBOB!G93 -> 0 | H52: =+NYH!I81 -> 0 | I52: =+NYH!J94 -> 0 | J52: =+NYH!K122 -> 0 | K52: =+NYH!L138 -> 0 | L52: =+NYH!M201 -> 0 | M52: =+NYH!N201 -> 0 | N52: =+NYH!O243 -> 0 | O52: =+NYH!P243 -> 0 | P52: =+NYH!Q268 -> 0 | Q52: =+NYH!R285 -> 0 | R52: =+NYH!S309 -> 0 | S52: =OFFSET(INDEX(NYH!$A$4:$BB$1048576,MATCH('settlement day'!$B$3,NYH!$A$4:$A$1048576,0),MATCH('settlement day'!S$3,NYH!$A$4:$BB$4,0)),-1,0) -> 0 | U52: =OFFSET(INDEX(NYH!$A$4:$BB$1048576,MATCH('settlement day'!$B$3,NYH!$A$4:$A$1048576,0),MATCH('settlement day'!T$3,NYH!$A$4:$BB$4,0)),-1,0) -> 0 | W52: =OFFSET(INDEX(NYH!$A$4:$BB$1048576,MATCH('settlement day'!$B$3,NYH!$A$4:$A$1048576,0),MATCH('settlement day'!U$3,NYH!$A$4:$BB$4,0)),-1,0) -> 0 | X52: =OFFSET(INDEX(NYH!$A$4:$BB$1048576,MATCH('settlement day'!$B$3,NYH!$A$4:$A$1048576,0),MATCH('settlement day'!W$3,NYH!$A$4:$BB$4,0)),-1,0) -> 0 | Y52: =OFFSET(INDEX(NYH!$A$4:$BB$1048576,MATCH('settlement day'!$B$3,NYH!$A$4:$A$1048576,0),MATCH('settlement day'!X$3,NYH!$A$4:$BB$4,0)),-1,0) -> 0 | Z52: =OFFSET(INDEX(NYH!$A$4:$BB$1048576,MATCH('settlement day'!$B$3,NYH!$A$4:$A$1048576,0),MATCH('settlement day'!Y$3,NYH!$A$4:$BB$4,0)),-1,0) -> 0 | AA52: =OFFSET(INDEX(NYH!$A$4:$BB$1048576,MATCH('settlement day'!$B$3,NYH!$A$4:$A$1048576,0),MATCH('settlement day'!Z$3,NYH!$A$4:$BB$4,0)),-1,0) -> 0 | AB52: =OFFSET(INDEX(NYH!$A$4:$BB$1048576,MATCH('settlement day'!$B$3,NYH!$A$4:$A$1048576,0),MATCH('settlement day'!AB$3,NYH!$A$4:$BB$4,0)),-1,0) -> 0 | AC52: =OFFSET(INDEX(NYH!$A$4:$BB$1048576,MATCH('settlement day'!$B$3,NYH!$A$4:$A$1048576,0),MATCH('settlement day'!AC$3,NYH!$A$4:$BB$4,0)),-1,0) -> 0 | AD52: =OFFSET(INDEX(NYH!$A$4:$BB$1048576,MATCH('settlement day'!$B$3,NYH!$A$4:$A$1048576,0),MATCH('settlement day'!AD$3,NYH!$A$4:$BB$4,0)),-1,0) -> 0 | AE52: =OFFSET(INDEX(NYH!$A$4:$BB$1048576,MATCH('settlement day'!$B$3,NYH!$A$4:$A$1048576,0),MATCH('settlement day'!AE$3,NYH!$A$4:$BB$4,0)),-1,0) -> 0 | AF52: =OFFSET(INDEX(NYH!$A$4:$BB$1048576,MATCH('settlement day'!$B$3,NYH!$A$4:$A$1048576,0),MATCH('settlement day'!AF$3,NYH!$A$4:$BB$4,0)),-1,0) -> 0 | AG52: =OFFSET(INDEX(NYH!$A$4:$BB$1048576,MATCH('settlement day'!$B$3,NYH!$A$4:$A$1048576,0),MATCH('settlement day'!AG$3,NYH!$A$4:$BB$4,0)),-1,0) -> 0 | AH52: =OFFSET(INDEX(NYH!$A$4:$BB$1048576,MATCH('settlement day'!$B$3,NYH!$A$4:$A$1048576,0),MATCH('settlement day'!AH$3,NYH!$A$4:$BB$4,0)),-1,0) -> 0 | AI52: =OFFSET(INDEX(NYH!$A$4:$BB$1048576,MATCH('settlement day'!$B$3,NYH!$A$4:$A$1048576,0),MATCH('settlement day'!AI$3,NYH!$A$4:$BB$4,0)),-1,0) -> 0 | ... AK52: =OFFSET(INDEX(NYH!$A$4:$BB$1048576,MATCH('settlement day'!$B$3,NYH!$A$4:$A$1048576,0),MATCH('settlement day'!AK$3,NYH!$A$4:$BB$4,0)),-1,0) -> 0 | AM52: =OFFSET(INDEX(NYH!$A$4:$BB$1048576,MATCH('settlement day'!$B$3,NYH!$A$4:$A$1048576,0),MATCH('settlement day'!AL$3,NYH!$A$4:$BB$4,0)),-1,0) -> 0 | AN52: =OFFSET(INDEX(NYH!$A$4:$BB$1048576,MATCH('settlement day'!$B$3,NYH!$A$4:$A$1048576,0),MATCH('settlement day'!AM$3,NYH!$A$4:$BB$4,0)),-1,0) -> 0 | AO52: =OFFSET(INDEX(NYH!$A$4:$BB$1048576,MATCH('settlement day'!$B$3,NYH!$A$4:$A$1048576,0),MATCH('settlement day'!AN$3,NYH!$A$4:$BB$4,0)),-1,0) -> 0 | AP52: =OFFSET(INDEX(NYH!$A$4:$BB$1048576,MATCH('settlement day'!$B$3,NYH!$A$4:$A$1048576,0),MATCH('settlement day'!AO$3,NYH!$A$4:$BB$4,0)),-1,0) -> 0 | AQ52: =OFFSET(INDEX(NYH!$A$4:$BB$1048576,MATCH('settlement day'!$B$3,NYH!$A$4:$A$1048576,0),MATCH('settlement day'!AP$3,NYH!$A$4:$BB$4,0)),-1,0) -> 0 | AR52: =OFFSET(INDEX(NYH!$A$4:$BB$1048576,MATCH('settlement day'!$B$3,NYH!$A$4:$A$1048576,0),MATCH('settlement day'!AQ$3,NYH!$A$4:$BB$4,0)),-1,0) -> 0 | AS52: =OFFSET(INDEX(NYH!$A$4:$BB$1048576,MATCH('settlement day'!$B$3,NYH!$A$4:$A$1048576,0),MATCH('settlement day'!AR$3,NYH!$A$4:$BB$4,0)),-1,0) -> 0 | AY52: =OFFSET(INDEX(NYH!$A$4:$BB$1048576,MATCH('settlement day'!$B$3,NYH!$A$4:$A$1048576,0),MATCH('settlement day'!AS$3,NYH!$A$4:$BB$4,0)),-1,0) -> 0 | AZ52: =OFFSET(INDEX(NYH!$A$4:$CC$1048576,MATCH('settlement day'!$B$3,NYH!$A$4:$A$1048576,0),MATCH('settlement day'!AV$3,NYH!$A$4:$CC$4,0)),-1,0) -> 0 | BA52: =OFFSET(INDEX(NYH!$A$4:$CC$1048576,MATCH('settlement day'!$B$3,NYH!$A$4:$A$1048576,0),MATCH('settlement day'!AW$3,NYH!$A$4:$CC$4,0)),-1,0) -> 0 | BB52: =OFFSET(INDEX(NYH!$A$4:$CC$1048576,MATCH('settlement day'!$B$3,NYH!$A$4:$A$1048576,0),MATCH('settlement day'!AX$3,NYH!$A$4:$CC$4,0)),-1,0) -> 0 | BC52: =OFFSET(INDEX(NYH!$A$4:$CC$1048576,MATCH('settlement day'!$B$3,NYH!$A$4:$A$1048576,0),MATCH('settlement day'!AY$3,NYH!$A$4:$CC$4,0)),-1,0) -> 0 | BD52: =OFFSET(INDEX(NYH!$A$4:$CC$1048576,MATCH('settlement day'!$B$3,NYH!$A$4:$A$1048576,0),MATCH('settlement day'!AZ$3,NYH!$A$4:$CC$4,0)),-1,0) -> 0 | BE52: =OFFSET(INDEX(NYH!$A$4:$CC$1048576,MATCH('settlement day'!$B$3,NYH!$A$4:$A$1048576,0),MATCH('settlement day'!BA$3,NYH!$A$4:$CC$4,0)),-1,0) -> 0 | BF52: =OFFSET(INDEX(NYH!$A$4:$CC$1048576,MATCH('settlement day'!$B$3,NYH!$A$4:$A$1048576,0),MATCH('settlement day'!BB$3,NYH!$A$4:$CC$4,0)),-1,0) -> 0 | BG52: =OFFSET(INDEX(NYH!$A$4:$CC$1048576,MATCH('settlement day'!$B$3,NYH!$A$4:$A$1048576,0),MATCH('settlement day'!BC$3,NYH!$A$4:$CC$4,0)),-1,0) -> 1.84 | ... BO52: =OFFSET(INDEX(NYH!$A$4:$CC$1048576,MATCH('settlement day'!$B$3,NYH!$A$4:$A$1048576,0),MATCH('settlement day'!BK$3,NYH!$A$4:$CC$4,0)),-1,0) -> #N/A
B53: Variation | C53: =C51-C52 -> 0 | D53: =D51-D52 -> 0 | E53: =E51-E52 -> 0 | F53: =F51-F52 -> 0 | G53: =G51-G52 -> 0 | H53: =H51-H52 -> 0 | I53: =I51-I52 -> 0 | J53: =J51-J52 -> 0 | ... S53: =S51-S52 -> 0 | U53: =U51-U52 -> 0 | W53: =W51-W52 -> 0 | X53: =X51-X52 -> 0 | Y53: =Y51-Y52 -> 0 | Z53: =Z51-Z52 -> 0 | AA53: =AA51-AA52 -> 0 | AB53: =AB51-AB52 -> 0 | AC53: =AC51-AC52 -> 0 | AD53: =AD51-AD52 -> 0 | ... AK53: =AK51-AK52 -> 0 | AM53: =AM51-AM52 -> 0 | AN53: =AN51-AN52 -> 0 | AO53: =AO51-AO52 -> 0 | AP53: =AP51-AP52 -> 0 | AQ53: =AQ51-AQ52 -> 0 | AR53: =AR51-AR52 -> 0 | AS53: =AS51-AS52 -> 0 | AY53: =AY51-AY52 -> 0 | AZ53: =AZ51-AZ52 -> 0 | BA53: =BA51-BA52 -> 0 | BB53: =BB51-BB52 -> 0 | BC53: =BC51-BC52 -> 0 | BD53: =BD51-BD52 -> 0 | BE53: =BE51-BE52 -> 0 | BF53: =BF51-BF52 -> 0 | ... BO53: =BO51-BO52 -> #N/A

Sheet PLATTS&OPIS
B3: Platts | L3: Ethanol US phys spot - OPIS | R3: RINs current year - OPIS | V3: CBIOS | W3: RINs current year - Platts
B4: Platts CHICAGO (cpg) | C4: Platts T2 (eur/cbm) | E4: Platts Hydrous (brl/cbm) | F4: Hydrous ANP - FOB Santos/Paranagua ($/cu m) | G4: Platts Anhydrous (brl/cbm) | H4: Platts FOB Brazil (usd/cbm) | I4: Anhydrous NNE Brazil delivered Suape* (R$/cu m) | J4: Platts FOB Grade B (usd/cbm) | K4: Spot Ex-mill Ribeirao Hydrous expressed as Raw Sugar equivalent (basis 96 degrees pol) (¢/lb) | L4: OPIS Chicago | M4: OPIS Rule 11 | N4: OPIS New York | O4: OPIS Gulf Coast | P4: OPIS Florida | Q4: OPIS California | R4: D6 | S4: D4 | T4: D5 | U4: CARB ($/CI) | V4: Cbio (R$/Cb) | W4: D6-P | X4: D4-P | Y4: D5-P | Z4: CARB ($/ton) | AA4: ETBE Northwest Europe ($/mt) FOB ARA
A5: 44286 | B5: 192.1 | C5: 543.25 | D5: 2.0125 | E5: 2850 | F5: 436 | G5: 2775 | H5: 488 | J5: 466 | K5: 12.54 | L5: 1.8675 | M5: 1.875 | N5: 1.97 | O5: 1.97 | P5: 2.11 | Q5: 2.265 | R5: 1.2975 | S5: 1.38 | T5: 1.375 | U5: 0.015485 | V5: 28.485078
A6: 44287 | B6: 191.45 | C6: 543.75 | E6: 2850 | F6: 434 | G6: 2775 | H6: 486 | J6: 464 | K6: 12.49 | L6: 1.9175 | M6: 1.89875 | N6: 1.99 | O6: 2.02 | P6: 2.105 | Q6: 2.29 | R6: 1.32625 | S6: 1.405 | T6: 1.4 | U6: 0.015405 | V6: 28.732344
A7: 44291 | B7: 190.6 | E7: 2855 | F7: 437 | G7: 2775 | H7: 488 | J7: 467 | K7: 12.57 | L7: 1.9075 | M7: 1.89 | N7: 1.99 | O7: 2.005 | P7: 2.1 | Q7: 2.29 | R7: 1.34 | S7: 1.4275 | T7: 1.4225 | U7: 0.015405 | V7: 28.972727
A8: 44292 | B8: 190.95 | C8: 534.75 | E8: 2855 | F8: 443 | G8: 2695 | H8: 481 | J8: 473 | K8: 12.74 | L8: 1.91 | M8: 1.895 | N8: 1.9925 | O8: 2.01 | P8: 2.11 | Q8: 2.2275 | R8: 1.345 | S8: 1.4325 | T8: 1.4275 | U8: 0.014505 | V8: 29.398536
A9: 44293 | B9: 192.7 | C9: 535 | E9: 2855 | F9: 442 | G9: 2695 | H9: 480 | J9: 472 | K9: 12.7 | L9: 1.9275 | M9: 1.9 | N9: 2.0075 | O9: 2.025 | P9: 2.125 | Q9: 2.24 | R9: 1.33 | S9: 1.4225 | T9: 1.4175 | U9: 0.014465 | V9: 29.988215
A10: 44294 | B10: 196.65 | C10: 536 | E10: 2940 | F10: 458 | G10: 2705 | H10: 486 | J10: 488 | K10: 13.17 | L10: 1.96625 | M10: 1.945 | N10: 2.0425 | O10: 2.065 | P10: 2.18 | Q10: 2.3 | R10: 1.335 | S10: 1.4175 | T10: 1.4125 | U10: 0.014465 | V10: 30.488696
A11: 44295 | B11: 195.95 | C11: 548.75 | E11: 2920 | F11: 447 | G11: 2755 | H11: 485 | I11: 2870 | J11: 477 | K11: 12.84 | L11: 1.96375 | M11: 1.95 | N11: 2.045 | O11: 2.07 | P11: 2.21 | Q11: 2.325 | R11: 1.335 | S11: 1.4225 | T11: 1.4175 | U11: 0.01459 | V11: 30.795814
A12: 44298 | B12: 194.25 | C12: 553.75 | E12: 2995 | F12: 456 | G12: 2895 | H12: 507 | J12: 486 | K12: 13.1 | L12: 1.94625 | M12: 1.945 | N12: 2.025 | O12: 2.04 | P12: 2.2 | Q12: 2.335 | R12: 1.32 | S12: 1.39 | T12: 1.385 | U12: 0.01475 | V12: 30.901317
A13: 44299 | B13: 197 | C13: 570.5 | E13: 3095 | F13: 471 | G13: 2895 | H13: 507 | J13: 501 | K13: 13.52 | L13: 1.97 | M13: 1.97 | N13: 2.045 | O13: 2.065 | P13: 2.205 | Q13: 2.36 | R13: 1.3275 | S13: 1.405 | T13: 1.4 | U13: 0.014875 | V13: 30.925862
A14: 44300 | B14: 202 | C14: 588 | E14: 3155 | F14: 481 | G14: 3045 | H14: 534 | J14: 511 | K14: 13.8 | L14: 2.0225 | M14: 2.02 | N14: 2.09625 | O14: 2.115 | P14: 2.265 | Q14: 2.405 | R14: 1.325 | S14: 1.39625 | T14: 1.39125 | U14: 0.01475 | V14: 30.965968
A15: 44301 | B15: 204.8 | C15: 576 | E15: 3205 | F15: 493 | G15: 3180 | H15: 563 | J15: 523 | K15: 14.15 | L15: 2.04875 | M15: 2.01 | N15: 2.145 | O15: 2.145 | P15: 2.275 | Q15: 2.415 | R15: 1.32875 | S15: 1.395 | T15: 1.39 | U15: 0.01475 | V15: 30.996
A16: 44302 | B16: 206.2 | C16: 586 | E16: 3270 | F16: 506 | G16: 3195 | H16: 569 | I16: 3150 | J16: 536 | K16: 14.51 | L16: 2.05875 | M16: 2.05 | N16: 2.145 | O16: 2.155 | P16: 2.285 | Q16: 2.425 | R16: 1.3475 | S16: 1.4125 | T16: 1.4075 | U16: 0.01451 | V16: 30.999825
A17: 44305 | B17: 215.6 | C17: 582 | E17: 3230 | F17: 505 | G17: 3205 | H17: 576 | J17: 535 | K17: 14.47 | L17: 2.143 | M17: 2.135 | N17: 2.225 | O17: 2.235 | P17: 2.35 | Q17: 2.46 | R17: 1.3525 | S17: 1.415 | T17: 1.41 | U17: 0.01443 | V17: 30.730887
A18: 44306 | B18: 219.3 | C18: 596 | E18: 3245 | F18: 507 | G18: 3145 | H18: 565 | J18: 537 | K18: 14.53 | L18: 2.1975 | M18: 2.23 | N18: 2.2875 | O18: 2.2925 | P18: 2.42 | Q18: 2.5 | R18: 1.3675 | S18: 1.435 | T18: 1.43 | U18: 0.014345 | V18: 30.953614
A19: 44307 | B19: 224.75 | C19: 601.25 | E19: 3245 | F19: 507 | G19: 3145 | H19: 565 | J19: 537 | K19: 14.53 | L19: 2.2475 | M19: 2.265 | N19: 2.325 | O19: 2.34 | P19: 2.435 | Q19: 2.53 | R19: 1.37 | S19: 1.45 | T19: 1.445 | U19: 0.01414
A20: 44308 | B20: 232 | C20: 603.5 | E20: 3250 | F20: 514 | G20: 3150 | H20: 573 | J20: 544 | K20: 14.72 | L20: 2.32 | M20: 2.315 | N20: 2.3875 | O20: 2.415 | P20: 2.505 | Q20: 2.59 | R20: 1.3875 | S20: 1.47 | T20: 1.465 | U20: 0.0141 | V20: 31.159828
A21: 44309 | B21: 231.55 | C21: 604.75 | E21: 3270 | F21: 514 | G21: 3155 | H21: 571 | I21: 3205 | J21: 544 | K21: 14.74 | L21: 2.31 | M21: 2.33 | N21: 2.3925 | O21: 2.405 | P21: 2.505 | Q21: 2.575 | R21: 1.3975 | S21: 1.4825 | T21: 1.4775 | U21: 0.01402 | V21: 31.189446
A22: 44312 | B22: 237.85 | C22: 606.75 | E22: 3245 | F22: 514 | G22: 3150 | H22: 574 | J22: 544 | K22: 14.75 | L22: 2.377 | M22: 2.395 | N22: 2.455 | O22: 2.46 | P22: 2.56 | Q22: 2.635 | R22: 1.4225 | S22: 1.51 | T22: 1.505 | U22: 0.0141 | V22: 31.101612
A23: 44313 | B23: 232.5 | C23: 628.25 | E23: 3215 | F23: 510 | G23: 3155 | H23: 576 | J23: 540 | K23: 14.63 | L23: 2.3425 | M23: 2.3725 | N23: 2.43 | O23: 2.44 | P23: 2.57 | Q23: 2.615 | R23: 1.485 | S23: 1.575 | T23: 1.57 | U23: 0.01408 | V23: 31.011065
A24: 44314 | B24: 232.95 | C24: 619 | E24: 3205 | F24: 514 | G24: 3145 | H24: 580 | J24: 544 | K24: 14.74 | L24: 2.33125 | M24: 2.37 | N24: 2.4275 | O24: 2.43 | P24: 2.545 | Q24: 2.6 | R24: 1.5075 | S24: 1.59 | T24: 1.585 | U24: 0.014245 | V24: 30.924332
A25: 44315 | B25: 226.85 | C25: 618.25 | E25: 3225 | F25: 520 | G25: 3155 | H25: 585 | J25: 550 | K25: 14.9 | L25: 2.27375 | M25: 2.28125 | N25: 2.3525 | O25: 2.375 | P25: 2.455 | Q25: 2.625 | R25: 1.53 | S25: 1.605 | T25: 1.6 | U25: 0.01443 | V25: 30.89903
A26: 44316 | B26: 234.65 | C26: 617 | D26: 2.46 | E26: 3265 | F26: 521 | G26: 3205 | H26: 588 | I26: 3445 | J26: 551 | K26: 14.94 | L26: 2.315 | M26: 2.3 | N26: 2.415 | O26: 2.415 | P26: 2.48 | Q26: 2.655 | R26: 1.495 | S26: 1.5775 | T26: 1.5725 | U26: 0.01443 | V26: 30.792113
A27: 44319 | B27: 233.25 | E27: 3305 | F27: 529 | G27: 3320 | H27: 611 | J27: 559 | K27: 15.16 | L27: 2.35 | M27: 2.35 | N27: 2.455 | O27: 2.4375 | P27: 2.5 | Q27: 2.655 | R27: 1.5475 | S27: 1.635 | T27: 1.63 | U27: 0.01459 | V27: 30.701087
A28: 44320 | B28: 247.55 | C28: 607 | E28: 3495 | F28: 555 | G28: 3510 | H28: 640 | J28: 585 | K28: 15.88 | L28: 2.439 | M28: 2.46 | N28: 2.555 | O28: 2.54 | P28: 2.565 | Q28: 2.7025 | R28: 1.605 | S28: 1.69 | T28: 1.685 | U28: 0.014635 | V28: 31.305117
A29: 44321 | B29: 256.45 | C29: 605 | E29: 3600 | F29: 579 | G29: 3600 | H29: 665 | J29: 609 | K29: 16.55 | L29: 2.535 | M29: 2.535 | N29: 2.635 | O29: 2.615 | P29: 2.7 | Q29: 2.86 | R29: 1.6375 | S29: 1.73 | T29: 1.725 | U29: 0.014875 | V29: 30.740488
A30: 44322 | B30: 262.5 | C30: 605.5 | E30: 3695 | F30: 601 | G30: 3650 | H30: 683 | I30: =3600+380 -> 3980 | J30: 631 | K30: 17.19 | L30: 2.6225 | M30: 2.6 | N30: 2.6725 | O30: 2.7125 | P30: 2.745 | Q30: 2.855 | R30: 1.6825 | S30: 1.77 | T30: 1.765 | U30: 0.01516 | V30: 30.727545
A31: 44323 | B31: 268 | C31: 613 | E31: 3695 | F31: 609 | G31: 3650 | H31: 692 | I31: 3960 | J31: 639 | K31: 17.41 | L31: 2.67875 | M31: 2.66 | N31: 2.7 | O31: 2.775 | P31: 2.84 | Q31: 2.905 | R31: 1.7375 | S31: 1.825 | T31: 1.82 | U31: 0.015405 | V31: 30.705192
A32: 44326 | B32: 263.9 | C32: 615 | E32: 3705 | F32: 609 | G32: 3660 | H32: 692 | J32: 639 | K32: 17.41 | L32: 2.639 | M32: 2.645 | N32: 2.665 | O32: 2.73 | P32: 2.815 | Q32: 2.88 | R32: 1.79 | S32: 1.865 | T32: 1.86 | U32: 0.015325 | V32: 30.6875
A33: 44327 | B33: 264.4 | C33: 647 | E33: 3705 | F33: 610 | G33: 3645 | H33: 691 | J33: 640 | K33: 17.75 | L33: 2.64 | M33: 2.66 | N33: 2.6725 | O33: 2.725 | P33: 2.825 | Q33: 2.95 | R33: 1.79 | S33: 1.8625 | T33: 1.8575 | U33: 0.015325 | V33: 30.678655
A34: 44328 | B34: 258.5 | C34: 654.75 | E34: 3695 | F34: 603 | G34: 3645 | H34: 684 | J34: 633 | K34: 17.24 | L34: 2.585 | M34: 2.5825 | N34: 2.595 | O34: 2.67 | P34: 2.78 | Q34: 2.855 | R34: 1.865 | S34: 1.9375 | T34: 1.9325 | U34: 0.01528 | V34: 30.47243
A35: 44329 | B35: 249.5 | C35: 646.75 | E35: 3695 | F35: 599 | G35: 3645 | H35: 680 | J35: 629 | K35: 17.13 | L35: 2.4925 | M35: 2.49 | N35: 2.485 | O35: 2.585 | P35: 2.68 | Q35: 2.765 | R35: 1.865 | S35: 1.935 | T35: 1.93 | U35: 0.015285 | V35: 30.656944
A36: 44330 | B36: 247.5 | C36: 634 | E36: 3695 | F36: 604 | G36: 3645 | H36: 685 | J36: 634 | K36: 17.27 | L36: 2.4725 | M36: 2.465 | N36: 2.49 | O36: 2.57 | P36: 2.68 | Q36: 2.765 | R36: 1.8475 | S36: 1.935 | T36: 1.93 | U36: 0.015285 | V36: 30.673753
A37: 44333 | B37: 257.6 | C37: 648.75 | E37: 3605 | F37: 591 | G37: 3645 | H37: 687 | J37: 621 | K37: 16.89 | L37: 2.5375 | M37: 2.49 | N37: 2.59 | O37: 2.59 | P37: 2.705 | Q37: 2.795 | R37: 1.865 | S37: 1.965 | T37: 1.96 | U37: 0.01508 | V37: 30.671222
A38: 44334 | B38: 262 | C38: 663.75 | E38: 3620 | F38: 593 | G38: 3645 | H38: 687 | J38: 623 | K38: 16.96 | L38: 2.62 | M38: 2.555 | N38: 2.645 | O38: 2.655 | P38: 2.745 | Q38: 2.85 | R38: 1.8975 | S38: 1.995 | T38: 1.99 | U38: 0.015325 | V38: 30.612153
A39: 44335 | B39: 260 | C39: 654 | E39: 3505 | F39: 572 | G39: 3555 | H39: 666 | J39: 602 | K39: 16.36 | L39: 2.585 | M39: 2.5 | N39: 2.63 | O39: 2.63 | P39: 2.725 | Q39: 2.83 | R39: 1.875 | S39: 1.97 | T39: 1.965 | U39: 0.015325 | V39: 30.638813
A40: 44336 | B40: 259.8 | C40: 648.75 | E40: 3445 | F40: 562 | G40: 3540 | H40: 664 | J40: 592 | K40: 16.1 | L40: 2.61375 | M40: 2.5 | N40: 2.5275 | O40: 2.67 | P40: 2.68 | Q40: 2.81 | R40: 1.8525 | S40: 1.9425 | T40: 1.9375 | U40: 0.015405 | V40: 30.584066
A41: 44337 | B41: 257.6 | C41: 636.75 | E41: 3415 | F41: 551 | G41: 3540 | H41: 657 | I41: 4015 | J41: 581 | K41: 15.79 | L41: 2.5975 | M41: 2.49 | N41: 2.485 | O41: 2.67 | P41: 2.68 | Q41: 2.81 | R41: 1.82 | S41: 1.915 | T41: 1.91 | U41: 0.01549 | V41: 30.548839
A42: 44340 | B42: 257.4 | C42: 637.5 | E42: 3430 | F42: 556 | G42: 3560 | H42: 663 | J42: 586 | K42: 15.91 | L42: 2.5725 | M42: 2.5 | N42: 2.51 | O42: 2.475 | P42: 2.675 | Q42: 2.805 | R42: 1.835 | S42: 1.925 | T42: 1.92 | U42: 0.01549 | V42: 30.497151
A43: 44341 | B43: 240 | C43: 636.25 | E43: 3430 | F43: 556 | G43: 3535 | H43: 658 | J43: 586 | K43: 15.92 | L43: 2.45 | M43: 2.4275 | N43: 2.4275 | O43: 2.42 | P43: 2.575 | Q43: 2.725 | R43: 1.8425 | S43: 1.94 | T43: 1.935 | U43: 0.01553 | V43: 30.500397
